Workbook
Name RevDemotoConv: #REF!
Name appraisalmultiplecs: #REF!
Name m1bdmproducitivity_preJun: #REF!
Name _C1_Accounts_per_CS: #REF!
Name ClusteroneROW: #REF!
Name Closedwontable: #REF!
Name m4bdmproducitivity_postJun: #REF!
Name NorthAmeria_UK: #REF!
Name NA_C2_ACV: #REF!
Name cbdrmm: #REF!
Name India_SEAME: #REF!
Name North_America___UK: #REF!
Name _C3_System_Implementation: #REF!
Name Auditor_India: #REF!
Name India_C2_ACV: #REF!
Name TE_India: #REF!
Name Changed: #REF!
Name Product___Engg__R_D: #REF!
Name expectedexpansion: #REF!
Name TEmultipleAE: #REF!
Name TEUS: #REF!
Name aeseration: #REF!
Name TEmultipleleader: #REF!
Name Moved1: #REF!
Name TE_US: #REF!
Name productivity2: #REF!
Name USmarekt: #REF!
Name expectedexpansion: #REF!
Name TE_multiple_leader: #REF!
Name cscapacitymax: #REF!
Name iscapacity: #REF!
Name jjellyfishcommissions: #REF!
Name USmarekt: #REF!
Name m1bdmproducitivity_postJun: #REF!
Name NA_C3_SQLtoDemoCVR: #REF!
Name bdmbdrratio: #REF!
Name generalandadmin: #REF!
Name CSTEAmratio: #REF!
Name m3bd: #REF!
Name Auditor_USA: #REF!
Name Product_and_Engineering: #REF!
Name m4bd: #REF!
Name salesandmarketing: #REF!
Name m1bd: #REF!
Name USAEquotaperc: #REF!
Name AE_Seration: #REF!
Name IndiaCScapacity: #REF!
Name IS_ARR: #REF!
Name naentbdr: #REF!
Name Appraisal_Multiple: #REF!
Name sqlconversionperc: #REF!
Name US_AE_Prod: #REF!
Name usaequota: #REF!
Name P_and_E_R_D: #REF!
Name traveltoUS: #REF!
Name NA_C3_ACV: #REF!
Name m4bdmproducitivity_preJun: #REF!
Name India_SEA_ME: #REF!
Name productivity0: #REF!
Name _C1_IS: #REF!

Sheet 1. Business Metrics
E1: Actuals | F1: Actuals | G1: Actuals | H1: Actuals | I1: Actuals | J1: Actuals | K1: Actuals | L1: Actuals | M1: Actuals | N1: Actuals | O1: Actuals | P1: Actuals | Q1: Actuals | R1: Actuals | S1: Actuals | T1: Actuals | U1: Actuals | V1: Planned | W1: Actuals | X1: Planned | Y1: Actuals | Z1: Planned | AA1: Actuals | AB1: Planned | AC1: Actuals | AD1: Planned | AE1: Actuals | AF1: Planned | AG1: Actuals | AH1: Planned | AI1: Actuals | AJ1: Planned | AK1: Actuals | AL1: Planned | AM1: Actuals | AN1: Planned | AO1: Actuals | AP1: Planned | AQ1: Actuals | AR1: Planned | AS1: Actuals | AT1: Planned | AU1: Actuals | AV1: Planned | AW1: Actuals | AX1: Planned | AY1: Actuals | AZ1: Planned | BA1: Actuals | BB1: Planned | BC1: Actuals | BD1: Planned | BE1: Actuals | BF1: Planned | BG1: Actuals | BH1: Planned | BI1: Actuals | BJ1: Planned | BK1: Actuals | BL1: Planned | BM1: Actuals | BN1: Planned | BO1: Actuals | BP1: Planned | BQ1: Actuals | BR1: Planned | BS1: Actuals | BT1: Planned | BU1: Actuals | BV1: Planned | BW1: Actuals | BX1: Planned | BY1: Actuals | BZ1: Planned | CA1: Actuals | CB1: Planned | CC1: Actuals | CD1: Planned | CE1: Actuals | CF1: Planned | CG1: Actuals | CH1: Planned | CI1: Actuals | CJ1: Planned | CK1: Actuals | CL1: Planned | CM1: Planned
E2: 44530 | F2: 44561 | G2: 44592 | H2: 44620 | I2: 44651 | J2: 44681 | K2: 44712 | L2: =EOMONTH(K2,1) -> 44742 | M2: =EOMONTH(L2,1) -> 44773 | N2: =EOMONTH(M2,1) -> 44804 | O2: =EOMONTH(N2,1) -> 44834 | P2: =EOMONTH(O2,1) -> 44865 | Q2: =EOMONTH(P2,1) -> 44895 | R2: =EOMONTH(Q2,1) -> 44926 | S2: =EOMONTH(R2,1) -> 44957 | ... V2: =EOMONTH(U2,1) -> 45046 | W2: =EOMONTH(U2,1) -> 45046 | X2: =EOMONTH(V2,1) -> 45077 | Y2: =EOMONTH(W2,1) -> 45077 | Z2: =EOMONTH(X2,1) -> 45107 | AA2: =EOMONTH(Y2,1) -> 45107 | AB2: =EOMONTH(Z2,1) -> 45138 | AC2: =EOMONTH(AA2,1) -> 45138 | AD2: =EOMONTH(AB2,1) -> 45169 | ... CL2: =EOMONTH(CJ2,1) -> 46081 | CM2: =EOMONTH(CL2,1) -> 46112
C3: Bookings
C4: =SUM(E4:U4)+W4+Y4+AA4+AC4+AE4+AG4+AI4+AK4+AM4+AO4+AQ4+AS4+AU4+AW4+AY4+BA4+BC4+BE4+BG4+BI4+BK4+BM4+BO4+BQ4+BS4+BU4+BW4+BY4+CA4+CC4+CE4+CG4+CI4+CK4 -> 18254652 | D4: Bookings (new customers) $ | E4: =E6+E7 -> 18000 | F4: =F6+F7 -> 27000 | G4: =G6+G7 -> 36000 | H4: =H6+H7 -> 24244 | I4: =I6+I7 -> 21500 | J4: =J6+J7 -> 80112 | K4: =K6+K7 -> 72033.33 | L4: =L6+L7 -> 41800 | ... CM4: =CM6+CM7 -> 682384.85 | CO4: Bookings (new customers) $ | CP4: =D4=CO4 -> TRUE
BG5: =BG4+BE4+BC4 -> 1134783.5 | BM5: =BM4+BK4+BI4 -> 1615813.5 | CP5: =D5=CO5 -> TRUE
C6: =SUM(E6:U6)+W6+Y6+AA6+AC6+AE6+AG6+AI6+AK6+AM6+AO6+AQ6+AS6+AU6+AW6+AY6+BA6+BC6+BE6+BG6+BI6+BK6+BM6+BO6+BQ6+BS6+BU6+BW6+BY6+CA6+CC6+CE6+CG6+CI6+CK6 -> 10466578 | D6: NA/EU | F6: 8000 | G6: 5000 | K6: 9000 | L6: 6500 | N6: 7500 | O6: 19500 | P6: 17400 | Q6: 25000 | R6: 45900 | S6: 20600 | T6: 33500 | U6: 137560 | V6: 158255.66 | W6: 109000 | X6: 154692.24 | Y6: 118390 | Z6: 160450.32 | AA6: 224750 | AB6: 155931.9 | AC6: 123000 | AD6: 182933.97 | AE6: 147875 | AF6: 216485.82 | AG6: 258480 | AH6: 224267.54 | AI6: 180300 | AJ6: 260600.36 | AK6: 156800 | AL6: 293828.25 | AM6: 212700 | AN6: =AN89*12 -> 171000 | AO6: 88000 | AP6: =AP89*12 -> 173430 | AQ6: 150120 | AR6: =AR89*12 -> 246285.6 | AS6: 207800 | AT6: =AT89*12 -> 225048.48 | AU6: 169000 | AV6: =AV89*12 -> 237900.44 | AW6: 287400 | AX6: =AX89*12 -> 222335.45 | AY6: 296550 | AZ6: =AZ89*12 -> 330279.01 | BA6: 201933.33 | BB6: =BB89*12 -> 377705.51 | BC6: 224350 | BD6: =BD89*12 -> 360666.55 | BE6: 272500 | BF6: =BF89*12 -> 382982.39 | BG6: 211050 | BH6: =BH89*12 -> 395356.86 | BI6: 340467 | BJ6: =BJ89*12 -> 437956.35 | BK6: 407800 | BL6: =BL89*12 -> 270886.61 | BM6: 316029 | BN6: =BN89*12 -> 286361.65 | BO6: 522156 | BP6: =BP89*12 -> 309960.92 | BQ6: 408400 | BR6: =BR89*12 -> 341250 | BS6: 311500 | BT6: =BT89*12 -> 328556.25 | BU6: 370540 | BV6: =BV89*12 -> 356228.91 | BW6: 571613 | BX6: =BX89*12 -> 364571.07 | BY6: 375045 | BZ6: =BZ89*12 -> 394883.99 | CA6: 510080 | CB6: =CB89*12 -> 426971.25 | CC6: 432255 | CD6: =CD89*12 -> 416030.93 | CE6: 538840 | CF6: =CF89*12 -> 439370.64 | CG6: 485920 | CH6: =CH89*12 -> 464278 | CI6: 566375 | CJ6: =CJ89*12 -> 490896.25 | CK6: 334100 | CL6: =CL89*12 -> 519381.31 | CM6: =CM89*12 -> 562995.76 | CO6: NA/EU | CP6: =D6=CO6 -> TRUE
A7: xx | C7: =SUM(E7:U7)+W7+Y7+AA7+AC7+AE7+AG7+AI7+AK7+AM7+AO7+AQ7+AS7+AU7+AW7+AY7+BA7+BC7+BE7+BG7+BI7+BK7+BM7+BO7+BQ7+BS7+BU7+BW7+BY7+CA7+CC7+CE7+CG7+CI7+CK7 -> 7788073.2 | D7: India/APAC | E7: 18000 | F7: 19000 | G7: 31000 | H7: 24244 | I7: 21500 | J7: 80112 | K7: 63033.33 | L7: 35300 | M7: 38400 | N7: 103585 | O7: 140643 | P7: 114552.67 | Q7: 96444 | R7: 114900 | S7: 128125 | T7: 158671 | U7: 239315 | V7: 208520 | W7: 149947 | X7: 213358 | Y7: 196220 | Z7: 224670.6 | AA7: 174531.25 | AB7: 223399.87 | AC7: 185095 | AD7: 228609.87 | AE7: 233875 | AF7: 233950.12 | AG7: 169187.5 | AH7: 239423.87 | AI7: 128575 | AJ7: 237845.89 | AK7: 166212.5 | AL7: 243417.04 | AM7: 206225.5 | AN7: =AN104*12 -> 132600 | AO7: 172431 | AP7: =AP104*12 -> 133986 | AQ7: 121764 | AR7: =AR104*12 -> 135386.76 | AS7: 204325 | AT7: =AT104*12 -> 161844.42 | AU7: 175412.75 | AV7: =AV104*12 -> 176209.09 | AW7: 164925 | AX7: =AX104*12 -> 183682.22 | AY7: 204409.5 | AZ7: =AZ104*12 -> 191163.96 | BA7: 170940.5 | BB7: =BB104*12 -> 191754.42 | BC7: 100080 | BD7: =BD104*12 -> 205871.64 | BE7: 221086 | BF7: =BF104*12 -> 220482.72 | BG7: 105717.5 | BH7: =BH104*12 -> 228205.96 | BI7: 162525.68 | BJ7: =BJ104*12 -> 229041.55 | BK7: 256553.44 | BL7: =BL104*12 -> 167316.27 | BM7: 132438.35 | BN7: =BN104*12 -> 173156.02 | BO7: 158773.01 | BP7: =BP104*12 -> 178609.98 | BQ7: 239459.72 | BR7: =BR104*12 -> 178933.93 | BS7: 154297.19 | BT7: =BT104*12 -> 173749.48 | BU7: 244624 | BV7: =BV104*12 -> 120332.96 | BW7: 243284 | BX7: =BX104*12 -> 120577.07 | BY7: 189244 | BZ7: =BZ104*12 -> 116761.32 | CA7: 191789.96 | CB7: =CB104*12 -> 115451.48 | CC7: 241960 | CD7: =CD104*12 -> 101255.19 | CE7: 248966.4 | CF7: =CF104*12 -> 111862.33 | CG7: 209521.32 | CH7: =CH104*12 -> 117412.14 | CI7: 229089 | CJ7: =CJ104*12 -> 113569.26 | CK7: 207762.14 | CL7: =CL104*12 -> 119138 | CM7: =CM104*12 -> 119389.09 | CO7: India/APAC | CP7: =D7=CO7 -> TRUE
CI8: =CI19+CG19+CE19 -> 385761.52 | CP8: =D8=CO8 -> TRUE
C9: =SUM(E9:U9)+W9+Y9+AA9+AC9+AE9+AG9+AI9+AK9+AM9+AO9+AQ9+AS9+AU9+AW9+AY9+BA9+BC9+BE9+BG9+BI9+BK9+BM9+BO9+BQ9+BS9+BU9+BW9+BY9+CA9+CC9+CE9+CG9+CI9+CK9 -> 21019628 | D9: Net ARR (New + Expansion) | E9: =SUM(E11:E12) -> 18000 | F9: =SUM(F11:F12) -> 27000 | G9: =SUM(G11:G12) -> 36000 | H9: =SUM(H11:H12) -> 24244 | I9: =SUM(I11:I12) -> 21500 | J9: =SUM(J11:J12) -> 80112 | K9: =SUM(K11:K12) -> 72033.33 | L9: =SUM(L11:L12) -> 41800 | ... CM9: =SUM(CM11:CM12) -> 913036.42 | CO9: Net ARR (New + Expansion) | CP9: =D9=CO9 -> TRUE
AB10: 22141 | AH10: 18483 | BG10: =BG9+BE9+BC9 -> 1387886.1 | BM10: =BM9+BK9+BI9 -> 1789807.6 | CI10: =CI9+CG9+CE9 -> 2664473.2 | CP10: =D10=CO10 -> TRUE
D11: NA/EU | E11: =E6+E21 -> 0 | F11: =F6+F21 -> 8000 | G11: =G6+G21 -> 5000 | H11: =H6+H21 -> 0 | I11: =I6+I21 -> 0 | J11: =J6+J21 -> 0 | K11: =K6+K21 -> 9000 | L11: =L6+L21 -> 6500 | ... CM11: =CM6+CM21 -> 689264.86 | CO11: NA/EU | CP11: =D11=CO11 -> TRUE
D12: India/APAC | E12: =E7+E22 -> 18000 | F12: =F7+F22 -> 19000 | G12: =G7+G22 -> 31000 | H12: =H7+H22 -> 24244 | I12: =I7+I22 -> 21500 | J12: =J7+J22 -> 80112 | K12: =K7+K22 -> 63033.33 | L12: =L7+L22 -> 35300 | ... CM12: =CM7+CM22 -> 223771.55 | CO12: India/APAC | CP12: =D12=CO12 -> TRUE
CI13: =CI11+CG11+CE11 -> 1769385 | CK13: =CI12+CG12+CE12 -> 895088.24 | CP13: =D13=CO13 -> TRUE
D14: Net New ARR | E14: =E16+E17 -> 18000 | F14: =F16+F17 -> 27000 | G14: =G16+G17 -> 36000 | H14: =H16+H17 -> 24244 | I14: =I16+I17 -> 21500 | J14: =J16+J17 -> 80112 | K14: =K16+K17 -> 72033.33 | L14: =L16+L17 -> 41800 | ... CM14: =CM16+CM17 -> 831413.04 | CO14: Net New ARR | CP14: =D14=CO14 -> TRUE
CP15: =D15=CO15 -> TRUE
D16: NA/EU | E16: =(E95-E88)*12 -> 0 | F16: =(F95-F88)*12 -> 8000 | G16: =(G95-G88)*12 -> 5000 | H16: =(H95-H88)*12 -> 0 | I16: =(I95-I88)*12 -> 0 | J16: =(J95-J88)*12 -> 0 | K16: =(K95-K88)*12 -> 9000 | L16: =(L95-L88)*12 -> 6500 | ... CM16: =(CM95-CM88)*12 -> 652317.55 | CO16: NA/EU | CP16: =D16=CO16 -> TRUE
D17: India/APAC | E17: =(E110-E103)*12 -> 18000 | F17: =(F110-F103)*12 -> 19000 | G17: =(G110-G103)*12 -> 31000 | H17: =(H110-H103)*12 -> 24244 | I17: =(I110-I103)*12 -> 21500 | J17: =(J110-J103)*12 -> 80112 | K17: =(K110-K103)*12 -> 63033.33 | L17: =(L110-L103)*12 -> 35300 | ... CM17: =(CM110-CM103)*12 -> 179095.49 | CO17: India/APAC | CP17: =D17=CO17 -> TRUE
CP18: =D18=CO18 -> TRUE
C19: =SUM(E19:U19)+W19+Y19+AA19+AC19+AE19+AG19+AI19+AK19+AM19+AO19+AQ19+AS19+AU19+AW19+AY19+BA19+BC19+BE19+BG19+BI19+BK19+BM19+BO19+BQ19+BS19+BU19+BW19+BY19+CA19+CC19+CE19+CG19+CI19+CK19 -> 2764976.6 | D19: Expansion | E19: =E21+E22 -> 0 | F19: =F21+F22 -> 0 | G19: =G21+G22 -> 0 | H19: =H21+H22 -> 0 | I19: =I21+I22 -> 0 | J19: =J21+J22 -> 0 | K19: =K21+K22 -> 0 | L19: =L21+L22 -> 0 | ... CM19: =CM21+CM22 -> 230651.57 | CO19: Expansion | CP19: =D19=CO19 -> TRUE
BI20: =BI19+BI24 -> 54989.203 | BJ20: =BJ19+BJ24 -> 91525.917 | BK20: =BK19+BK24 -> 67573.808 | BL20: =BL19+BL24 -> 101508.12 | BM20: =BM19+BM24 -> 57990.76 | BN20: =BN19+BN24 -> 108998.23 | BO20: =BO19+BO24 -> 79131.497 | BP20: =BP19+BP24 -> 113385.58 | ... CE20: =CE19+CE24 -> 116652.97 | CP20: =D20=CO20 -> TRUE
A21: x | C21: =SUM(E21:U21)+W21+Y21+AA21+AC21+AE21+AG21+AI21+AK21+AM21+AO21+AQ21+AS21+AU21+AW21+AY21+BA21+BC21+BE21+BG21+BI21+BK21+BM21+BO21+BQ21+BS21+BU21+BW21+BY21+CA21+CC21+CE21+CG21+CI21+CK21 -> 985029.24 | D21: NA/EU | E21: 0 | F21: 0 | G21: 0 | H21: 0 | I21: 0 | J21: 0 | K21: 0 | L21: 0 | M21: 0 | N21: 0 | O21: 0 | P21: 0 | Q21: 0 | R21: 0 | S21: 0 | T21: 0 | U21: 6000 | V21: =V90*12 -> 250 | W21: 0 | X21: =X90*12 -> 161.25 | Y21: 0 | Z21: =Z90*12 -> 0 | AA21: 3500 | AB21: =AB90*12 -> 372.68906 | AC21: 10000 | AD21: =AD90*12 -> 1034.9886 | AE21: 26200 | AF21: =AF90*12 -> 929.56999 | AG21: 1000 | AH21: =AH90*12 -> 0 | AI21: 1500 | AJ21: =AJ90*12 -> 0 | AK21: 4000 | AL21: =AL90*12 -> 0 | AM21: 4100 | AN21: =AN90*12 -> 8000 | AO21: 23000 | AP21: =AP90*12 -> 8300 | AQ21: 6000 | AR21: =AR90*12 -> 8612 | AS21: 13500 | AT21: =AT90*12 -> 8936.51 | AU21: 17000 | AV21: =AV90*12 -> 9274.0628 | AW21: 26500 | AX21: =AX90*12 -> 9625.2151 | AY21: 25006 | AZ21: =AZ90*12 -> 14010.835 | BA21: 49500 | BB21: =BB90*12 -> 14591.972 | BC21: 25000 | BD21: =BD90*12 -> 15198.583 | BE21: 21800 | BF21: =BF90*12 -> 20485.82 | BG21: 47500 | BH21: =BH90*12 -> 21379.634 | BI21: 7500 | BJ21: =BJ90*12 -> 29235.393 | BK21: 22018.24 | BL21: =BL90*12 -> 20180.541 | BM21: 2500 | BN21: =BN90*12 -> 24289.299 | BO21: 25000 | BP21: =BP90*12 -> 28422.528 | BQ21: 79250 | BR21: =BR90*12 -> 28507.795 | BS21: 16600 | BT21: =BT90*12 -> 36762.838 | BU21: 18750 | BV21: =BV90*12 -> 36873.127 | BW21: 66500 | BX21: =BX90*12 -> 45202.356 | BY21: 51295 | BZ21: =BZ90*12 -> 49459.596 | CA21: 43600 | CB21: =CB90*12 -> 62009.969 | CC21: 80975 | CD21: =CD90*12 -> 62195.999 | CE21: 60450 | CF21: =CF90*12 -> 74859.104 | CG21: 62200 | CH21: =CH90*12 -> 83426.313 | CI21: 55600 | CJ21: =CJ90*12 -> 92044.251 | CK21: 81685 | CL21: =CL90*12 -> 109105.91 | CM21: =CM90*12 -> 126269.11 | CO21: NA/EU | CP21: =D21=CO21 -> TRUE
A22: xx | C22: =SUM(E22:U22)+W22+Y22+AA22+AC22+AE22+AG22+AI22+AK22+AM22+AO22+AQ22+AS22+AU22+AW22+AY22+BA22+BC22+BE22+BG22+BI22+BK22+BM22+BO22+BQ22+BS22+BU22+BW22+BY22+CA22+CC22+CE22+CG22+CI22+CK22 -> 1779947.3 | D22: India/APAC | E22: 0 | F22: 0 | G22: 0 | H22: 0 | I22: 0 | J22: 0 | K22: 0 | L22: 0 | M22: 0 | N22: 0 | O22: 2380 | P22: 2000 | Q22: 0 | R22: 4533 | S22: 2500 | T22: 3350 | U22: 14250 | V22: =V105*12 -> 3705 | W22: 19375 | X22: =X105*12 -> 5011.2738 | Y22: 39810 | Z22: =Z105*12 -> 3757.3991 | AA22: 45550 | AB22: =AB105*12 -> 3298.174 | AC22: 13465 | AD22: =AD105*12 -> 11113.106 | AE22: 33075 | AF22: =AF105*12 -> 7146.0632 | AG22: 24237.5 | AH22: =AH105*12 -> 7737.6472 | AI22: 40896 | AJ22: =AJ105*12 -> 9102.9793 | AK22: 38887.5 | AL22: =AL105*12 -> 10079.274 | AM22: 54382.15 | AN22: =AN105*12 -> 33000 | AO22: 40308.33 | AP22: =AP105*12 -> 36050 | AQ22: 50536 | AR22: =AR105*12 -> 37131.5 | AS22: 23250 | AT22: =AT105*12 -> 38245.445 | AU22: 62912.5 | AV22: =AV105*12 -> 39392.808 | AW22: 88944 | AX22: =AX105*12 -> 44052.415 | AY22: 47825 | AZ22: =AZ105*12 -> 47762.092 | BA22: 51679 | BB22: =BB105*12 -> 49194.955 | BC22: 61397 | BD22: =BD105*12 -> 50670.803 | BE22: 56343 | BF22: =BF105*12 -> 54800.474 | BG22: 41062.64 | BH22: =BH105*12 -> 56444.488 | BI22: 46589.203 | BJ22: =BJ105*12 -> 62290.524 | BK22: 42340.568 | BL22: =BL105*12 -> 81327.578 | BM22: 53046.072 | BN22: =BN105*12 -> 84708.929 | BO22: 50470.247 | BP22: =BP105*12 -> 84963.056 | BQ22: 65498.88 | BR22: =BR105*12 -> 88374.165 | BS22: 57345.786 | BT22: =BT105*12 -> 88639.287 | BU22: 58456 | BV22: =BV105*12 -> 92080.391 | BW22: 83316.4 | BX22: =BX105*12 -> 92356.632 | BY22: 53964.8 | BZ22: =BZ105*12 -> 92633.702 | CA22: 59601 | CB22: =CB105*12 -> 99319.3 | CC22: 104729.05 | CD22: =CD105*12 -> 99617.258 | CE22: 37352.04 | CF22: =CF105*12 -> 99916.11 | CG22: 87759 | CH22: =CH105*12 -> 100215.86 | CI22: 82400.48 | CJ22: =CJ105*12 -> 103758.97 | CK22: 34129.2 | CL22: =CL105*12 -> 104070.25 | CM22: =CM105*12 -> 104382.46 | CO22: India/APAC | CP22: =D22=CO22 -> TRUE
CE23: =CE20+CC20+CA20+BY20+BW20+BU20+BS20+BQ20+BO20+BM20+BK20+BI20 -> 1295229.9 | CP23: =D23=CO23 -> TRUE
C24: =SUM(E24:U24)+W24+Y24+AA24+AC24+AE24+AG24+AI24+AK24+AM24+AO24+AQ24+AS24+AU24+AW24+AY24+BA24+BC24+BE24+BG24+BI24+BK24+BM24+BO24+BQ24+BS24+BU24+BW24+BY24+CA24+CC24+CE24+CG24+CI24+CK24 -> 156076.82 | D24: Revenue Expansion | E24: =E26+E27 -> 0 | F24: =F26+F27 -> 0 | G24: =G26+G27 -> 0 | H24: =H26+H27 -> 0 | I24: =I26+I27 -> 0 | J24: =J26+J27 -> 0 | K24: =K26+K27 -> 0 | L24: =L26+L27 -> 0 | ... U24: =U26+U27 -> 0 | V24: 0 | W24: =W26+W27 -> 0 | X24: 0 | Y24: =Y26+Y27 -> 0 | Z24: 0 | AA24: =AA26+AA27 -> 1500 | AB24: 0 | AC24: =AC26+AC27 -> 0 | AD24: 0 | AE24: =AE26+AE27 -> 0 | AF24: 0 | AG24: =AG26+AG27 -> 0 | AH24: 0 | AI24: =AI26+AI27 -> 0 | AJ24: 0 | AK24: =AK26+AK27 -> 0 | AL24: 0 | AM24: =AM26+AM27 -> 563 | AN24: 0 | AO24: =AO26+AO27 -> 473 | AP24: 0 | AQ24: =AQ26+AQ27 -> 150 | AR24: 0 | AS24: =AS26+AS27 -> 0 | AT24: 0 | AU24: =AU26+AU27 -> 5325 | AV24: 0 | AW24: =AW26+AW27 -> 2587.5 | AX24: 0 | AY24: =AY26+AY27 -> 6522.5 | AZ24: 0 | BA24: =BA26+BA27 -> 2862.5 | BB24: 0 | BC24: =BC26+BC27 -> 4696.875 | BD24: 0 | BE24: =BE26+BE27 -> 2682.5 | BF24: 0 | BG24: =BG26+BG27 -> 2437.5 | BH24: 0 | BI24: =BI26+BI27 -> 900 | BJ24: 0 | BK24: =BK26+BK27 -> 3215 | BL24: 0 | BM24: =BM26+BM27 -> 2444.6875 | BN24: 0 | BO24: =BO26+BO27 -> 3661.25 | BP24: 0 | BQ24: =BQ26+BQ27 -> 3172.5 | BR24: 0 | BS24: =BS26+BS27 -> 6575 | BT24: 0 | BU24: =BU26+BU27 -> 9924.375 | BV24: 0 | BW24: =BW26+BW27 -> 21371.737 | BX24: 0 | BY24: =BY26+BY27 -> 14000 | BZ24: 0 | CA24: =CA26+CA27 -> 6918.175 | CB24: 0 | CC24: =CC26+CC27 -> 17047.969 | CD24: 0 | CE24: =CE26+CE27 -> 18850.93 | CF24: 0 | CG24: =CG26+CG27 -> 3898.0817 | CH24: 0 | CI24: =CI26+CI27 -> 4010 | CJ24: 0 | CK24: =CK26+CK27 -> 10286.74 | CL24: 0 | CM24: 0 | CO24: Revenue Expansion | CP24: =D24=CO24 -> TRUE
CP25: =D25=CO25 -> TRUE
C26: =SUM(E26:U26)+W26+Y26+AA26+AC26+AE26+AG26+AI26+AK26+AM26+AO26+AQ26+AS26+AU26+AW26+AY26+BA26+BC26+BE26+BG26+BI26+BK26+BM26+BO26+BQ26+BS26+BU26+BW26+BY26+CA26+CC26+CE26+CG26+CI26+CK26 -> 104108.74 | D26: NA/EU | E26: 0 | F26: 0 | G26: 0 | H26: 0 | I26: 0 | J26: 0 | K26: 0 | L26: 0 | M26: 0 | N26: 0 | O26: 0 | P26: 0 | Q26: 0 | R26: 0 | S26: 0 | T26: 0 | U26: 0 | V26: 0 | W26: 0 | X26: 0 | Y26: 0 | Z26: 0 | AA26: 1500 | AB26: 0 | AC26: 0 | AD26: 0 | AE26: 0 | AF26: 0 | AG26: 0 | AH26: 0 | AI26: 0 | AJ26: 0 | AK26: 0 | AL26: 0 | AM26: 0 | AN26: 0 | AO26: 0 | AP26: 0 | AR26: 0 | AS26: 0 | AT26: 0 | AU26: 2325 | AV26: 0 | AW26: 1537.5 | AX26: 0 | AY26: 5310 | AZ26: 0 | BA26: 1600 | BB26: 0 | BC26: 2490 | BD26: 0 | BE26: 2330 | BF26: 0 | BG26: 1800 | BH26: 0 | BJ26: 0 | BK26: 3215 | BL26: 0 | BM26: 1352.5 | BN26: 0 | BO26: 2436 | BP26: 0 | BQ26: 3172.5 | BR26: 0 | BS26: 5825 | BT26: 0 | BU26: 6097.5 | BV26: 0 | BW26: 13455.45 | BX26: 0 | BY26: 10472.5 | BZ26: 0 | CA26: 5342.5 | CB26: 0 | CC26: 7452.5 | CD26: 0 | CE26: 13054.75 | CF26: 0 | CG26: 1528.8 | CH26: 0 | CI26: 3310 | CJ26: 0 | CK26: 8501.24 | CL26: 0 | CM26: 0 | CO26: NA/EU | CP26: =D26=CO26 -> TRUE
C27: =SUM(E27:U27)+W27+Y27+AA27+AC27+AE27+AG27+AI27+AK27+AM27+AO27+AQ27+AS27+AU27+AW27+AY27+BA27+BC27+BE27+BG27+BI27+BK27+BM27+BO27+BQ27+BS27+BU27+BW27+BY27+CA27+CC27+CE27+CG27+CI27+CK27 -> 51968.081 | D27: India/APAC | E27: 0 | F27: 0 | G27: 0 | H27: 0 | I27: 0 | J27: 0 | K27: 0 | L27: 0 | M27: 0 | N27: 0 | O27: 0 | P27: 0 | Q27: 0 | R27: 0 | S27: 0 | T27: 0 | U27: 0 | V27: 0 | W27: 0 | X27: 0 | Y27: 0 | Z27: 0 | AA27: 0 | AB27: 0 | AC27: 0 | AD27: 0 | AE27: 0 | AF27: 0 | AG27: 0 | AH27: 0 | AI27: 0 | AJ27: 0 | AK27: 0 | AL27: 0 | AM27: 563 | AN27: 0 | AO27: 473 | AP27: 0 | AQ27: 150 | AR27: 0 | AS27: 0 | AT27: 0 | AU27: 3000 | AV27: 0 | AW27: 1050 | AX27: 0 | AY27: 1212.5 | AZ27: 0 | BA27: 1262.5 | BB27: 0 | BC27: 2206.875 | BD27: 0 | BE27: 352.5 | BF27: 0 | BG27: 637.5 | BH27: 0 | BI27: 900 | BJ27: 0 | BL27: 0 | BM27: 1092.1875 | BN27: 0 | BO27: 1225.25 | BP27: 0 | BR27: 0 | BS27: 750 | BT27: 0 | BU27: 3826.875 | BV27: 0 | BW27: 7916.2875 | BX27: 0 | BY27: 3527.5 | BZ27: 0 | CA27: 1575.675 | CB27: 0 | CC27: 9595.469 | CD27: 0 | CE27: 5796.18 | CF27: 0 | CG27: 2369.2817 | CH27: 0 | CI27: 700 | CJ27: 0 | CK27: 1785.5 | CL27: 0 | CM27: 0 | CO27: India/APAC | CP27: =D27=CO27 -> TRUE
CP28: =D28=CO28 -> TRUE
C29: =SUM(E29:U29)+W29+Y29+AA29+AC29+AE29+AG29+AI29+AK29+AM29+AO29+AQ29+AS29+AU29+AW29+AY29+BA29+BC29+BE29+BG29+BI29+BK29+BM29+BO29+BQ29+BS29+BU29+BW29+BY29+CA29+CC29+CE29+CG29+CI29+CK29 -> 3584579.5 | D29: Logo Churn | E29: =SUM(E31:E32) -> 0 | F29: =SUM(F31:F32) -> 0 | G29: =SUM(G31:G32) -> 0 | H29: =SUM(H31:H32) -> 0 | I29: =SUM(I31:I32) -> 0 | J29: =SUM(J31:J32) -> 0 | K29: =SUM(K31:K32) -> 0 | L29: =SUM(L31:L32) -> 0 | ... CM29: =SUM(CM31:CM32) -> 81623.376 | CO29: Logo Churn | CP29: =D29=CO29 -> TRUE
BI30: =BI29+BI34 -> 141515.5 | BK30: =BK29+BK34 -> 119395 | BM30: =BM29+BM34 -> 111955 | BO30: =BO29+BO34 -> 186375 | BQ30: =BQ29+BQ34 -> 410620.33 | BS30: =BS29+BS34 -> 158861 | BU30: =BU29+BU34 -> 30326.4 | BW30: =BW29+BW34 -> 218023 | BY30: =BY29+BY34 -> 185123.5 | CA30: =CA29+CA34 -> 234320 | CC30: =CC29+CC34 -> 270812.94 | CE30: =CE29+CE34 -> 412544.22 | CP30: =D30=CO30 -> TRUE
C31: =SUM(E31:U31)+W31+Y31+AA31+AC31+AE31+AG31+AI31+AK31+AM31+AO31+AQ31+AS31+AU31+AW31+AY31+BA31+BC31+BE31+BG31+BI31+BK31+BM31+BO31+BQ31+BS31+BU31+BW31+BY31+CA31+CC31+CE31+CG31+CI31+CK31 -> 1497526 | D31: NA/EU | E31: 0 | F31: 0 | G31: 0 | H31: 0 | I31: 0 | J31: 0 | K31: 0 | L31: 0 | M31: 0 | N31: 0 | O31: 0 | P31: 0 | Q31: 0 | R31: 0 | S31: 0 | T31: 0 | U31: 0 | V31: =-V92*12 -> 750 | W31: 0 | X31: =-X92*12 -> 450 | Y31: 0 | Z31: =-Z92*12 -> 0 | AA31: 6600 | AB31: =-AB92*12 -> 900 | AC31: 0 | AD31: =-AD92*12 -> 2325 | AE31: 0 | AF31: =-AF92*12 -> 647.5 | AG31: 5000 | AH31: =-AH92*12 -> 0 | AI31: 8000 | AJ31: =-AJ92*12 -> 0 | AK31: 50840 | AL31: =-AL92*12 -> 0 | AM31: 18000 | AN31: =-AN92*12 -> 22823.244 | AO31: 0 | AP31: =-AP92*12 -> 24697.365 | AQ31: 16000 | AR31: =-AR92*12 -> 26581.757 | AS31: 21000 | AT31: =-AT92*12 -> 26878.085 | AU31: 20000 | AV31: =-AV92*12 -> 29156.261 | AW31: 10000 | AX31: =-AX92*12 -> 31554.461 | AY31: 0 | AZ31: =-AZ92*12 -> 24551.949 | BA31: 16500 | BB31: =-BB92*12 -> 16943.657 | BC31: 30500 | BD31: =-BD92*12 -> 18820.426 | BE31: 14000 | BF31: =-BF92*12 -> 20605.65 | BG31: 20000 | BH31: =-BH92*12 -> 22519.963 | BI31: 47200 | BJ31: =-BJ92*12 -> 24491.045 | BK31: 63000 | BL31: =-BL92*12 -> 14278.17 | BM31: 13300 | BN31: =-BN92*12 -> 15108.537 | BO31: 84000 | BP31: =-BP92*12 -> 15995.164 | BQ31: 151866 | BR31: =-BR92*12 -> 28270.548 | BS31: 63500 | BT31: =-BT92*12 -> 29977.984 | BU31: 7000 | BV31: =-BV92*12 -> 31654.69 | BW31: 96950 | BX31: =-BX92*12 -> 23423.349 | BY31: 54870 | BZ31: =-BZ92*12 -> 24775.574 | CA31: 129910 | CB31: =-CB92*12 -> 26244.062 | CC31: 148350 | CD31: =-CD92*12 -> 27863.642 | CE31: 202080 | CF31: =-CF92*12 -> 29439.913 | CG31: 42660 | CH31: =-CH92*12 -> 31136.678 | CI31: 95850 | CJ31: =-CJ92*12 -> 32944.665 | CK31: 60550 | CL31: =-CL92*12 -> 34869.65 | CM31: =-CM92*12 -> 36947.312 | CO31: NA/EU | CP31: =D31=CO31 -> TRUE
C32: =SUM(E32:U32)+W32+Y32+AA32+AC32+AE32+AG32+AI32+AK32+AM32+AO32+AQ32+AS32+AU32+AW32+AY32+BA32+BC32+BE32+BG32+BI32+BK32+BM32+BO32+BQ32+BS32+BU32+BW32+BY32+CA32+CC32+CE32+CG32+CI32+CK32 -> 2087053.5 | D32: India/APAC | E32: 0 | F32: 0 | G32: 0 | H32: 0 | I32: 0 | J32: 0 | K32: 0 | L32: 0 | M32: 0 | N32: 0 | O32: 0 | P32: 0 | Q32: 12000 | R32: 15000 | S32: 4000 | T32: 4500 | U32: 5500 | V32: =-V107*12 -> 11115 | W32: 33000 | X32: =-X107*12 -> 13984.95 | Y32: 22000 | Z32: =-Z107*12 -> 9754.2 | AA32: 4000 | AB32: =-AB107*12 -> 7964.7 | AC32: 28660 | AD32: =-AD107*12 -> 24964.5 | AE32: 9000 | AF32: =-AF107*12 -> 4977.652 | AG32: 40300 | AH32: =-AH107*12 -> 4888.3552 | AI32: 35666.67 | AJ32: =-AJ107*12 -> 5215.9514 | AK32: 58665 | AL32: =-AL107*12 -> 5238.1192 | AM32: 63039.25 | AN32: =-AN107*12 -> 89300.31 | AO32: 43225 | AP32: =-AP107*12 -> 91398.551 | AQ32: 58771 | AR32: =-AR107*12 -> 93561.081 | AS32: 81375 | AT32: =-AT107*12 -> 95732.404 | AU32: 25418.65 | AV32: =-AV107*12 -> 98602.234 | AW32: 53250 | AX32: =-AX107*12 -> 101819.72 | AY32: 6250 | AZ32: =-AZ107*12 -> 72740.557 | BA32: 74511 | BB32: =-BB107*12 -> 39946.358 | BC32: 48425 | BD32: =-BD107*12 -> 41956.389 | BE32: 65925 | BF32: =-BF107*12 -> 44102.249 | BG32: 67675 | BH32: =-BH107*12 -> 46414.059 | BI32: 69931 | BJ32: =-BJ107*12 -> 48796.423 | BK32: 54395 | BL32: =-BL107*12 -> 48952.643 | BM32: 91300 | BN32: =-BN107*12 -> 50949.555 | BO32: 97375 | BP32: =-BP107*12 -> 53018.709 | BQ32: 155434.33 | BR32: =-BR107*12 -> 44099.401 | BS32: 40413 | BT32: =-BT107*12 -> 45885.071 | BU32: 15826.4 | BV32: =-BV107*12 -> 47617.101 | BW32: 117060 | BX32: =-BX107*12 -> 48935.471 | BY32: 100590.5 | BZ32: =-BZ107*12 -> 50247.456 | CA32: 87045 | CB32: =-CB107*12 -> 51520.637 | CC32: 75725 | CD32: =-CD107*12 -> 46223.308 | CE32: 138268.2 | CF32: =-CF107*12 -> 47305.852 | CG32: 54268 | CH32: =-CH107*12 -> 48457.16 | CI32: 65384.28 | CJ32: =-CJ107*12 -> 42549.734 | CK32: 63881.196 | CL32: =-CL107*12 -> 43598.405 | CM32: =-CM107*12 -> 44676.064 | CO32: India/APAC | CP32: =D32=CO32 -> TRUE
CE33: =CE30+CC30+CA30+BY30+BW30+BU30+BS30+BQ30+BO30+BM30+BK30+BI30 -> 2479871.9 | CP33: =D33=CO33 -> TRUE
C34: =SUM(E34:U34)+W34+Y34+AA34+AC34+AE34+AG34+AI34+AK34+AM34+AO34+AQ34+AS34+AU34+AW34+AY34+BA34+BC34+BE34+BG34+BI34+BK34+BM34+BO34+BQ34+BS34+BU34+BW34+BY34+CA34+CC34+CE34+CG34+CI34+CK34 -> 494513.7 | D34: Revenue Churn | E34: =SUM(E36:E37) -> 0 | F34: =SUM(F36:F37) -> 0 | G34: =SUM(G36:G37) -> 0 | H34: =SUM(H36:H37) -> 0 | I34: =SUM(I36:I37) -> 0 | J34: =SUM(J36:J37) -> 0 | K34: =SUM(K36:K37) -> 0 | L34: =SUM(L36:L37) -> 0 | ... CM34: =SUM(CM36:CM37) -> 0 | CO34: Revenue Churn | CP34: =D34=CO34 -> TRUE
CG35: =CE29+CG29+CI29+CE34+CG34+CI34 -> 701731.31 | CP35: =D35=CO35 -> TRUE
C36: =SUM(E36:U36)+W36+Y36+AA36+AC36+AE36+AG36+AI36+AK36+AM36+AO36+AQ36+AS36+AU36+AW36+AY36+BA36+BC36+BE36+BG36+BI36+BK36+BM36+BO36+BQ36+BS36+BU36+BW36+BY36+CA36+CC36+CE36+CG36+CI36+CK36 -> 110371.93 | D36: NA/EU | E36: 0 | F36: 0 | G36: 0 | H36: 0 | I36: 0 | J36: 0 | K36: 0 | L36: 0 | M36: 0 | N36: 0 | O36: 0 | P36: 0 | Q36: 0 | R36: 0 | S36: 0 | T36: 0 | U36: 0 | V36: =-V93*12 -> 0 | W36: 0 | X36: =-X93*12 -> 0 | Y36: 0 | Z36: =-Z93*12 -> 0 | AA36: 0 | AB36: =-AB93*12 -> 0 | AC36: 0 | AD36: =-AD93*12 -> 0 | AE36: 0 | AF36: =-AF93*12 -> 0 | AG36: 0 | AH36: =-AH93*12 -> 0 | AI36: 2000 | AJ36: =-AJ93*12 -> 0 | AK36: 0 | AL36: =-AL93*12 -> 0 | AM36: 0 | AN36: =-AN93*12 -> 0 | AO36: 833 | AP36: =-AP93*12 -> 0 | AQ36: 0 | AR36: =-AR93*12 -> 0 | AS36: 300 | AT36: =-AT93*12 -> 0 | AU36: 0 | AV36: =-AV93*12 -> 0 | AW36: 0 | AX36: =-AX93*12 -> 0 | AY36: 0 | AZ36: =-AZ93*12 -> 0 | BA36: 0 | BB36: =-BB93*12 -> 0 | BC36: 0 | BD36: =-BD93*12 -> 0 | BE36: 0 | BF36: =-BF93*12 -> 0 | BG36: 0 | BH36: =-BH93*12 -> 0 | BI36: 4500 | BJ36: =-BJ93*12 -> 0 | BK36: 2000 | BL36: =-BL93*12 -> 0 | BM36: 0 | BN36: =-BN93*12 -> 0 | BO36: 0 | BP36: =-BP93*12 -> 0 | BQ36: 9750 | BR36: =-BR93*12 -> 0 | BS36: 12600 | BT36: =-BT93*12 -> 0 | BU36: 0 | BV36: =-BV93*12 -> 0 | BW36: 0 | BX36: =-BX93*12 -> 0 | BY36: 8500 | BZ36: =-BZ93*12 -> 0 | CA36: 10000 | CB36: =-CB93*12 -> 0 | CC36: 11981.425 | CD36: =-CD93*12 -> 0 | CE36: 29300 | CF36: =-CF93*12 -> 0 | CG36: 7087.5 | CH36: =-CH93*12 -> 0 | CI36: 3000 | CJ36: =-CJ93*12 -> 0 | CK36: 8520 | CL36: =-CL93*12 -> 0 | CM36: =-CM93*12 -> 0 | CO36: NA/EU | CP36: =D36=CO36 -> TRUE
C37: =SUM(E37:U37)+W37+Y37+AA37+AC37+AE37+AG37+AI37+AK37+AM37+AO37+AQ37+AS37+AU37+AW37+AY37+BA37+BC37+BE37+BG37+BI37+BK37+BM37+BO37+BQ37+BS37+BU37+BW37+BY37+CA37+CC37+CE37+CG37+CI37+CK37 -> 384141.77 | D37: India/APAC | E37: 0 | F37: 0 | G37: 0 | H37: 0 | I37: 0 | J37: 0 | K37: 0 | L37: 0 | M37: 0 | N37: 0 | O37: 0 | P37: 0 | Q37: 561 | R37: 0 | S37: 1500 | T37: 0 | U37: 0 | V37: =-V108*12 -> 0 | W37: 5789 | X37: =-X108*12 -> 0 | Y37: 3500 | Z37: =-Z108*12 -> 0 | AA37: 1000 | AB37: =-AB108*12 -> 0 | AC37: 1452 | AD37: =-AD108*12 -> 0 | AE37: 7300 | AF37: =-AF108*12 -> 0 | AG37: 4034 | AH37: =-AH108*12 -> 0 | AI37: 4854 | AJ37: =-AJ108*12 -> 0 | AK37: 6231 | AL37: =-AL108*12 -> 0 | AM37: 6000 | AN37: =-AN108*12 -> 0 | AO37: 5111.5 | AP37: =-AP108*12 -> 0 | AQ37: 7100 | AR37: =-AR108*12 -> 0 | AS37: 0 | AT37: =-AT108*12 -> 0 | AU37: 0 | AV37: =-AV108*12 -> 0 | AW37: 0 | AX37: =-AX108*12 -> 0 | AY37: 0 | AZ37: =-AZ108*12 -> 0 | BA37: 1125 | BB37: =-BB108*12 -> 0 | BC37: 0 | BD37: =-BD108*12 -> 0 | BE37: 0 | BF37: =-BF108*12 -> 0 | BG37: 5500 | BH37: =-BH108*12 -> 0 | BI37: 19884.5 | BJ37: =-BJ108*12 -> 0 | BK37: 0 | BL37: =-BL108*12 -> 0 | BM37: 7355 | BN37: =-BN108*12 -> 0 | BO37: 5000 | BP37: =-BP108*12 -> 0 | BQ37: 93570 | BR37: =-BR108*12 -> 0 | BS37: 42348 | BT37: =-BT108*12 -> 0 | BU37: 7500 | BV37: =-BV108*12 -> 0 | BW37: 4013 | BX37: =-BX108*12 -> 0 | BY37: 21163 | BZ37: =-BZ108*12 -> 0 | CA37: 7365 | CB37: =-CB108*12 -> 0 | CC37: 34756.519 | CD37: =-CD108*12 -> 0 | CE37: 42896.022 | CF37: =-CF108*12 -> 0 | CG37: 6541.232 | CH37: =-CH108*12 -> 0 | CI37: 14396.08 | CJ37: =-CJ108*12 -> 0 | CK37: 16295.92 | CL37: =-CL108*12 -> 0 | CM37: =-CM108*12 -> 0 | CO37: India/APAC | CP37: =D37=CO37 -> TRUE
CP38: =D38=CO38 -> TRUE
C39: =SUM(E39:U39)+W39+Y39+AA39+AC39+AE39+AG39+AI39+AK39+AM39+AO39+AQ39+AS39+AU39+AW39+AY39+BA39+BC39+BE39+BG39+BI39+BK39+BM39+BO39+BQ39+BS39+BU39+BW39+BY39+CA39+CC39+CE39+CG39+CI39+CK39 -> 298742.54 | D39: One time revenue booked for the month (GMV) | M39: 2000 | N39: 783 | O39: 1280 | P39: 3530 | Q39: 5842 | R39: 2709 | S39: 2000 | T39: 0 | U39: 5775 | V39: 0 | W39: 16091 | X39: 0 | Y39: 925 | Z39: 0 | AA39: 4250 | AB39: 0 | AC39: 1075 | AD39: 0 | AE39: 1000 | AF39: 0 | AG39: 2775 | AH39: 0 | AI39: 5300 | AJ39: 0 | AK39: 250 | AL39: 0 | AM39: 8283.41 | AN39: 0 | AO39: 7742.5 | AP39: 0 | AQ39: 1625 | AR39: 0 | AS39: 19010 | AT39: 0 | AU39: 9075 | AV39: 0 | AW39: 14833.75 | AX39: 0 | AY39: 3600 | AZ39: 0 | BA39: 9900 | BB39: 0 | BC39: 3820 | BD39: 0 | BE39: 11692 | BF39: 0 | BG39: 3650 | BH39: 0 | BI39: 9390 | BJ39: 0 | BK39: 5800 | BL39: 0 | BM39: 8243.556 | BN39: 0 | BO39: 15158.63 | BP39: 0 | BQ39: 5138 | BR39: 0 | BS39: 11941.38 | BT39: 0 | BU39: 6000 | BV39: 0 | BW39: 8717.91 | BX39: 0 | BY39: 7300 | BZ39: 0 | CA39: 8785 | CB39: 0 | CC39: 20341 | CD39: 0 | CE39: 8342 | CF39: 0 | CG39: 10500 | CH39: 0 | CI39: 11768.4 | CJ39: 0 | CK39: 12500 | CL39: 0 | CM39: 0 | CO39: One time revenue booked for the month (GMV) | CP39: =D39=CO39 -> TRUE
CP40: =D40=CO40 -> TRUE
D41: New ACV/ Average ACV (new contracts) | E41: =SUM(E4)/E56 -> 6000 | F41: =SUM(F4)/F56 -> 6750 | G41: =SUM(G4)/G56 -> 4500 | H41: =SUM(H4)/H56 -> 4848.8 | I41: =SUM(I4)/I56 -> 5375 | J41: =SUM(J4)/J56 -> 7282.9091 | K41: =SUM(K4)/K56 -> 7203.333 | L41: =SUM(L4)/L56 -> 5225 | ... U41: =SUM(U4)/U56 -> 5798.0769 | V41: =SUM(V4,V39)/V56 -> 7053.3781 | W41: =SUM(W4)/W56 -> 6639.6667 | X41: =SUM(X4,X39)/X56 -> 7361.0049 | Y41: =SUM(Y4)/Y56 -> 7490.7143 | Z41: =SUM(Z4,Z39)/Z56 -> 7551.3906 | AA41: =SUM(AA4)/AA56 -> 8680.0272 | AB41: =SUM(AB4,AB39)/AB56 -> 7741.4647 | AC41: =SUM(AC4)/AC56 -> 7514.5122 | AD41: =SUM(AD4,AD39)/AD56 -> 8230.8767 | AE41: =SUM(AE4)/AE56 -> 7341.3462 | AF41: =SUM(AF4,AF39)/AF56 -> 8662.2295 | AG41: =SUM(AG4)/AG56 -> 7919.7685 | AH41: =SUM(AH4,AH39)/AH56 -> 8917.1425 | AI41: =SUM(AI4)/AI56 -> 9084.5588 | AJ41: =SUM(AJ4,AJ39)/AJ56 -> 9404.6462 | AK41: =SUM(AK4)/AK56 -> 8075.3125 | AL41: =SUM(AL4,AL39)/AL56 -> 9948.9868 | AM41: =SUM(AM4)/AM56 -> 8549.5 | AN41: =SUM(AN4,AN39)/AN56 -> 9200 | AO41: =SUM(AO4)/AO56 -> 6853.4474 | AP41: =SUM(AP4,AP39)/AP56 -> 9315.6364 | AQ41: =SUM(AQ4)/AQ56 -> 7154.8421 | AR41: =SUM(AR4,AR39)/AR56 -> 10315.469 | AS41: =SUM(AS4)/AS56 -> 7359.375 | AT41: =SUM(AT4,AT39)/AT56 -> 10181.392 | AU41: =SUM(AU4)/AU56 -> 7327.9309 | AV41: =SUM(AV4,AV39)/AV56 -> 10100.232 | AW41: =SUM(AW4)/AW56 -> 8224.0909 | AX41: =SUM(AX4,AX39)/AX56 -> 9902.8701 | AY41: =SUM(AY4)/AY56 -> 7367.0515 | AZ41: =SUM(AZ4,AZ39)/AZ56 -> 10027.749 | BA41: =SUM(BA4)/BA56 -> 6658.4613 | BB41: =SUM(BB4,BB39)/BB56 -> 10353.817 | BC41: =SUM(BC4)/BC56 -> 6902.766 | BD41: =SUM(BD4,BD39)/BD56 -> 10300.694 | BE41: =SUM(BE4)/BE56 -> 6581.1467 | BF41: =SUM(BF4,BF39)/BF56 -> 10228.222 | BG41: =SUM(BG4)/BG56 -> 7039.2778 | BH41: =SUM(BH4,BH39)/BH56 -> 10222.341 | BI41: =SUM(BI4)/BI56 -> 7396.9512 | BJ41: =SUM(BJ4,BJ39)/BJ56 -> 10587.268 | BK41: =SUM(BK4)/BK56 -> 6513.269 | BL41: =SUM(BL4,BL39)/BL56 -> 6846.9199 | BM41: =SUM(BM4)/BM56 -> 7351.9238 | BN41: =SUM(BN4,BN39)/BN56 -> 6962.389 | BO41: =SUM(BO4)/BO56 -> 7826.7702 | BP41: =SUM(BP4,BP39)/BP56 -> 7080.7377 | BQ41: =SUM(BQ4)/BQ56 -> 6966.2335 | BR41: =SUM(BR4,BR39)/BR56 -> 7326.5342 | BS41: =SUM(BS4)/BS56 -> 6654.2455 | BT41: =SUM(BT4,BT39)/BT56 -> 7386.8489 | BU41: =SUM(BU4)/BU56 -> 7323.381 | BV41: =SUM(BV4,BV39)/BV56 -> 7942.6978 | BW41: =SUM(BW4)/BW56 -> 7989.1863 | BX41: =SUM(BX4,BX39)/BX56 -> 8085.8023 | BY41: =SUM(BY4)/BY56 -> 6966.5309 | BZ41: =SUM(BZ4,BZ39)/BZ56 -> 8387.628 | CA41: =SUM(CA4)/CA56 -> 7798.5551 | CB41: =SUM(CB4,CB39)/CB56 -> 8609.8845 | CC41: =SUM(CC4)/CC56 -> 6879.7449 | CD41: =SUM(CD4,CD39)/CD56 -> 8918.7262 | CE41: =SUM(CE4)/CE56 -> 7033.9857 | CF41: =SUM(CF4,CF39)/CF56 -> 9036.606 | CG41: =SUM(CG4)/CG56 -> 7902.7423 | CH41: =SUM(CH4,CH39)/CH56 -> 9233.1767 | CI41: =SUM(CI4)/CI56 -> 7798.6667 | CJ41: =SUM(CJ4,CJ39)/CJ56 -> 9594.6907 | CK41: =SUM(CK4)/CK56 -> 7224.8285 | CL41: =SUM(CL4,CL39)/CL56 -> 9823.3739 | CM41: =SUM(CM4,CM39)/CM56 -> 10184.848 | CO41: New ACV/ Average ACV (new contracts) | CP41: =D41=CO41 -> TRUE
CP42: =D42=CO42 -> TRUE
D43: NA/EU | E43: =IFERROR((SUM(E6)/E58),0) -> 0 | F43: =IFERROR((SUM(F6)/F58),0) -> 8000 | G43: =IFERROR((SUM(G6)/G58),0) -> 5000 | H43: =IFERROR((SUM(H6)/H58),0) -> 0 | I43: =IFERROR((SUM(I6)/I58),0) -> 0 | J43: =IFERROR((SUM(J6)/J58),0) -> 0 | K43: =IFERROR((SUM(K6)/K58),0) -> 9000 | L43: =IFERROR((SUM(L6)/L58),0) -> 6500 | ... CM43: =IFERROR((SUM(CM6)/CM58),0) -> 13092.925 | CO43: NA/EU | CP43: =D43=CO43 -> TRUE
D44: India/APAC | E44: =IFERROR((SUM(E7)/E59),0) -> 6000 | F44: =IFERROR((SUM(F7)/F59),0) -> 6333.3333 | G44: =IFERROR((SUM(G7)/G59),0) -> 4428.5714 | H44: =IFERROR((SUM(H7)/H59),0) -> 4848.8 | I44: =IFERROR((SUM(I7)/I59),0) -> 5375 | J44: =IFERROR((SUM(J7)/J59),0) -> 7282.9091 | K44: =IFERROR((SUM(K7)/K59),0) -> 7003.7033 | L44: =IFERROR((SUM(L7)/L59),0) -> 5042.8571 | ... CM44: =IFERROR((SUM(CM7)/CM59),0) -> 4974.5455 | CO44: India/APAC | CP44: =D44=CO44 -> TRUE
CP45: =D45=CO45 -> TRUE
D46: Net Blended ACV | E46: =E81/E142 -> 6000 | F46: =F81/F142 -> 6428.5714 | G46: =G81/G142 -> 5400 | H46: =H81/H142 -> 5262.2 | I46: =I81/I142 -> 5281 | J46: =J81/J142 -> 5910.1714 | K46: =K81/K142 -> 6197.5407 | L46: =L81/L142 -> 6050.7421 | ... CM46: =CM81/CM142 -> 8445.1951 | CO46: Net Blended ACV | CP46: =D46=CO46 -> TRUE
CP47: =D47=CO47 -> TRUE
D48: NA/EU | E48: =IFERROR(E96/E149,"") | F48: =IFERROR(F96/F149,"") -> 8000 | G48: =IFERROR(G96/G149,"") -> 6500 | H48: =IFERROR(H96/H149,"") -> 6500 | I48: =IFERROR(I96/I149,"") -> 6500 | J48: =IFERROR(J96/J149,"") -> 6500 | K48: =IFERROR(K96/K149,"") -> 7333.3333 | L48: =IFERROR(L96/L149,"") -> 7125 | ... CM48: =IFERROR(CM96/CM149,"") -> 11431.142 | CO48: NA/EU | CP48: =D48=CO48 -> TRUE
D49: India/APAC | E49: =IFERROR(E111/E156,"") -> 6000 | F49: =IFERROR(F111/F156,"") -> 6166.6667 | G49: =IFERROR(G111/G156,"") -> 5230.7692 | H49: =IFERROR(H111/H156,"") -> 5124.6667 | I49: =IFERROR(I111/I156,"") -> 5170.1818 | J49: =IFERROR(J111/J156,"") -> 5874.4242 | K49: =IFERROR(K111/K156,"") -> 6116.4126 | L49: =IFERROR(L111/L156,"") -> 5963.0476 | ... CM49: =IFERROR(CM111/CM156,"") -> 6102.1352 | CO49: India/APAC | CP49: =D49=CO49 -> TRUE
CP50: =D50=CO50 -> TRUE
D51: Avg MRR (for new customers) | E51: =E41/12 -> 500 | F51: =F41/12 -> 562.5 | G51: =G41/12 -> 375 | H51: =H41/12 -> 404.06667 | I51: =I41/12 -> 447.91667 | J51: =J41/12 -> 606.90909 | K51: =K41/12 -> 600.27775 | L51: =L41/12 -> 435.41667 | ... CM51: =CM41/12 -> 848.73737 | CO51: Avg MRR (for new customers) | CP51: =D51=CO51 -> TRUE
CP52: =D52=CO52 -> TRUE
D53: NA/EU | E53: =E43/12 -> 0 | F53: =F43/12 -> 666.66667 | G53: =G43/12 -> 416.66667 | H53: =H43/12 -> 0 | I53: =I43/12 -> 0 | J53: =J43/12 -> 0 | K53: =K43/12 -> 750 | L53: =L43/12 -> 541.66667 | ... CM53: =CM43/12 -> 1091.077 | CO53: NA/EU | CP53: =D53=CO53 -> TRUE
D54: India/APAC | E54: =E44/12 -> 500 | F54: =F44/12 -> 527.77778 | G54: =G44/12 -> 369.04762 | H54: =H44/12 -> 404.06667 | I54: =I44/12 -> 447.91667 | J54: =J44/12 -> 606.90909 | K54: =K44/12 -> 583.64194 | L54: =L44/12 -> 420.2381 | ... CM54: =CM44/12 -> 414.54546 | CO54: India/APAC | CP54: =D54=CO54 -> TRUE
CP55: =D55=CO55 -> TRUE
C56: =SUM(E56:U56)+W56+Y56+AA56+AC56+AE56+AG56+AI56+AK56+AM56+AO56+AQ56+AS56+AU56+AW56+AY56+BA56+BC56+BE56+BG56+BI56+BK56+BM56+BO56+BQ56+BS56+BU56+BW56+BY56+CA56+CC56+CE56+CG56+CI56+CK56 -> 2542 | D56: Number of Customers (new) | E56: =E58+E59 -> 3 | F56: =F58+F59 -> 4 | G56: =G58+G59 -> 8 | H56: =H58+H59 -> 5 | I56: =I58+I59 -> 4 | J56: =J58+J59 -> 11 | K56: =K58+K59 -> 10 | L56: =L58+L59 -> 8 | ... CM56: =CM58+CM59 -> 67 | CO56: Number of Customers (new) | CP56: =D56=CO56 -> TRUE
CP57: =D57=CO57 -> TRUE
A58: x | C58: =SUM(E58:U58)+W58+Y58+AA58+AC58+AE58+AG58+AI58+AK58+AM58+AO58+AQ58+AS58+AU58+AW58+AY58+BA58+BC58+BE58+BG58+BI58+BK58+BM58+BO58+BQ58+BS58+BU58+BW58+BY58+CA58+CC58+CE58+CG58+CI58+CK58 -> 1153 | D58: NA/EU | F58: 1 | G58: 1 | K58: 1 | L58: 1 | N58: 1 | O58: 5 | P58: 2 | Q58: 3 | R58: 5 | S58: 4 | T58: 5 | U58: 18 | V58: 18 | W58: 12 | X58: 16 | Y58: 12 | Z58: 16 | AA58: 21 | AB58: 15 | AC58: 10 | AD58: 16 | AE58: 15 | AF58: 18 | AG58: 27 | AH58: 18 | AI58: 17 | AJ58: 20 | AK58: 14 | AL58: 21 | AM58: 22 | AN58: 14 | AO58: 10 | AP58: 14 | AQ58: 16 | AR58: 18 | AS58: 24 | AT58: 17 | AU58: 17 | AV58: 18 | AW58: 28 | AX58: 17 | AY58: 32 | AZ58: 27 | BA58: 23 | BB58: 30 | BC58: 28 | BD58: 29 | BE58: 34 | BF58: 31 | BG58: 25 | BH58: 32 | BI58: 38 | BJ58: 34 | BK58: 54 | BL58: 30 | BM58: 35 | BN58: 31 | BO58: 56 | BP58: 33 | BQ58: 53 | BR58: 35 | BS58: 40 | BT58: 33 | BU58: 49 | BV58: 35 | BW58: 55 | BX58: 35 | BY58: 42 | BZ58: 37 | CA58: 49 | CB58: 39 | CC58: 50 | CD58: 37 | CE58: 62 | CF58: 38 | CG58: 46 | CH58: 39 | CI58: 56 | CJ58: 40 | CK58: 34 | CL58: 41 | CM58: 43 | CO58: NA/EU | CP58: =D58=CO58 -> TRUE
A59: x | C59: =SUM(E59:U59)+W59+Y59+AA59+AC59+AE59+AG59+AI59+AK59+AM59+AO59+AQ59+AS59+AU59+AW59+AY59+BA59+BC59+BE59+BG59+BI59+BK59+BM59+BO59+BQ59+BS59+BU59+BW59+BY59+CA59+CC59+CE59+CG59+CI59+CK59 -> 1389 | D59: India/APAC | E59: 3 | F59: 3 | G59: 7 | H59: 5 | I59: 4 | J59: 11 | K59: 9 | L59: 7 | M59: 10 | N59: 18 | O59: 21 | P59: 23 | Q59: 20 | R59: 22 | S59: 22 | T59: 28 | U59: 47 | V59: 34 | W59: 27 | X59: 34 | Y59: 30 | Z59: 35 | AA59: 25 | AB59: 34 | AC59: 31 | AD59: 34 | AE59: 37 | AF59: 34 | AG59: 27 | AH59: 34 | AI59: 17 | AJ59: 33 | AK59: 26 | AL59: 33 | AM59: 27 | AN59: 19 | AO59: 28 | AP59: 19 | AQ59: 22 | AR59: 19 | AS59: 32 | AT59: 21 | AU59: 30 | AV59: 23 | AW59: 27 | AX59: 24 | AY59: 36 | AZ59: 25 | BA59: 33 | BB59: 25 | BC59: 19 | BD59: 26 | BE59: 41 | BF59: 28 | BG59: 20 | BH59: 29 | BI59: 30 | BJ59: 29 | BK59: 48 | BL59: 34 | BM59: 26 | BN59: 35 | BO59: 31 | BP59: 36 | BQ59: 40 | BR59: 36 | BS59: 30 | BT59: 35 | BU59: 35 | BV59: 25 | BW59: 47 | BX59: 25 | BY59: 39 | BZ59: 24 | CA59: 41 | CB59: 24 | CC59: 48 | CD59: 21 | CE59: 50 | CF59: 23 | CG59: 42 | CH59: 24 | CI59: 46 | CJ59: 23 | CK59: 41 | CL59: 24 | CM59: 24 | CO59: India/APAC | CP59: =D59=CO59 -> TRUE
CP60: =D60=CO60 -> TRUE
D61: Avg MRR across installed base | E61: =E80/E142 -> 500 | F61: =F80/F142 -> 535.71429 | G61: =G80/G142 -> 450 | H61: =H80/H142 -> 438.51667 | I61: =I80/I142 -> 440.08333 | J61: =J80/J142 -> 492.51429 | K61: =K80/K142 -> 516.46172 | L61: =L80/L142 -> 504.22851 | ... CM61: =CM80/CM142 -> 703.76626
CP62: =D62=CO62 -> TRUE
D63: NA/EU | E63: =IFERROR(E95/E149,"") | F63: =IFERROR(F95/F149,"") -> 666.66667 | G63: =IFERROR(G95/G149,"") -> 541.66667 | H63: =IFERROR(H95/H149,"") -> 541.66667 | I63: =IFERROR(I95/I149,"") -> 541.66667 | J63: =IFERROR(J95/J149,"") -> 541.66667 | K63: =IFERROR(K95/K149,"") -> 611.11111 | L63: =IFERROR(L95/L149,"") -> 593.75 | ... CM63: =IFERROR(CM95/CM149,"") -> 952.59519 | CO63: NA/EU | CP63: =D63=CO63 -> TRUE
D64: India/APAC | E64: =IFERROR(E110/E156,"") -> 500 | F64: =IFERROR(F110/F156,"") -> 513.88889 | G64: =IFERROR(G110/G156,"") -> 435.89744 | H64: =IFERROR(H110/H156,"") -> 427.05556 | I64: =IFERROR(I110/I156,"") -> 430.84848 | J64: =IFERROR(J110/J156,"") -> 489.53535 | K64: =IFERROR(K110/K156,"") -> 509.70105 | L64: =IFERROR(L110/L156,"") -> 496.92063 | ... CM64: =IFERROR(CM110/CM156,"") -> 508.51127 | CO64: India/APAC | CP64: =D64=CO64 -> TRUE
CP65: =D65=CO65 -> TRUE
C66: Projections | CP66: =D66=CO66 -> TRUE
D67: Total MRR Planned | V67: ='2. Financial Metrics Actual Aud'!W5 -> 194906.64 | W67: =V67 -> 194906.64 | X67: ='2. Financial Metrics Actual Aud'!Y5 -> 224805.62 | Y67: =X67 -> 224805.62 | Z67: ='2. Financial Metrics Actual Aud'!AA5 -> 256399.3 | AA67: =Z67 -> 256399.3 | AB67: ='2. Financial Metrics Actual Aud'!AC5 -> 287577.46 | AC67: =AB67 -> 287577.46 | AD67: ='2. Financial Metrics Actual Aud'!AE5 -> 320611 | AE67: =AD67 -> 320611 | AF67: ='2. Financial Metrics Actual Aud'!AG5 -> 358351.53 | AG67: =AF67 -> 358351.53 | AH67: ='2. Financial Metrics Actual Aud'!AI5 -> 397229.92 | AI67: =AH67 -> 397229.92 | AJ67: ='2. Financial Metrics Actual Aud'!AK5 -> 439091.03 | AK67: =AJ67 -> 439091.03 | AL67: ='2. Financial Metrics Actual Aud'!AM5 -> 484264.9 | AM67: =AL67 -> 484264.9 | AN67: ='2. Financial Metrics Actual Aud'!AO5 -> 448474.79 | AO67: =AN67 -> 448474.79 | AP67: ='2. Financial Metrics Actual Aud'!AQ5 -> 468113.96 | AQ67: =AP67 -> 468113.96 | AR67: ='2. Financial Metrics Actual Aud'!AS5 -> 493720.05 | AS67: =AR67 -> 493720.05 | AT67: ='2. Financial Metrics Actual Aud'!AU5 -> 519675.41 | AU67: =AT67 -> 519675.41 | AV67: ='2. Financial Metrics Actual Aud'!AW5 -> 547593.57 | AW67: =AV67 -> 547593.57 | AX67: ='2. Financial Metrics Actual Aud'!AY5 -> 574786.99 | AY67: =AX67 -> 574786.99 | AZ67: ='2. Financial Metrics Actual Aud'!BA5 -> 615280.61 | BA67: =AZ67 -> 615280.61 | BB67: ='2. Financial Metrics Actual Aud'!BC5 -> 663310.35 | BC67: =BB67 -> 663310.35 | BD67: ='2. Financial Metrics Actual Aud'!BE5 -> 710946.24 | BE67: =BD67 -> 710946.24 | BF67: ='2. Financial Metrics Actual Aud'!BG5 -> 762116.54 | BG67: =BF67 -> 762116.54 | BH67: ='2. Financial Metrics Actual Aud'!BI5 -> 814820.95 | BI67: =BH67 -> 814820.95 | BJ67: ='2. Financial Metrics Actual Aud'!BK5 -> 871923.98 | BK67: =BJ67 -> 871923.98 | BL67: ='2. Financial Metrics Actual Aud'!BM5 -> 844261.2 | BM67: =BL67 -> 844261.2 | BN67: ='2. Financial Metrics Actual Aud'!BO5 -> 886132.68 | BO67: =BN67 -> 886132.68 | BP67: ='2. Financial Metrics Actual Aud'!BQ5 -> 930544.57 | BQ67: =BP67 -> 930544.57 | BR67: ='2. Financial Metrics Actual Aud'!BS5 -> 977602.56 | BS67: =BR67 -> 977602.56 | BT67: ='2. Financial Metrics Actual Aud'!BU5 -> 1023589.6 | BU67: =BT67 -> 1023589.6 | BV67: ='2. Financial Metrics Actual Aud'!BW5 -> 1067443.3 | BW67: =BV67 -> 1067443.3 | BX67: ='2. Financial Metrics Actual Aud'!BY5 -> 1113305.6 | BY67: =BX67 -> 1113305.6 | BZ67: ='2. Financial Metrics Actual Aud'!CA5 -> 1161531.9 | CA67: =BZ67 -> 1161531.9 | CB67: ='2. Financial Metrics Actual Aud'!CC5 -> 1213697.5 | CC67: =CB67 -> 1213697.5 | CD67: ='2. Financial Metrics Actual Aud'!CE5 -> 1264115.2 | CE67: =CD67 -> 1264115.2 | CF67: ='2. Financial Metrics Actual Aud'!CG5 -> 1318220.4 | CG67: =CF67 -> 1318220.4 | CH67: ='2. Financial Metrics Actual Aud'!CI5 -> 1375365.3 | CI67: =CH67 -> 1375365.3 | CJ67: ='2. Financial Metrics Actual Aud'!CK5 -> 1435763.2 | CK67: =CJ67 -> 1435763.2 | CL67: ='2. Financial Metrics Actual Aud'!CM5 -> 1500198.8 | CM67: ='2. Financial Metrics Actual Aud'!CN5 -> 1569483.2 | CO67: Total MRR Planned | CP67: =D67=CO67 -> TRUE
D68: Total MRR Actual | E68: =E80 -> 1500 | F68: =F80 -> 3750 | G68: =G80 -> 6750 | H68: =H80 -> 8770.3333 | I68: =I80 -> 10562 | J68: =J80 -> 17238 | K68: =K80 -> 23240.778 | L68: =L80 -> 26724.111 | ... BQ68: =BQ80 -> 923221.61 | BS68: =BS80 -> 955509.69 | BU68: =BU80 -> 1011507 | BW68: =BW80 -> 1075512.2 | BY68: =BY80 -> 1117047.6 | CA68: =CA80 -> 1165186.7 | CC68: =CC80 -> 1215699.6 | CE68: =CE80 -> 1256692.5 | CG68: =CG80 -> 1318254.3 | CI68: =CI80 -> 1381491.3 | CK68: =CK80 -> 1424717.6
D69: Actual MRR % Planned MRR | W69: =W68/W67 -> 0.85244659 | Y69: =Y68/Y67 -> 0.86099937 | Z69: =Z68/Z67 -> 0.92661934 | AA69: =AA68/AA67 -> 0.89733775 | AB69: =AB68/AB67 -> 0.93457502 | AC69: =AC68/AC67 -> 0.88740417 | AD69: =AD68/AD67 -> 0.94131596 | AE69: =AE68/AE67 -> 0.90636688 | AF69: =AF68/AF67 -> 0.94749639 | ... BQ69: =BQ68/BQ67 -> 0.99213046 | BS69: =BS68/BS67 -> 0.97740096 | BU69: =BU68/BU67 -> 0.98819584 | BW69: =BW68/BW67 -> 1.0075591 | BY69: =BY68/BY67 -> 1.0033612 | CA69: =CA68/CA67 -> 1.0031465 | CC69: =CC68/CC67 -> 1.0016495 | CE69: =CE68/CE67 -> 0.99412812 | CG69: =CG68/CG67 -> 1.0000257 | CI69: =CI68/CI67 -> 1.0044541 | CK69: =CK68/CK67 -> 0.99230687
BI71: =BG81 -> 8696311.3 | BK71: =BI71-CE33 -> 6216439.4 | BM71: =BK71/BI71 -> 0.71483635
C72: MRR | BK72: 1295229.9 | BM72: =BK71+BK72 -> 7511669.3 | BO72: =BM72/BI71 -> 0.8637765
C73: Overall | D73: - Opening MRR | E73: =E88+E103 -> 0 | F73: =F88+F103 -> 1500 | G73: =G88+G103 -> 3750 | H73: =H88+H103 -> 6750 | I73: =I88+I103 -> 8770.3333 | J73: =J88+J103 -> 10562 | K73: =K88+K103 -> 17238 | L73: =L88+L103 -> 23240.778 | ... CM73: =CM88+CM103 -> 1500198.8
B74: =C74*12-C4 -> -3.7252903e-09 | C74: =SUM(E74:U74)+W74+Y74+AA74+AC74+AE74+AG74+AI74+AK74+AM74+AO74+AQ74+AS74+AU74+AW74+AY74+BA74+BC74+BE74+BG74+BI74+BK74+BM74+BO74+BQ74+BS74+BU74+BW74+BY74+CA74+CC74+CE74+CG74+CI74+CK74 -> 1521221 | D74: - New Bookings ($) | E74: =E89+E104 -> 1500 | F74: =F89+F104 -> 2250 | G74: =G89+G104 -> 3000 | H74: =H89+H104 -> 2020.3333 | I74: =I89+I104 -> 1791.6667 | J74: =J89+J104 -> 6676 | K74: =K89+K104 -> 6002.7775 | L74: =L89+L104 -> 3483.3333 | ... CM74: =CM89+CM104 -> 56865.404
B75: =C75*12-C19 -> 9.3132257e-10 | C75: =SUM(E75:U75)+W75+Y75+AA75+AC75+AE75+AG75+AI75+AK75+AM75+AO75+AQ75+AS75+AU75+AW75+AY75+BA75+BC75+BE75+BG75+BI75+BK75+BM75+BO75+BQ75+BS75+BU75+BW75+BY75+CA75+CC75+CE75+CG75+CI75+CK75 -> 230414.72 | D75: - MRR Expansion ($) | E75: =E90+E105 -> 0 | F75: =F90+F105 -> 0 | G75: =G90+G105 -> 0 | H75: =H90+H105 -> 0 | I75: =I90+I105 -> 0 | J75: =J90+J105 -> 0 | K75: =K90+K105 -> 0 | L75: =L90+L105 -> 0 | ... CM75: =CM90+CM105 -> 19220.964
B76: =C76*12-C24 -> 0 | C76: =SUM(E76:U76)+W76+Y76+AA76+AC76+AE76+AG76+AI76+AK76+AM76+AO76+AQ76+AS76+AU76+AW76+AY76+BA76+BC76+BE76+BG76+BI76+BK76+BM76+BO76+BQ76+BS76+BU76+BW76+BY76+CA76+CC76+CE76+CG76+CI76+CK76 -> 13006.402 | D76: - Revenue expansion ($) | E76: =E91+E106 -> 0 | F76: =F91+F106 -> 0 | G76: =G91+G106 -> 0 | H76: =H91+H106 -> 0 | I76: =I91+I106 -> 0 | J76: =J91+J106 -> 0 | K76: =K91+K106 -> 0 | L76: =L91+L106 -> 0 | ... CM76: =CM91+CM106 -> 0
B77: =C77*12+C29 -> 0 | C77: =SUM(E77:U77)+W77+Y77+AA77+AC77+AE77+AG77+AI77+AK77+AM77+AO77+AQ77+AS77+AU77+AW77+AY77+BA77+BC77+BE77+BG77+BI77+BK77+BM77+BO77+BQ77+BS77+BU77+BW77+BY77+CA77+CC77+CE77+CG77+CI77+CK77 -> -298714.96 | D77: - Gross MRR Churn ($) | E77: =E92+E107 -> 0 | F77: =F92+F107 -> 0 | G77: =G92+G107 -> 0 | H77: =H92+H107 -> 0 | I77: =I92+I107 -> 0 | J77: =J92+J107 -> 0 | K77: =K92+K107 -> 0 | L77: =L92+L107 -> 0 | ... CM77: =CM92+CM107 -> -6801.948
B78: =C78*12+C34 -> 0 | C78: =SUM(E78:U78)+W78+Y78+AA78+AC78+AE78+AG78+AI78+AK78+AM78+AO78+AQ78+AS78+AU78+AW78+AY78+BA78+BC78+BE78+BG78+BI78+BK78+BM78+BO78+BQ78+BS78+BU78+BW78+BY78+CA78+CC78+CE78+CG78+CI78+CK78 -> -41209.475 | D78: - Revenue Churn ($) | E78: =E93+E108 -> 0 | F78: =F93+F108 -> 0 | G78: =G93+G108 -> 0 | H78: =H93+H108 -> 0 | I78: =I93+I108 -> 0 | J78: =J93+J108 -> 0 | K78: =K93+K108 -> 0 | L78: =L93+L108 -> 0 | ... CM78: =CM93+CM108 -> 0
C79: =SUM(E79:U79)+W79+Y79+AA79+AC79+AE79+AG79+AI79+AK79+AM79+AO79+AQ79+AS79+AU79+AW79+AY79+BA79+BC79+BE79+BG79+BI79+BK79+BM79+BO79+BQ79+BS79+BU79+BW79+BY79+CA79+CC79+CE79+CG79+CI79+CK79 -> -96503.314 | D79: - Net MRR Churn ($) | E79: =E94+E109 -> 0 | F79: =F94+F109 -> 0 | G79: =G94+G109 -> 0 | H79: =H94+H109 -> 0 | I79: =I94+I109 -> 0 | J79: =J94+J109 -> 0 | K79: =K94+K109 -> 0 | L79: =L94+L109 -> 0 | ... CM79: =CM94+CM109 -> 12419.016
B80: =C80*12 -> 3.0289385e+08 | C80: =SUM(E80:U80)+W80+Y80+AA80+AC80+AE80+AG80+AI80+AK80+AM80+AO80+AQ80+AS80+AU80+AW80+AY80+BA80+BC80+BE80+BG80+BI80+BK80+BM80+BO80+BQ80+BS80+BU80+BW80+BY80+CA80+CC80+CE80+CG80+CI80+CK80 -> 25241155 | D80: - Closing MRR ($) | E80: =E110+E95 -> 1500 | F80: =F110+F95 -> 3750 | G80: =G110+G95 -> 6750 | H80: =H110+H95 -> 8770.3333 | I80: =I110+I95 -> 10562 | J80: =J110+J95 -> 17238 | K80: =K110+K95 -> 23240.778 | L80: =L110+L95 -> 26724.111 | ... CM80: =CM110+CM95 -> 1569483.2
B81: =B80-C81 -> 0 | C81: =SUM(E81:U81)+W81+Y81+AA81+AC81+AE81+AG81+AI81+AK81+AM81+AO81+AQ81+AS81+AU81+AW81+AY81+BA81+BC81+BE81+BG81+BI81+BK81+BM81+BO81+BQ81+BS81+BU81+BW81+BY81+CA81+CC81+CE81+CG81+CI81+CK81 -> 3.0289385e+08 | D81: Exit ARR | E81: =E80*12 -> 18000 | F81: =F80*12 -> 45000 | G81: =G80*12 -> 81000 | H81: =H80*12 -> 105244 | I81: =I80*12 -> 126744 | J81: =J80*12 -> 206856 | K81: =K80*12 -> 278889.33 | L81: =L80*12 -> 320689.33 | ... CM81: =CM80*12 -> 18833798 | CO81: Total MRR Actual | CP81: =D81=CO81 -> FALSE
D82: % MRR Expansion | E82: =IFERROR(E75/E73,0) -> 0 | F82: =IFERROR(F75/F73,0) -> 0 | G82: =IFERROR(G75/G73,0) -> 0 | H82: =IFERROR(H75/H73,0) -> 0 | I82: =IFERROR(I75/I73,0) -> 0 | J82: =IFERROR(J75/J73,0) -> 0 | K82: =IFERROR(K75/K73,0) -> 0 | L82: =IFERROR(L75/L73,0) -> 0 | ... CM82: =IFERROR(CM75/CM73,0) -> 0.012812278 | CO82: Actual MRR % Planned MRR | CP82: =D82=CO82 -> FALSE
D83: % Gross MRR Churn | E83: =IFERROR((E77+E78)/E73,0) -> 0 | F83: =IFERROR((F77+F78)/F73,0) -> 0 | G83: =IFERROR((G77+G78)/G73,0) -> 0 | H83: =IFERROR((H77+H78)/H73,0) -> 0 | I83: =IFERROR((I77+I78)/I73,0) -> 0 | J83: =IFERROR((J77+J78)/J73,0) -> 0 | K83: =IFERROR((K77+K78)/K73,0) -> 0 | L83: =IFERROR((L77+L78)/L73,0) -> 0 | ... CM83: =IFERROR((CM77+CM78)/CM73,0) -> -0.0045340311 | CP83: =D83=CO83 -> FALSE
D84: % Net MRR Churn | E84: =IFERROR(E79/E73,0) -> 0 | F84: =IFERROR(F79/F73,0) -> 0 | G84: =IFERROR(G79/G73,0) -> 0 | H84: =IFERROR(H79/H73,0) -> 0 | I84: =IFERROR(I79/I73,0) -> 0 | J84: =IFERROR(J79/J73,0) -> 0 | K84: =IFERROR(K79/K73,0) -> 0 | L84: =IFERROR(L79/L73,0) -> 0 | ... CM84: =IFERROR(CM79/CM73,0) -> 0.008278247 | CP84: =D84=CO84 -> FALSE
D85: % MoM MRR growth | F85: =F80/E80 -> 2.5 | G85: =G80/F80 -> 1.8 | H85: =H80/G80 -> 1.2993086 | I85: =I80/H80 -> 1.2042872 | J85: =J80/I80 -> 1.6320773 | K85: =K80/J80 -> 1.3482293 | L85: =L80/K80 -> 1.1498802 | M85: =M80/L80 -> 1.1197421 | ... BS85: =BS80/BR80 -> 0.97740096 | BT85: =BT80/BR80 -> 1.0470407 | BU85: =BU80/BT80 -> 0.98819584 | BV85: =BV80/BT80 -> 1.042843 | BW85: =BW80/BV80 -> 1.0075591 | BX85: =BX80/BV80 -> 1.0429647 | BY85: =BY80/BX80 -> 1.0033612 | BZ85: =BZ80/BX80 -> 1.0433181 | CA85: =CA80/BZ80 -> 1.0031465 | CB85: =CB80/BZ80 -> 1.044911 | CC85: =CC80/CB80 -> 1.0016495 | CD85: =CD80/CB80 -> 1.0415406 | CE85: =CE80/CD80 -> 0.99412812 | CF85: =CF80/CD80 -> 1.0428008 | CG85: =CG80/CF80 -> 1.0000257 | CH85: =CH80/CF80 -> 1.04335 | CI85: =CI80/CH80 -> 1.0044541 | CJ85: =CJ80/CH80 -> 1.0439141 | CK85: =CK80/CJ80 -> 0.99230687 | CL85: =CL80/CJ80 -> 1.044879 | CM85: =CM80/CL80 -> 1.0461835 | CO85: - Opening MRR | CP85: =D85=CO85 -> FALSE
D86: Monthly NRR | F86: =SUM(F73,F79)/F73 -> 1 | G86: =SUM(G73,G79)/G73 -> 1 | H86: =SUM(H73,H79)/H73 -> 1 | I86: =SUM(I73,I79)/I73 -> 1 | J86: =SUM(J73,J79)/J73 -> 1 | K86: =SUM(K73,K79)/K73 -> 1 | L86: =SUM(L73,L79)/L73 -> 1 | M86: =SUM(M73,M79)/M73 -> 1 | ... CM86: =SUM(CM73,CM79)/CM73 -> 1.0082782 | CO86: - New Bookings ($) | CP86: =D86=CO86 -> FALSE
CO87: - MRR Expansion ($) | CP87: =D87=CO87 -> FALSE
A88: 251940 | C88: NA/EU | D88: - Opening MRR | E88: 0 | F88: =E95 -> 0 | G88: =F95 -> 666.66667 | H88: =G95 -> 1083.3333 | I88: =H95 -> 1083.3333 | J88: =I95 -> 1083.3333 | K88: =J95 -> 1083.3333 | L88: =K95 -> 1833.3333 | M88: =L95 -> 2375 | ... V88: =U95 -> 28455 | W88: =U95 -> 28455 | X88: =V95 -> 41601.305 | Y88: =W95 -> 37538.333 | Z88: =X95 -> 54468.263 | AA88: =Y95 -> 47404.167 | AB88: =Z95 -> 67839.123 | AC88: =AA95 -> 66000 | AD88: =AB95 -> 80789.505 | ... AM88: =AK95 -> 136276.25 | AN88: 158494.75 | AO88: =AM95 -> 152842.92 | AP88: =AN95 -> 171509.48 | AQ88: =AO95 -> 162023.5 | AR88: =AP95 -> 184595.53 | AS88: =AQ95 -> 173700.17 | AT88: =AR95 -> 203621.85 | AU88: =AS95 -> 190366.83 | AV88: =AT95 -> 220880.76 | ... BK88: =BI95 -> 363512.57 | BL88: =4759389.95552268/12 -> 396615.83 | BM88: =BK95 -> 394182.01 | BN88: =BL95 -> 419681.58 | BO88: =BM95 -> 419730.46 | BP88: =BN95 -> 444310.11 | BQ88: =BO95 -> 458529.8 | BR88: =BP95 -> 471175.8 | BS88: =BQ95 -> 485963.67 | BT88: =BR95 -> 499633.07 | ... CL88: =CJ95 -> 830229.76 | CM88: =CL95 -> 879697.89 | CO88: - Revenue expansion ($) | CP88: =D88=CO88 -> FALSE
B89: =C6-C89*12 -> 1.8626451e-09 | C89: =SUM(E89:U89)+W89+Y89+AA89+AC89+AE89+AG89+AI89+AK89+AM89+AO89+AQ89+AS89+AU89+AW89+AY89+BA89+BC89+BE89+BG89+BI89+BK89+BM89+BO89+BQ89+BS89+BU89+BW89+BY89+CA89+CC89+CE89+CG89+CI89+CK89 -> 872214.86 | D89: - New Bookings ($) | E89: =E6/12 -> 0 | F89: =F6/12 -> 666.66667 | G89: =G6/12 -> 416.66667 | H89: =H6/12 -> 0 | I89: =I6/12 -> 0 | J89: =J6/12 -> 0 | K89: =K6/12 -> 750 | L89: =L6/12 -> 541.66667 | ... U89: =U6/12 -> 11463.333 | V89: 13187.972 | W89: =W6/12 -> 9083.3333 | X89: 12891.02 | Y89: =Y6/12 -> 9865.8333 | Z89: 13370.86 | AA89: =AA6/12 -> 18729.167 | AB89: 12994.325 | AC89: =AC6/12 -> 10250 | AD89: 15244.497 | AE89: =AE6/12 -> 12322.917 | AF89: 18040.485 | AG89: =AG6/12 -> 21540 | AH89: 18688.962 | AI89: =AI6/12 -> 15025 | AJ89: 21716.696 | AK89: =AK6/12 -> 13066.667 | AL89: 24485.688 | AM89: =AM6/12 -> 17725 | AN89: 14250 | AO89: =AO6/12 -> 7333.3333 | AP89: 14452.5 | AQ89: =AQ6/12 -> 12510 | AR89: 20523.8 | AS89: =AS6/12 -> 17316.667 | AT89: 18754.04 | AU89: =AU6/12 -> 14083.333 | AV89: 19825.036 | AW89: =AW6/12 -> 23950 | AX89: 18527.954 | AY89: =AY6/12 -> 24712.5 | AZ89: 27523.25 | BA89: =BA6/12 -> 16827.778 | BB89: 31475.459 | BC89: =BC6/12 -> 18695.833 | BD89: 30055.546 | BE89: =BE6/12 -> 22708.333 | BF89: 31915.2 | BG89: =BG6/12 -> 17587.5 | BH89: 32946.405 | BI89: =BI6/12 -> 28372.25 | BJ89: 36496.363 | BK89: =BK6/12 -> 33983.333 | BL89: 22573.884 | BM89: =BM6/12 -> 26335.75 | BN89: 23863.471 | BO89: =BO6/12 -> 43513 | BP89: 25830.077 | BQ89: =BQ6/12 -> 34033.333 | BR89: 28437.5 | BS89: =BS6/12 -> 25958.333 | BT89: 27379.688 | BU89: =BU6/12 -> 30878.333 | BV89: 29685.742 | BW89: =BW6/12 -> 47634.417 | BX89: 30380.923 | BY89: =BY6/12 -> 31253.75 | BZ89: 32906.999 | CA89: =CA6/12 -> 42506.667 | CB89: 35580.937 | CC89: =CC6/12 -> 36021.25 | CD89: 34669.244 | CE89: =CE6/12 -> 44903.333 | CF89: 36614.22 | CG89: =CG6/12 -> 40493.333 | CH89: 38689.833 | CI89: =CI6/12 -> 47197.917 | CJ89: 40908.021 | CK89: =CK6/12 -> 27841.667 | CL89: 43281.776 | CM89: 46916.313 | CO89: - Gross MRR Churn ($) | CP89: =D89=CO89 -> FALSE
B90: =C21-C90*12 -> 1.1641532e-10 | C90: =SUM(E90:U90)+W90+Y90+AA90+AC90+AE90+AG90+AI90+AK90+AM90+AO90+AQ90+AS90+AU90+AW90+AY90+BA90+BC90+BE90+BG90+BI90+BK90+BM90+BO90+BQ90+BS90+BU90+BW90+BY90+CA90+CC90+CE90+CG90+CI90+CK90 -> 82085.77 | D90: - MRR Expansion ($) | E90: =E21/12 -> 0 | F90: =F21/12 -> 0 | G90: =G21/12 -> 0 | H90: =H21/12 -> 0 | I90: =I21/12 -> 0 | J90: =J21/12 -> 0 | K90: =K21/12 -> 0 | L90: =L21/12 -> 0 | ... U90: =U21/12 -> 500 | V90: 20.833333 | W90: =W21/12 -> 0 | X90: 13.4375 | Y90: =Y21/12 -> 0 | Z90: 0 | AA90: =AA21/12 -> 291.66667 | AB90: 31.057422 | AC90: =AC21/12 -> 833.33333 | AD90: 86.249049 | AE90: =AE21/12 -> 2183.3333 | AF90: 77.464166 | AG90: =AG21/12 -> 83.333333 | AH90: 0 | AI90: =AI21/12 -> 125 | AJ90: 0 | AK90: =AK21/12 -> 333.33333 | AL90: 0 | AM90: =AM21/12 -> 341.66667 | AN90: 666.66667 | AO90: =AO21/12 -> 1916.6667 | AP90: 691.66667 | AQ90: =AQ21/12 -> 500 | AR90: 717.66667 | AS90: =AS21/12 -> 1125 | AT90: 744.70917 | AU90: =AU21/12 -> 1416.6667 | AV90: 772.83857 | AW90: =AW21/12 -> 2208.3333 | AX90: 802.10125 | AY90: =AY21/12 -> 2083.8333 | AZ90: 1167.5696 | BA90: =BA21/12 -> 4125 | BB90: 1215.9977 | BC90: =BC21/12 -> 2083.3333 | BD90: 1266.5486 | BE90: =BE21/12 -> 1816.6667 | BF90: 1707.1517 | BG90: =BG21/12 -> 3958.3333 | BH90: 1781.6361 | BI90: =BI21/12 -> 625 | BJ90: 2436.2827 | BK90: =BK21/12 -> 1834.8533 | BL90: 1681.7117 | BM90: =BM21/12 -> 208.33333 | BN90: 2024.1082 | BO90: =BO21/12 -> 2083.3333 | BP90: 2368.544 | BQ90: =BQ21/12 -> 6604.1667 | BR90: 2375.6496 | BS90: =BS21/12 -> 1383.3333 | BT90: 3063.5698 | BU90: =BU21/12 -> 1562.5 | BV90: 3072.7606 | BW90: =BW21/12 -> 5541.6667 | BX90: 3766.863 | BY90: =BY21/12 -> 4274.5833 | BZ90: 4121.633 | CA90: =CA21/12 -> 3633.3333 | CB90: 5167.4974 | CC90: =CC21/12 -> 6747.9167 | CD90: 5182.9999 | CE90: =CE21/12 -> 5037.5 | CF90: 6238.2587 | CG90: =CG21/12 -> 5183.3333 | CH90: 6952.1927 | CI90: =CI21/12 -> 4633.3333 | CJ90: 7670.3542 | CK90: =CK21/12 -> 6807.0833 | CL90: 9092.159 | CM90: 10522.426 | CO90: - Revenue Churn ($) | CP90: =D90=CO90 -> FALSE
A91: xxxno change | B91: =C91*12-C26 -> 0 | C91: =SUM(E91:U91)+W91+Y91+AA91+AC91+AE91+AG91+AI91+AK91+AM91+AO91+AQ91+AS91+AU91+AW91+AY91+BA91+BC91+BE91+BG91+BI91+BK91+BM91+BO91+BQ91+BS91+BU91+BW91+BY91+CA91+CC91+CE91+CG91+CI91+CK91 -> 8675.7283 | D91: - Revenue expansion ($) | E91: =E26/12 -> 0 | F91: =F26/12 -> 0 | G91: =G26/12 -> 0 | H91: =H26/12 -> 0 | I91: =I26/12 -> 0 | J91: =J26/12 -> 0 | K91: =K26/12 -> 0 | L91: =L26/12 -> 0 | ... U91: =U26/12 -> 0 | W91: =W26/12 -> 0 | Y91: =Y26/12 -> 0 | AA91: =AA26/12 -> 125 | AC91: =AC26/12 -> 0 | AE91: =AE26/12 -> 0 | AG91: =AG26/12 -> 0 | AI91: =AI26/12 -> 0 | AK91: =AK26/12 -> 0 | AM91: =AM26/12 -> 0 | AO91: =AO26/12 -> 0 | AQ91: =AQ26/12 -> 0 | AS91: =AS26/12 -> 0 | AU91: =AU26/12 -> 193.75 | AW91: =AW26/12 -> 128.125 | AY91: =AY26/12 -> 442.5 | BA91: =BA26/12 -> 133.33333 | BC91: =BC26/12 -> 207.5 | BE91: =BE26/12 -> 194.16667 | BG91: =BG26/12 -> 150 | BI91: =BI26/12 -> 0 | BK91: =BK26/12 -> 267.91667 | BM91: =BM26/12 -> 112.70833 | BO91: =BO26/12 -> 203 | BQ91: =BQ26/12 -> 264.375 | BS91: =BS26/12 -> 485.41667 | BU91: =BU26/12 -> 508.125 | BW91: =BW26/12 -> 1121.2875 | BY91: =BY26/12 -> 872.70833 | CA91: =CA26/12 -> 445.20833 | CC91: =CC26/12 -> 621.04167 | CE91: =CE26/12 -> 1087.8958 | CG91: =CG26/12 -> 127.4 | CI91: =CI26/12 -> 275.83333 | CK91: =CK26/12 -> 708.43667 | CO91: - Net MRR Churn ($) | CP91: =D91=CO91 -> FALSE
A92: x | B92: =C31+C92*12 -> 2.3283064e-10 | C92: =SUM(E92:U92)+W92+Y92+AA92+AC92+AE92+AG92+AI92+AK92+AM92+AO92+AQ92+AS92+AU92+AW92+AY92+BA92+BC92+BE92+BG92+BI92+BK92+BM92+BO92+BQ92+BS92+BU92+BW92+BY92+CA92+CC92+CE92+CG92+CI92+CK92 -> -124793.83 | D92: - Gross MRR Churn ($) | E92: =IFERROR(-E31/12,0) -> 0 | F92: =IFERROR(-F31/12,0) -> 0 | G92: =IFERROR(-G31/12,0) -> 0 | H92: =IFERROR(-H31/12,0) -> 0 | I92: =IFERROR(-I31/12,0) -> 0 | J92: =IFERROR(-J31/12,0) -> 0 | K92: =IFERROR(-K31/12,0) -> 0 | L92: =IFERROR(-L31/12,0) -> 0 | ... U92: =IFERROR(-U31/12,0) -> 0 | V92: -62.5 | W92: =IFERROR(-W31/12,0) -> 0 | X92: -37.5 | Y92: =IFERROR(-Y31/12,0) -> 0 | Z92: 0 | AA92: =IFERROR(-AA31/12,0) -> -550 | AB92: -75 | AC92: =IFERROR(-AC31/12,0) -> 0 | AD92: -193.75 | AE92: =IFERROR(-AE31/12,0) -> 0 | AF92: -53.958333 | AG92: =IFERROR(-AG31/12,0) -> -416.66667 | AH92: 0 | AI92: =IFERROR(-AI31/12,0) -> -666.66667 | AJ92: 0 | AK92: =IFERROR(-AK31/12,0) -> -4236.6667 | AL92: 0 | AM92: =IFERROR(-AM31/12,0) -> -1500 | AN92: -1901.937 | AO92: =IFERROR(-AO31/12,0) -> 0 | AP92: -2058.1138 | AQ92: =IFERROR(-AQ31/12,0) -> -1333.3333 | AR92: -2215.1464 | AS92: =IFERROR(-AS31/12,0) -> -1750 | AT92: -2239.8404 | AU92: =IFERROR(-AU31/12,0) -> -1666.6667 | AV92: -2429.6884 | AW92: =IFERROR(-AW31/12,0) -> -833.33333 | AX92: -2629.5384 | AY92: =IFERROR(-AY31/12,0) -> 0 | AZ92: -2045.9957 | BA92: =IFERROR(-BA31/12,0) -> -1375 | BB92: -1411.9714 | BC92: =IFERROR(-BC31/12,0) -> -2541.6667 | BD92: -1568.3689 | BE92: =IFERROR(-BE31/12,0) -> -1166.6667 | BF92: -1717.1375 | BG92: =IFERROR(-BG31/12,0) -> -1666.6667 | BH92: -1876.6636 | BI92: =IFERROR(-BI31/12,0) -> -3933.3333 | BJ92: -2040.9205 | BK92: =IFERROR(-BK31/12,0) -> -5250 | BL92: -1189.8475 | BM92: =IFERROR(-BM31/12,0) -> -1108.3333 | BN92: -1259.0447 | BO92: =IFERROR(-BO31/12,0) -> -7000 | BP92: -1332.9303 | BQ92: =IFERROR(-BQ31/12,0) -> -12655.5 | BR92: -2355.879 | BS92: =IFERROR(-BS31/12,0) -> -5291.6667 | BT92: -2498.1654 | BU92: =IFERROR(-BU31/12,0) -> -583.33333 | BV92: -2637.8908 | BW92: =IFERROR(-BW31/12,0) -> -8079.1667 | BX92: -1951.9457 | BY92: =IFERROR(-BY31/12,0) -> -4572.5 | BZ92: -2064.6312 | CA92: =IFERROR(-CA31/12,0) -> -10825.833 | CB92: -2187.0052 | CC92: =IFERROR(-CC31/12,0) -> -12362.5 | CD92: -2321.9702 | CE92: =IFERROR(-CE31/12,0) -> -16840 | CF92: -2453.3261 | CG92: =IFERROR(-CG31/12,0) -> -3555 | CH92: -2594.7232 | CI92: =IFERROR(-CI31/12,0) -> -7987.5 | CJ92: -2745.3887 | CK92: =IFERROR(-CK31/12,0) -> -5045.8333 | CL92: -2905.8042 | CM92: -3078.9426 | CO92: - Closing MRR ($) | CP92: =D92=CO92 -> FALSE
A93: xxx no change | B93: =C36+C93*12 -> 0 | C93: =SUM(E93:U93)+W93+Y93+AA93+AC93+AE93+AG93+AI93+AK93+AM93+AO93+AQ93+AS93+AU93+AW93+AY93+BA93+BC93+BE93+BG93+BI93+BK93+BM93+BO93+BQ93+BS93+BU93+BW93+BY93+CA93+CC93+CE93+CG93+CI93+CK93 -> -9197.6604 | D93: - Revenue Churn ($) | E93: =-E36/12 -> 0 | F93: =-F36/12 -> 0 | G93: =-G36/12 -> 0 | H93: =-H36/12 -> 0 | I93: =-I36/12 -> 0 | J93: =-J36/12 -> 0 | K93: =-K36/12 -> 0 | L93: =-L36/12 -> 0 | ... U93: =-U36/12 -> 0 | W93: =-W36/12 -> 0 | Y93: =-Y36/12 -> 0 | AA93: =-AA36/12 -> 0 | AC93: =-AC36/12 -> 0 | AE93: =-AE36/12 -> 0 | AG93: =-AG36/12 -> 0 | AI93: =-AI36/12 -> -166.66667 | AK93: =-AK36/12 -> 0 | AM93: =-AM36/12 -> 0 | AO93: =-AO36/12 -> -69.416667 | AQ93: =-AQ36/12 -> 0 | AS93: =-AS36/12 -> -25 | AU93: =-AU36/12 -> 0 | AW93: =-AW36/12 -> 0 | AY93: =-AY36/12 -> 0 | BA93: =-BA36/12 -> 0 | BC93: =-BC36/12 -> 0 | BE93: =-BE36/12 -> 0 | BG93: =-BG36/12 -> 0 | BI93: =-BI36/12 -> -375 | BK93: =-BK36/12 -> -166.66667 | BM93: =-BM36/12 -> 0 | BO93: =-BO36/12 -> 0 | BQ93: =-BQ36/12 -> -812.5 | BS93: =-BS36/12 -> -1050 | BU93: =-BU36/12 -> 0 | BW93: =-BW36/12 -> 0 | BY93: =-BY36/12 -> -708.33333 | CA93: =-CA36/12 -> -833.33333 | CC93: =-CC36/12 -> -998.4521 | CE93: =-CE36/12 -> -2441.6667 | CG93: =-CG36/12 -> -590.625 | CI93: =-CI36/12 -> -250 | CK93: =-CK36/12 -> -710 | CO93: Exit ARR | CP93: =D93=CO93 -> FALSE
C94: =SUM(E94:U94)+W94+Y94+AA94+AC94+AE94+AG94+AI94+AK94+AM94+AO94+AQ94+AS94+AU94+AW94+AY94+BA94+BC94+BE94+BG94+BI94+BK94+BM94+BO94+BQ94+BS94+BU94+BW94+BY94+CA94+CC94+CE94+CG94+CI94+CK94 -> -43229.995 | D94: - Net MRR Churn ($) | E94: =SUM(E90:E93) -> 0 | F94: =SUM(F90:F93) -> 0 | G94: =SUM(G90:G93) -> 0 | H94: =SUM(H90:H93) -> 0 | I94: =SUM(I90:I93) -> 0 | J94: =SUM(J90:J93) -> 0 | K94: =SUM(K90:K93) -> 0 | L94: =SUM(L90:L93) -> 0 | ... CM94: =SUM(CM90:CM93) -> 7443.4829 | CO94: % MRR Expansion | CP94: =D94=CO94 -> FALSE
B95: =C95*12 -> 1.46449e+08 | C95: =SUM(E95:U95)+W95+Y95+AA95+AC95+AE95+AG95+AI95+AK95+AM95+AO95+AQ95+AS95+AU95+AW95+AY95+BA95+BC95+BE95+BG95+BI95+BK95+BM95+BO95+BQ95+BS95+BU95+BW95+BY95+CA95+CC95+CE95+CG95+CI95+CK95 -> 12204084 | D95: - Closing MRR ($) | E95: =E88+E89+E94 -> 0 | F95: =F88+F89+F94 -> 666.66667 | G95: =G88+G89+G94 -> 1083.3333 | H95: =H88+H89+H94 -> 1083.3333 | I95: =I88+I89+I94 -> 1083.3333 | J95: =J88+J89+J94 -> 1083.3333 | K95: =K88+K89+K94 -> 1833.3333 | L95: =L88+L89+L94 -> 2375 | ... CM95: =CM88+CM89+CM94 -> 934057.69 | CO95: % Gross MRR Churn | CP95: =D95=CO95 -> FALSE
B96: =B95-C96 -> 5.9604645e-08 | C96: =SUM(E96:U96)+W96+Y96+AA96+AC96+AE96+AG96+AI96+AK96+AM96+AO96+AQ96+AS96+AU96+AW96+AY96+BA96+BC96+BE96+BG96+BI96+BK96+BM96+BO96+BQ96+BS96+BU96+BW96+BY96+CA96+CC96+CE96+CG96+CI96+CK96 -> 1.46449e+08 | D96: Exit ARR | E96: =E95*12 -> 0 | F96: =F95*12 -> 8000 | G96: =G95*12 -> 13000 | H96: =H95*12 -> 13000 | I96: =I95*12 -> 13000 | J96: =J95*12 -> 13000 | K96: =K95*12 -> 22000 | L96: =L95*12 -> 28500 | ... CM96: =CM95*12 -> 11208692 | CO96: % Net MRR Churn | CP96: =D96=CO96 -> FALSE
D97: % MRR Expansion | E97: =IFERROR(E90/E$88,0) -> 0 | F97: =IFERROR(F90/F$88,0) -> 0 | G97: =IFERROR(G90/G$88,0) -> 0 | H97: =IFERROR(H90/H$88,0) -> 0 | I97: =IFERROR(I90/I$88,0) -> 0 | J97: =IFERROR(J90/J$88,0) -> 0 | K97: =IFERROR(K90/K$88,0) -> 0 | L97: =IFERROR(L90/L$88,0) -> 0 | ... CM97: =IFERROR(CM90/CM$88,0) -> 0.011961408 | CO97: % MoM MRR growth | CP97: =D97=CO97 -> FALSE
D98: % Gross MRR Churn | E98: =IFERROR((E92+E93)/E$88,0) -> 0 | F98: =IFERROR((F92+F93)/F$88,0) -> 0 | G98: =IFERROR((G92+G93)/G$88,0) -> 0 | H98: =IFERROR((H92+H93)/H$88,0) -> 0 | I98: =IFERROR((I92+I93)/I$88,0) -> 0 | J98: =IFERROR((J92+J93)/J$88,0) -> 0 | K98: =IFERROR((K92+K93)/K$88,0) -> 0 | L98: =IFERROR((L92+L93)/L$88,0) -> 0 | ... CM98: =IFERROR((CM92+CM93)/CM$88,0) -> -0.0035 | CO98: Monthly NRR | CP98: =D98=CO98 -> FALSE
D99: % Net MRR Churn | E99: =IFERROR(E94/E$88,0) -> 0 | F99: =IFERROR(F94/F$88,0) -> 0 | G99: =IFERROR(G94/G$88,0) -> 0 | H99: =IFERROR(H94/H$88,0) -> 0 | I99: =IFERROR(I94/I$88,0) -> 0 | J99: =IFERROR(J94/J$88,0) -> 0 | K99: =IFERROR(K94/K$88,0) -> 0 | L99: =IFERROR(L94/L$88,0) -> 0 | ... CM99: =IFERROR(CM94/CM$88,0) -> 0.0084614081 | CP99: =D99=CO99 -> FALSE
D100: % MoM MRR growth | F100: =IFERROR(F95/E95,0) -> 0 | G100: =G95/F95 -> 1.625 | H100: =H95/G95 -> 1 | I100: =I95/H95 -> 1 | J100: =J95/I95 -> 1 | K100: =K95/J95 -> 1.6923077 | L100: =L95/K95 -> 1.2954545 | M100: =M95/L95 -> 1 | N100: =N95/M95 -> 1.2631579 | ... V100: =V95/U95 -> 1.4620033 | W100: =W95/U95 -> 1.3192175 | X100: =X95/V95 -> 1.3092922 | Y100: =Y95/W95 -> 1.2628202 | Z100: =Z95/X95 -> 1.2454798 | AA100: =AA95/Y95 -> 1.3922827 | AB100: =AB95/Z95 -> 1.1908984 | AC100: =AC95/AA95 -> 1.1679293 | AD100: =AD95/AB95 -> 1.1873634 | ... CL100: =CL95/CJ95 -> 1.0595837 | CM100: =CM95/CL95 -> 1.0617937 | CO100: - Opening MRR | CP100: =D100=CO100 -> FALSE
D101: Monthly NRR | F101: =IFERROR(SUM(F88,F94)/F88,0) -> 0 | G101: =SUM(G88,G94)/G88 -> 1 | H101: =SUM(H88,H94)/H88 -> 1 | I101: =SUM(I88,I94)/I88 -> 1 | J101: =SUM(J88,J94)/J88 -> 1 | K101: =SUM(K88,K94)/K88 -> 1 | L101: =SUM(L88,L94)/L88 -> 1 | M101: =SUM(M88,M94)/M88 -> 1 | N101: =SUM(N88,N94)/N88 -> 1 | ... CM101: =SUM(CM88,CM94)/CM88 -> 1.0084614 | CO101: - New Bookings ($) | CP101: =D101=CO101 -> FALSE
...

Sheet 2. Financial Metrics Actual Aud
E1: Particulars | F1: 44530 | G1: =EOMONTH(F1,1) -> 44561 | H1: =EOMONTH(G1,1) -> 44592 | I1: =EOMONTH(H1,1) -> 44620 | J1: =EOMONTH(I1,1) -> 44651 | K1: =EOMONTH(J1,1) -> 44681 | L1: =EOMONTH(K1,1) -> 44712 | M1: =EOMONTH(L1,1) -> 44742 | N1: =EOMONTH(M1,1) -> 44773 | ... V1: =EOMONTH(U1,1) -> 45016 | W1: 45046 | X1: =W1 -> 45046 | Y1: 45076 | Z1: =EOMONTH(X1,1) -> 45077 | AA1: 45107 | AB1: =AA1 -> 45107 | AC1: 45137 | AD1: =EOMONTH(AB1,1) -> 45138 | AE1: 45168 | AF1: =EOMONTH(AD1,1) -> 45169 | AG1: 45199 | AH1: =EOMONTH(AF1,1) -> 45199 | AI1: 45229 | AJ1: =EOMONTH(AH1,1) -> 45230 | AK1: 45260 | AL1: =EOMONTH(AJ1,1) -> 45260 | AM1: 45290 | AN1: =EOMONTH(AL1,1) -> 45291 | AO1: 45321 | AP1: =EOMONTH(AN1,1) -> 45322 | AQ1: 45351 | AR1: =EOMONTH(AP1,1) -> 45351 | AS1: 45380 | AT1: =EOMONTH(AR1,1) -> 45382 | AU1: =EOMONTH(AS1,1) -> 45412 | AV1: =AU1 -> 45412 | AW1: =EOMONTH(AU1,1) -> 45443 | AX1: =AW1 -> 45443 | AY1: =EOMONTH(AW1,1) -> 45473 | AZ1: =AY1 -> 45473 | BA1: =EOMONTH(AY1,1) -> 45504 | BB1: =BA1 -> 45504 | BC1: =EOMONTH(BA1,1) -> 45535 | BD1: =BC1 -> 45535 | BE1: =EOMONTH(BC1,1) -> 45565 | BF1: =BE1 -> 45565 | BG1: =EOMONTH(BE1,1) -> 45596 | BH1: =BG1 -> 45596 | BI1: =EOMONTH(BG1,1) -> 45626 | BJ1: =BI1 -> 45626 | BK1: =EOMONTH(BI1,1) -> 45657 | BL1: =BK1 -> 45657 | BM1: =EOMONTH(BK1,1) -> 45688 | BN1: =BM1 -> 45688 | BO1: =EOMONTH(BM1,1) -> 45716 | BP1: =BO1 -> 45716 | BQ1: =EOMONTH(BO1,1) -> 45747 | BR1: =BQ1 -> 45747 | BS1: =EOMONTH(BQ1,1) -> 45777 | BT1: =BS1 -> 45777 | BU1: =EOMONTH(BS1,1) -> 45808 | BV1: =BU1 -> 45808 | BW1: =EOMONTH(BU1,1) -> 45838 | BX1: =BW1 -> 45838 | BY1: =EOMONTH(BW1,1) -> 45869 | BZ1: =BY1 -> 45869 | CA1: =EOMONTH(BY1,1) -> 45900 | CB1: =CA1 -> 45900 | CC1: =EOMONTH(CA1,1) -> 45930 | CD1: =CC1 -> 45930 | CE1: =EOMONTH(CC1,1) -> 45961 | CF1: =CE1 -> 45961 | CG1: =EOMONTH(CE1,1) -> 45991 | CH1: =CG1 -> 45991 | CI1: =EOMONTH(CG1,1) -> 46022 | CJ1: =CI1 -> 46022 | CK1: =EOMONTH(CI1,1) -> 46053 | CL1: =CK1 -> 46053 | CM1: =EOMONTH(CK1,1) -> 46081 | CN1: =EOMONTH(CM1,1) -> 46112
F2: Actual | G2: Actual | H2: Actual | I2: Actual | J2: Actual | K2: Actual | L2: Actual | M2: Actual | N2: Actual | O2: Actual | P2: Actual | Q2: Actual | R2: Actual | S2: Actual | T2: Actual | U2: Actual | V2: Actual | W2: Plan | X2: Actual | Y2: Plan | Z2: Actual | AA2: Plan | AB2: Actual | AC2: Plan | AD2: Actual | AE2: Plan | AF2: Actual | AG2: Plan | AH2: Actual | AI2: Plan | AJ2: Actual | AK2: Plan | AL2: Actual | AM2: Plan | AN2: Actual | AO2: Plan | AP2: Actual | AQ2: Plan | AR2: Actual | AS2: Plan | AT2: Actual | AU2: Plan | AV2: Actual | AW2: Plan | AX2: Actual | AY2: Plan | AZ2: Actual | BA2: Plan | BB2: Actual | BC2: Plan | BD2: Actual | BE2: Plan | BF2: Actual | BG2: Plan | BH2: Actual | BI2: Plan | BJ2: Actual | BK2: Plan | BL2: Actual | BM2: Plan | BN2: Actual | BO2: Plan | BP2: Actual | BQ2: Plan | BR2: Actual | BS2: Plan | BT2: Actual | BU2: Plan | BV2: Actual | BW2: Plan | BX2: Actual | BY2: Plan | BZ2: Actual | CA2: Plan | CB2: Actual | CC2: Plan | CD2: Actual | CE2: Plan | CF2: Actual | CG2: Plan | CH2: Actual | CI2: Plan | CJ2: Actual | CK2: Plan | CL2: Actual | CM2: Plan | CN2: Plan
B3: =X3+Z3+AB3+AD3+AF3+AH3+AJ3+AL3+AN3+AP3+AR3+AT3 -> 3771270 | D3: =SUM(F3:V3)+X3+Z3+AB3+AD3+AF3+AH3+AJ3+AL3+AN3+AP3+AR3+AT3+AV3+AX3+AZ3+BB3+BD3+BF3+BH3+BJ3+BL3+BN3 -> 10827577 | E3: Revenue | F3: =F5+F10 -> 2173 | G3: =G5+G10 -> 3756 | H3: =H5+H10 -> 6626 | I3: =I5+I10 -> 8675 | J3: =J5+J10 -> 10229 | K3: =K5+K10 -> 15888 | L3: =L5+L10 -> 20370 | M3: =M5+M10 -> 23751 | ... CN3: =CN5+CN10 -> 1569483.2
CJ4: =CJ5*12 -> 16487484 | CL4: =CL5*12 -> 17061168
A5: =AV5+AX5+AZ5+BB5+BD5+BF5 -> 3400255 | B5: =SUM(F5:V5)+X5+AP5+AN5+AL5+AJ5+AH5+AF5+AD5+AB5+Z5+AR5+AT5 -> 4411856 | D5: =SUM(F5:V5)+X5+Z5+AB5+AD5+AF5+AH5+AJ5+AL5+AN5+AP5+AR5+AT5+AV5+AX5+AZ5+BB5+BD5+BF5+BH5+BJ5+BL5+BN5 -> 10701959 | E5: Subscription Revenue | F5: =F7+F8 -> 2173 | G5: =G7+G8 -> 3756 | H5: =H7+H8 -> 6626 | I5: =I7+I8 -> 8675 | J5: =J7+J8 -> 10229 | K5: =K7+K8 -> 15888 | L5: =L7+L8 -> 20370 | M5: =M7+M8 -> 23751 | ... CN5: =CN7+CN8 -> 1569483.2
CF6: =CF5*12 -> 15098208 | CJ6: =CJ8*12 -> 9642540 | CL6: =CL7*12 -> 7074120
B7: =SUM(F7:V7)+X7+AP7+AN7+AL7+AJ7+AH7+AF7+AD7+AB7+Z7+AR7+AT7+AV7+AX7+AZ7+BB7+BD7+BF7 -> 4771921 | D7: =SUM(F7:V7)+X7+Z7+AB7+AD7+AF7+AH7+AJ7+AL7+AN7+AP7+AR7+AT7+AV7+AX7+AZ7+BB7+BD7+BF7+BH7+BJ7+BL7+BN7 -> 6210949 | E7: India/APAC | F7: 1506 | G7: 3089 | H7: 5542 | I7: 7591 | J7: 9145 | K7: 14804 | L7: 18536 | M7: 21417 | N7: 23810 | O7: 29498 | P7: 39142 | Q7: 47563 | R7: 51871 | S7: 58109 | T7: 70577 | U7: 83178 | V7: 102303 | W7: 42312.972 | X7: 113400 | Y7: 55179.93 | Z7: 131106 | AA7: 68550.789 | AB7: 145203 | AC7: 81501.171 | AD7: 160126 | AE7: 96638.168 | AF7: 181367 | AG7: 114702.16 | AH7: 191676 | AI7: 133391.12 | AJ7: 202269 | AK7: 155107.82 | AL7: 215514 | AM7: 179593.5 | AN7: 234003 | AO7: 171509.48 | AP7: 245191 | AQ7: 184595.53 | AR7: 253609 | AS7: 203621.85 | AT7: 264946 | AU7: 220880.76 | AV7: 277680 | AW7: 239048.95 | AX7: 291420 | AY7: 255749.47 | AZ7: 305242 | BA7: 282394.29 | BB7: 317242 | BC7: 313673.77 | BD7: 320934 | BE7: 343427.5 | BF7: 333312 | BG7: 375332.71 | BH7: 337979 | BI7: 408184.09 | BJ7: 351369 | BK7: 445075.82 | BL7: 371136 | BM7: 419681.58 | BN7: 378544 | BO7: 444310.11 | BP7: 391807 | BQ7: 471175.8 | BR7: 411051 | BS7: 499633.07 | BT7: 423123 | BU7: 527578.17 | BV7: 440887 | BW7: 557698.78 | BX7: 463987 | BY7: 589894.62 | BZ7: 481220 | CA7: 624858.62 | CB7: 496125 | CC7: 663420.05 | CD7: 521879 | CE7: 700950.32 | CF7: 540683 | CG7: 741349.47 | CH7: 562524 | CI7: 784396.78 | CJ7: 570412 | CK7: 830229.76 | CL7: 589510 | CM7: 879697.89 | CN7: 934057.69
B8: =X8+Z8+AB8+AD8+AF8+AH8+AJ8+AL8+AN8+AP8+AR8+AT8 -> 1385628 | D8: =SUM(F8:V8)+X8+Z8+AB8+AD8+AF8+AH8+AJ8+AL8+AN8+AP8+AR8+AT8+AV8+AX8+AZ8+BB8+BD8+BF8+BH8+BJ8+BL8+BN8 -> 4491010 | E8: NA/EU | F8: 667 | G8: 667 | H8: 1084 | I8: 1084 | J8: 1084 | K8: 1084 | L8: 1834 | M8: 2334 | N8: 2334 | O8: 2959 | P8: 4597 | Q8: 5430 | R8: 6985 | S8: 11260 | T8: 12895 | U8: 15687 | V8: 28152 | W8: 152593.67 | X8: 37069 | Y8: 169625.69 | Z8: 47231 | AA8: 187848.51 | AB8: 67755 | AC8: 206076.29 | AD8: 78460 | AE8: 223972.83 | AF8: 90826 | AG8: 243649.37 | AH8: 106550 | AI8: 263838.8 | AJ8: 126968 | AK8: 283983.21 | AL8: 139617 | AM8: 304671.4 | AN8: 154172 | AO8: 276965.31 | AP8: 166473 | AQ8: 283518.43 | AR8: 177149 | AS8: 290098.19 | AT8: 193358 | AU8: 298794.65 | AV8: 206593 | AW8: 308544.62 | AX8: 229938 | AY8: 319037.53 | AZ8: 255393 | BA8: 332886.32 | BB8: 274088 | BC8: 349636.57 | BD8: 282492 | BE8: 367518.74 | BF8: 305921 | BG8: 386783.82 | BH8: 325896 | BI8: 406636.85 | BJ8: 349693 | BK8: 426848.16 | BL8: 374065 | BM8: 424579.62 | BN8: 401166 | BO8: 441822.57 | BP8: 443202 | BQ8: 459368.77 | BR8: 476325 | BS8: 477969.49 | BT8: 498445 | BU8: 496011.46 | BV8: 517737 | BW8: 509744.49 | BX8: 567204 | BY8: 523411 | BZ8: 598856 | CA8: 536673.3 | CB8: 640206 | CC8: 550277.48 | CD8: 677024 | CE8: 563164.91 | CF8: 717501 | CG8: 576870.96 | CH8: 756733 | CI8: 590968.53 | CJ8: 803545 | CK8: 605533.4 | CL8: 832254 | CM8: 620500.89 | CN8: 635425.51
CJ9: =CJ7*12 -> 6844944 | CL9: =CL8*12 -> 9987048
B10: =SUM(F10:V10)+X10+AP10+AN10+AL10+AJ10+AH10+AF10+AD10+AB10+Z10+AR10+AT10+AV10+AX10+AZ10+BB10+BD10+BF10 -> 94270 | D10: =SUM(F10:V10)+X10+Z10+AB10+AD10+AF10+AH10+AJ10+AL10+AN10+AP10+AR10+AT10+AV10+AX10+AZ10+BB10+BD10+BF10+BH10+BJ10+BL10+BN10 -> 125618 | E10: Non-Recurring Revenue | F10: 0 | G10: 0 | H10: 0 | I10: 0 | J10: 0 | K10: 0 | L10: 0 | M10: 0 | N10: 158 | O10: 223 | P10: 293 | Q10: 600 | R10: 908 | S10: 1102 | T10: 1220 | U10: 1220 | V10: 1697 | X10: 3034 | Z10: 3088 | AB10: 3439 | AD10: 3375 | AF10: 3433 | AH10: 3549 | AJ10: 3937 | AL10: 3661 | AN10: 4233 | AP10: 4695 | AR10: 4828 | AT10: 5960 | AV10: 5252 | AX10: 6382 | AZ10: 6332 | BB10: 6906 | BD10: 7078 | BF10: 7667 | BH10: 7368 | BJ10: 8170 | BL10: 7904 | BN10: 7906 | BP10: 9123 | BR10: 8249 | BT10: 8505 | BV10: 7980 | BX10: 8407 | BZ10: 8357 | CB10: 8722 | CD10: 9169 | CF10: 9564 | CH10: 9633 | CJ10: 10150 | CL10: 11208
E12: Cost of Goods Sold (COGS) | F12: =SUM(F14:F15) -> 649.0122 | G12: =SUM(G14:G15) -> 375 | H12: =SUM(H14:H15) -> 1348 | I12: =SUM(I14:I15) -> 1864 | J12: =SUM(J14:J15) -> 2245 | K12: =SUM(K14:K15) -> 3392.5488 | L12: =SUM(L14:L15) -> 5215.2805 | M12: =SUM(M14:M15) -> 5090.9878 | ... CN12: =SUM(CN14:CN15) -> 271448.45
W13: 0.6 | Y13: 0.6 | AA13: 0.6 | AC13: 0.6 | AE13: 0.6 | AG13: 0.6 | AI13: 0.6 | AK13: 0.6 | AM13: 0.6 | AO13: 0.6 | AQ13: 0.6 | AS13: 0.6 | AU13: 0.6 | AW13: 0.6 | AY13: 0.6 | BA13: 0.6 | BC13: 0.6 | BE13: 0.6 | BG13: 0.6 | BI13: 0.6 | BK13: 0.6 | BM13: 0.6 | BO13: 0.6 | BQ13: 0.6 | BS13: 0.6 | BU13: 0.6 | BW13: 0.6 | BY13: 0.6 | CA13: 0.6 | CC13: 0.6 | CE13: 0.6 | CG13: 0.6 | CI13: 0.6 | CK13: 0.6 | CM13: 0.6 | CN13: 0.6
A14: =$E$12&E14 -> Cost of Goods Sold (COGS)Server Hosting charges - Direct expenses | E14: Server Hosting charges - Direct expenses | F14: 649.0122 | G14: 0 | H14: 0 | I14: 0 | J14: 0 | K14: 77.54878 | L14: 927.28049 | M14: 187.9878 | N14: 0 | O14: 0 | P14: 69.048057 | Q14: 70.929103 | R14: 0 | S14: 0 | T14: 3.5308537 | U14: 377.33764 | V14: 0 | W14: 5629 | X14: 70.856098 | Y14: 6396 | Z14: 233.03195 | AA14: 7178 | AB14: 71.049756 | AC14: 7929 | AD14: 71.221951 | AE14: 8696 | AF14: 2885.5999 | AG14: 9494 | AH14: 2393.3604 | AI14: 10291 | AJ14: 10067.012 | AK14: 11104 | AL14: 13594.867 | AM14: 11933 | AN14: 14779.524 | AO14: 20000 | AP14: 13933.258 | AQ14: 21000 | AR14: 14861.563 | AS14: 22050 | AT14: 16545.515 | AU14: 23152.5 | AV14: 16194.994 | AW14: 24310.125 | AX14: 21332.801 | AY14: 25525.631 | AZ14: 22090.418 | BA14: 26801.913 | BB14: 25852.186 | BC14: 28142.008 | BD14: 26012.77 | BE14: 29549.109 | BF14: 29337.19 | BG14: 31026.564 | BH14: 31880.434 | BI14: 32577.893 | BJ14: 32982.835 | BK14: 34206.787 | BL14: 33589.732 | BM14: 35917.127 | BN14: 35202.978 | BO14: 37712.983 | BP14: 35202.978 | BQ14: 41484.281 | BR14: 35202.978 | BS14: 45632.709 | BT14: 43998.504 | BU14: 50195.98 | BV14: 43457.636 | BW14: 55215.578 | BX14: 49491.65 | BY14: 60737.136 | BZ14: 47989.219 | CA14: 66810.85 | CB14: 53346.931 | CC14: 73491.935 | CD14: 58932.474 | CE14: 80841.128 | CF14: 53610.119 | CG14: 88925.241 | CH14: 53267.091 | CI14: 97817.765 | CJ14: 58503.515 | CK14: 107599.54 | CL14: 61913.64 | CM14: 118359.5 | CN14: 130195.45
A15: =$E$12&E15 -> Cost of Goods Sold (COGS)Direct Expenses for third-party Audit | B15: =X15+Z15+AB15+AD15+AF15+AH15+AJ15+AL15+AN15+AP15+AR15+AT15+SUM(F15:U15) -> 687310 | E15: Direct Expenses for third-party Audit | F15: 0 | G15: 375 | H15: 1348 | I15: 1864 | J15: 2245 | K15: 3315 | L15: 4288 | M15: 4903 | N15: 5620 | O15: 7509 | P15: 9586 | Q15: 11476 | R15: 12889 | S15: 14764 | T15: 16805 | U15: 19317 | V15: 24573 | W15: 33533.333 | X15: 28534 | Y15: 37750 | Z15: 33172 | AA15: 42146.667 | AB15: 37685 | AC15: 46225 | AD15: 40781 | AE15: 50391.667 | AF15: 45095 | AG15: 54771.667 | AH15: 49629 | AI15: 59271.667 | AJ15: 49807 | AK15: 63430 | AL15: 52160 | AM15: 67538.333 | AN15: 56181 | AO15: 50000 | AP15: 57766 | AQ15: 44170.525 | AR15: 59267 | AS15: 37707.213 | AT15: 60929 | AU15: 43018.223 | AV15: 60756 | AW15: 37375.725 | AX15: 61996 | AY15: 36851.969 | AZ15: 63280 | BA15: 39158.534 | BB15: 63281 | BC15: 58310.806 | BD15: 62681 | BE15: 69162.82 | BF15: 63337 | BG15: 68595.692 | BH15: 63850 | BI15: 73685.221 | BJ15: 65641 | BK15: 75894.35 | BL15: 67426 | BM15: 84426 | BN15: 67942 | BO15: 88613 | BP15: 71325 | BQ15: 93054 | BR15: 74298 | BS15: 97760 | BT15: 74382 | BU15: 102359 | BV15: 73058 | BW15: 106744 | BX15: 77284 | BY15: 105764 | BZ15: 80568 | CA15: 110346 | CB15: 78588 | CC15: 115301 | CD15: 79967 | CE15: 120091 | CF15: 80952 | CG15: 118640 | CH15: 82470 | CI15: 123783 | CJ15: 83191 | CK15: 129219 | CL15: 85159 | CM15: 135018 | CN15: 141253
E17: Customer Success | F17: =SUM(F18:F20) -> 0 | G17: =SUM(G18:G20) -> 0 | H17: =SUM(H18:H20) -> 0 | I17: =SUM(I18:I20) -> 80.378049 | J17: =SUM(J18:J20) -> 1941.8462 | K17: =SUM(K18:K20) -> 4839.1171 | L17: =SUM(L18:L20) -> 6040.9012 | M17: =SUM(M18:M20) -> 6573.4774 | ... CN17: =SUM(CN18:CN20) -> 75379.498
A18: =$E$17&E18 -> Customer SuccessPeople cost | E18: People cost | F18: 0 | G18: 0 | H18: 0 | I18: 80.378049 | J18: 1811.5657 | K18: 4408.5439 | L18: 5494.7122 | M18: 5518.3098 | N18: 12565.105 | O18: 7347.578 | P18: 9429.4046 | Q18: 15857.144 | R18: 7281.5927 | S18: 8079.2488 | T18: 16948.288 | U18: 15504.585 | V18: 16942.427 | W18: 26054.878 | X18: 19138.476 | Y18: 28213.415 | Z18: 22591.854 | AA18: 27774.39 | AB18: 22756.432 | AC18: 28213.415 | AD18: 24854.164 | AE18: 28213.415 | AF18: 21100.62 | AG18: 34207.317 | AH18: 22127.457 | AI18: 34207.317 | AJ18: 24891.362 | AK18: 34207.317 | AL18: 24942.857 | AM18: 42615.854 | AN18: 29502.437 | AO18: 17405.866 | AP18: 31508.956 | AQ18: 17607.944 | AR18: 26173.211 | AS18: 31572.897 | AT18: 28861.034 | AU18: 34425.19 | AV18: 36691.331 | AW18: 49420.688 | AX18: 35241.281 | AY18: 49660.504 | AZ18: 27378.524 | BA18: 52330.54 | BB18: 31099.617 | BC18: 52983.182 | BD18: 32805.338 | BE18: 61455.029 | BF18: 33158.388 | BG18: 53857.742 | BH18: 37263.781 | BI18: 55376.004 | BJ18: 39643.067 | BK18: 56979.091 | BL18: 40054.288 | BM18: 40490.453 | BN18: 44544.271 | BO18: 41990.453 | BP18: 43095.588 | BQ18: 42890.453 | BR18: 43571.642 | BS18: 44390.453 | BT18: 55503.874 | BU18: 45290.453 | BV18: 63789.899 | BW18: 46534.498 | BX18: 67453.103 | BY18: 60019.498 | BZ18: 71392.147 | CA18: 60019.498 | CB18: 71485.056 | CC18: 63559.498 | CD18: 66824.746 | CE18: 62659.498 | CF18: 67964.129 | CG18: 67699.498 | CH18: 69770.346 | CI18: 66199.498 | CJ18: 72648.867 | CK18: 70339.498 | CL18: 71151.117 | CM18: 71989.498 | CN18: 73879.498
A19: =$E$17&E19 -> Customer SuccessTravel and expenses | E19: Travel and expenses | F19: 0 | G19: 0 | H19: 0 | I19: 0 | J19: 130.28049 | K19: 248.93902 | L19: 346.55488 | M19: 341.28049 | N19: 0 | O19: 321.26024 | P19: 16.231707 | Q19: 417.58537 | R19: 1088.0838 | S19: 0 | T19: 348.96415 | U19: 24.317073 | V19: 317.95744 | W19: 0 | X19: 0 | Y19: 0 | Z19: 35.426829 | AA19: 0 | AB19: 0 | AC19: 0 | AD19: 21.853659 | AE19: 0 | AF19: 83.378049 | AG19: 0 | AH19: 0 | AI19: 0 | AJ19: 115.85366 | AK19: 0 | AL19: 0 | AM19: 0 | AN19: 1777.0637 | AO19: 0 | AP19: 0 | AQ19: 0 | AR19: 180.72289 | AS19: 0 | AT19: 51.771084 | AU19: 0 | AV19: 440.79548 | AW19: 0 | AX19: 1059.9735 | AY19: 0 | AZ19: 927.26512 | BA19: 0 | BB19: 293.88095 | BC19: 0 | BD19: 1329.8089 | BE19: 0 | BF19: 373.30429 | BG19: 0 | BH19: 879.12048 | BI19: 0 | BJ19: 579.65333 | BK19: 0 | BL19: 992.84929 | BM19: 0 | BN19: 2146.57 | BO19: 0 | BP19: 1191.7598 | BQ19: 0 | BR19: 4344.3087 | BS19: 0 | BT19: 2630.7406 | BU19: 0 | BV19: 0 | BW19: 0 | BX19: 891.50906 | BY19: 0 | BZ19: 808.96365 | CA19: 0 | CB19: 929.29635 | CC19: 0 | CD19: 1807.7594 | CE19: 0 | CF19: 202.32941 | CG19: 0 | CH19: 484.336 | CI19: 0 | CJ19: 493.76141 | CK19: 0 | CL19: 0 | CM19: 0 | CN19: 0
A20: =$E$17&E20 -> Customer SuccessSoftware subscription | E20: Software subscription | F20: 0 | G20: 0 | H20: 0 | I20: 0 | J20: 0 | K20: 181.63415 | L20: 199.63415 | M20: 713.8872 | N20: 713.8872 | O20: 713.8872 | P20: 1729.8872 | Q20: 1729.7848 | R20: 2448.924 | S20: 2317.4439 | T20: 3217.6024 | U20: 2317.4439 | V20: 2399.4289 | W20: 2511 | X20: 2566.8382 | Y20: 2547 | Z20: 2389.8748 | AA20: 2547 | AB20: 1875.6217 | AC20: 3003 | AD20: 1875.6217 | AE20: 3003 | AF20: 1875.6217 | AG20: 3003 | AH20: 875.62172 | AI20: 3213 | AJ20: 841.72412 | AK20: 3423 | AL20: 372.06504 | AM20: 3423 | AN20: 758.06504 | AO20: 1500 | AP20: 755.00402 | AQ20: 1500 | AR20: 755.00402 | AS20: 1500 | AT20: 755.00402 | AU20: 1500 | AV20: 503.75 | AW20: 1500 | AX20: 503.75 | AY20: 1500 | AZ20: 503.75 | BA20: 1500 | BB20: 1810.56 | BC20: 1500 | BD20: 1810.56 | BE20: 1500 | BF20: 1810.56 | BG20: 1500 | BH20: 1810.56 | BI20: 1500 | BJ20: 1693.02 | BK20: 1500 | BL20: 1306.81 | BM20: 1500 | BN20: 1306.81 | BO20: 1500 | BP20: 1306.81 | BQ20: 1500 | BR20: 1306.81 | BS20: 1500 | BT20: 1340.4608 | BU20: 1500 | BV20: 1327.7989 | BW20: 1500 | BX20: 1695.33 | BY20: 1500 | BZ20: 1638.52 | CA20: 1500 | CB20: 2971.85 | CC20: 1500 | CD20: 2971.85 | CE20: 1500 | CF20: 2959.6265 | CG20: 1500 | CH20: 4913.81 | CI20: 1500 | CJ20: 3525.46 | CK20: 1500 | CL20: 2971.85 | CM20: 1500 | CN20: 1500
E22: Total COGS | F22: =SUM(F12,F17) -> 649.0122 | G22: =SUM(G12,G17) -> 375 | H22: =SUM(H12,H17) -> 1348 | I22: =SUM(I12,I17) -> 1944.378 | J22: =SUM(J12,J17) -> 4186.8462 | K22: =SUM(K12,K17) -> 8231.6659 | L22: =SUM(L12,L17) -> 11256.182 | M22: =SUM(M12,M17) -> 11664.465 | ... CN22: =SUM(CN12,CN17) -> 346827.94
E24: Gross profit | F24: =F3-SUM(F14:F15)-SUM(F18:F20) -> 1523.9878 | G24: =G3-SUM(G14:G15)-SUM(G18:G20) -> 3381 | H24: =H3-SUM(H14:H15)-SUM(H18:H20) -> 5278 | I24: =I3-SUM(I14:I15)-SUM(I18:I20) -> 6730.622 | J24: =J3-SUM(J14:J15)-SUM(J18:J20) -> 6042.1538 | K24: =K3-SUM(K14:K15)-SUM(K18:K20) -> 7656.3341 | L24: =L3-SUM(L14:L15)-SUM(L18:L20) -> 9113.8183 | M24: =M3-SUM(M14:M15)-SUM(M18:M20) -> 12086.535 | ... CN24: =CN3-SUM(CN14:CN15)-SUM(CN18:CN20) -> 1222655.3
E25: Gross Margin (%) | F25: =F24/F3 -> 0.70132895 | G25: =G24/G3 -> 0.90015974 | H25: =H24/H3 -> 0.79655901 | I25: =I24/I3 -> 0.7758642 | J25: =J24/J3 -> 0.59068861 | K25: =+K24/K3 -> 0.48189414 | L25: =+L24/L3 -> 0.44741376 | M25: =+M24/M3 -> 0.5088853 | N25: =N24/N3 -> 0.28146179 | O25: =O24/O3 -> 0.51371709 | P25: =P24/P3 -> 0.52692198 | Q25: =Q24/Q3 -> 0.44859509 | R25: =R24/R3 -> 0.60331302 | S25: =S24/S3 -> 0.64296388 | T25: =T24/T3 -> 0.55930448 | U25: =U24/U3 -> 0.62491199 | ... CN25: =CN24/CN3 -> 0.77901774
A27: =E27&E27 -> Other IncomeOther Income | E27: Other Income | F27: 0 | G27: 0 | H27: 0 | I27: 0 | J27: 0 | K27: 0 | L27: 0 | M27: 0 | N27: 0 | O27: 0 | W27: 0 | Y27: 0 | AA27: 0 | AC27: 0 | AE27: 0 | AG27: 0 | AI27: 0 | AK27: 0 | AM27: 0 | AO27: 0 | AQ27: 0 | AS27: 0 | AU27: 0 | AW27: 0 | AY27: 0 | BA27: 0 | BC27: 0 | BE27: 0 | BG27: 0 | BI27: 0 | BK27: 0 | BM27: 0 | BO27: 0 | BQ27: 0 | BS27: 0 | BU27: 0 | BW27: 0 | BY27: 0 | CA27: 0 | CC27: 0 | CE27: 0 | CG27: 0 | CI27: 0 | CK27: 0 | CM27: 0 | CN27: 0
E28: Less: Cost
E29: Sales and Marketing Costs | F29: =SUM(F30:F37) -> 215.67634 | G29: =SUM(G30:G37) -> 513.97744 | H29: =SUM(H30:H37) -> 3818.9423 | I29: =SUM(I30:I37) -> 1240.0004 | J29: =SUM(J30:J37) -> 12171.891 | K29: =SUM(K30:K37) -> 15259.626 | L29: =SUM(L30:L37) -> 22311.458 | M29: =SUM(M30:M37) -> 32442.607 | ... AN29: =SUM(AN30:AN37) -> 305621.07 | AO29: =SUM(AO30:AO38) -> 488889.92 | AP29: =SUM(AP30:AP38) -> 410081.68 | AQ29: =SUM(AQ30:AQ38) -> 490739.59 | AR29: =SUM(AR30:AR38) -> 434726.51 | AS29: =SUM(AS30:AS38) -> 513824.82 | AT29: =SUM(AT30:AT38) -> 454074.99 | AU29: =SUM(AU30:AU38) -> 521269.27 | AV29: =SUM(AV30:AV38) -> 491256.13 | ... CN29: =SUM(CN30:CN38) -> 883744.92
A30: =$E$29&E30 -> Sales and Marketing CostsPeople cost | E30: People cost | F30: 121.95122 | G30: 0 | H30: 0 | I30: 609.34146 | J30: 2987.3678 | K30: 9462.4049 | L30: 9981.8174 | M30: 15489.498 | N30: 27217.872 | O30: 17267.461 | P30: 22233.108 | Q30: 47076.007 | R30: 32462.96 | S30: 55344.064 | T30: 98013.455 | U30: 124771.76 | V30: 150036.63 | W30: 185326 | X30: 190508.87 | Y30: 185538 | Z30: 195476.53 | AA30: 192048 | AB30: 172968.82 | AC30: 187367 | AD30: 191208.82 | AE30: 195370 | AF30: 177873.5 | AG30: 198714 | AH30: 184108.31 | AI30: 210528 | AJ30: 176158.7 | AK30: 209995 | AL30: 190077.19 | AM30: 223763 | AN30: 202423.04 | AO30: 211168.25 | AP30: 220160.56 | AQ30: 217418.25 | AR30: 219630.87 | AS30: 236168.25 | AT30: 216705.89 | AU30: 278039.33 | AV30: 266256.47 | AW30: 278039.33 | AX30: 260064.43 | AY30: 279351.83 | AZ30: 242793.61 | BA30: 266638.33 | BB30: 293937.09 | BC30: 274006.59 | BD30: 231369.95 | BE30: 292756.59 | BF30: 252301.71 | BG30: 307083.17 | BH30: 276056.97 | BI30: 307083.17 | BJ30: 267971.98 | BK30: 307083.17 | BL30: 338969.45 | BM30: 320245.91 | BN30: 315548.14 | BO30: 323192.58 | BP30: 320184.46 | BQ30: 311359.25 | BR30: 286909.55 | BS30: 324497.59 | BT30: 341285.99 | BU30: 310072.59 | BV30: 340828.98 | BW30: 326709.59 | BX30: 395297.83 | BY30: 339694.51 | BZ30: 311095.88 | CA30: 334397.09 | CB30: 329903.88 | CC30: 332060.5 | CD30: 344346.56 | CE30: 357400.58 | CF30: 379463.71 | CG30: 374732.25 | CH30: 376599.69 | CI30: 416963.08 | CJ30: 386587.34 | CK30: 402394.67 | CL30: 389680.68 | CM30: 384592.69 | CN30: 393759.35
A31: =$E$29&E31 -> Sales and Marketing CostsTravel and expenses | E31: Travel and expenses | F31: 0 | G31: 0 | H31: 0 | I31: 0 | J31: 0 | K31: 103.26829 | L31: 783.28049 | M31: 296.29268 | N31: 1886.5884 | O31: 1373.6818 | P31: 2993.9756 | Q31: 1225.8415 | R31: 6800.0809 | S31: 13191.976 | T31: 1981.8482 | U31: 12469.123 | V31: 5031.3894 | W31: 24097.561 | X31: 7056.6017 | Y31: 24097.561 | Z31: 14606.364 | AA31: 24097.561 | AB31: 5933.3143 | AC31: 23275.61 | AD31: 24531.59 | AE31: 23275.61 | AF31: 20689.305 | AG31: 23275.61 | AH31: 41496.658 | AI31: 23653.659 | AJ31: 29052.203 | AK31: 23653.659 | AL31: 20648.609 | AM31: 24409.756 | AN31: 8405.2498 | AO31: 26675 | AP31: 15032.623 | AQ31: 28341.667 | AR31: 23843.306 | AS31: 28445.833 | AT31: 22492.2 | AU31: 29383.333 | AV31: 44783.074 | AW31: 29383.333 | AX31: 22355.383 | AY31: 29383.333 | AZ31: 5171.2168 | BA31: 29591.667 | BB31: 14462.177 | BC31: 29800 | BD31: 11193.15 | BE31: 30633.333 | BF31: 3881.2852 | BG31: 31050 | BH31: 22174.092 | BI31: 31050 | BJ31: 10667.803 | BK31: 31050 | BL31: 15191.272 | BM31: 12479.167 | BN31: 5105.5321 | BO31: 12479.167 | BP31: 1223.0979 | BQ31: 12479.167 | BR31: 9422.4119 | BS31: 12479.167 | BT31: 10923.405 | BU31: 12479.167 | BV31: 19717.548 | BW31: 12062.5 | BX31: 11143.985 | BY31: 12479.167 | BZ31: 2909.9082 | CA31: 12062.5 | CB31: 2788.23 | CC31: 12062.5 | CD31: 19087.38 | CE31: 12479.167 | CF31: 14276.253 | CG31: 12479.167 | CH31: 1631.8598 | CI31: 12479.167 | CJ31: 7363.2701 | CK31: 12479.167 | CL31: 20417.681 | CM31: 12479.167 | CN31: 12479.167
A32: =$E$29&E32 -> Sales and Marketing CostsDemand Gen | E32: Demand Gen | F32: 24.365854 | G32: 365.85366 | H32: 205.08537 | I32: 404.87841 | J32: 6519.061 | K32: 4548.7927 | L32: 7638.7667 | M32: 5280.5 | N32: 3940.3576 | O32: 5303.1707 | P32: 9079.1629 | Q32: 12691.733 | R32: 18908.637 | S32: 20575.841 | T32: 14591.844 | U32: 11843.529 | V32: 32730.908 | W32: 113572 | X32: 19031.307 | Y32: 117210 | Z32: 66417.076 | AA32: 124143 | AB32: 42851.508 | AC32: 132309 | AD32: 39497.355 | AE32: 141354 | AF32: 58775.596 | AG32: 145773 | AH32: 48956.375 | AI32: 145591 | AJ32: 52157.081 | AK32: 145410 | AL32: 66542.676 | AM32: 144702 | AN32: 52985.611 | AO32: 132733.33 | AP32: 118497.86 | AQ32: 125538.33 | AR32: 125713.71 | AS32: 129802.78 | AT32: 125749.28 | AU32: 107853.95 | AV32: 106301.94 | AW32: 118863.15 | AX32: 132156.59 | AY32: 122053.64 | AZ32: 111895.94 | BA32: 124171.27 | BB32: 134984.71 | BC32: 152685.32 | BD32: 214443.18 | BE32: 187557.71 | BF32: 175400.46 | BG32: 209649.87 | BH32: 277428.81 | BI32: 213182.74 | BJ32: 249307.6 | BK32: 224745.88 | BL32: 195105.12 | BM32: 248760.94 | BN32: 243153.34 | BO32: 257327.06 | BP32: 297327.48 | BQ32: 266292.16 | BR32: 275907.03 | BS32: 250741.43 | BT32: 254066.7 | BU32: 257819.55 | BV32: 271400.6 | BW32: 265251.53 | BX32: 296909.76 | BY32: 272546.05 | BZ32: 309836.89 | CA32: 276847.15 | CB32: 267119.88 | CC32: 280257.92 | CD32: 410063.55 | CE32: 283794.51 | CF32: 425524.58 | CG32: 286319.26 | CH32: 278581.68 | CI32: 288524.52 | CJ32: 288037.53 | CK32: 290768.93 | CL32: 241478.75 | CM32: 293053.75 | CN32: 294985.63
A33: =$E$29&E33 -> Sales and Marketing CostsBranding and community | E33: Branding and community | F33: 0 | G33: 0 | H33: 0 | I33: 0 | J33: 0 | K33: 0 | L33: 0 | M33: 0 | N33: 2274.7073 | O33: 2302.7195 | P33: 0 | Q33: 408.66854 | R33: 1941.0122 | S33: 2176.2601 | T33: 1707.3171 | U33: 10934.837 | V33: 2312.7347 | W33: 8100 | X33: 19481.149 | Y33: 8100 | Z33: 0 | AA33: 8100 | AB33: 0 | AC33: 20750 | AD33: 7637.0336 | AE33: 20750 | AF33: 10960.815 | AG33: 20750 | AH33: 4288.9228 | AI33: 20750 | AJ33: 4288.9228 | AK33: 20750 | AL33: 6156.8435 | AM33: 20750 | AN33: 6156.8435 | AO33: 17250 | AP33: 6082.6647 | AQ33: 17250 | AR33: 6082.6647 | AS33: 17250 | AT33: 15934.172 | AU33: 2916.6667 | AV33: 25554.308 | AW33: 2916.6667 | AX33: 13938.936 | AY33: 2916.6667 | AZ33: 27157.889 | BA33: 2916.6667 | BB33: 3879.9402 | BC33: 2916.6667 | BD33: 9544.9402 | BE33: 2916.6667 | BF33: 31773.988 | BG33: 27916.667 | BH33: 32131.387 | BI33: 27916.667 | BJ33: 20908.631 | BK33: 27916.667 | BL33: 29640.391 | BM33: 25833.333 | BN33: 19194.156 | BO33: 25833.333 | BP33: 20601.979 | BQ33: 25833.333 | BR33: 56012.236 | BS33: 29828.467 | BT33: 69206.888 | BU33: 29948.467 | BV33: 76812.743 | BW33: 30071.8 | BX33: 55728.502 | BY33: 30198.467 | BZ33: 42645.211 | CA33: 30328.467 | CB33: 20847.106 | CC33: 32961.8 | CD33: 18242.097 | CE33: 33101.8 | CF33: 11564.81 | CG33: 33101.8 | CH33: 11446.894 | CI33: 33101.8 | CJ33: 15433.45 | CK33: 34833.333 | CL33: 12705.141 | CM33: 34833.333 | CN33: 34833.333
A34: =$E$29&E34 -> Sales and Marketing CostsMarketing Tech Stack | E34: Marketing Tech Stack | F34: 55.871463 | G34: 28.400854 | H34: 2691.857 | I34: 0 | J34: 2433.0844 | K34: 763.52049 | L34: 2483.6122 | M34: 3080.0669 | N34: 1923.3144 | O34: 3820.8916 | P34: 2771.5731 | Q34: 4246.6987 | R34: 5064.429 | S34: 3388.6898 | T34: 5399.9064 | U34: 3273.3351 | V34: 2186.5751 | W34: 11921.951 | X34: 49286.417 | Y34: 11800 | Z34: 24708.869 | AA34: 26150 | AB34: 24362.622 | AC34: 11921.951 | AD34: 15163.444 | AE34: 12226.829 | AF34: 17950.254 | AG34: 12226.829 | AH34: 18396.654 | AI34: 12470.732 | AJ34: 10471.585 | AK34: 12470.732 | AL34: 9041.7052 | AM34: 12714.634 | AN34: 5898.4552 | AO34: 24330 | AP34: 11068.886 | AQ34: 24795 | AR34: 16777.536 | AS34: 25271.625 | AT34: 20731.516 | AU34: 26280.166 | AV34: 19285.986 | AW34: 26780.92 | AX34: 28884.936 | AY34: 27294.193 | AZ34: 15876.187 | BA34: 29077.909 | BB34: 16990.749 | BC34: 30073.265 | BD34: 16444.843 | BE34: 31115.78 | BF34: 24737.16 | BG34: 32207.746 | BH34: 19972.812 | BI34: 33351.569 | BJ34: 21413.902 | BK34: 34549.774 | BL34: 25919.356 | BM34: 35805.67 | BN34: 20895.669 | BO34: 37121.392 | BP34: 25107.122 | BQ34: 38499.858 | BR34: 36684.911 | BS34: 39661.334 | BT34: 37555.488 | BU34: 41043.543 | BV34: 21009.778 | BW34: 42494.862 | BX34: 21059.618 | BY34: 44018.747 | BZ34: 23934.648 | CA34: 45618.826 | CB34: 21632.738 | CC34: 47298.909 | CD34: 22646.588 | CE34: 49062.996 | CF34: 20957.328 | CG34: 50915.288 | CH34: 28042.403 | CI34: 52860.194 | CJ34: 23299.033 | CK34: 54902.346 | CL34: 23309.378 | CM34: 57046.605 | CN34: 59298.077
A35: =$E$29&E35 -> Sales and Marketing CostsContent | E35: Content | F35: 13.487805 | G35: 119.72293 | H35: 922 | I35: 225.78049 | J35: 232.37805 | K35: 381.63976 | L35: 40.176341 | M35: 4714.969 | N35: 40.176341 | O35: 11115.457 | P35: 12334.969 | Q35: 9978.8916 | R35: 4186.6924 | S35: 6757.3554 | T35: 8143.5787 | U35: 3774.7293 | V35: 9567.2796 | W35: 13395.122 | X35: 13715.524 | Y35: 13395.122 | Z35: 23324.329 | AA35: 18395.122 | AB35: 16886.256 | AC35: 13395.122 | AD35: 13370.376 | AE35: 12195.122 | AF35: 10898.915 | AG35: 21195.122 | AH35: 10940.585 | AI35: 16195.122 | AJ35: 10531.273 | AK35: 16195.122 | AL35: 10699.153 | AM35: 21195.122 | AN35: 10785.395 | AO35: 24033.333 | AP35: 10490.325 | AQ35: 24533.333 | AR35: 10731.289 | AS35: 23858.333 | AT35: 12396.108 | AU35: 24109.583 | AV35: 6475 | AW35: 24688.396 | AX35: 6475 | AY35: 25296.149 | AZ35: 6825 | BA35: 24734.29 | BB35: 6475 | BC35: 25404.338 | BD35: 13425 | BE35: 24007.888 | BF35: 0 | BG35: 24233.333 | BH35: 9767.95 | BI35: 24233.333 | BJ35: 0 | BK35: 30900 | BL35: 6733.67 | BM35: 18417.857 | BN35: 1666.67 | BO35: 18496.607 | BP35: 17021.67 | BQ35: 18579.295 | BR35: 8666.67 | BS35: 18666.117 | BT35: 1666.67 | BU35: 18757.279 | BV35: 15666.67 | BW35: 18853.001 | BX35: 8666.67 | BY35: 18953.508 | BZ35: 8676.67 | CA35: 19059.04 | CB35: 1676.67 | CC35: 19169.849 | CD35: 1691.67 | CE35: 19286.199 | CF35: 1691.67 | CG35: 19408.366 | CH35: 17691.67 | CI35: 12869.975 | CJ35: 2225 | CK35: 13004.664 | CL35: 2225 | CM35: 13146.088 | CN35: 13294.583
A36: =$E$29&E36 -> Sales and Marketing CostsReferrals and Expansion | E36: Referrals and Expansion | F36: 0 | G36: 0 | H36: 0 | I36: 0 | J36: 0 | K36: 0 | L36: 1383.8049 | M36: 3581.2805 | N36: 3828.4634 | O36: 0 | P36: 0 | Q36: 3413.4146 | R36: 0 | S36: 1189.0244 | T36: 2990.3049 | U36: 0 | V36: 2226.0732 | W36: 13062.613 | X36: 5040.6146 | Y36: 14112.69 | Z36: 10778.085 | AA36: 14927.741 | AB36: 18436.512 | AC36: 15732.972 | AD36: 3397.2439 | AE36: 16439.519 | AF36: 14923.707 | AG36: 17085.425 | AH36: 14837.317 | AI36: 17975.268 | AJ36: 16714.951 | AK36: 19850.979 | AL36: 11075.305 | AM36: 20888.562 | AN36: 6690.2439 | AO36: 14500 | AP36: 18922.528 | AQ36: 14663 | AR36: 14302.44 | AS36: 14827.99 | AT36: 12793.524 | AU36: 13811.252 | AV36: 7142.8571 | AW36: 18626.946 | AX36: 0 | AY36: 18775.066 | AZ36: 1200 | BA36: 18844.56 | BB36: 5475 | BC36: 18876.406 | BD36: 4499 | BE36: 22157.14 | BF36: 2854.6667 | BG36: 22222.112 | BH36: 8538.3333 | BI36: 23667.733 | BJ36: 5522.619 | BK36: 23734.01 | BL36: 6408.4286 | BM36: 15296.237 | BN36: 4551.4706 | BO36: 15444.223 | BP36: 11320.5 | BQ36: 16273.396 | BR36: 10351.088 | BS36: 19136.369 | BT36: 8295 | BU36: 20108.075 | BV36: 14571 | BW36: 22685.934 | BX36: 17820.75 | BY36: 23047.393 | BZ36: 9690 | CA36: 24730.738 | CB36: 14160 | CC36: 27025.238 | CD36: 23017.907 | CE36: 24830.629 | CF36: 18245.654 | CG36: 26047.09 | CH36: 15581.692 | CI36: 26584.174 | CJ36: 16716.597 | CK36: 26853.001 | CL36: 10807.689 | CM36: 27469.639 | CN36: 30094.769
A37: =$E$29&E37 -> Sales and Marketing CostsEvents | E37: Events | F37: 0 | G37: 0 | H37: 0 | I37: 0 | J37: 0 | K37: 0 | L37: 0 | M37: 0 | N37: 74.914634 | O37: 64.756098 | P37: 1144.5122 | Q37: 1371.9512 | R37: 1371.9512 | S37: 11927.537 | T37: 1371.9512 | U37: 36581.111 | V37: 32386.651 | W37: 70555.556 | X37: 1603.7712 | Y37: 15000 | Z37: 3341.3124 | AA37: 70000 | AB37: 12486.395 | AC37: 41000 | AD37: 6241.8483 | AE37: 33000 | AF37: 19623.139 | AG37: 48000 | AH37: 28452.757 | AI37: 18000 | AJ37: 8534.142 | AK37: 48000 | AL37: 8925.8666 | AM37: 48000 | AN37: 12276.235 | AO37: 26666.667 | AP37: 9826.2332 | AQ37: 26666.667 | AR37: 17644.693 | AS37: 26666.667 | AT37: 27272.31 | AU37: 26666.667 | AV37: 15456.497 | AW37: 26666.667 | AX37: 12127.021 | AY37: 26666.667 | AZ37: 11609.301 | BA37: 26666.667 | BB37: 11781.3 | BC37: 26666.667 | BD37: 12289.135 | BE37: 26666.667 | BF37: 17506.991 | BG37: 42000 | BH37: 22339.87 | BI37: 42000 | BJ37: 30360.418 | BK37: 42000 | BL37: 19105.877 | BM37: 30000 | BN37: 41428.18 | BO37: 30000 | BP37: 36765.5 | BQ37: 30000 | BR37: 99383.77 | BS37: 30000 | BT37: 49106.537 | BU37: 30000 | BV37: 17407.59 | BW37: 30000 | BX37: 54663.37 | BY37: 30000 | BZ37: 73787.646 | CA37: 30000 | CB37: 41659.174 | CC37: 30000 | CD37: 20758.895 | CE37: 30000 | CF37: 20314.203 | CG37: 30000 | CH37: 13939.652 | CI37: 30000 | CJ37: 22484.36 | CK37: 30000 | CL37: 50572.506 | CM37: 30000 | CN37: 30000
A38: =$E$29&E38 -> Sales and Marketing CostsPartnerships | E38: Partnerships | AO38: 11533.333 | AQ38: 11533.333 | AS38: 11533.333 | AU38: 12208.333 | AV38: 0 | AW38: 12208.333 | AX38: 0 | AY38: 12208.333 | AZ38: 0 | BA38: 12208.333 | BB38: 0 | BC38: 13208.333 | BD38: 0 | BE38: 13208.333 | BF38: 0 | BG38: 13208.333 | BH38: 0 | BI38: 13208.333 | BJ38: 0 | BK38: 13208.333 | BL38: 0 | BM38: 12333.333 | BN38: 0 | BO38: 12333.333 | BP38: 0 | BQ38: 12333.333 | BR38: 0 | BS38: 12500 | BT38: 0 | BU38: 12500 | BV38: 0 | BW38: 12500 | BX38: 0 | BY38: 12500 | BZ38: 0 | CA38: 12500 | CB38: 0 | CC38: 12500 | CD38: 0 | CE38: 15000 | CF38: 0 | CG38: 15000 | CH38: 0 | CI38: 15000 | CJ38: 0 | CK38: 15000 | CL38: 0 | CM38: 15000 | CN38: 15000
E40: Product and Engineering | F40: =SUM(F41:F46) -> 1687.5284 | G40: =SUM(G41:G46) -> 1687.5284 | H40: =SUM(H41:H46) -> 1687.5284 | I40: =SUM(I41:I46) -> 1714.3211 | J40: =SUM(J41:J46) -> 4500.4068 | K40: =SUM(K41:K46) -> 9368.8527 | L40: =SUM(L41:L46) -> 17689.069 | M40: =SUM(M41:M46) -> 22105.612 | ... CN40: =SUM(CN41:CN46) -> 370992.78
A41: =$E$40&E41 -> Product and EngineeringPeople cost- Product & Engineering | E41: People cost- Product & Engineering | F41: 1687.5284 | G41: 1687.5284 | H41: 1687.5284 | I41: 1714.3211 | J41: 4500.4068 | K41: 9352.3073 | L41: 17468.86 | M41: 21925.034 | N41: 23519.244 | O41: 22020.4 | P41: 28319.55 | Q41: 28354.837 | R41: 27643.185 | S41: 33397.01 | T41: 41242.185 | U41: 46544.285 | V41: 55408.467 | W41: 104132.11 | X41: 62460.662 | Y41: 123957.32 | Z41: 71433.266 | AA41: 127367.89 | AB41: 71396.441 | AC41: 167412.6 | AD41: 80098.388 | AE41: 168428.86 | AF41: 88258.517 | AG41: 170426.83 | AH41: 90849.579 | AI41: 193410.57 | AJ41: 110434.64 | AK41: 196662.6 | AL41: 108666.29 | AM41: 202945.12 | AN41: 114278.67 | AO41: 93945.017 | AP41: 122530.17 | AQ41: 130365.37 | AR41: 132824.92 | AS41: 152664.89 | AT41: 139996.82 | AU41: 208857.53 | AV41: 206578.01 | AW41: 287919.4 | AX41: 186691.87 | AY41: 292917.9 | AZ41: 202740.87 | BA41: 292997.84 | BB41: 244436.84 | BC41: 317518.8 | BD41: 195391.4 | BE41: 328877.18 | BF41: 201530.46 | BG41: 253847.95 | BH41: 212218.41 | BI41: 267982.19 | BJ41: 214328.33 | BK41: 275988.28 | BL41: 214784 | BM41: 242056.35 | BN41: 221817.75 | BO41: 242556.35 | BP41: 229646.54 | BQ41: 242856.35 | BR41: 277111.55 | BS41: 270330.96 | BT41: 326852.13 | BU41: 256413.11 | BV41: 299504.83 | BW41: 259477.79 | BX41: 306621.66 | BY41: 282941.04 | BZ41: 313082.32 | CA41: 299809.05 | CB41: 311725.08 | CC41: 287249.02 | CD41: 317672.83 | CE41: 303949.02 | CF41: 318136.05 | CG41: 295795.68 | CH41: 321567.64 | CI41: 294621.08 | CJ41: 319157.87 | CK41: 301621.07 | CL41: 319813.05 | CM41: 301129.45 | CN41: 301759.45
E42: People cost- R&D | AO42: 10000 | AQ42: 24166.667 | AS42: 24166.667 | AU42: 24166.667 | AV42: 0 | AW42: 32751.984 | AX42: 0 | AY42: 32751.984 | AZ42: 0 | BA42: 32751.984 | BB42: 0 | BC42: 32751.984 | BD42: 0 | BE42: 22751.984 | BF42: 0 | BG42: 27216.27 | BH42: 0 | BI42: 27216.27 | BJ42: 0 | BK42: 27216.27 | BL42: 0 | BM42: 15666.667 | BN42: 0 | BO42: 15666.667 | BP42: 0 | BQ42: 15666.667 | BR42: 0 | BS42: 15666.667 | BT42: 0 | BU42: 17233.333 | BV42: 0 | BW42: 17233.333 | BX42: 0 | BY42: 17233.333 | BZ42: 0 | CA42: 17233.333 | CB42: 0 | CC42: 17233.333 | CD42: 0 | CE42: 17233.333 | CF42: 0 | CG42: 17233.333 | CH42: 0 | CI42: 17233.333 | CJ42: 0 | CK42: 17233.333 | CL42: 0 | CM42: 17233.333 | CN42: 17233.333
A43: =$E$40&E43 -> Product and EngineeringTravel and expenses | E43: Travel and expenses | F43: 0 | G43: 0 | H43: 0 | I43: 0 | J43: 0 | K43: 9.5853659 | L43: 78.762195 | M43: 0 | N43: 0 | O43: 1003.9332 | P43: 680.09756 | Q43: 202.67683 | R43: 214.14634 | S43: 270.79268 | T43: 0 | U43: 0 | V43: 20.231707 | W43: 0 | X43: 64.670732 | Y43: 0 | Z43: 0 | AA43: 0 | AB43: 186.38902 | AC43: 0 | AD43: 443.02439 | AE43: 0 | AF43: 3.7560976 | AG43: 0 | AH43: 176.07317 | AI43: 0 | AJ43: 81.678049 | AK43: 0 | AL43: 0 | AM43: 0 | AN43: 0 | AO43: 1562.5 | AP43: 0 | AQ43: 1562.5 | AR43: 0 | AS43: 1562.5 | AT43: 92.542169 | AU43: 1562.5 | AV43: 12053.503 | AW43: 1562.5 | AX43: 9643.5102 | AY43: 1562.5 | AZ43: 3555.2479 | BA43: 1562.5 | BB43: 5692.2014 | BC43: 1562.5 | BD43: 3183.0683 | BE43: 1562.5 | BF43: 596.80679 | BG43: 1562.5 | BH43: 9213.2588 | BI43: 1562.5 | BJ43: 6798.6468 | BK43: 1562.5 | BL43: 1081.6767 | BM43: 0 | BN43: 2237.4198 | BO43: 0 | BP43: 26429.856 | BQ43: 0 | BR43: 13343.782 | BS43: 0 | BT43: 15256.885 | BU43: 0 | BV43: 21534.952 | BW43: 0 | BX43: 1366.7338 | BY43: 0 | BZ43: 402.20624 | CA43: 0 | CB43: 495.21541 | CC43: 0 | CD43: 4304.2856 | CE43: 0 | CF43: 913.60376 | CG43: 0 | CH43: 197.06447 | CI43: 0 | CJ43: 5000.8101 | CK43: 0 | CL43: 300.51765 | CM43: 0 | CN43: 0
A44: =$E$40&E44 -> Product and EngineeringSoftware subscription | E44: Software subscription | F44: 0 | G44: 0 | H44: 0 | I44: 0 | J44: 0 | K44: 6.96 | L44: 141.44636 | M44: 180.57806 | N44: 560.75733 | O44: 557.68782 | P44: 2020.5961 | Q44: 2452.9112 | R44: 2729.6966 | S44: 2867.0486 | T44: 3047.8321 | U44: 2980.038 | V44: 5034.7357 | W44: 9387.3494 | X44: 9130.6554 | Y44: 10747.922 | Z44: 11518.071 | AA44: 11316.447 | AB44: 7086.1229 | AC44: 14178.751 | AD44: 9753.2422 | AE44: 14612.688 | AF44: 10536.734 | AG44: 15068.323 | AH44: 17210.372 | AI44: 28035.144 | AJ44: 12028.107 | AK44: 28611.902 | AL44: 13316.44 | AM44: 29217.497 | AN44: 22994.821 | AO44: 14153.846 | AP44: 16673.894 | AQ44: 16307.692 | AR44: 22018.85 | AS44: 18461.538 | AT44: 20919.468 | AU44: 20615.385 | AV44: 33941.039 | AW44: 22769.231 | AX44: 45440.031 | AY44: 24923.077 | AZ44: 34256.678 | BA44: 27076.923 | BB44: 36463.376 | BC44: 29230.769 | BD44: 46617.594 | BE44: 31384.615 | BF44: 59210.606 | BG44: 33538.462 | BH44: 25660.079 | BI44: 35692.308 | BJ44: 32671.536 | BK44: 37846.154 | BL44: 35507.361 | BM44: 32000 | BN44: 24965.44 | BO44: 32000 | BP44: 34442.237 | BQ44: 32000 | BR44: 32879.016 | BS44: 32000 | BT44: 33503.932 | BU44: 32000 | BV44: 38693.003 | BW44: 32000 | BX44: 41260.011 | BY44: 32000 | BZ44: 49019.619 | CA44: 32000 | CB44: 38893.892 | CC44: 32000 | CD44: 53561.264 | CE44: 32000 | CF44: 67311.03 | CG44: 32000 | CH44: 77551.358 | CI44: 32000 | CJ44: 63438.499 | CK44: 32000 | CL44: 51298.081 | CM44: 32000 | CN44: 32000
A45: =$E$40&E45 -> Product and EngineeringResearch and development | E45: Research and development | F45: 0 | G45: 0 | H45: 0 | I45: 0 | J45: 0 | K45: 0 | L45: 0 | M45: 0 | N45: 0 | O45: 0 | P45: 0 | Q45: 0 | R45: 0 | S45: 0 | T45: 0 | U45: 0 | V45: 0 | W45: 1829.2683 | X45: 5111.1138 | Y45: 1829.2683 | Z45: 5527.7805 | AA45: 1829.2683 | AB45: 5527.7805 | AC45: 1829.2683 | AD45: 5527.7805 | AE45: 1829.2683 | AF45: 5527.7805 | AG45: 1829.2683 | AH45: 5527.7805 | AI45: 1829.2683 | AJ45: 5527.7805 | AK45: 1829.2683 | AL45: 6093.1972 | AM45: 1829.2683 | AN45: 6093.1972 | AO45: 15000 | AP45: 6019.7851 | AQ45: 15000 | AR45: 6019.7851 | AS45: 15000 | AT45: 6019.7851 | AU45: 15000 | AV45: 807.62599 | AW45: 15000 | AX45: -9.1773016 | AY45: 15000 | AZ45: -9.1773016 | BA45: 15000 | BB45: 32.489484 | BC45: 15000 | BD45: -9.1770635 | BE45: 15000 | BF45: 551.95437 | BG45: 15000 | BH45: 551.95437 | BI45: 15000 | BJ45: 0 | BK45: 15000 | BL45: 0 | BM45: 0 | BN45: 0 | BO45: 0 | BP45: 0 | BQ45: 0 | BR45: 0 | BS45: 10000 | BT45: 0 | BU45: 10000 | BV45: 0 | BW45: 10000 | BX45: 0 | BY45: 10000 | BZ45: 0 | CA45: 10000 | CB45: 0 | CC45: 10000 | CD45: 0 | CE45: 10000 | CF45: 0 | CG45: 10000 | CH45: 0 | CI45: 10000 | CJ45: 0 | CK45: 10000 | CL45: 0 | CM45: 10000 | CN45: 10000
A46: =$E$40&E46 -> Product and EngineeringExternal Consultants | E46: External Consultants | F46: 0 | G46: 0 | H46: 0 | I46: 0 | J46: 0 | K46: 0 | L46: 0 | M46: 0 | N46: 3756.0976 | O46: 3658.5366 | P46: 0 | Q46: 3658.5366 | R46: 4804.1463 | S46: 1853.6585 | T46: 939.02439 | U46: 16454.227 | V46: 12611.815 | X46: 1223.5732 | Z46: 6338.3049 | AB46: 3378.0488 | AD46: 4852.935 | AF46: 9040.5691 | AH46: 3953.252 | AJ46: 3953.252 | AL46: 3831.3008 | AN46: 4477.0935 | AO46: 2380.9524 | AP46: 2700.8032 | AQ46: 10000 | AR46: 4529.7189 | AS46: 10000 | AT46: 4628.5141 | AU46: 10000 | AV46: 3452.8902 | AW46: 10000 | AX46: 8925.2427 | AY46: 10000 | AZ46: 22585.733 | BA46: 10000 | BB46: 10884.726 | BC46: 10000 | BD46: 23005.238 | BE46: 10000 | BF46: 4464.2857 | BG46: 10000 | BH46: 1501.7857 | BI46: 10000 | BJ46: 2998.7143 | BK46: 10000 | BL46: 3071.4286 | BM46: 5000 | BN46: 4272.8824 | BO46: 5000 | BP46: 8124.3765 | BQ46: 5000 | BR46: 3058.8235 | BS46: 10000 | BT46: 1991.5294 | BU46: 10000 | BV46: 1122.8235 | BW46: 10000 | BX46: 11764.706 | BY46: 10000 | BZ46: 0 | CA46: 10000 | CB46: 0 | CC46: 10000 | CD46: 5914.7116 | CE46: 10000 | CF46: 0 | CG46: 10000 | CH46: 2076.1936 | CI46: 10000 | CJ46: 0 | CK46: 10000 | CL46: 0 | CM46: 10000 | CN46: 10000
E48: General and Administrative | F48: =SUM(F49:F57) -> 1321.9731 | G48: =SUM(G49:G57) -> 1159.8171 | H48: =SUM(H49:H57) -> 11702.116 | I48: =SUM(I49:I57) -> 11165.561 | J48: =SUM(J49:J57) -> 36437.606 | K48: =SUM(K49:K57) -> 53053.972 | L48: =SUM(L49:L57) -> 43697.106 | M48: =SUM(M49:M57) -> 69403.852 | ... AN48: =SUM(AN49:AN57) -> 129769.81 | AO48: =SUM(AO49:AO58) -> 220651.22 | AP48: =SUM(AP49:AP58) -> 114945.98 | AQ48: =SUM(AQ49:AQ58) -> 265307.26 | AR48: =SUM(AR49:AR58) -> 131000.37 | AS48: =SUM(AS49:AS58) -> 269098.19 | AT48: =SUM(AT49:AT58) -> 191666.13 | AU48: =SUM(AU49:AU58) -> 251297.21 | AV48: =SUM(AV49:AV58) -> 106275.07 | ... CN48: =SUM(CN49:CN58) -> 146266.66
A49: =$E$48&E49 -> General and AdministrativePeople cost | E49: People cost | F49: 634.14634 | G49: 329.26829 | H49: 0 | I49: 0 | J49: 0 | K49: 939.02439 | L49: 8202 | M49: 10040.961 | N49: 15181.218 | O49: 10040.969 | P49: 10162.92 | Q49: 17346.841 | R49: 15823.408 | S49: 20586.798 | T49: 21663.181 | U49: 23028.737 | V49: 27623.584 | W49: 24005.42 | X49: 33404.492 | Y49: 21647.696 | Z49: 49287.224 | AA49: 22379.404 | AB49: 24673.339 | AC49: 34178.184 | AD49: 27910.554 | AE49: 34178.184 | AF49: 50339.594 | AG49: 24188.347 | AH49: 28834.448 | AI49: 38202.575 | AJ49: 54472.735 | AK49: 41886.856 | AL49: 31563.427 | AM49: 28888.889 | AN49: 28132.843 | AO49: 33234.69 | AP49: 33077.292 | AQ49: 64318.381 | AR49: 29680.908 | AS49: 66035.957 | AT49: 26208.269 | AU49: 67688.767 | AV49: 29444.015 | AW49: 47146.329 | AX49: 28096.647 | AY49: 47834.374 | AZ49: 32370.373 | BA49: 57504.058 | BB49: 34142.84 | BC49: 43754.178 | BD49: 34815.888 | BE49: 32164.869 | BF49: 35367.63 | BG49: 47498.824 | BH49: 34690.452 | BI49: 47701.565 | BJ49: 36384.061 | BK49: 47938.874 | BL49: 35903.902 | BM49: 44009.903 | BN49: 37554.457 | BO49: 46509.903 | BP49: 32308.541 | BQ49: 46509.903 | BR49: 33468.291 | BS49: 54647.794 | BT49: 38582.215 | BU49: 71059.302 | BV49: 38263.415 | BW49: 68985.893 | BX49: 38583.555 | BY49: 52410.893 | BZ49: 36564.78 | CA49: 50910.893 | CB49: 40133.098 | CC49: 53410.893 | CD49: 38622.721 | CE49: 52410.893 | CF49: 46561.656 | CG49: 50910.893 | CH49: 41062.262 | CI49: 56160.893 | CJ49: 39637.839 | CK49: 52410.893 | CL49: 40869.215 | CM49: 57660.893 | CN49: 53660.893
A50: =$E$48&E50 -> General and AdministrativeTravel and expenses | E50: Travel and expenses | F50: 0 | G50: 313.78049 | H50: 0 | I50: 654.08537 | J50: 902.12561 | K50: 1046.6341 | L50: 1227.7024 | M50: 1446.652 | N50: 3853.7484 | O50: 5367.362 | P50: 3071.9145 | Q50: 1699.6829 | R50: 2696.5807 | S50: 573.13195 | T50: 11078.157 | U50: 9827.0348 | V50: 26006.977 | W50: 15902.439 | X50: 15339.706 | Y50: 3402.439 | Z50: 9142.5781 | AA50: 3402.439 | AB50: 18985.257 | AC50: 15902.439 | AD50: 15275.405 | AE50: 3402.439 | AF50: 23032.869 | AG50: 3402.439 | AH50: 18394.109 | AI50: 15902.439 | AJ50: 5881.5366 | AK50: 3402.439 | AL50: 21314.464 | AM50: 3402.439 | AN50: 6567.9835 | AO50: 13718.75 | AP50: 7427.9172 | AQ50: 13718.75 | AR50: 21208.304 | AS50: 13718.75 | AT50: 16560.678 | AU50: 13718.75 | AV50: 12751.961 | AW50: 13718.75 | AX50: 8472.8302 | AY50: 13718.75 | AZ50: 4925.5887 | BA50: 13718.75 | BB50: 12416.077 | BC50: 13718.75 | BD50: 11701.891 | BE50: 13718.75 | BF50: 8265.9251 | BG50: 13718.75 | BH50: 8540.1819 | BI50: 13718.75 | BJ50: 5767.7387 | BK50: 13718.75 | BL50: 13610.134 | BM50: 4500 | BN50: 4336.1821 | BO50: 4500 | BP50: 11289.929 | BQ50: 4500 | BR50: 1341.5067 | BS50: 4500 | BT50: 5227.8999 | BU50: 4500 | BV50: 10660.112 | BW50: 4500 | BX50: 3431.4052 | BY50: 4500 | BZ50: 2948.0912 | CA50: 4500 | CB50: 2796.9921 | CC50: 4500 | CD50: 1764.2211 | CE50: 4500 | CF50: 10770.716 | CG50: 4500 | CH50: 2054.6855 | CI50: 4500 | CJ50: 16314.713 | CK50: 4500 | CL50: 10593.365 | CM50: 4500 | CN50: 4500
A51: =$E$48&E51 -> General and AdministrativeRent and utilities | E51: Rent and utilities | F51: 0 | G51: 0 | H51: 0 | I51: 0 | J51: 2277.5976 | K51: 1214.5515 | L51: 991.95317 | M51: 1100.248 | N51: 995.37805 | O51: 1031.8049 | P51: 1445.8171 | Q51: 5043.2317 | R51: 4725.854 | S51: 5274.9073 | T51: 5111.1193 | U51: 5320.7737 | V51: 7166.2456 | W51: 11341 | X51: 6084.2784 | Y51: 11817 | Z51: 6532.743 | AA51: 12610 | AB51: 5747.9052 | AC51: 14866 | AD51: 5774.8448 | AE51: 15366 | AF51: 6160.4821 | AG51: 15366 | AH51: 5667.9935 | AI51: 17744 | AJ51: 10950.176 | AK51: 17744 | AL51: 13594.51 | AM51: 17939 | AN51: 10841.786 | AO51: 22400 | AP51: 9126.6727 | AQ51: 22400 | AR51: 11711.698 | AS51: 22400 | AT51: 9893.4186 | AU51: 22400 | AV51: 11689.81 | AW51: 22400 | AX51: 10831.828 | AY51: 22400 | AZ51: 11067.715 | BA51: 22400 | BB51: 10655.63 | BC51: 16500 | BD51: 10472.539 | BE51: 16500 | BF51: 10480.839 | BG51: 16500 | BH51: 10963.66 | BI51: 16500 | BJ51: 12518.7 | BK51: 16500 | BL51: 10254.12 | BM51: 14500 | BN51: 10006.174 | BO51: 14500 | BP51: 10005.534 | BQ51: 14500 | BR51: 11306.73 | BS51: 16500 | BT51: 10019.538 | BU51: 16500 | BV51: 10194.074 | BW51: 16500 | BX51: 10409.284 | BY51: 16500 | BZ51: 10022.564 | CA51: 16500 | CB51: 10018.764 | CC51: 16500 | CD51: 9829.6671 | CE51: 16500 | CF51: 10466.381 | CG51: 16500 | CH51: 10464.881 | CI51: 16500 | CJ51: 10465.371 | CK51: 16500 | CL51: 9763.8353 | CM51: 16500 | CN51: 16500
A52: =$E$48&E52 -> General and AdministrativeProfessional Services (Legal, Recruitment, etc.) | E52: Professional Services (Legal, Recruitment, etc.) | F52: 0 | G52: 0 | H52: 2450 | I52: 2256.0976 | J52: 10282.633 | K52: 30112.195 | L52: 10519.74 | M52: 7986.8127 | N52: 2769.7396 | O52: 2873.3981 | P52: 3536.5854 | Q52: 25348.11 | R52: 50926.833 | S52: 50656.664 | T52: 60504.835 | U52: 17004.326 | V52: 31201.918 | W52: 20049 | X52: 59450.884 | Y52: 16390 | Z52: 41306.398 | AA52: 16380 | AB52: 22205.004 | AC52: 9390 | AD52: 25174.925 | AE52: 9390 | AF52: 30397.523 | AG52: 34829 | AH52: 43348.145 | AI52: 9390 | AJ52: 28641.135 | AK52: 9390 | AL52: 54167.411 | AM52: 34098 | AN52: 42512.027 | AO52: 88640.9 | AP52: 37669.352 | AQ52: 102232.03 | AR52: 38956.556 | AS52: 107935.75 | AT52: 87457.416 | AU52: 52169.652 | AV52: 6495.2381 | AW52: 14944.815 | AX52: 17716.015 | AY52: 15763.716 | AZ52: 75906.587 | BA52: 16764.956 | BB52: 99650.149 | BC52: 21006.019 | BD52: 74102.887 | BE52: 27561.905 | BF52: 48172.274 | BG52: 40174.774 | BH52: 30276.964 | BI52: 30755.198 | BJ52: 24144.762 | BK52: 35058.313 | BL52: 62565.211 | BM52: 10382.095 | BN52: 86782.948 | BO52: 10238.095 | BP52: 12816.712 | BQ52: 15038.095 | BR52: 58374.23 | BS52: 5000 | BT52: 83742.889 | BU52: 5000 | BV52: 22553.905 | BW52: 5000 | BX52: 22443.962 | BY52: 11159.314 | BZ52: 10690.162 | CA52: 646.4 | CB52: 13936.622 | CC52: 5000 | CD52: 22094.279 | CE52: 5000 | CF52: 25134.279 | CG52: 5000 | CH52: 6830.1029 | CI52: 5000 | CJ52: 31624.92 | CK52: 7285.7143 | CL52: 3700.8024 | CM52: 5000 | CN52: 5000
A53: =$E$48&E53 -> General and AdministrativeFounders' Salary | E53: Founders' Salary | F53: 508.13415 | G53: 508.13415 | H53: 7808.9268 | I53: 4986.1829 | J53: 10757.339 | K53: 7317.0732 | L53: 7317.0732 | M53: 7317.0732 | N53: 7317.0732 | O53: 7317.0732 | P53: 7317.0732 | Q53: 7317.0732 | R53: 7317.0732 | S53: 7317.0732 | T53: 7317.0732 | U53: 7317.0732 | V53: 7317.0732 | W53: 7621.9512 | X53: 7317.0732 | Y53: 7621.9512 | Z53: 7317.0732 | AA53: 7621.9512 | AB53: 7317.0732 | AC53: 7621.9512 | AD53: 7317.0732 | AE53: 7621.9512 | AF53: 7317.0732 | AG53: 7621.9512 | AH53: 7317.0732 | AI53: 7621.9512 | AJ53: 7317.0732 | AK53: 7621.9512 | AL53: 7317.0732 | AM53: 7621.9512 | AN53: 7317.0732 | AO53: 22936.508 | AP53: 7228.9157 | AQ53: 22936.508 | AR53: 7228.9157 | AS53: 22936.508 | AT53: 17631.825 | AU53: 22936.508 | AV53: 22936.5 | AW53: 22936.508 | AX53: 22936.5 | AY53: 22936.508 | AZ53: 22936.5 | BA53: 22936.508 | BB53: 22936.5 | BC53: 22936.508 | BD53: 22936.5 | BE53: 22936.508 | BF53: 22936.5 | BG53: 22936.508 | BH53: 22936.5 | BI53: 22936.508 | BJ53: 22936.5 | BK53: 22936.508 | BL53: 22936.5 | BM53: 22936.508 | BN53: 22843.129 | BO53: 22936.508 | BP53: 22843.129 | BQ53: 22936.508 | BR53: 22843.129 | BS53: 22936.508 | BT53: 22843.129 | BU53: 22936.508 | BV53: 22843.129 | BW53: 22936.508 | BX53: 22843.129 | BY53: 22936.508 | BZ53: 22843.129 | CA53: 22936.508 | CB53: 22843.129 | CC53: 22936.508 | CD53: 22843.129 | CE53: 22936.508 | CF53: 22843.129 | CG53: 22936.508 | CH53: 22843.129 | CI53: 22936.508 | CJ53: 22843.129 | CK53: 22936.508 | CL53: 22843.129 | CM53: 22936.508 | CN53: 22936.508
A54: =$E$48&E54 -> General and AdministrativeOther expenses | E54: Other expenses | F54: 4.3170732 | G54: 8.6341463 | H54: 7.0008537 | I54: 199.63378 | J54: 29.640732 | K54: 327.5122 | L54: 2181.8171 | M54: 1123.9973 | N54: 2144.7246 | O54: 2250.1341 | P54: 3571.7967 | Q54: 5606.5708 | R54: 3305.5761 | S54: 2702.2109 | T54: 5493.8632 | U54: 4722.5768 | V54: 19311.649 | W54: 11024 | X54: 9912.0022 | Y54: 11134 | Z54: 6028.9704 | AA54: 11817 | AB54: 17932.334 | AC54: 12976 | AD54: 14503.21 | AE54: 13476 | AF54: 12542.063 | AG54: 13476 | AH54: 12059.791 | AI54: 15085 | AJ54: 20104.777 | AK54: 15085 | AL54: 26627.166 | AM54: 15207 | AN54: 19970.958 | AO54: 34695.847 | AP54: 14673.358 | AQ54: 34571.522 | AR54: 16263.25 | AS54: 29509.097 | AT54: 14224.694 | AU54: 65612.575 | AV54: 8270.6991 | AW54: 16796.461 | AX54: 7101.4363 | AY54: 15310.813 | AZ54: 7246.9586 | BA54: 35747.883 | BB54: 8459.8316 | BC54: 21464.81 | BD54: 7109.5933 | BE54: 14377.711 | BF54: 15065.348 | BG54: 42526.989 | BH54: 19165.187 | BI54: 20295.848 | BJ54: 19258.425 | BK54: 22247.312 | BL54: 3277.0552 | BM54: 19485.714 | BN54: 6299.3225 | BO54: 13592.857 | BP54: 7205.9485 | BQ54: 13964.286 | BR54: 12484.572 | BS54: 9642.8571 | BT54: 3891.2445 | BU54: 9750 | BV54: 28106.961 | BW54: 9714.2857 | BX54: 2078.7507 | BY54: 25071.429 | BZ54: 8167.6082 | CA54: 10035.714 | CB54: 16291.582 | CC54: 14642.857 | CD54: 29181.347 | CE54: 22692.857 | CF54: 64207.189 | CG54: 13764.286 | CH54: 14822.642 | CI54: 15371.429 | CJ54: 29175.068 | CK54: 18550 | CL54: 4294.1894 | CM54: 14121.429 | CN54: 12657.143
A55: =$E$48&E55 -> General and AdministrativeProvision for Doubtful Debts | E55: Provision for Doubtful Debts | BT55: 0 | BV55: 0 | BW55: 9714.2857 | BX55: 0 | BY55: 10071.429 | BZ55: 0 | CA55: 10035.714 | CB55: 0 | CC55: 10142.857 | CD55: 0 | CE55: 10692.857 | CF55: 0 | CG55: 10764.286 | CH55: 110988.24 | CI55: 10871.429 | CJ55: 110988.24 | CK55: 11050 | CL55: 110988.24
A56: =$E$48&E56 -> General and AdministrativeSoftware subscription | E56: Software subscription | F56: 175.37557 | G56: 0 | H56: 155.70091 | I56: 203.70732 | J56: 487.35532 | K56: 396.06707 | L56: 1555.9061 | M56: 2055.1073 | N56: 1211.9789 | O56: 1417.0713 | P56: 1890.4645 | Q56: 2161.4242 | R56: 2267.0094 | S56: 2699.1057 | T56: 4262.7524 | U56: 3416.7954 | V56: 3855.339 | W56: 3201 | X56: 1543.4889 | Y56: 3585 | Z56: 1709.7398 | AA56: 3756 | AB56: 3411.5507 | AC56: 4567 | AD56: 6041.6285 | AE56: 4610 | AF56: 1864.3471 | AG56: 4610 | AH56: 2388.4968 | AI56: 5122 | AJ56: 4115.575 | AK56: 5122 | AL56: 2491.7754 | AM56: 5207 | AN56: 3989.1245 | AO56: 375 | AP56: 2798.2825 | AQ56: 416.66667 | AR56: 2999.0635 | AS56: 416.66667 | AT56: 4271.2616 | AU56: 541.66667 | AV56: 10835.566 | AW56: 541.66667 | AX56: 3344.343 | AY56: 541.66667 | AZ56: 7958.0117 | BA56: 541.66667 | BB56: 2330.104 | BC56: 541.66667 | BD56: 4684.3546 | BE56: 541.66667 | BF56: 4141.4336 | BG56: 541.66667 | BH56: 8057.9055 | BI56: 541.66667 | BJ56: 6962.8902 | BK56: 541.66667 | BL56: 4111.9431 | BM56: 500 | BN56: 4115.342 | BO56: 541.66667 | BP56: 5326.9901 | BQ56: 541.66667 | BR56: 9923.2975 | BS56: 541.66667 | BT56: 7550.466 | BU56: 541.66667 | BV56: 9888.2105 | BW56: 541.66667 | BX56: 6186.7959 | BY56: 541.66667 | BZ56: 13899.221 | CA56: 541.66667 | CB56: 14269.079 | CC56: 541.66667 | CD56: 9888.1135 | CE56: 541.66667 | CF56: 5710.7532 | CG56: 541.66667 | CH56: 5798.6641 | CI56: 541.66667 | CJ56: 9577.5168 | CK56: 541.66667 | CL56: 4988.3459 | CM56: 541.66667 | CN56: 541.66667
A57: =$E$48&E57 -> General and AdministrativeConsulting | E57: Consulting | F57: 0 | G57: 0 | H57: 1280.4878 | I57: 2865.8537 | J57: 11700.915 | K57: 11700.915 | L57: 11700.915 | M57: 38333 | N57: 38333 | O57: 0 | P57: 38741.574 | Q57: 0 | R57: 0 | S57: 38559.398 | T57: 38741.574 | U57: 40875.72 | V57: 77406.481 | W57: 0 | X57: 38664.908 | Y57: 0 | Z57: 30479.463 | AA57: 0 | AB57: 38100.61 | AC57: 0 | AD57: 15515.244 | AE57: 0 | AF57: 5111.7724 | AG57: 0 | AH57: 11880.065 | AI57: 0 | AJ57: 15463.139 | AK57: 0 | AL57: 10498.994 | AM57: 0 | AN57: 10438.018 | AO57: 0 | AP57: 2059.247 | AQ57: 0 | AR57: 2249.7043 | AS57: 0 | AT57: 14659.343 | AU57: 0 | AV57: 2219.4995 | AW57: 0 | AX57: 2555.0551 | AY57: 0 | AZ57: 1840.7694 | BA57: 0 | BB57: 1840.7694 | BC57: 0 | BD57: 1652.5794 | BE57: 0 | BF57: 2069.2461 | BG57: 0 | BH57: 0 | BI57: 0 | BJ57: 0 | BK57: 0 | BL57: 0 | BM57: 0 | BN57: 0 | BO57: 0 | BP57: 236.94329 | BQ57: 0 | BR57: 0 | BS57: 0 | BT57: 3000 | BU57: 0 | BV57: 3000 | BW57: 0 | BX57: 470.58824 | BY57: 0 | BZ57: 0 | CA57: 0 | CB57: 6885 | CC57: 0 | CD57: 588.23529 | CE57: 0 | CF57: 0 | CG57: 0 | CH57: 1650 | CI57: 0 | CJ57: 2250 | CK57: 0 | CL57: 0 | CM57: 0 | CN57: 0
E58: Payment Processing Costs | X58: 0 | Z58: 0 | AB58: 0 | AD58: 0 | AF58: 0 | AH58: 0 | AJ58: 0 | AL58: 0 | AN58: 0 | AO58: 4649.5289 | AP58: 884.94723 | AQ58: 4713.4017 | AR58: 701.97422 | AS58: 6145.4604 | AT58: 759.22229 | AU58: 6229.2874 | AV58: 1631.7844 | AW58: 6700.358 | AX58: 975.66095 | AY58: 6526.4223 | AZ58: 1212.7275 | BA58: 9718.4677 | BB58: 1055.7433 | BC58: 11527.137 | BD58: 1004.8569 | BE58: 11432.615 | BF58: 768.19917 | BG58: 12280.87 | BH58: 980.5181 | BI58: 12649.058 | BJ58: 1336.3218 | BK58: 13704.727 | BL58: 2161.2123 | BM58: 17648.784 | BN58: 4267.6729 | BO58: 16651.898 | BP58: 3976.2588 | BQ58: 18562.973 | BR58: 3173.9161 | BS58: 19411.616 | BT58: 3870.8029 | BU58: 21143.703 | BV58: 3402.1342 | BW58: 21782.9 | BX58: 2052.2832 | BY58: 22427.167 | BZ58: 4012.0318 | CA58: 23992.346 | CB58: 1708.0504 | CC58: 25406.718 | CD58: 344.54659 | CE58: 27155.952 | CF58: 1960.6502 | CG58: 27325.574 | CH58: 3379.5019 | CI58: 28177.959 | CJ58: 7636.0393 | CK58: 29326.52 | CL58: 3386.4971 | CM58: 30004.698 | CN58: 30470.448
E60: Bad Debts Written off | AV60: 0.026309524 | AW60: 0 | AX60: 0 | AY60: 0 | AZ60: 0.023809524 | BA60: 0 | BB60: 0.037261905 | BC60: 0 | BD60: 2204.2145 | BE60: 0 | BF60: 195.31464 | BG60: 0 | BH60: 1580.3579 | BI60: 0 | BJ60: 24502.18 | BK60: 0 | BL60: 9186.9117 | BM60: 0 | BN60: 3609.4493 | BO60: 0 | BP60: 1473.5775 | BQ60: 0 | BR60: 12392.273 | BS60: 0 | BT60: 10049.726 | BU60: 0 | BV60: 2221.3153 | BX60: 9908.7131 | BZ60: 0.092 | CB60: 0.079882353 | CD60: 8356.5052 | CF60: 0 | CH60: 13579.316 | CJ60: 0 | CL60: 0
E62: Total Operating Expenses | F62: =SUM(F48,F40,F29) -> 3225.1779 | G62: =SUM(G48,G40,G29) -> 3361.3229 | H62: =SUM(H48,H40,H29) -> 17208.587 | I62: =SUM(I48,I40,I29) -> 14119.882 | J62: =SUM(J48,J40,J29) -> 53109.904 | K62: =SUM(K48,K40,K29) -> 77682.451 | L62: =SUM(L48,L40,L29) -> 83697.633 | M62: =SUM(M48,M40,M29) -> 123952.07 | ... AU62: =SUM(AU48,AU40,AU29) -> 1052768.6 | AV62: =SUM(AV48,AV40,AV29,AV60) -> 854364.3 | AW62: =SUM(AW48,AW40,AW29,AW60) -> 1053361.7 | AX62: =SUM(AX48,AX40,AX29,AX60) -> 828724.09 | AY62: =SUM(AY48,AY40,AY29,AY60) -> 1066133.6 | AZ62: =SUM(AZ48,AZ40,AZ29,AZ60) -> 851123.75 | BA62: =SUM(BA48,BA40,BA29,BA60) -> 1093571.2 | BB62: =SUM(BB48,BB40,BB29,BB60) -> 978983.28 | BC62: =SUM(BC48,BC40,BC29,BC60) -> 1131150.7 | ... CN62: =SUM(CN48,CN40,CN29,CN60) -> 1401004.4
E64: EBIDTA | F64: =F3-F62-F22 -> -1701.1901 | G64: =G3-G62-G22 -> 19.677073 | H64: =H3-H62-H22 -> -11930.587 | I64: =I3-I62-I22 -> -7389.2601 | J64: =J3-J62-J22 -> -47067.75 | K64: =K3-K62-K22 -> -70026.117 | L64: =L3-L62-L22 -> -74583.814 | M64: =M3-M62-M22 -> -111865.54 | ... CN64: =CN3-CN62-CN22 -> -178349.1
E65: EBIDTA% | F65: =F64/F3 -> -0.78287625 | G65: =G64/G3 -> 0.0052388374 | H65: =H64/H3 -> -1.8005716 | I65: =I64/I3 -> -0.85178791 | J65: =J64/J3 -> -4.6014029 | K65: =K64/K3 -> -4.4074847 | L65: =L64/L3 -> -3.6614538 | M65: =M64/M3 -> -4.7099295 | ... CN65: =CN64/CN3 -> -0.11363556
CH66: =(CF64+CH64+CJ64)/SUM(CF3+CH3+CJ3) -> -0.23334899
A67: EBIDTADepreciation | E67: Amortisation & Depreciation | F67: 0 | G67: 0 | H67: 0 | I67: 0 | J67: 0 | K67: 851.57022 | L67: 1193.3859 | M67: 1383.2043 | N67: 1564.2549 | O67: 1777.0183 | P67: 2258.0722 | Q67: 2563.9545 | R67: 2880.8339 | S67: 3076.8251 | T67: 3301.8521 | U67: 3495.5808 | V67: 3899.6553 | W67: 3750 | X67: 4050.9266 | Y67: 4200 | Z67: 4343.5909 | AA67: 4400 | AB67: 4436.8164 | AC67: 5350 | AD67: 4470.2199 | AE67: 5400 | AF67: 4986.5394 | AG67: 5400 | AH67: 5419.0965 | AI67: 6000 | AJ67: 6213.8132 | AK67: 6000 | AL67: 6161.9221 | AM67: 6100 | AN67: 6302.2767 | AO67: 9628.1536 | AP67: 6103.4101 | AQ67: 10404.666 | AR67: 6545.612 | AS67: 10989.235 | AT67: 7376.7291 | AU67: 12374.274 | AV67: 6913.0693 | AW67: 12461.964 | AX67: 7467.1958 | AY67: 12498.675 | AZ67: 7719.864 | BA67: 8802.3415 | BB67: 8487.3143 | BC67: 9022.1816 | BD67: 9216.8889 | BE67: 9022.1816 | BF67: 9257.241 | BG67: 9443.7615 | BH67: 9826.0182 | BI67: 9617.4125 | BJ67: 9594.7235 | BK67: 9847.0015 | BL67: 10027.937 | BM67: 8401 | BN67: 10080.469 | BO67: 8551 | BP67: 9588.6591 | BQ67: 8701 | BR67: 11278.093 | BS67: 8701 | BT67: 5702.4709 | BU67: 9201 | BV67: 6163.3748 | BW67: 9201 | BX67: 6120.2269 | BY67: 9351 | BZ67: 6500.7372 | CA67: 9751 | CB67: 6500.7372 | CC67: 9851 | CD67: 6329.1733 | CE67: 10001 | CF67: 6567.0541 | CG67: 10251 | CH67: 6583.1815 | CI67: 10351 | CJ67: 7057.0761 | CK67: 10401 | CL67: 7057.0706 | CM67: 10351 | CN67: 10401
E68: Exchange Gain or Loss | AV68: 1115.615 | AX68: 1556.6104 | AZ68: 1319.8907 | BB68: 1199.3345 | BD68: 1614.4052 | BF68: 1035.6069 | BH68: 536.29679 | BJ68: 332.62036 | BL68: -361.5994 | BN68: -8010.4805 | BP68: -798.58565 | BR68: -24.433647 | BT68: 918.78035 | BV68: 799.11341 | BX68: -317.82071 | BZ68: 340.666 | CB68: -585.32024 | CD68: 50.362 | CF68: 11.779059 | CH68: -528.94035 | CJ68: -288.30918 | CL68: -34471.929
E69: Fundraising Costs | AV69: 0 | AX69: 0 | AZ69: 0 | BB69: 0 | BD69: 0 | BF69: 0 | BH69: 0 | BJ69: 0 | BL69: 0 | BN69: 0 | BP69: 0 | BQ69: 100000 | BR69: 31543.447 | BS69: 100000 | BT69: 36800.694 | BU69: 100000 | BV69: 36800.694 | BW69: 100000 | BX69: 22011.706 | BY69: 100000 | BZ69: 10421.176 | CA69: 100000 | CB69: 15095.694 | CC69: 100000 | CD69: 10687.765 | CE69: 100000 | CF69: 0 | CG69: 100000 | CH69: 0 | CI69: 100000 | CJ69: 0 | CK69: 100000 | CL69: 14656.471 | CM69: 100000 | CN69: 100000
E70: Fund Management fee
E72: Profit / (Loss) for the month | F72: =F64-F67 -> -1701.1901 | G72: =G64-G67 -> 19.677073 | H72: =H64-H67 -> -11930.587 | I72: =I64-I67 -> -7389.2601 | J72: =J64-J67 -> -47067.75 | K72: =K64-K67 -> -70877.687 | L72: =L64-L67 -> -75777.2 | M72: =M64-M67 -> -113248.74 | ... AN72: =AN64-AN67 -> -300127.03 | AO72: =AO64-AO67-AO69 -> -496642.69 | AP72: =AP64-AP67-AP69 -> -366659.95 | AQ72: =AQ64-AQ67-AQ69 -> -580018.26 | AR72: =AR64-AR67-AR69 -> -403317.27 | AS72: =AS64-AS67-AS69 -> -614877.9 | AT72: =AT64-AT67-AT69 -> -467653.3 | AU72: =AU64-AU67-AU69 -> -647563.34 | AV72: =AV64-AV67-AV69 -> -486339.24 | ... CN72: =CN64-CN67-CN69 -> -288750.1
E74: Cash flow
E75: Opening Balance | F75: 44807.762 | G75: =F81 -> 41211.737 | H75: =G81 -> 38039.623 | I75: =H81 -> 25262.355 | J75: =I81 -> 20734.343 | K75: =J81 -> 2684134.2 | L75: =K81 -> 2628068.7 | M75: =L81 -> 2558584.8 | N75: =M81 -> 2496054.5 | ... V75: =U81 -> 1111744.5 | W75: 8078547 | X75: =V81 -> 8088128.2 | Y75: =W81 -> 7602273.4 | Z75: =X81 -> 7638193.3 | AA75: =Y81 -> 7484569.1 | AB75: =Z81 -> 7171093.3 | AC75: =AA81 -> 7051057.2 | AD75: =AB81 -> 6838580.4 | AE75: =AC81 -> 6627980.9 | ... AN75: =AL81 -> 5365984.7 | AO75: 5000000 | AP75: =AN81 -> 5054500.8 | AQ75: =AO81 -> 13485947 | AR75: =AP81 -> 4669366.8 | AS75: =AQ81 -> 12910372 | AT75: =AR81 -> 13448938 | AU75: =AS81 -> 12334037 | AV75: =AT81 -> 13209859 | AW75: =AU81 -> 11759601 | ... BB75: =AZ81 -> 12939952 | BC75: 12185327 | BD75: =BB81 -> 12446292 | BE75: =BC81 -> 11676228 | BF75: =BD81 -> 12086883 | BG75: =BE81 -> 11094397 | BH75: =BF81 -> 11659986 | BI75: =BG81 -> 10482888 | BJ75: =BH81 -> 11117887 | BK75: =BI81 -> 9885955.6 | BL75: =BJ81 -> 10669512 | BM75: 9952008.1 | BN75: =BL81 -> 10545552 | BO75: =BM81 -> 9515854.2 | BP75: =BN81 -> 9868272.6 | BQ75: =BP81 -> 9525350.9 | BR75: =BP81 -> 9525350.9 | BS75: =BR81 -> 9414035.6 | BT75: =BR81 -> 9414035.6 | BU75: =BS81 -> 9096507.9 | BV75: =BT81 -> 8669877.3 | BW75: =BU81 -> 8799513.6 | BX75: =BV81 -> 8102892.3 | BY75: =BW81 -> 8530919.9 | BZ75: =BX81 -> 7830689.4 | CA75: =BY81 -> 8262653.6 | ... CM75: =CK81 -> 7042842.2 | CN75: =CM81 -> 5316375
E76: Revenue Collected | F76: 9.0731707 | G76: 8.7804878 | H76: 9502.7927 | I76: 2732.7317 | J76: 2564.4268 | K76: =SUM('3. Cash Flow Statement '!C22,'3. Cash Flow Statement '!C34) -> 20046.266 | L76: =SUM('3. Cash Flow Statement '!D22,'3. Cash Flow Statement '!D34) -> 11489.024 | M76: =SUM('3. Cash Flow Statement '!E22,'3. Cash Flow Statement '!E34) -> 29970.742 | N76: =SUM('3. Cash Flow Statement '!F22,'3. Cash Flow Statement '!F34) -> 51473.881 | O76: =SUM('3. Cash Flow Statement '!G22,'3. Cash Flow Statement '!G34) -> 28644.268 | P76: =SUM('3. Cash Flow Statement '!H22,'3. Cash Flow Statement '!H34) -> 74000.081 | Q76: =SUM('3. Cash Flow Statement '!I22,'3. Cash Flow Statement '!I34) -> 89887.903 | R76: =SUM('3. Cash Flow Statement '!J22,'3. Cash Flow Statement '!J34) -> 75287.563 | ... V76: =SUM('3. Cash Flow Statement '!N22,'3. Cash Flow Statement '!N34) -> 203656.78 | W76: 243729 | X76: =SUM('3. Cash Flow Statement '!P22,'3. Cash Flow Statement '!P34) -> 204631.43 | Y76: 262788 | Z76: =SUM('3. Cash Flow Statement '!R22,'3. Cash Flow Statement '!R34) -> 238942.05 | AA76: 346876 | AB76: =SUM('3. Cash Flow Statement '!T22,'3. Cash Flow Statement '!T34) -> 265925.55 | AC76: 396318 | AD76: =SUM('3. Cash Flow Statement '!V22,'3. Cash Flow Statement '!V34) -> 215309.88 | AE76: 397419 | AF76: =SUM('3. Cash Flow Statement '!X22,'3. Cash Flow Statement '!X34) -> 259200.07 | AG76: 413866 | AH76: =SUM('3. Cash Flow Statement '!Z22,'3. Cash Flow Statement '!Z34) -> 291726.64 | AI76: 501288 | AJ76: =SUM('3. Cash Flow Statement '!AB22,'3. Cash Flow Statement '!AB34) -> 291437.05 | AK76: 538889 | AL76: =SUM('3. Cash Flow Statement '!AD22,'3. Cash Flow Statement '!AD34) -> 342119.83 | AM76: 552640 | AN76: =SUM('3. Cash Flow Statement '!AF22,'3. Cash Flow Statement '!AF34) -> 432680.48 | AO76: 431064.12 | AP76: =SUM('3. Cash Flow Statement '!AH22,'3. Cash Flow Statement '!AH34) -> 526035.94 | AQ76: 472557.13 | AR76: =SUM('3. Cash Flow Statement '!AJ22,'3. Cash Flow Statement '!AJ34) -> 499490.1 | AS76: 532263.21 | AT76: =SUM('3. Cash Flow Statement '!AL22,'3. Cash Flow Statement '!AL34) -> 548802.44 | AU76: 592803.41 | AV76: =SUM('3. Cash Flow Statement '!AN22,'3. Cash Flow Statement '!AN34) -> 564295.05 | AW76: 656066.26 | AX76: =SUM('3. Cash Flow Statement '!AP22,'3. Cash Flow Statement '!AP34) -> 597856.97 | AY76: 721489.46 | AZ76: =SUM('3. Cash Flow Statement '!AR22,'3. Cash Flow Statement '!AR34) -> 569796.84 | BA76: 662278.05 | BB76: =SUM('3. Cash Flow Statement '!AT22,'3. Cash Flow Statement '!AT34) -> 931081.45 | BC76: 772010.17 | BD76: =SUM('3. Cash Flow Statement '!AV22,'3. Cash Flow Statement '!AV34) -> 682010.99 | BE76: 768688.65 | BF76: =SUM('3. Cash Flow Statement '!AX22,'3. Cash Flow Statement '!AX34) -> 627332.34 | BG76: 799829.57 | BH76: =SUM('3. Cash Flow Statement '!AZ22,'3. Cash Flow Statement '!AZ34) -> 773121.61 | BI76: 814069.15 | BJ76: =SUM('3. Cash Flow Statement '!BB22,'3. Cash Flow Statement '!BB34) -> 703033.48 | BK76: 759852.79 | BL76: =SUM('3. Cash Flow Statement '!BD22,'3. Cash Flow Statement '!BD34) -> 946498.62 | BM76: 882439.2 | BN76: =SUM('3. Cash Flow Statement '!BF22,'3. Cash Flow Statement '!BF34) -> 888969.57 | BO76: 832594.92 | BP76: =SUM('3. Cash Flow Statement '!BH22,'3. Cash Flow Statement '!BH34) -> 784653.72 | BQ76: 970580.78 | BR76: =SUM('3. Cash Flow Statement '!BJ22,'3. Cash Flow Statement '!BJ34) -> 1198398.6 | BS76: 1089145 | BT76: =SUM('3. Cash Flow Statement '!BL22,'3. Cash Flow Statement '!BL34) -> 948577.98 | BU76: 1121358.4 | BV76: =SUM('3. Cash Flow Statement '!BN22,'3. Cash Flow Statement '!BN34) -> 1022028.2 | BW76: 1199617.3 | BX76: =SUM('3. Cash Flow Statement '!BP22,'3. Cash Flow Statement '!BP34) -> 1176771.2 | BY76: 1270335.9 | BZ76: =SUM('3. Cash Flow Statement '!BR22,'3. Cash Flow Statement '!BR34) -> 1307449.4 | CA76: 1357797.6 | CB76: =SUM('3. Cash Flow Statement '!BT22,'3. Cash Flow Statement '!BT34) -> 1174430.4 | CC76: 1366278.7 | CD76: =SUM('3. Cash Flow Statement '!BV22,'3. Cash Flow Statement '!BV34) -> 1160804.7 | CE76: 1408897.9 | CF76: =SUM('3. Cash Flow Statement '!BX22,'3. Cash Flow Statement '!BX34) -> 1275534.8 | CG76: 1466326 | CH76: =SUM('3. Cash Flow Statement '!BZ22,'3. Cash Flow Statement '!BZ34) -> 1276138.6 | CI76: 1500234.9 | CJ76: =SUM('3. Cash Flow Statement '!CB22,'3. Cash Flow Statement '!CB34) -> 1533202.6 | CK76: 1523522.4 | CL76: =SUM('3. Cash Flow Statement '!CD22,'3. Cash Flow Statement '!CD34) -> 1284712.8 | CM76: 0 | CN76: 0
E77: Inter Entity Financing | K77: =-'3. Cash Flow Statement '!C32 -> 0 | L77: =-'3. Cash Flow Statement '!D32 -> 0 | M77: =-'3. Cash Flow Statement '!E32 -> 0 | N77: =-'3. Cash Flow Statement '!F32 -> 0 | O77: =-'3. Cash Flow Statement '!G32 -> 0 | P77: =-'3. Cash Flow Statement '!H32 -> 0 | Q77: =-'3. Cash Flow Statement '!I32 -> 0 | R77: =-'3. Cash Flow Statement '!J32 -> 0 | ... V77: =-'3. Cash Flow Statement '!N32 -> 0 | X77: =-'3. Cash Flow Statement '!P32 -> -499969.5 | Z77: =-'3. Cash Flow Statement '!R32 -> 0 | AB77: =-'3. Cash Flow Statement '!T32 -> 0 | AD77: =-'3. Cash Flow Statement '!V32 -> -50000 | AF77: =-'3. Cash Flow Statement '!X32 -> -499960 | AH77: =-'3. Cash Flow Statement '!Z32 -> 0 | AJ77: =-'3. Cash Flow Statement '!AB32 -> 0 | AL77: =-'3. Cash Flow Statement '!AD32 -> 0 | AN77: =-'3. Cash Flow Statement '!AF32 -> -1218439 | AP77: =-'3. Cash Flow Statement '!AH32 -> 0 | AR77: =-'3. Cash Flow Statement '!AJ32 -> 0 | AT77: =-'3. Cash Flow Statement '!AL32 -> 0 | AV77: =-'3. Cash Flow Statement '!AN32 -> 0 | AX77: =-'3. Cash Flow Statement '!AP32 -> 0 | AZ77: =-'3. Cash Flow Statement '!AR32 -> 0 | BB77: =-'3. Cash Flow Statement '!AT32 -> 0 | BD77: =-'3. Cash Flow Statement '!AV32 -> 0 | BF77: =-'3. Cash Flow Statement '!AX32 -> 0 | BH77: =-'3. Cash Flow Statement '!AZ32 -> 0 | BJ77: =-'3. Cash Flow Statement '!BB32 -> 0 | BL77: =-'3. Cash Flow Statement '!BD32 -> 0 | BN77: =-'3. Cash Flow Statement '!BF32 -> 0 | BP77: =-'3. Cash Flow Statement '!BH32 -> 0 | BR77: =-'3. Cash Flow Statement '!BJ32 -> 0 | BT77: =-'3. Cash Flow Statement '!BL32 -> 0 | BV77: =-'3. Cash Flow Statement '!BN32 -> 0 | BX77: =-'3. Cash Flow Statement '!BP32 -> 0 | BZ77: =-'3. Cash Flow Statement '!BR32 -> 0 | CB77: =-'3. Cash Flow Statement '!BT32 -> 0 | CD77: =-'3. Cash Flow Statement '!BV32 -> 0 | CF77: =-'3. Cash Flow Statement '!BX32 -> 0 | CH77: =-'3. Cash Flow Statement '!BZ32 -> 0 | CJ77: =-'3. Cash Flow Statement '!CB32 -> 0 | CL77: =-'3. Cash Flow Statement '!CD32 -> -555516
E78: Capital Investment | J78: 2756044.5 | K78: ='3. Cash Flow Statement '!C33 -> 0 | L78: ='3. Cash Flow Statement '!D33 -> 0 | M78: ='3. Cash Flow Statement '!E33 -> 0 | N78: ='3. Cash Flow Statement '!F33 -> 0 | O78: ='3. Cash Flow Statement '!G33 -> 0 | P78: ='3. Cash Flow Statement '!H33 -> 0 | Q78: ='3. Cash Flow Statement '!I33 -> 0 | R78: ='3. Cash Flow Statement '!J33 -> 0 | ... V78: ='3. Cash Flow Statement '!N33 -> 7358178.9 | X78: ='3. Cash Flow Statement '!P33 -> 0 | Y78: 300000 | Z78: ='3. Cash Flow Statement '!R33 -> 0 | AB78: ='3. Cash Flow Statement '!T33 -> 0 | AD78: ='3. Cash Flow Statement '!V33 -> 0 | AF78: ='3. Cash Flow Statement '!X33 -> 100186 | AH78: ='3. Cash Flow Statement '!Z33 -> 354.73695 | AJ78: ='3. Cash Flow Statement '!AB33 -> 302771.32 | AL78: ='3. Cash Flow Statement '!AD33 -> 135396.48 | AN78: ='3. Cash Flow Statement '!AF33 | AO78: 9000000 | AP78: ='3. Cash Flow Statement '!AH33 | AR78: ='3. Cash Flow Statement '!AJ33 -> 9006025.4 | AT78: ='3. Cash Flow Statement '!AL33 -> 0 | AV78: ='3. Cash Flow Statement '!AN33 | AX78: ='3. Cash Flow Statement '!AP33 -> 1000655 | AZ78: ='3. Cash Flow Statement '!AR33 -> 0 | BB78: ='3. Cash Flow Statement '!AT33 -> 0 | BD78: ='3. Cash Flow Statement '!AV33 -> 0 | BF78: ='3. Cash Flow Statement '!AX33 -> 0 | BH78: ='3. Cash Flow Statement '!AZ33 -> 0 | BJ78: ='3. Cash Flow Statement '!BB33 | BL78: ='3. Cash Flow Statement '!BD33 | BN78: ='3. Cash Flow Statement '!BF33 | BP78: ='3. Cash Flow Statement '!BH33 | BR78: ='3. Cash Flow Statement '!BJ33 | BS78: 0 | BT78: ='3. Cash Flow Statement '!BL33 | BV78: ='3. Cash Flow Statement '!BN33 | BX78: ='3. Cash Flow Statement '!BP33 | BZ78: ='3. Cash Flow Statement '!BR33 | CB78: ='3. Cash Flow Statement '!BT33 | CD78: ='3. Cash Flow Statement '!BV33 | CF78: ='3. Cash Flow Statement '!BX33 | CH78: ='3. Cash Flow Statement '!BZ33 | CJ78: ='3. Cash Flow Statement '!CB33 | CL78: ='3. Cash Flow Statement '!CD33
E79: Inter Entity Investment | K79: ='3. Cash Flow Statement '!C37 -> 0 | L79: ='3. Cash Flow Statement '!D37 -> 0 | M79: ='3. Cash Flow Statement '!E37 -> 0 | N79: ='3. Cash Flow Statement '!F37 -> 0 | O79: ='3. Cash Flow Statement '!G37 -> 0 | P79: ='3. Cash Flow Statement '!H37 -> 0 | Q79: ='3. Cash Flow Statement '!I37 -> 0 | R79: ='3. Cash Flow Statement '!J37 -> 0 | ... V79: ='3. Cash Flow Statement '!N37 -> 0 | X79: ='3. Cash Flow Statement '!P37 -> 499969.5 | Z79: ='3. Cash Flow Statement '!R37 -> 0 | AB79: ='3. Cash Flow Statement '!T37 -> 0 | AD79: ='3. Cash Flow Statement '!V37 -> 50000 | AF79: ='3. Cash Flow Statement '!X37 -> 499960 | AH79: ='3. Cash Flow Statement '!Z37 | AJ79: ='3. Cash Flow Statement '!AB37 | AL79: ='3. Cash Flow Statement '!AD37 | AN79: ='3. Cash Flow Statement '!AF37 -> 1218439 | AP79: ='3. Cash Flow Statement '!AH37 -> 0 | AR79: ='3. Cash Flow Statement '!AJ37 -> 0 | AT79: ='3. Cash Flow Statement '!AL37 -> 0 | AV79: ='3. Cash Flow Statement '!AN37 | AX79: ='3. Cash Flow Statement '!AP37 | AZ79: ='3. Cash Flow Statement '!AR37 -> 0 | BB79: ='3. Cash Flow Statement '!AT37 -> 0 | BD79: ='3. Cash Flow Statement '!AV37 | BF79: ='3. Cash Flow Statement '!AX37 | BH79: ='3. Cash Flow Statement '!AZ37 | BJ79: ='3. Cash Flow Statement '!BB37 | BL79: ='3. Cash Flow Statement '!BD37 | BN79: ='3. Cash Flow Statement '!BF37 | BP79: ='3. Cash Flow Statement '!BH37 | BR79: ='3. Cash Flow Statement '!BJ37 | BT79: ='3. Cash Flow Statement '!BL37 | BV79: ='3. Cash Flow Statement '!BN37 | BX79: ='3. Cash Flow Statement '!BP37 | BZ79: ='3. Cash Flow Statement '!BR37 | CB79: ='3. Cash Flow Statement '!BT37 | CD79: ='3. Cash Flow Statement '!BV37 | CF79: ='3. Cash Flow Statement '!BX37 | CH79: ='3. Cash Flow Statement '!BZ37 | CJ79: ='3. Cash Flow Statement '!CB37 | CL79: ='3. Cash Flow Statement '!CD37 -> 555516
E80: Cash outflow | F80: -3605.0976 | G80: -3180.8946 | H80: -22280.061 | I80: -7260.7439 | J80: -95209.098 | K80: =-SUM('3. Cash Flow Statement '!C24:C29,'3. Cash Flow Statement '!C36,'3. Cash Flow Statement '!C38:C40) -> -76111.777 | L80: =-SUM('3. Cash Flow Statement '!D24:D29,'3. Cash Flow Statement '!D36,'3. Cash Flow Statement '!D38:D40) -> -80972.939 | M80: =-SUM('3. Cash Flow Statement '!E24:E29,'3. Cash Flow Statement '!E36,'3. Cash Flow Statement '!E38:E40) -> -92500.992 | N80: =-SUM('3. Cash Flow Statement '!F24:F29,'3. Cash Flow Statement '!F36,'3. Cash Flow Statement '!F38:F40) -> -170715.92 | O80: =-SUM('3. Cash Flow Statement '!G24:G29,'3. Cash Flow Statement '!G36,'3. Cash Flow Statement '!G38:G40) -> -185675.63 | P80: =-SUM('3. Cash Flow Statement '!H24:H29,'3. Cash Flow Statement '!H36,'3. Cash Flow Statement '!H38:H40) -> -184658.71 | Q80: =-SUM('3. Cash Flow Statement '!I24:I29,'3. Cash Flow Statement '!I36,'3. Cash Flow Statement '!I38:I40) -> -277405.8 | R80: =-SUM('3. Cash Flow Statement '!J24:J29,'3. Cash Flow Statement '!J36,'3. Cash Flow Statement '!J38:J40) -> -217460.51 | ... V80: =-SUM('3. Cash Flow Statement '!N24:N29,'3. Cash Flow Statement '!N36,'3. Cash Flow Statement '!N38:N40) -> -585451.91 | W80: =-SUM(W67,W62,W22) -> -720002.56 | X80: =-SUM('3. Cash Flow Statement '!P24:P29,'3. Cash Flow Statement '!P36,'3. Cash Flow Statement '!P38:P40) -> -654566.4 | Y80: =-SUM(Y67,Y62,Y22) -> -680492.38 | Z80: =-SUM('3. Cash Flow Statement '!R24:R29,'3. Cash Flow Statement '!R36,'3. Cash Flow Statement '!R38:R40) -> -706041.99 | AA80: =-SUM(AA67,AA62,AA22) -> -780387.88 | AB80: =-SUM('3. Cash Flow Statement '!T24:T29,'3. Cash Flow Statement '!T36,'3. Cash Flow Statement '!T38:T40) -> -598438.51 | AC80: =-SUM(AC67,AC62,AC22) -> -819394.26 | AD80: =-SUM('3. Cash Flow Statement '!V24:V29,'3. Cash Flow Statement '!V36,'3. Cash Flow Statement '!V38:V40) -> -607928.92 | AE80: =-SUM(AE67,AE62,AE22) -> -823230.55 | AF80: =-SUM('3. Cash Flow Statement '!X24:X29,'3. Cash Flow Statement '!X36,'3. Cash Flow Statement '!X38:X39) -> -730408.94 | AG80: =-SUM(AG67,AG62,AG22) -> -884714.13 | AH80: =-SUM('3. Cash Flow Statement '!Z24:Z29,'3. Cash Flow Statement '!Z36,'3. Cash Flow Statement '!Z38:Z39) -> -663574.28 | AI80: =-SUM(AI67,AI62,AI22) -> -910489.71 | AJ80: =-SUM('3. Cash Flow Statement '!AB24:AB29,'3. Cash Flow Statement '!AB36,'3. Cash Flow Statement '!AB38:AB39) -> -747140.17 | AK80: =-SUM(AK67,AK62,AK22) -> -941845.83 | AL80: =-SUM('3. Cash Flow Statement '!AD24:AD29,'3. Cash Flow Statement '!AD36,'3. Cash Flow Statement '!AD38:AD39) -> -662045.37 | AM80: =-SUM(AM67,AM62,AM22) -> -994389.43 | AN80: =-SUM('3. Cash Flow Statement '!AF24:AF29,'3. Cash Flow Statement '!AF36,'3. Cash Flow Statement '!AF38:AF39) -> -744164.38 | AO80: =-SUM(AO67,AO62,AO22) -> -945117.48 | AP80: =-SUM('3. Cash Flow Statement '!AH24:AH29,'3. Cash Flow Statement '!AH36,'3. Cash Flow Statement '!AH38:AH39) -> -911169.97 | AQ80: =-SUM(AQ67,AQ62,AQ22) -> -1048132.2 | AR80: =-SUM('3. Cash Flow Statement '!AJ24:AJ29,'3. Cash Flow Statement '!AJ36,'3. Cash Flow Statement '!AJ38:AJ39) -> -725944.75 | AS80: =-SUM(AS67,AS62,AS22) -> -1108597.9 | AT80: =-SUM('3. Cash Flow Statement '!AL24:AL29,'3. Cash Flow Statement '!AL36,'3. Cash Flow Statement '!AL38:AL39) -> -787881.22 | AU80: =-SUM(AU67,AU62,AU22) -> -1167238.8 | AV80: =-SUM('3. Cash Flow Statement '!AN24:AN29,'3. Cash Flow Statement '!AN36,'3. Cash Flow Statement '!AN38:AN39) -> -1078928.6 | AW80: =-SUM(AW67,AW62,AW22) -> -1178430.2 | AX80: =-SUM('3. Cash Flow Statement '!AP24:AP29,'3. Cash Flow Statement '!AP36,'3. Cash Flow Statement '!AP38:AP39) -> -1046481.2 | AY80: =-SUM(AY67,AY62,AY22) -> -1192170.4 | AZ80: =-SUM('3. Cash Flow Statement '!AR24:AR29,'3. Cash Flow Statement '!AR36,'3. Cash Flow Statement '!AR38:AR39) -> -877100.88 | BA80: =-SUM(BA67,BA62,BA22) -> -1222164.6 | BB80: =-SUM('3. Cash Flow Statement '!AT24:AT29,'3. Cash Flow Statement '!AT36,'3. Cash Flow Statement '!AT38:AT39) -> -1424741.6 | BC80: =-SUM(BC67,BC62,BC22) -> -1281108.9 | BD80: =-SUM('3. Cash Flow Statement '!AV24:AV29,'3. Cash Flow Statement '!AV36,'3. Cash Flow Statement '!AV38:AV39) -> -1041419.4 | BE80: =-SUM(BE67,BE62,BE22) -> -1350519.6 | BF80: =-SUM('3. Cash Flow Statement '!AX24:AX29,'3. Cash Flow Statement '!AX36,'3. Cash Flow Statement '!AX38:AX39) -> -1054229.4 | BG80: =-SUM(BG67,BG62,BG22) -> -1411338.6 | BH80: =-SUM('3. Cash Flow Statement '!AZ24:AZ29,'3. Cash Flow Statement '!AZ36,'3. Cash Flow Statement '!AZ38:AZ39) -> -1315221 | BI80: =-SUM(BI67,BI62,BI22) -> -1411001.9 | BJ80: =-SUM('3. Cash Flow Statement '!BB24:BB29,'3. Cash Flow Statement '!BB36,'3. Cash Flow Statement '!BB38:BB39) -> -1151408 | BK80: =-SUM(BK67,BK62,BK22) -> -1453874.4 | BL80: =-SUM('3. Cash Flow Statement '!BD24:BD29,'3. Cash Flow Statement '!BD36,'3. Cash Flow Statement '!BD38:BD39) -> -1070458.8 | BM80: =-SUM(BM67,BM62,BM22) -> -1318593.1 | BN80: =-SUM('3. Cash Flow Statement '!BF24:BF29,'3. Cash Flow Statement '!BF36,'3. Cash Flow Statement '!BF38:BF39) -> -1566249.2 | BO80: =-SUM(BO67,BO62,BO22) -> -1335289.1 | BP80: =-SUM('3. Cash Flow Statement '!BH24:BH29,'3. Cash Flow Statement '!BH36,'3. Cash Flow Statement '!BH38:BH39) -> -1127575.4 | BQ80: =-SUM(BQ67,BQ62,BQ22) -> -1351356 | BR80: =-SUM('3. Cash Flow Statement '!BJ24:BJ29,'3. Cash Flow Statement '!BJ36,'3. Cash Flow Statement '!BJ38:BJ39) -> -1309713.9 | BS80: =-SUM(BS67,BS62,BS22) -> -1406672.7 | BT80: =-SUM('3. Cash Flow Statement '!BL24:BL29,'3. Cash Flow Statement '!BL36,'3. Cash Flow Statement '!BL38:BL40) -> -1692736.3 | BU80: =-SUM(BU67,BU62,BU22) -> -1418352.7 | BV80: =-SUM('3. Cash Flow Statement '!BN24:BN29,'3. Cash Flow Statement '!BN36,'3. Cash Flow Statement '!BN38:BN40) -> -1589013.1 | BW80: =-SUM(BW67,BW62,BW22) -> -1468211 | BX80: =-SUM('3. Cash Flow Statement '!BP24:BP29,'3. Cash Flow Statement '!BP36,'3. Cash Flow Statement '!BP38:BP40) -> -1448974.1 | BY80: =-SUM(BY67,BY62,BY22) -> -1538602.3 | BZ80: =-SUM('3. Cash Flow Statement '!BR24:BR29,'3. Cash Flow Statement '!BR36,'3. Cash Flow Statement '!BR38:BR40) -> -1720752.3 | CA80: =-SUM(CA67,CA62,CA22) -> -1543112.8 | CB80: =-SUM('3. Cash Flow Statement '!BT24:BT29,'3. Cash Flow Statement '!BT36,'3. Cash Flow Statement '!BT38:BT40) -> -1413994.8 | CC80: =-SUM(CC67,CC62,CC22) -> -1566604 | CD80: =-SUM('3. Cash Flow Statement '!BV24:BV29,'3. Cash Flow Statement '!BV36,'3. Cash Flow Statement '!BV38:BV40) -> -1447667.6 | CE80: =-SUM(CE67,CE62,CE22) -> -1635661.6 | CF80: =-SUM('3. Cash Flow Statement '!BX24:BX29,'3. Cash Flow Statement '!BX36,'3. Cash Flow Statement '!BX38:BX40) -> -1434229.5 | CG80: =-SUM(CG67,CG62,CG22) -> -1652291.2 | CH80: =-SUM('3. Cash Flow Statement '!BZ24:BZ29,'3. Cash Flow Statement '!BZ36,'3. Cash Flow Statement '!BZ38:BZ40) -> -1966576.5 | CI80: =-SUM(CI67,CI62,CI22) -> -1711948.5 | CJ80: =-SUM('3. Cash Flow Statement '!CB24:CB29,'3. Cash Flow Statement '!CB36,'3. Cash Flow Statement '!CB38:CB40) -> -1737880.4 | CK80: =-SUM(CK67,CK62,CK22) -> -1733250.9 | CL80: =-SUM('3. Cash Flow Statement '!CD24:CD29,'3. Cash Flow Statement '!CD36,'3. Cash Flow Statement '!CD38:CD40) -> -1680016 | CM80: =-SUM(CM67,CM62,CM22) -> -1726467.2 | CN80: =-SUM(CN67,CN62,CN22) -> -1758233.3
E81: Closing Balance | F81: =F75+F76+F78+F80 -> 41211.737 | G81: =G75+G76+G78+G80 -> 38039.623 | H81: =H75+H76+H78+H80 -> 25262.355 | I81: =I75+I76+I78+I80 -> 20734.343 | J81: =J75+J76+J78+J80 -> 2684134.2 | K81: =K75+K76+K78+K80 -> 2628068.7 | L81: =L75+L76+L78+L80 -> 2558584.8 | M81: =M75+M76+M78+M80 -> 2496054.5 | ... AE81: =AE75+AE76+AE78+AE80 -> 6202169.4 | AF81: =SUM(AF75:AF80) -> 6074938.5 | AG81: =AG75+AG76+AG78+AG80 -> 5731321.2 | AH81: =SUM(AH75:AH80) -> 5703445.6 | AI81: =AI75+AI76+AI78+AI80 -> 5322119.5 | AJ81: =SUM(AJ75:AJ80) -> 5550513.8 | AK81: =AK75+AK76+AK78+AK80 -> 4919162.7 | AL81: =SUM(AL75:AL80) -> 5365984.7 | AM81: =AM75+AM76+AM78+AM80 -> 4477413.3 | AN81: =SUM(AN75:AN80) -> 5054500.8 | AO81: =AO75+AO76+AO78+AO80 -> 13485947 | AP81: =SUM(AP75:AP80) -> 4669366.8 | AQ81: =AQ75+AQ76+AQ78+AQ80 -> 12910372 | AR81: =SUM(AR75:AR80) -> 13448938 | AS81: =AS75+AS76+AS78+AS80 -> 12334037 | AT81: =SUM(AT75:AT80) -> 13209859 | AU81: =AU75+AU76+AU78+AU80 -> 11759601 | AV81: =SUM(AV75:AV80) -> 12695225 | AW81: =AW75+AW76+AW78+AW80 -> 11237238 | AX81: =SUM(AX75:AX80) -> 13247256 | AY81: =AY75+AY76+AY78+AY80 -> 10766557 | AZ81: =SUM(AZ75:AZ80) -> 12939952 | BA81: =BA75+BA76+BA78+BA80 -> 10206670 | BB81: =SUM(BB75:BB80) -> 12446292 | BC81: =BC75+BC76+BC78+BC80 -> 11676228 | BD81: =SUM(BD75:BD80) -> 12086883 | BE81: =BE75+BE76+BE78+BE80 -> 11094397 | BF81: =SUM(BF75:BF80) -> 11659986 | BG81: =BG75+BG76+BG78+BG80 -> 10482888 | BH81: =SUM(BH75:BH80) -> 11117887 | BI81: =BI75+BI76+BI78+BI80 -> 9885955.6 | BJ81: =SUM(BJ75:BJ80) -> 10669512 | BK81: =BK75+BK76+BK78+BK80 -> 9191934 | BL81: =SUM(BL75:BL80) -> 10545552 | BM81: =BM75+BM76+BM78+BM80 -> 9515854.2 | BN81: =SUM(BN75:BN80) -> 9868272.6 | BO81: =BO75+BO76+BO78+BO80 -> 9013160.1 | BP81: =SUM(BP75:BP80) -> 9525350.9 | BQ81: =BQ75+BQ76+BQ78+BQ80 -> 9144575.7 | BR81: =SUM(BR75:BR80) -> 9414035.6 | BS81: =BS75+BS76+BS78+BS80 -> 9096507.9 | BT81: =SUM(BT75:BT80) -> 8669877.3 | BU81: =BU75+BU76+BU78+BU80 -> 8799513.6 | BV81: =SUM(BV75:BV80) -> 8102892.3 | BW81: =BW75+BW76+BW78+BW80 -> 8530919.9 | BX81: =SUM(BX75:BX80) -> 7830689.4 | BY81: =BY75+BY76+BY78+BY80 -> 8262653.6 | BZ81: =SUM(BZ75:BZ80) -> 7417386.5 | CA81: =CA75+CA76+CA78+CA80 -> 8077338.4 | CB81: =SUM(CB75:CB80) -> 7177822.2 | CC81: =CC75+CC76+CC78+CC80 -> 7877013.1 | CD81: =SUM(CD75:CD80) -> 6890959.3 | CE81: =CE75+CE76+CE78+CE80 -> 7650249.4 | CF81: =SUM(CF75:CF80) -> 6732264.6 | CG81: =CG75+CG76+CG78+CG80 -> 7464284.2 | CH81: =SUM(CH75:CH80) -> 6041826.7 | CI81: =CI75+CI76+CI78+CI80 -> 7252570.7 | CJ81: =SUM(CJ75:CJ80) -> 5837148.9 | CK81: =CK75+CK76+CK78+CK80 -> 7042842.2 | CL81: =SUM(CL75:CL80) -> 5441845.6 | CM81: =CM75+CM76+CM78+CM80 -> 5316375 | CN81: =CN75+CN76+CN78+CN80 -> 3558141.7
E83: Net Burn (Op-cl) | F83: =F75-F81 -> 3596.0244 | G83: =G75-G81 -> 3172.1141 | H83: =H75-H81 -> 12777.268 | I83: =I75-I81 -> 4528.0122 | J83: =J75-J81 -> -2663399.9 | K83: =K75-K81+K78 -> 56065.511 | L83: =L75-L81+L78 -> 69483.914 | M83: =M75-M81+M78 -> 62530.25 | N83: =N75-N81+N78 -> 119242.04 | O83: =O75-O81+O78 -> 157031.36 | P83: =P75-P81+P78 -> 110658.62 | Q83: =Q75-Q81+Q78 -> 187517.9 | R83: =R75-R81+R78 -> 142172.95 | ... W83: =W75-W81+W78 -> 476273.56 | X83: =X75-X81 -> 449934.97 | Y83: =-(Y81-Y75-Y78) -> 417704.38 | Z83: =Z75-Z81 -> 467099.94 | AA83: =-(AA81-AA75-AA78) -> 433511.88 | AB83: =AB75-AB81 -> 332512.96 | AC83: =-(AC81-AC75-AC78) -> 423076.26 | AD83: =AD75-AD81 -> 392619.04 | AE83: =-(AE81-AE75-AE78) -> 425811.55 | AF83: =-(AF81-AF75-AF78) -> 471208.87 | AG83: =-(AG81-AG75-AG78) -> 470848.13 | AH83: =-(AH81-AH75-AH78) -> 371847.63 | AI83: =-(AI81-AI75-AI78) -> 409201.71 | AJ83: =-(AJ81-AJ75-AJ78) -> 455703.12 | AK83: =-(AK81-AK75-AK78) -> 402956.83 | AL83: =-(AL81-AL75-AL78) -> 319925.54 | ... CN83: =-(CN81-CN75-CN78) -> 1758233.3
CJ84: =CF83+CH83+CJ83 -> 1053810.3
E85: Runway | F85: =IFERROR(F81/F83,0) -> 11.460361 | G85: =IFERROR(G81/G83,0) -> 11.991884 | H85: =IFERROR(H81/H83,0) -> 1.9771327 | I85: =IFERROR(I81/I83,0) -> 4.579127 | J85: =IFERROR(J81/J83,0) -> -1.0077849 | K85: =IFERROR(K81/K83,0) -> 46.874962 | L85: =IFERROR(L81/L83,0) -> 36.822692 | M85: =IFERROR(M81/M83,0) -> 39.917553 | ... AN85: =IFERROR(AN81/AN83,0) -> 16.227165 | AO85: =AO81/AVERAGE(AM83,AK83,AO83) -> 29.775568 | AP85: =AP81/AVERAGE(AN83,AL83,AP83) -> 13.780129 | AQ85: =AQ81/AVERAGE(AO83,AM83,AQ83) -> 25.291677 | AR85: =AR81/AVERAGE(AP83,AN83,AR83) -> 43.709252 | AS85: =AS81/AVERAGE(AQ83,AO83,AS83) -> 22.210641 | AT85: =AT81/AVERAGE(AR83,AP83,AT83) -> 46.586449 | AU85: =AU81/AVERAGE(AS83,AQ83,AU83) -> 20.435545 | AV85: =AV81/AVERAGE(AT83,AR83,AV83) -> 38.856311 | ... BJ85: =BJ81/AVERAGE(BH83,BF83,BJ83) -> 22.583035 | BK85: =BK81/AVERAGE(BG83,BI83,BK83) -> 14.494787 | BL85: =BL81/AVERAGE(BJ83,BH83,BL83) -> 28.388091 | BM85: =BM81/AVERAGE(BI83,BK83,BM83) -> 16.52911 | BN85: =BN81/AVERAGE(BL83,BJ83,BN83) -> 23.691163 | BO85: =BO81/AVERAGE(BK83,BM83,BO83) -> 16.559485 | BP85: =BP81/AVERAGE(BN83,BL83,BP83) -> 24.975541 | BQ85: =BQ81/AVERAGE(BO83,BP83,BQ83) -> 22.369478 | BR85: =BR81/AVERAGE(BP83,BN83,BR83) -> 24.959515 | BS85: =BS81/AVERAGE(BQ83,BR83,BS83) -> 33.706657 | BT85: =BT81/AVERAGE(BR83,BP83,BT83) -> 21.703715 | BU85: =BU81/AVERAGE(BR83,BS83,BU83) -> 36.369772 | BV85: =BV81/AVERAGE(BT83,BR83,BV83) -> 17.089198 | BW85: =BW81/AVERAGE(BS83,BU83,BW83) -> 28.980076 | BX85: =BX81/AVERAGE(BV83,BT83,BX83) -> 14.836975 | BY85: =BY81/AVERAGE(BU83,BW83,BY83) -> 29.726967 | BZ85: =BZ81/AVERAGE(BX83,BV83,BZ83) -> 17.766327 | CA85: =CA81/AVERAGE(BW83,BY83,CA83) -> 33.554206 | CB85: =CB81/AVERAGE(BZ83,BX83,CB83) -> 23.277657 | CC85: =CC81/AVERAGE(BY83,CA83,CC83) -> 36.138235 | CD85: =CD81/AVERAGE(CB83,BZ83,CD83) -> 21.998738 | CE85: =CE81/AVERAGE(CA83,CC83,CE83) -> 37.476474 | CF85: =CF81/AVERAGE(CD83,CB83,CF83) -> 29.479122 | CG85: =CG81/AVERAGE(CC83,CE83,CG83) -> 36.526715 | CH85: =CH81/AVERAGE(CF83,CD83,CH83) -> 15.955592 | CI85: =CI81/AVERAGE(CE83,CG83,CI83) -> 34.843425 | CJ85: =CJ81/AVERAGE(CH83,CF83,CJ83) -> 16.617266 | CK85: =CK81/AVERAGE(CG83,CI83,CK83) -> 34.78478 | CL85: =CL81/AVERAGE(CJ83,CH83,CL83) -> 12.651346 | CM85: =CM81/AVERAGE(CI83,CK83,CM83) -> 7.4254183 | CN85: =CN81/AVERAGE(CK83,CM83,CN83) -> 2.8893301
BR87: =SUM(BN64,BP64,BR64)/SUM(BR3,BP3,BN3) -> -0.56579856 | BX87: =SUM(BT64,BV64,BX64)/SUM(BX3,BV3,BT3) -> -0.54103734 | CD87: =SUM(BZ64,CB64,CD64)/SUM(CD3,CB3,BZ3) -> -0.28983886 | CJ87: =SUM(CF64,CH64,CJ64)/SUM(CJ3,CH3,CF3) -> -0.23334899

Sheet 3. Cash Flow Statement 
C1: Cash Flow Statement (Cash Basis) for the period ending 30.04.2023 | BF1: 85 | BH1: 85 | BJ1: 85 | BL1: 85 | BN1: 85 | BP1: 85 | BR1: 85 | BT1: 85 | BV1: 85 | BX1: 85 | BZ1: 85 | CB1: 89 | CD1: 89
AB2: 60466
B3: In USD | C3: 44681 | D3: 44712 | E3: 44742 | F3: 44773 | G3: 44804 | H3: 44834 | I3: 44865 | J3: 44895 | K3: 44926 | L3: 44957 | M3: 44985 | N3: 45016 | P3: 45046 | R3: 45077 | T3: 45107 | V3: 45138 | X3: 45169 | Z3: 45199 | AB3: 45230 | AD3: 45260 | AF3: 45291 | AH3: 45322 | AJ3: 45351 | AL3: 45382 | AN3: 45412 | AP3: 45443 | AR3: 45473 | AT3: 45504 | AV3: 45535 | AX3: 45565 | AZ3: 45596 | BB3: =EOMONTH(AZ3,1) -> 45626 | BD3: =EOMONTH(BB3,1) -> 45657 | BF3: =EOMONTH(BD3,1) -> 45688 | BH3: =EOMONTH(BF3,1) -> 45716 | BJ3: =EOMONTH(BH3,1) -> 45747 | BL3: =EOMONTH(BJ3,1) -> 45777 | BN3: =EOMONTH(BL3,1) -> 45808 | BP3: =EOMONTH(BN3,1) -> 45838 | BR3: =EOMONTH(BP3,1) -> 45869 | BT3: =EOMONTH(BR3,1) -> 45900 | BV3: =EOMONTH(BT3,1) -> 45930 | BX3: =EOMONTH(BV3,1) -> 45961 | BZ3: =EOMONTH(BX3,1) -> 45991 | CB3: =EOMONTH(BZ3,1) -> 46022 | CD3: =EOMONTH(CB3,1) -> 46053
B4: Cash at the beginning of the period | C4: =SUM(C5:C20) -> 2684134.2 | D4: =SUM(D5:D20) -> 2628068.7 | E4: =SUM(E5:E20) -> 2558584.8 | F4: =SUM(F5:F20) -> 2496054.5 | G4: =SUM(G5:G20) -> 2376812.5 | H4: =SUM(H5:H20) -> 2219781.1 | I4: =SUM(I5:I20) -> 2109122.5 | J4: =SUM(J5:J20) -> 1921604.6 | ... BP4: =SUM(BP5:BP20) -> 8102892.3 | BR4: =SUM(BR5:BR20) -> 7830689.4 | BT4: =SUM(BT5:BT20) -> 7417386.5 | BV4: =SUM(BV5:BV20) -> 7177822.1 | BX4: =SUM(BX5:BX20) -> 6890958.6 | BZ4: =SUM(BZ5:BZ20) -> 6732264 | CB4: =SUM(CB5:CB20) -> 6041825.8 | CD4: =SUM(CD5:CD20) -> 5837148
B5: Kotak Bank 9651 | C5: 12603.532 | D5: =C43 -> 24830.704 | E5: =D43 -> 41639.938 | F5: =E43 -> 66748.527 | G5: =F43 -> 87829.047 | H5: =G43 -> 24208.857 | I5: =H43 -> 80842.37 | J5: =I43 -> 42160.85 | K5: =J43 -> 35515.643 | ... N5: =M43 -> 95075.939 | O5: =M43 -> 95075.939 | P5: =N43 -> 186263.49 | R5: =P43 -> 564039.15 | T5: =R43 -> 946015.09 | V5: =T43 -> 144229.13 | X5: =V43 -> 99679.41 | Z5: =X43 -> 218742.1 | AB5: =Z43 -> 228223.75 | AD5: =AB43 -> 125676.49 | AF5: =AD43 -> 128518.02 | AH5: =AF43 -> 498258.95 | AJ5: =AH43 -> 360658.09 | AL5: =AJ43 -> 220630.14 | AN5: =AL43 -> 111863.97 | AP5: =AN43 -> 52566.353 | AQ5: =AO43 | AR5: =AP43 -> 182823.19 | AT5: =AR43 -> 129360.42 | AV5: =AT43 -> 234677.27 | AX5: =AV43 -> 140877.41 | AZ5: =AX43 -> 376891.89 | BB5: =AZ43 -> 252447.7 | BD5: =BB43 -> 69344.745 | BF5: =BD43 -> 355217.39 | BH5: =BF43 -> 482539.9 | BJ5: =BH43 -> 331175.88 | BL5: =BJ43 -> 295097.11 | BN5: =BL43 -> 751952.45 | BO5: =BM43 | BP5: =BN43 -> 572888.55 | BR5: =BP43 -> 648164.35 | BT5: =BR43 -> 607020.27 | BV5: =BT43 -> 722581.33 | BX5: =BV43 -> 149705 | BZ5: =BX43 -> 781522.81 | CB5: =BZ43 -> 564004.01 | CD5: =CB43 -> 1333183.1
B6: Kotak Bank 5102 | C6: 2671530.7 | D6: =C44 -> 2603238 | E6: =D44 -> 2516944.9 | F6: =E44 -> 2429306 | G6: =F44 -> 2274428 | H6: =G44 -> 2191501.1 | I6: =H44 -> 2014671.9 | J6: =I44 -> 1868330.4 | K6: =J44 -> 1721988.9 | ... N6: =M44 -> 976866.99 | O6: =M44 -> 976866.99 | P6: =N44 -> 7834914.2 | R6: =P44 -> 1335311.3 | T6: =R44 -> 591864.73 | V6: =T44 -> 36986.685 | X6: =V44 -> 724405.49 | Z6: =X44 -> 173903.61 | AB6: =Z44 -> 137672.98 | AD6: =AB44 -> 213536.69 | AF6: =AD44 -> 239177.07 | AH6: =AF44 -> 203693.8 | AJ6: =AH44 -> 128950.5 | AL6: =AJ44 -> 82666.064 | AN6: =AL44 -> 82666.064 | AP6: =AN44 -> 203147.99 | AQ6: =AO44 | AR6: =AP44 -> 1083321.1 | AT6: =AR44 -> 1100558 | AV6: =AT44 -> 136702.53 | AX6: =AV44 -> 178129.18 | AZ6: =AX44 -> 141771.34 | BB6: =AZ44 -> 139874.26 | BD6: =BB44 -> 730235.71 | BF6: =BD44 -> 368789.93 | BH6: =BF44 -> 242465.46 | BJ6: =BH44 -> 359696.04 | BL6: =BJ44 -> 594781.93 | BN6: =BL44 -> 6546.6329 | BO6: =BM44 | BP6: =BN44 -> 124193.69 | BR6: =BP44 -> 6546.6329 | BT6: =BR44 -> 6539.6918 | BV6: =BT44 -> 6539.6918 | BX6: =BV44 -> 594774.99 | BZ6: =BX44 -> 241833.81 | CB6: =BZ44 -> 6532.7506 | CD6: =CB44 -> 6232.5146
B7: HSBC-14-001 | D7: =C45 | E7: =D45 | F7: =E45 | G7: =F45 | H7: =G45 | I7: =H45 | J7: =I45 | K7: =J45 | ... N7: =M45 | O7: =M45 | P7: =N45 | R7: =P45 | T7: =R45 | V7: =T45 | X7: =V45 | Z7: =X45 | AB7: =Z45 | AD7: =AB45 | AF7: =AD45 | AH7: =AF45 | AJ7: =AH45 | AL7: =AJ45 | AN7: =AL45 | AP7: =AN45 | AQ7: =AO45 | AR7: =AP45 | AT7: =AR45 | AV7: =AT45 | AX7: =AV45 | AZ7: =AX45 | BB7: =AZ45 | BD7: =BB45 -> 1204.8193 | BF7: =BD45 -> 1204.8193 | BH7: =BF45 -> 1176.4706 | BJ7: =BH45 -> 1176.4706 | BL7: =BJ45 -> 1176.4706 | BN7: =BL45 -> 1162.6298 | BO7: =BM45 | BP7: =BN45 -> 1162.6298 | BR7: =BP45 -> 1162.6298 | BT7: =BR45 -> 1162.6298 | BV7: =BT45 -> 1162.6298 | BX7: =BV45 -> 1162.6298 | BZ7: =BX45 -> 1162.6298 | CB7: =BZ45 -> 1162.6298 | CD7: =CB45 -> 1110.3767
B8: My Biz Wallet | D8: =C46 | E8: =D46 | F8: =E46 | G8: =F46 | H8: =G46 | I8: =H46 | J8: =I46 | K8: =J46 | ... N8: =M46 -> 1604.11 | O8: =M46 -> 1604.11 | P8: =N46 -> 9581.4146 | R8: =P46 -> 5286.4026 | T8: =R46 -> 19.744024 | V8: =T46 -> 8372.427 | X8: =V46 -> 1085.3782 | Z8: =X46 -> 10764.622 | AB8: =Z46 -> 6147.1099 | AD8: =AB46 -> 12604.171 | AF8: =AD46 -> 2401.1099 | AH8: =AF46 -> 8500.5367 | AJ8: =AH46 -> 13024.47 | AL8: =AJ46 -> 2180.8555 | AN8: =AL46 -> -2204.6023 | AP8: =AN46 -> 23594.398 | AQ8: =AO46 | AR8: =AP46 -> 9600.4339 | AT8: =AR46 -> 22859.434 | AV8: =AT46 -> 11692.265 | AX8: =AV46 -> 3310.8796 | AZ8: =AX46 -> 13993.482 | BB8: =AZ46 -> 2365.1929 | BD8: =BB46 -> 13396.615 | BF8: =BD46 -> 10624.313 | BH8: =BF46 -> 16791.906 | BJ8: =BH46 -> 17409.586 | BL8: =BJ46 -> 28135.894 | BN8: =BL46 -> 17141.588 | BO8: =BM46 | BP8: =BN46 -> 3125.13 | BR8: =BP46 -> 21613.955 | BT8: =BR46 -> 14871.793 | BV8: =BT46 -> 12317.368 | BX8: =BV46 -> 22112.983 | BZ8: =BX46 -> 5774.8724 | CB8: =BZ46 -> 26244.785 | CD8: =CB46 -> 3283.8382
B9: Karbon Card | D9: =C47 | E9: =D47 | F9: =E47 | G9: =F47 | H9: =G47 -> 3589.4391 | I9: =H47 -> 11548.399 | J9: =I47 -> 9774.7004 | K9: =J47 -> 9356.5178 | ... N9: =M47 -> 15752.582 | O9: =M47 -> 15752.582 | P9: =N47 -> 29342.626 | R9: =P47 -> 29342.63 | T9: =R47 -> 29342.626 | V9: =T47 -> 0 | X9: =V47 -> 0 | Z9: =X47 -> 0 | AB9: =Z47 -> 0 | AD9: =AB47 -> 0 | AF9: =AD47 | AH9: =AF47 | AJ9: =AH47 -> 0 | AL9: =AJ47 -> 0 | AN9: =AL47 -> 0 | AP9: =AN47 -> 36010.8 | AQ9: =AO47 | AR9: =AP47 -> 35180.321 | AT9: =AR47 -> 34269.174 | AV9: =AT47 -> 33257.297 | AX9: =AV47 -> 32926.32 | AZ9: =AX47 -> 32420.1 | BB9: =AZ47 -> 32279.298 | BD9: =BB47 -> 32219.057 | BF9: =BD47 -> 31795.714 | BH9: =BF47 -> 30478.588 | BJ9: =BH47 -> 29516.203 | BL9: =BJ47 -> 28954.423 | BN9: =BL47 -> 28413.659 | BO9: =BM47 | BP9: =BN47 -> 27123.308 | BR9: =BP47 -> 26944.473 | BT9: =BR47 -> 24919.28 | BV9: =BT47 -> 24444.719 | BX9: =BV47 -> 23947.66 | BZ9: =BX47 -> 23247.213 | CB9: =BZ47 -> 21919.022 | CD9: =CB47 -> 20350.62
B10: Razorpay | D10: =C48 | E10: =D48 | F10: =E48 | G10: =F48 -> 14555.488 | H10: =G48 -> 481.70732 | I10: =H48 -> 2059.8782 | J10: =I48 -> 1338.6617 | K10: =J48 -> 12570.564 | ... N10: =M48 -> 22445.025 | O10: =M48 -> 22445.025 | P10: =N48 -> 23526.71 | R10: =P48 -> 13639.524 | T10: =R48 -> 33169.753 | V10: =T48 -> 19357.527 | X10: =V48 -> 57740.286 | Z10: =X48 -> 79423.246 | AB10: =Z48 -> 70264.175 | AD10: =AB48 -> 16743.55 | AF10: =AD48 -> 38704.07 | AH10: =AF48 -> 30981.049 | AJ10: =AH48 -> 39487.737 | AL10: =AJ48 -> 14169.467 | AN10: =AL48 -> 19706.677 | AP10: =AN48 -> 47696.206 | AQ10: =AO48 | AR10: =AP48 -> 14295.965 | AT10: =AR48 -> 1928.9225 | AV10: =AT48 -> 12559.361 | AX10: =AV48 -> 11688.875 | AZ10: =AX48 -> 3011.6672 | BB10: =AZ48 -> 10283.472 | BD10: =BB48 -> 120207.69 | BF10: =BD48 -> 106435.11 | BH10: =BF48 -> 152820.81 | BJ10: =BH48 -> 15421.642 | BL10: =BJ48 -> 13120.315 | BN10: =BL48 -> 11375.672 | BO10: =BM48 | BP10: =BN48 -> 80106.399 | BR10: =BP48 -> 22943.647 | BT10: =BR48 -> 28261.96 | BV10: =BT48 -> 22661.354 | BX10: =BV48 -> 5560.4532 | BZ10: =BX48 -> 33483.64 | CB10: =BZ48 -> 13946.598 | CD10: =CB48 -> 46825.529
B11: Kotak Credit Card | D11: =C49 | E11: =D49 | F11: =E49 | G11: =F49 | H11: =G49 | I11: =H49 | J11: =I49 | K11: =J49 | ... N11: =M49 | O11: =M49 | P11: =N49 | R11: =P49 | T11: =R49 | V11: =T49 | X11: =V49 | Z11: =X49 | AB11: =Z49 | AD11: =AB49 | AF11: =AD49 | AH11: =AF49 | AJ11: =AH49 | AL11: =AJ49 | AN11: =AL49 | AP11: =AN49 | AQ11: =AO49 | AR11: =AP49 | AT11: =AR49 | AV11: =AT49 -> -19.60241 | AX11: =AV49 -> -45.204819 | AZ11: =AX49 -> -86.659277 | BB11: =AZ49 -> -163.4253 | BD11: =BB49 -> -619.89542 | BF11: =BD49 -> -1235.0633 | BH11: =BF49 -> -632.89129 | BJ11: =BH49 -> -1182.632 | BL11: =BJ49 -> -759.80259 | BN11: =BL49 -> -609.25929 | BO11: =BM49 | BP11: =BN49 -> -341.51094 | BR11: =BP49 -> -424.90612 | BT11: =BR49 -> -447.76529 | BV11: =BT49 -> -1957.1262 | BX11: =BV49 -> -258.69259 | BZ11: =BX49 -> -254.52565 | CB11: =BZ49 -> -679.42682 | CD11: =CB49 -> -1178.7179
B12: Razorpay Collection Wallet | D12: =C50 | E12: =D50 | F12: =E50 | G12: =F50 | H12: =G50 | I12: =H50 | J12: =I50 | K12: =J50 | ... N12: =M50 | O12: =M50 | P12: =N50 | R12: =P50 | T12: =R50 | V12: =T50 | X12: =V50 | Z12: =X50 | AB12: =Z50 | AD12: =AB50 | AF12: =AD50 | AH12: =AF50 | AJ12: =AH50 | AL12: =AJ50 | AN12: =AL50 | AP12: =AN50 | AQ12: =AO50 | AR12: =AP50 | AT12: =AR50 | AV12: =AT50 -> 8863.5155 | AX12: =AV50 -> 6684.9801 | AZ12: =AX50 -> 10273.381 | BB12: =AZ50 -> 1593.7045 | BD12: =BB50 -> 8957.8377 | BF12: =BD50 -> 4227.176 | BH12: =BF50 -> 2745.61 | BJ12: =BH50 -> 5330.3896 | BL12: =BJ50 -> 3074.0591 | BN12: =BL50 -> 9272.8056 | BO12: =BM50 | BP12: =BN50 -> 3894.3031 | BR12: =BP50 -> 4658.7389 | BT12: =BR50 -> 4658.7389 | BV12: =BT50 -> 4658.7389 | BX12: =BV50 -> 4658.7389 | BZ12: =BX50 -> 4658.7389 | CB12: =BZ50 -> 4658.7389 | CD12: =CB50 -> 4449.3574
B13: Customer Advance | D13: =C51 | E13: =D51 | F13: =E51 | G13: =F51 | H13: =G51 | I13: =H51 | J13: =I51 | K13: =J51 | ... N13: =M51 | P13: =N51 | R13: =P51 | T13: =R51 | V13: =T51 | X13: =V51 | Z13: =X51 | AB13: =Z51 | AD13: =AB51 | AF13: =AD51 | AH13: =AF51 | AJ13: =AH51 | AL13: =AJ51 | AN13: =AL51 | AP13: =AN51 | AR13: =AP51 | AT13: =AR51 | AV13: =AT51 | AX13: =AV51 | AZ13: =AX51 | BB13: =AZ51 | BD13: =BB51 | BF13: =BD51 | BH13: =BF51 | BJ13: =BH51 | BL13: =BJ51 | BN13: =BL51 | BO13: =BM51 | BP13: =BN51 -> 15000 | BR13: =BP51 -> 15000 | BT13: =BR51 -> 15000 | BV13: =BT51 -> 15000 | BX13: =BV51 -> 15000 | BZ13: =BX51 -> 15000 | CB13: =BZ51 -> 15000 | CD13: =CB51 -> 15000
B14: Mercury Bank Scrut Inc. | D14: =C52 | E14: =D52 | F14: =E52 | G14: =F52 | H14: =G52 | I14: =H52 | J14: =I52 | K14: =J52 | ... N14: =M52 | O14: =M52 | P14: =N52 -> 4500 | R14: =P52 -> 324720.56 | T14: =R52 -> 192632.59 | V14: =T52 -> 154024.85 | X14: =V52 -> 67542.75 | Z14: =X52 -> 438298.24 | AB14: =Z52 -> 274022.02 | AD14: =AB52 -> 198156.7 | AF14: =AD52 -> 118193.17 | AH14: =AF52 -> 1248535.9 | AJ14: =AH52 -> 1112835.5 | AL14: =AJ52 -> 124103.32 | AN14: =AL52 -> 143053.12 | AP14: =AN52 -> 152146.34 | AQ14: =AO52 | AR14: =AP52 -> 147450.64 | AT14: =AR52 -> 147421.35 | AV14: =AT52 -> 173936.68 | AX14: =AV52 -> 202109.73 | AZ14: =AX52 -> 235881.81 | BB14: =AZ52 -> 281189.23 | BD14: =BB52 -> 353974.34 | BF14: =BD52 -> 570466.3 | BH14: =BF52 -> 168961.17 | BJ14: =BH52 -> 295288.92 | BL14: =BJ52 -> 230621.36 | BN14: =BL52 -> 191138.46 | BO14: =BM52 | BP14: =BN52 -> 198535.95 | BR14: =BP52 -> 332924.51 | BT14: =BR52 -> 95289 | BV14: =BT52 -> 99747 | BX14: =BV52 -> 153430 | BZ14: =BX52 -> 325282 | CB14: =BZ52 -> 365125.11 | CD14: =CB52 -> 282828.08
B15: State Bank of India | C15: 0 | D15: =C53 | E15: =D53 | F15: =E53 | G15: =F53 | H15: =G53 | I15: =H53 | J15: =I53 | K15: =J53 | ... N15: =M53 | O15: =M53 | P15: =N53 | R15: =P53 | T15: =R53 -> 12195.122 | V15: =T53 -> 12195.122 | X15: =V53 -> 12195.122 | Z15: =X53 -> 12195.122 | AB15: =Z53 -> 12195.122 | AD15: =AB53 -> 12195.122 | AF15: =AD53 -> 12195.122 | AH15: =AF53 -> 12195.122 | AJ15: =AH53 -> 12048.193 | AL15: =AJ53 -> 12048.193 | AN15: =AL53 -> 12048.193 | AP15: =AN53 -> 12048.193 | AQ15: =AO53 | AR15: =AP53 -> 12048.193 | AT15: =AR53 -> 12048.193 | AV15: =AT53 -> 11813.829 | AX15: =AV53 -> 11756.961 | AZ15: =AX53 -> 11700.094 | BB15: =AZ53 -> 11643.226 | BD15: =BB53 -> 11586.359 | BF15: =BD53 -> 11529.491 | BH15: =BF53 -> 11202.68 | BJ15: =BH53 -> 11258.209 | BL15: =BJ53 -> 11258.209 | BN15: =BL53 -> 11083.986 | BO15: =BM53 | BP15: =BN53 -> 11125.76 | BR15: =BP53 -> 11083.986 | BT15: =BR53 -> 11083.986 | BV15: =BT53 -> 11083.986 | BX15: =BV53 -> 11083.986 | BZ15: =BX53 -> 11083.986 | CB15: =BZ53 -> 11083.986 | CD15: =CB53 -> 10585.829
B16: RHO | C16: 0 | D16: =C54 | E16: =D54 | F16: =E54 | G16: =F54 | H16: =G54 | I16: =H54 | J16: =I54 | K16: =J54 | ... N16: =M54 | O16: =M54 | P16: =N54 | R16: =P54 | T16: =R54 | V16: =T54 | X16: =V54 | Z16: =X54 | AB16: =Z54 -> 37282.5 | AD16: =AB54 -> 21136.98 | AF16: =AD54 -> 52674.28 | AH16: =AF54 -> 33422.96 | AJ16: =AH54 -> 19178.95 | AL16: =AJ54 -> 23811.53 | AN16: =AL54 -> 48397.37 | AP16: =AN54 -> 18945.78 | AQ16: =AO54 | AR16: =AP54 -> 49933.42 | AT16: =AR54 -> 34724.02 | AV16: =AT54 -> 22018.34 | AX16: =AV54 -> 66384.09 | AZ16: =AX54 -> 61396.67 | BB16: =AZ54 -> 42878.14 | BD16: =BB54 -> 29308.38 | BF16: =BD54 -> 25431.31 | BH16: =BF54 -> 24832.926 | BJ16: =BH54 -> 45706.15 | BL16: =BJ54 -> 27650.51 | BN16: =BL54 -> 9360.4 | BO16: =BM54 | BP16: =BN54 -> 63948.94 | BR16: =BP54 -> 54067.93 | BT16: =BR54 -> 47916 | BV16: =BT54 -> 19206 | BX16: =BV54 -> 20028 | BZ16: =BX54 -> 17475 | CB16: =BZ54 -> 56737.66 | CD16: =CB54 -> 36018.66
B17: Treasury | D17: =C55 | E17: =D55 | F17: =E55 | G17: =F55 | H17: =G55 | I17: =H55 | J17: =I55 | K17: =J55 | ... N17: =M55 | O17: =M55 | P17: =N55 | R17: =P55 | T17: =R55 | V17: =T55 | X17: =V55 | Z17: =X55 | AB17: =Z55 | AD17: =AB55 | AF17: =AD55 | AH17: =AF55 | AJ17: =AH55 | AL17: =AJ55 -> 950000 | AN17: =AL55 -> 775000 | AP17: =AN55 -> 580702.88 | AQ17: =AO55 | AR17: =AP55 -> 483334.9 | AT17: =AR55 -> 485729.5 | AV17: =AT55 -> 387706.81 | AX17: =AV55 -> 389535.26 | AZ17: =AX55 -> 391137.91 | BB17: =AZ55 -> 392643.72 | BD17: =BB55 -> 394111.19 | BF17: =BD55 -> 395491.53 | BH17: =BF55 -> 596695.76 | BJ17: =BH55 -> 598317.79 | BL17: =BJ55 -> 910180.48 | BN17: =BL55 -> 1001715.7 | BO17: =BM55 | BP17: =BN55 -> 1004983.9 | BR17: =BP55 -> 1111621.9 | BT17: =BR55 -> 1511923.3 | BV17: =BT55 -> 1811622 | BX17: =BV55 -> 2002798 | BZ17: =BX55 -> 2008959 | CB17: =BZ55 -> 2315429.5 | CD17: =CB55 -> 2322062.7
B18: Rent Security Deposit | C18: 0 | D18: =C56 -> 0 | E18: =D56 -> 0 | F18: =E56 -> 0 | G18: =F56 -> 0 | H18: =G56 -> 0 | I18: =H56 -> 0 | J18: =I56 -> 0 | K18: =J56 -> 0 | ... N18: =M56 -> 0 | O18: =M56 -> 0 | P18: =N56 -> 0 | R18: =P56 -> 0 | T18: =R56 -> 0 | V18: =T56 -> 0 | X18: =V56 -> 0 | Z18: =X56 -> 26696.341 | AB18: =Z56 -> 26696.341 | AD18: =AB56 -> 53392.683 | AF18: =AD56 -> 53392.683 | AH18: =AF56 -> 53392.683 | AJ18: =AH56 -> 53392.683 | AL18: =AJ56 -> 53392.683 | AN18: =AL56 -> 53392.683 | AP18: =AN56 -> 53392.683 | AQ18: =AO56 | AR18: =AP56 -> 53392.683 | AT18: =AR56 -> 53392.683 | AV18: =AT56 -> 60674.641 | AX18: =AV56 -> 60674.641 | AZ18: =AX56 -> 60674.641 | BB18: =AZ56 -> 60674.641 | BD18: =BB56 -> 60674.641 | BF18: =BD56 -> 59481.857 | BH18: =BF56 -> 58082.284 | BJ18: =BH56 -> 58082.284 | BL18: =BJ56 -> 57665.014 | BN18: =BL56 -> 56986.602 | BO18: =BM56 | BP18: =BN56 -> 56986.602 | BR18: =BP56 -> 56986.602 | BT18: =BR56 -> 56986.602 | BV18: =BT56 -> 57221.892 | BX18: =BV56 -> 57221.892 | BZ18: =BX56 -> 57221.892 | CB18: =BZ56 -> 57221.892 | CD18: =CB56 -> 54885.411
B19: Fixed Deposit | D19: =C57 | E19: =D57 | F19: =E57 | G19: =F57 | H19: =G57 | I19: =H57 | J19: =I57 | K19: =J57 | ... N19: =M57 | O19: =M57 | P19: =N57 | R19: =P57 | T19: =R57 -> 243902.44 | V19: =T57 -> 243902.44 | X19: =V57 -> 243902.44 | Z19: =X57 -> 243902.44 | AB19: =Z57 -> 243902.44 | AD19: =AB57 -> 243902.44 | AF19: =AD57 -> 243902.44 | AH19: =AF57 -> 243902.44 | AJ19: =AH57 -> 240963.86 | AL19: =AJ57 -> 240963.86 | AN19: =AL57 -> 240963.86 | AP19: =AN57 -> 240963.86 | AQ19: =AO57 | AR19: =AP57 -> 240963.86 | AT19: =AR57 -> 240963.86 | AV19: =AT57 -> 26506.024 | AX19: =AV57 -> 26506.024 | AZ19: =AX57 -> 26506.024 | BB19: =AZ57 -> 26506.024 | BD19: =BB57 -> 26506.024 | BF19: =BD57 -> 26506.024 | BH19: =BF57 -> 25882.353 | BJ19: =BH57 -> 25882.353 | BL19: =BJ57 -> 25882.353 | BN19: =BL57 -> 25577.855 | BO19: =BM57 | BP19: =BN57 -> 25577.855 | BR19: =BP57 -> 25577.855 | BT19: =BR57 -> 25577.855 | BV19: =BT57 -> 25577.855 | BX19: =BV57 -> 25577.855 | BZ19: =BX57 -> 25577.855 | CB19: =BZ57 -> 25577.855 | CD19: =CB57 -> 24428.288
B20: Kotak Liquid Investments | D20: =C58 | E20: =D58 | F20: =E58 | G20: =F58 | H20: =G58 | I20: =H58 | J20: =I58 | K20: =J58 | ... N20: =M58 | O20: =M58 | P20: =N58 | R20: =P58 -> 5365853.7 | T20: =R58 -> 5121951.2 | V20: =T58 -> 6219512.2 | X20: =V58 -> 5252467.9 | Z20: =X58 -> 4891060.4 | AB20: =Z58 -> 4653168.9 | AD20: =AB58 -> 4653168.9 | AF20: =AD58 -> 4476826.7 | AH20: =AF58 -> 2721617.4 | AJ20: =AH58 -> 2688826.8 | AL20: =AJ58 -> 11724971 | AN20: =AL58 -> 11724971 | AP20: =AN58 -> 11274010 | AQ20: =AO58 -> 0 | AR20: =AP58 -> 10934911 | AT20: =AR58 -> 10927400 | AV20: =AT58 -> 11325903 | AX20: =AV58 -> 10956344 | AZ20: =AX58 -> 10294414 | BB20: =AZ58 -> 9863671.8 | BD20: =BB58 -> 8818404.9 | BF20: =BD58 -> 8579586.4 | BH20: =BF58 -> 8054229.6 | BJ20: =BH58 -> 7732271.7 | BL20: =BJ58 -> 7187197.3 | BN20: =BL58 -> 6548758.1 | BO20: =BM58 -> 0 | BP20: =BN58 -> 5914580.8 | BR20: =BP58 -> 5491817.1 | BT20: =BR58 -> 4966623.2 | BV20: =BT58 -> 4345954.6 | BX20: =BV58 -> 3804155.1 | BZ20: =BX58 -> 3180235 | CB20: =BZ58 -> 2557860.7 | CD20: =CB58 -> 1677082.5
B21: Operating
B22: Cash Inflow (from customers) | C22: 20046.266 | D22: 11489.024 | E22: 29970.742 | F22: 51473.881 | G22: 28644.268 | H22: 74000.081 | I22: 89887.903 | J22: 75287.563 | K22: 119944.12 | L22: 106949.4 | M22: 117178.64 | N22: 203656.78 | P22: 204631.43 | R22: 209827.7 | T22: 265925.55 | V22: 215309.88 | X22: 259200.07 | Z22: 291715.06 | AB22: 265367.19 | AD22: 335523.59 | AF22: 314868.33 | AH22: 526024.49 | AJ22: 499478.67 | AL22: 548792.5 | AN22: 527626.19 | AP22: 578644.06 | AR22: 566805.98 | AT22: 839676.02 | AV22: 648097.41 | AX22: 560493.62 | AZ22: 729965.51 | BB22: 654485.37 | BD22: 818090.34 | BF22: 885023.45 | BH22: 739124.89 | BJ22: =1143232.7747619 -> 1143232.8 | BL22: =315091.393647059+566450.56-6198.74658823529 -> 875343.21 | BN22: =337971.833764706+611898.53 -> 949870.36 | BP22: =313054.165058824+813460.47 -> 1126514.6 | BR22: =459933.959176471+783917.71 -> 1243851.7 | BT22: =340043.55+748351.61 -> 1088395.2 | BV22: =350408.654823529+762919.65 -> 1113328.3 | BX22: 1185278.2 | BZ22: 1197704.1 | CB22: 1386831.4 | CD22: 1274394.1
B23: Cash Outflow | AV23: 0 | AX23: 0 | AZ23: 0
B24: Cost of Goods Sold (COGS) | C24: 1585.3659 | D24: 1969.9778 | E24: 14462.875 | F24: 17253.659 | G24: 25972.683 | H24: 13989.741 | I24: 83.667561 | J24: 8350.2439 | K24: 14408.78 | L24: 17312.799 | M24: 42000.38 | N24: 26872.571 | P24: 28119.512 | R24: 23268.297 | T24: 99304.882 | V24: 25933.13 | X24: 88175 | Z24: 33391.098 | AB24: 25192.428 | AD24: 36965.854 | AF24: 48962.195 | AH24: 34243.373 | AJ24: 67621.975 | AL24: 40445.416 | AN24: 24934.34 | AP24: 51324.16 | AR24: 37277.615 | AT24: 40933.642 | AV24: 58559.645 | AX24: 71001.867 | AZ24: 37346.53 | BB24: 26538.072 | BD24: 4846.988 | BF24: 69782.238 | BH24: 19362.737 | BJ24: 83283.101 | BL24: 86465.035 | BN24: 89289.324 | BP24: 59972.034 | BR24: =70658.7372941176+52000 -> 122658.74 | BT24: =65484.43+23400 -> 88884.43 | BV24: =126701.498941176+31000 -> 157701.5 | BX24: 73608.47 | BZ24: 102731.48 | CB24: 208150.01 | CD24: 182819.42
B25: Customer Success | C25: 4595.992 | D25: 7984.7049 | E25: 3324.7744 | F25: 32007.666 | G25: 10797.22 | H25: 25397.216 | I25: 24518.263 | J25: 18875.243 | K25: 11703.598 | L25: 24318.098 | M25: 15416.732 | N25: 17513.549 | P25: 22224.704 | R25: 35862.188 | T25: 24146.345 | V25: 39448.73 | X25: 22576 | Z25: 24292.11 | AB25: 55061.236 | AD25: 22396.865 | AF25: 31986.732 | AH25: 48341.705 | AJ25: 36229.486 | AL25: 36983.916 | AN25: 65104.649 | AP25: 46554.16 | AR25: 34313.687 | AT25: 70654.06 | AV25: 56172.265 | AX25: 40285.759 | AZ25: 74448.253 | BB25: 46867.048 | BD25: 46231.193 | BF25: 70045.602 | BH25: 46903.274 | BJ25: 52316.607 | BL25: 46736.263 | BN25: 59379.871 | BP25: 57466.379 | BR25: =105189.240235294+496 -> 105685.24 | BT25: =61202.22+122613.79 -> 183816.01 | BV25: =60455.3547058824+22396.66 -> 82852.015 | BX25: =106649.717647059+8479.66 -> 115129.38 | BZ25: 71938.68 | CB25: 68598.46 | CD25: 117160.22
B26: Sales and Marketing Costs | C26: 14233.232 | D26: 9738.4277 | E26: 23100.762 | F26: 43077.995 | G26: 54125.637 | H26: 42578.777 | I26: 75723.87 | J26: 58170.84 | K26: 147400.66 | L26: 106618.52 | M26: 152935.13 | N26: 239549.95 | P26: 276229.9 | R26: 389506.16 | T26: 227697.64 | V26: 364840.86 | X26: 312077.36 | Z26: 285081.83 | AB26: 401981.56 | AD26: 299553.41 | AF26: 376645.76 | AH26: 519431.92 | AJ26: 282247.27 | AL26: 331433.98 | AN26: 425827.35 | AP26: 552066.14 | AR26: 418613.17 | AT26: 659797.75 | AV26: 441855.35 | AX26: 547660.57 | AZ26: 693999.13 | BB26: 568295.08 | BD26: 533473.59 | BF26: 766868.93 | BH26: =539084.732857143+10019.6649956964 -> 549104.4 | BJ26: =746845.927857143+1547.33142857254 -> 748393.26 | BL26: =461255.76+442641.52 -> 903897.28 | BN26: =421637.346588235+323518.79-15000 -> 730156.14 | BP26: =422785.713764706+354450.15+15000 -> 792235.86 | BR26: =566512.765647059+170659.86 -> 737172.63 | BT26: =443352.57+183776.11 -> 627128.68 | BV26: =402142.889764706+307057.03 -> 709199.92 | BX26: 485682.07 | BZ26: 1225123.7 | CB26: 713341.54 | CD26: 726969.3
B27: Product and Engineering | C27: 3163.1098 | D27: 16649.593 | E27: 1768.6889 | F27: 32988.388 | G27: 13479.646 | H27: 24241.987 | I27: 24743.774 | J27: 28087.496 | K27: 30211.987 | L27: 33673.091 | M27: 53582.22 | N27: 51706.07 | P27: 59055.995 | R27: 85114.36 | T27: 54628.235 | V27: 67388.366 | X27: 71313.62 | Z27: 78906.712 | AB27: 104821.66 | AD27: 93309.447 | AF27: 79618.857 | AH27: 121114.93 | AJ27: 105072.74 | AL27: 112502.16 | AN27: 149226.03 | AP27: 177863.83 | AR27: 149203.78 | AT27: 195606.24 | AV27: 206412.04 | AX27: 196165.47 | AZ27: 247028.26 | BB27: 235658.87 | BD27: 220989.71 | BF27: 159242.36 | BH27: 217229.58 | BJ27: 225836.97 | BL27: =195436.179176471+89982.3 -> 285418.48 | BN27: =188516.984941176+90508.04 -> 279025.02 | BP27: =174214.630941176+67751.28 -> 241965.91 | BR27: =178615.997176471+127998.29 -> 306614.29 | BT27: =164894.48+73092.73 -> 237987.21 | BV27: =171455.107294118+115741.36 -> 287196.47 | BX27: =194424.796823529+145612.29 -> 340037.09 | BZ27: 258341.14 | CB27: 268671.05 | CD27: 357993.55
B28: General and Administrative | C28: 40636.646 | D28: 26300.65 | E28: 33252.577 | F28: 30769.515 | G28: 60111.998 | H28: 46937.076 | I28: 114281.21 | J28: 69725.43 | K28: 117222.07 | L28: 68819.868 | M28: 70435.625 | N28: 214893.94 | P28: 203642.32 | R28: 128534.72 | T28: 150468.22 | V28: 66013.71 | X28: 165042.76 | Z28: 179556.51 | AB28: 104072.27 | AD28: 139307.58 | AF28: 159113.45 | AH28: 125430.63 | AJ28: 138494.48 | AL28: 190186.64 | AN28: =294367.952891566+6848.64807228744 -> 301216.6 | AP28: 157366.56 | AR28: 152012.25 | AT28: 378359.64 | AV28: 150226.06 | AX28: 109251.64 | AZ28: 185599.39 | BB28: 167429.13 | BD28: 126070.14 | BF28: =196647.512650603+114046.700632176+72020.020820694 -> 382714.23 | BH28: 152912.15 | BJ28: =93183.224047619 -> 93183.224 | BL28: =128515.900117647+93901.49+6198.74658823529+35.43-BL40 -> 194584.64 | BN28: =172054.385294118+146653.65+16744.944813841-BN40 -> 255963.48 | BP28: =67830.7063529412+137594.05+4586.96048027836 -> 210011.72 | BR28: =76709.4208235294+142831.7 -> 219541.12 | BT28: =100451.46+67568.34 -> 168019.8 | BV28: =81216.574+38096.74 -> 119313.31 | BX28: =157240.76+714 -> 157954.76 | BZ28: 150462.95 | CB28: =243674.6+147833.633018014 -> 391508.23 | CD28: =144843.48+6553.8404494382 -> 151397.32
B29: Duties and Taxes | C29: 3261.3098 | D29: 10339.39 | E29: 9583.5339 | F29: 11905.749 | G29: 16461.53 | H29: 13408.336 | I29: 29360.506 | J29: 23555.906 | K29: 12854.873 | L29: 18875.237 | M29: 23474.885 | N29: 22382.643 | P29: 55467.919 | R29: 33609.598 | T29: 37160.726 | V29: 35264.86 | X29: 54929 | Z29: 44339.114 | AB29: 40472.03 | AD29: 58999.508 | AF29: 43767.241 | AH29: 54350.497 | AJ29: 69405.606 | AL29: 44268.383 | AN29: 86469.672 | AP29: 53974.081 | AR29: 67944.197 | AT29: 69246.667 | AV29: 115562.69 | AX29: 76098.981 | AZ29: 74717.711 | BB29: 105515.82 | BD29: 136030.13 | BF29: 106137.41 | BH29: 136359.67 | BJ29: 87081.952 | BL29: 139223.92 | BN29: 81844.906 | BP29: 87322.212 | BR29: =88232.3529411765+134264.63 -> 222496.98 | BT29: =104894.69+3264.01 -> 108158.7 | BV29: =87429.1176470588+3975.25 -> 91404.368 | BX29: 213787.25 | BZ29: 157978.59 | CB29: 87611.14 | CD29: 143676.23
B31: Non Operating
B32: Inter Entity Financing | C32: 0 | D32: 0 | E32: 0 | F32: 0 | G32: 0 | H32: 0 | I32: 0 | J32: 0 | K32: 0 | L32: 0 | M32: 0 | N32: 0 | P32: 499969.5 | R32: 0 | T32: 0 | V32: 50000 | X32: 499960 | AF32: 1218439 | AH32: 0 | AJ32: 0 | AL32: 0 | CD32: =588520.185882353*85/89-6553.8404494382 -> 555516
B33: Cash Inflow (fundraise, etc.) | C33: 0 | D33: 0 | E33: 0 | F33: 0 | G33: 0 | H33: 0 | I33: 0 | J33: 0 | K33: 0 | L33: 0 | M33: 0 | N33: 7358178.9 | P33: 0 | R33: 0 | T33: 0 | V33: 0 | X33: 100186 | Z33: 354.73695 | AB33: 302771.32 | AD33: 135396.48 | AJ33: 9006025.4 | AL33: 0 | AP33: 1000655 | AR33: 0 | AT33: 0 | AV33: 0 | AX33: 0 | AZ33: 0
B34: Other income (interest, Profit on Sale of MF)) | C34: 0 | D34: 0 | E34: 0 | F34: 0 | G34: 0 | H34: 0 | I34: 0 | J34: 0 | K34: 0 | L34: 0 | M34: 0 | N34: 0 | P34: 0 | R34: 29114.353 | T34: 0 | V34: 0 | X34: 0 | Z34: 11.585366 | AB34: 26069.861 | AC34: 0 | AD34: 6596.2446 | AE34: 0 | AF34: 117812.15 | AH34: 11.445783 | AJ34: 11.421687 | AL34: 9.939759 | AN34: 36668.853 | AO34: 0 | AP34: 19212.912 | AR34: 2990.8595 | AT34: =2211.14397590361+252828.281707171-163633.997590361 -> 91405.428 | AV34: =2434.22156626506+31479.3562650606 -> 33913.578 | AX34: =2386.58951807229+72787.220361447-8335.08060241118 -> 66838.729 | AZ34: =2468.43602409639+40687.6569879521 -> 43156.093 | BB34: 48548.107 | BD34: 128408.27 | BF34: =3186.1956626506+759.924042522907 -> 3946.1197 | BH34: =(11.7738095238095+2633572/84)+144.87+14020.132955078 -> 45528.824 | BJ34: =(10.25+4256940/84)+4788.78+6609.64000280946-6920.71082353219 -> 55165.816 | BL34: =71887.4918823529+1347.28 -> 73234.772 | BN34: =71716.3882352941+441.410000000001 -> 72157.798 | BP34: =48427.7058823529+1828.87 -> 50256.576 | BR34: =63052.7176470588+545.03 -> 63597.748 | BT34: =85225.46+1111.15-301.33 -> 86035.28 | BV34: =65439.4235294118+1028.93-1614318/85 -> 47476.377 | BX34: =81962.25+8294.38 -> 90256.63 | BZ34: 78434.54 | CB34: 146371.21 | CD34: 10318.67
B35: Cash Outflow
B36: Fixed Deposit | C36: 0 | D36: 0 | E36: 0 | F36: 0 | G36: 0 | H36: 0 | I36: 0 | J36: 0 | K36: 0 | L36: 24390.244 | M36: 0 | N36: 0 | P36: 0 | R36: 0 | T36: 0 | V36: 0 | X36: 0 | AJ36: 0 | AL36: 0
B37: Inter Entity Investment | C37: 0 | D37: 0 | E37: 0 | F37: 0 | G37: 0 | H37: 0 | I37: 0 | J37: 0 | K37: 0 | L37: 0 | M37: 0 | N37: 0 | P37: 499969.5 | R37: 0 | T37: 0 | V37: 50000 | X37: 499960 | AF37: 1218439 | AH37: 0 | AJ37: 0 | AL37: 0 | AR37: 0 | AT37: 0 | CD37: 555516
B38: Fixed Assets Purchased | C38: 8636.122 | D38: 7990.1951 | E38: 7007.7805 | F38: 2712.9512 | G38: 4726.9146 | H38: 18105.573 | I38: 8694.5122 | J38: 10695.354 | K38: 6203.3415 | L38: 10086.877 | M38: 9814.329 | N38: 12533.183 | P38: 9826.0488 | R38: 10146.671 | T38: 5032.4634 | V38: 9039.27 | X38: 16295.2 | Z38: 18006.909 | AB38: 15538.981 | AD38: 11512.709 | AF38: 4070.1461 | AH38: 5452.4402 | AJ38: 18856.555 | AL38: 17280.733 | AN38: 26150 | AP38: 7332.2528 | AR38: 17736.189 | AT38: =10143.6022891566 -> 10143.602 | AV38: 12631.325 | AX38: 13765.065 | AZ38: 2081.6928 | BB38: 1104.0241 | BD38: 2817.0404 | BF38: 11458.414 | BH38: 5703.6125 | BJ38: 19618.807 | BL38: 2343.7646 | BN38: 13864.871 | BP38: 0 | BR38: 6583.3022 | BT38: 0 | BX38: 7954.49
B39: Share Allotment Expenses | AH39: 2804.4819 | AJ39: 8016.6386 | AL39: =1242.65060240964+13537.343373494 -> 14779.994
B40: Fundrasing Cost | C40: 0 | D40: 0 | E40: 0 | F40: 0 | G40: 0 | H40: 0 | I40: 0 | J40: 0 | K40: 0 | L40: 0 | M40: 0 | N40: 0 | P40: 0 | R40: 0 | T40: 0 | V40: 0 | X40: 0 | Z40: 0 | AB40: 0 | AD40: 0 | AF40: 0 | AH40: 0 | AJ40: 0 | AL40: 0 | AN40: 0 | AP40: 0 | AR40: 0 | AT40: 0 | AV40: 0 | AX40: 0 | AZ40: 0 | BB40: 0 | BD40: 0 | BF40: 0 | BH40: 0 | BJ40: 0 | BL40: 34066.923 | BN40: 79489.499 | BP40: 0 | BR40: 0 | BT40: 0 | BX40: 40075.99
B42: Closing Balance | C42: =C4-C59 -> 2628068.7 | D42: =D4-D59 -> 2558584.8 | E42: =E4-E59 -> 2496054.5 | F42: =F4-F59 -> 2376812.5 | G42: =G4-G59 -> 2219781.1 | H42: =H4-H59 -> 2109122.5 | I42: =I4-I59 -> 1921604.6 | J42: =J4-J59 -> 1779431.7 | ... N42: =N4-N59 -> 8088128.4 | P42: =P4-P59 -> 7638193.4 | Q42: =Q4-Q59 -> 0 | R42: =R4-R59 -> 7171093.3 | S42: =S4-S59 -> 0 | T42: =T4-T59 -> 6838580.4 | U42: =U4-U59 -> 0 | V42: =V4-V59 -> 6445961.3 | W42: =W4-W59 -> 0 | ... BP42: =BP4-BP59 -> 7830689.4 | BR42: =BR4-BR59 -> 7417386.6 | BT42: =BT4-BT59 -> 7177822.2 | BV42: =BV4-BV59 -> 6890959.2 | BX42: =BX4-BX59 -> 6732264 | BZ42: =BZ4-BZ59 -> 6041826.1 | CB42: =CB4-CB59 -> 5837148 | CD42: =CD4-CD59 -> 5441844.7 | CE42: =CD42-CD55 -> 2862479.7
B43: Kotak Bank 9651 | C43: 24830.704 | D43: 41639.938 | E43: 66748.527 | F43: 87829.047 | G43: 24208.857 | H43: 80842.37 | I43: 42160.85 | J43: 35515.643 | K43: 46333.18 | L43: 37769.075 | M43: 95075.939 | N43: 186263.49 | P43: 564039.15 | R43: 946015.09 | T43: 144229.13 | V43: 99679.41 | X43: 218742.1 | Z43: 228223.75 | AB43: 125676.49 | AD43: 128518.02 | AF43: 498258.95 | AH43: 360658.09 | AJ43: 220630.14 | AL43: 111863.97 | AN43: 52566.353 | AP43: 182823.19 | AR43: 129360.42 | AT43: =19478213.21/83 -> 234677.27 | AV43: 140877.41 | AX43: 376891.89 | AZ43: 252447.7 | BB43: 69344.745 | BD43: 355217.39 | BF43: =41015891.13/85 -> 482539.9 | BH43: =28149949.98/85 -> 331175.88 | BJ43: =25083254.1/85 -> 295097.11 | BL43: =63915958.24/85 -> 751952.45 | BN43: =48695527.06/85 -> 572888.55 | BP43: =55093969.98/85 -> 648164.35 | BR43: =51596722.8/85 -> 607020.27 | BT43: =61419413/85 -> 722581.33 | BV43: =12724925/85 -> 149705 | BX43: =66429439.04/85 -> 781522.81 | BZ43: =47940341.27/85 -> 564004.01 | CB43: =69212368.21/89+555516 -> 1333183.1 | CD43: =56753011.73/89 -> 637674.29
B44: Kotak Bank 5102 | C44: 2603238 | D44: 2516944.9 | E44: 2429306 | F44: 2274428 | G44: 2191501.1 | H44: 2014671.9 | I44: 1868330.4 | J44: 1721988.9 | K44: 1502476.7 | L44: 1287842.6 | M44: 976866.99 | N44: 7834914.2 | P44: 1335311.3 | R44: 591864.73 | T44: 36986.685 | V44: 724405.49 | X44: 173903.61 | Z44: 137672.98 | AB44: 213536.69 | AD44: 239177.07 | AF44: 203693.8 | AH44: 128950.5 | AJ44: 82666.064 | AL44: 82666.064 | AN44: 203147.99 | AP44: 1083321.1 | AR44: 1100558 | AT44: =11346310.02/83 -> 136702.53 | AV44: 178129.18 | AX44: 141771.34 | AZ44: 139874.26 | BB44: 730235.71 | BD44: 368789.93 | BF44: =20609563.8/85 -> 242465.46 | BH44: =30574163.8/85 -> 359696.04 | BJ44: =50556463.8/85 -> 594781.93 | BL44: =556463.8/85 -> 6546.6329 | BN44: =10556463.8/85 -> 124193.69 | BP44: =556463.8/85 -> 6546.6329 | BR44: =555873.8/85 -> 6539.6918 | BT44: =555873.8/85 -> 6539.6918 | BV44: =50555873.8/85 -> 594774.99 | BX44: =20555873.8/85 -> 241833.81 | BZ44: =555283.8/85 -> 6532.7506 | CB44: =554693.8/89 -> 6232.5146 | CD44: =554693.8/89 -> 6232.5146
B45: HSBC-14-001 | BB45: 1204.8193 | BD45: 1204.8193 | BF45: =BD45*83/85 -> 1176.4706 | BH45: =BF45 -> 1176.4706 | BJ45: =BH45 -> 1176.4706 | BL45: =BJ45*84/85 -> 1162.6298 | BN45: =BL45 -> 1162.6298 | BP45: =BN45 -> 1162.6298 | BR45: =BP45 -> 1162.6298 | BT45: =BR45 -> 1162.6298 | BV45: =BT45 -> 1162.6298 | BX45: =BV45 -> 1162.6298 | BZ45: =BX45 -> 1162.6298 | CB45: =BZ45*85/89 -> 1110.3767 | CD45: =CB45 -> 1110.3767
B46: My Biz Wallet | L46: 6598.48 | M46: 1604.11 | N46: 9581.4146 | P46: 5286.4026 | R46: 19.744024 | T46: 8372.427 | V46: 1085.3782 | X46: 10764.622 | Z46: 6147.1099 | AB46: 12604.171 | AD46: 2401.1099 | AF46: 8500.5367 | AH46: 13024.47 | AJ46: 2180.8555 | AL46: -2204.6023 | AN46: 23594.398 | AP46: 9600.4339 | AR46: 22859.434 | AT46: =970458/83 -> 11692.265 | AV46: 3310.8796 | AX46: 13993.482 | AZ46: 2365.1929 | BB46: 13396.615 | BD46: 10624.313 | BF46: =1427312.01/85 -> 16791.906 | BH46: =1479814.81/85 -> 17409.586 | BJ46: =2391551.01/85 -> 28135.894 | BL46: =1457035.01/85 -> 17141.588 | BN46: =265636.05/85 -> 3125.13 | BP46: =1837186.19/85 -> 21613.955 | BR46: =1264102.39/85 -> 14871.793 | BT46: =1046976.26/85 -> 12317.368 | BV46: =1879603.54/85 -> 22112.983 | BX46: =490864.15/85 -> 5774.8724 | BZ46: =2230806.69/85 -> 26244.785 | CB46: =292261.6/89 -> 3283.8382 | CD46: =922506.72/89 -> 10365.244
B47: Karbon Card | G47: 3589.4391 | H47: 11548.399 | I47: 9774.7004 | J47: 9356.5178 | K47: 8335.8166 | L47: 27459.651 | M47: 15752.582 | N47: 29342.626 | P47: 29342.63 | R47: 29342.626 | T47: 0 | V47: 0 | X47: 0 | Z47: 0 | AB47: 0 | AH47: 0 | AJ47: 0 | AL47: 0 | AN47: 36010.8 | AP47: 35180.321 | AR47: 34269.174 | AT47: =2760355.62/83 -> 33257.297 | AV47: 32926.32 | AX47: 32420.1 | AZ47: 32279.298 | BB47: 32219.057 | BD47: 31795.714 | BF47: =2590680/85 -> 30478.588 | BH47: =2508877.22/85 -> 29516.203 | BJ47: =2461125.94/85 -> 28954.423 | BL47: =2415160.99/85 -> 28413.659 | BN47: =2305481.17/85 -> 27123.308 | BP47: =2290280.17/85 -> 26944.473 | BR47: =2118138.77/85 -> 24919.28 | BT47: =2077801.15/85 -> 24444.719 | BV47: =2035551.14/85 -> 23947.66 | BX47: =1976013.07/85 -> 23247.213 | BZ47: =1863116.88/85 -> 21919.022 | CB47: =1811205.15/89 -> 20350.62 | CD47: =1771756.78/89 -> 19907.38
B48: Razorpay | F48: 14555.488 | G48: 481.70732 | H48: 2059.8782 | I48: 1338.6617 | J48: 12570.564 | K48: 2224.8967 | L48: 2555.5038 | M48: 22445.025 | N48: 23526.71 | P48: 13639.524 | R48: 33169.753 | T48: 19357.527 | V48: 57740.286 | X48: 79423.246 | Z48: 70264.175 | AB48: 16743.55 | AD48: 38704.07 | AF48: 30981.049 | AH48: 39487.737 | AJ48: 14169.467 | AL48: 19706.677 | AN48: 47696.206 | AP48: 14295.965 | AR48: 1928.9225 | AT48: =1042426.98/83 -> 12559.361 | AV48: 11688.875 | AX48: 3011.6672 | AZ48: 10283.472 | BB48: 120207.69 | BD48: 106435.11 | BF48: =12989768.45/85 -> 152820.81 | BH48: =1310839.57/85 -> 15421.642 | BJ48: =1115226.76/85 -> 13120.315 | BL48: =966932.16/85 -> 11375.672 | BN48: =6809043.89/85 -> 80106.399 | BP48: =1950210.01/85 -> 22943.647 | BR48: =2402266.59/85 -> 28261.96 | BT48: =1865525.09/85+714 -> 22661.354 | BV48: =411948.52/85+714 -> 5560.4532 | BX48: =(3756631.78/85)-9998.02776470594-714 -> 33483.64 | BZ48: =1185460.84/85 -> 13946.598 | CB48: =4167472.1/89 -> 46825.529 | CD48: =2533521.85/89 -> 28466.538
B49: Kotak Credit Card | AT49: -19.60241 | AV49: -45.204819 | AX49: =-7192.72/83 -> -86.659277 | AZ49: =-13564.3/83 -> -163.4253 | BB49: =-51451.32/83 -> -619.89542 | BD49: =-102510.25/83 -> -1235.0633 | BF49: =-53795.76/85 -> -632.89129 | BH49: =-100523.72/85 -> -1182.632 | BJ49: =-64583.22/85 -> -759.80259 | BL49: =-51787.04/85 -> -609.25929 | BN49: =-29028.43/85 -> -341.51094 | BP49: =-36117.02/85 -> -424.90612 | BR49: =-38060.05/85 -> -447.76529 | BT49: =-166355.73/85 -> -1957.1262 | BV49: =-21988.87/85 -> -258.69259 | BX49: =-21634.68/85 -> -254.52565 | BZ49: =-57751.28/85 -> -679.42682 | CB49: =-104905.89/89 -> -1178.7179 | CD49: =-10058.44/89 -> -113.01618
B50: Razorpay Collection Wallet | AT50: =735671.79/83 -> 8863.5155 | AV50: =554853.35/83 -> 6684.9801 | AX50: =852690.6/83 -> 10273.381 | AZ50: =132277.47/83 -> 1593.7045 | BB50: =743500.53/83 -> 8957.8377 | BD50: =350855.61/83 -> 4227.176 | BF50: =233376.85/85 -> 2745.61 | BH50: =453083.12/85 -> 5330.3896 | BJ50: =261295.02/85 -> 3074.0591 | BL50: =788188.48/85 -> 9272.8056 | BN50: =331015.76/85 -> 3894.3031 | BP50: =395992.81/85 -> 4658.7389 | BR50: =395992.81/85 -> 4658.7389 | BT50: =BR50 -> 4658.7389 | BV50: =BT50 -> 4658.7389 | BX50: =BV50 -> 4658.7389 | BZ50: =BX50 -> 4658.7389 | CB50: =BZ50*85/89 -> 4449.3574 | CD50: =CB50 -> 4449.3574
B51: Vendor Advance | BN51: 15000 | BP51: 15000 | BR51: 15000 | BT51: =BR51 -> 15000 | BV51: =BT51 -> 15000 | BX51: =BV51 -> 15000 | BZ51: =BX51 -> 15000 | CB51: =BZ51 -> 15000 | CD51: =CB51 -> 15000
B52: Mercury Bank Scrut Inc. | N52: 4500 | P52: 324720.56 | R52: 192632.59 | T52: 154024.85 | V52: 67542.75 | X52: 438298.24 | Z52: 274022.02 | AB52: 198156.7 | AD52: 118193.17 | AF52: 1248535.9 | AH52: 1112835.5 | AJ52: 124103.32 | AL52: 143053.12 | AN52: 152146.34 | AP52: 147450.64 | AR52: 147421.35 | AT52: 173936.68 | AV52: 202109.73 | AX52: 235881.81 | AZ52: 281189.23 | BB52: 353974.34 | BD52: 570466.3 | BF52: 168961.17 | BH52: 295288.92 | BJ52: 230621.36 | BL52: 191138.46 | BN52: 198535.95 | BP52: 332924.51 | BR52: 95289 | BT52: 99747 | BV52: 153430 | BX52: 325282 | BZ52: 365125.11 | CB52: =282828.08 -> 282828.08 | CD52: 363108
B53: State Bank of India | R53: 12195.122 | T53: 12195.122 | V53: 12195.122 | X53: 12195.122 | Z53: 12195.122 | AB53: 12195.122 | AD53: 12195.122 | AF53: 12195.122 | AH53: 12048.193 | AJ53: 12048.193 | AL53: 12048.193 | AN53: 12048.193 | AP53: 12048.193 | AR53: 12048.193 | AT53: =980547.78/83 -> 11813.829 | AV53: =975827.78/83 -> 11756.961 | AX53: =971107.78/83 -> 11700.094 | AY53: =AW53 | AZ53: =966387.78/83 -> 11643.226 | BA53: =AY53 | BB53: =961667.78/83 -> 11586.359 | BC53: =BA53 | BD53: =956947.78/83 -> 11529.491 | BE53: =BC53 | BF53: =952227.78/85 -> 11202.68 | BH53: =956947.78/85 -> 11258.209 | BJ53: =956947.78/85 -> 11258.209 | BL53: =942138.78/85 -> 11083.986 | BN53: =945689.570823529/85 -> 11125.76 | BP53: =942138.78/85 -> 11083.986 | BR53: =942138.78/85 -> 11083.986 | BT53: =BR53 -> 11083.986 | BV53: =BT53 -> 11083.986 | BX53: =BV53 -> 11083.986 | BZ53: =BX53 -> 11083.986 | CB53: =BZ53*85/89 -> 10585.829 | CD53: =CB53 -> 10585.829
B54: RHO | Z54: 37282.5 | AB54: 21136.98 | AD54: 52674.28 | AF54: 33422.96 | AH54: 19178.95 | AJ54: 23811.53 | AL54: 48397.37 | AN54: 18945.78 | AP54: 49933.42 | AR54: 34724.02 | AT54: 22018.34 | AV54: 66384.09 | AX54: 61396.67 | AZ54: 42878.14 | BB54: 29308.38 | BD54: 25431.31 | BF54: =BD54*83/85 -> 24832.926 | BH54: 45706.15 | BJ54: 27650.51 | BL54: 9360.4 | BN54: 63948.94 | BP54: 54067.93 | BR54: 47916 | BT54: 19206 | BV54: 20028 | BX54: 17475 | BZ54: 56737.66 | CB54: 36018.66 | CD54: 24860
B55: Treasury | AJ55: 950000 | AL55: 775000 | AN55: 580702.88 | AP55: 483334.9 | AR55: 485729.5 | AT55: 387706.81 | AV55: 389535.26 | AX55: 391137.91 | AZ55: 392643.72 | BB55: 394111.19 | BD55: 395491.53 | BF55: 596695.76 | BH55: 598317.79 | BJ55: 910180.48 | BL55: =1001715.72 -> 1001715.7 | BN55: 1004983.9 | BP55: 1111621.9 | BR55: =1511622+301.33 -> 1511923.3 | BT55: 1811622 | BV55: 2002798 | BX55: 2008959 | BZ55: 2315429.5 | CB55: 2322062.7 | CD55: 2579365
B56: Rent Security Deposit | C56: 0 | D56: 0 | E56: 0 | F56: 0 | G56: 0 | H56: 0 | I56: 0 | J56: 0 | K56: 0 | L56: 0 | M56: 0 | N56: 0 | P56: 0 | R56: 0 | T56: 0 | V56: 0 | X56: 26696.341 | Z56: 26696.341 | AB56: 53392.683 | AD56: 53392.683 | AF56: 53392.683 | AH56: 53392.683 | AJ56: 53392.683 | AL56: 53392.683 | AN56: 53392.683 | AP56: 53392.683 | AR56: 53392.683 | AT56: =5035995.24/83 -> 60674.641 | AV56: =AT56 -> 60674.641 | AX56: =AV56 -> 60674.641 | AZ56: =AX56 -> 60674.641 | BB56: =AZ56 -> 60674.641 | BD56: =4936994.16/83 -> 59481.857 | BF56: =BD56*83/85 -> 58082.284 | BH56: =BF56 -> 58082.284 | BJ56: =4901526.16/85 -> 57665.014 | BL56: =BJ56*84/85 -> 56986.602 | BN56: =BL56 -> 56986.602 | BP56: =BN56 -> 56986.602 | BR56: =BP56 -> 56986.602 | BT56: =BR56+235.29 -> 57221.892 | BV56: =BT56 -> 57221.892 | BX56: =BV56 -> 57221.892 | BZ56: =BX56 -> 57221.892 | CB56: =BZ56*85/89+235.29 -> 54885.411 | CD56: =CB56 -> 54885.411
B57: Fixed Deposit | R57: 243902.44 | T57: 243902.44 | V57: 243902.44 | X57: 243902.44 | Z57: 243902.44 | AB57: 243902.44 | AD57: 243902.44 | AF57: 243902.44 | AH57: 240963.86 | AJ57: 240963.86 | AL57: 240963.86 | AN57: 240963.86 | AP57: =AN57 -> 240963.86 | AR57: 240963.86 | AT57: =2200000/83 -> 26506.024 | AV57: =AT57 -> 26506.024 | AX57: =AV57 -> 26506.024 | AZ57: =AX57 -> 26506.024 | BB57: =AZ57 -> 26506.024 | BD57: =BB57 -> 26506.024 | BF57: =BD57*83/85 -> 25882.353 | BH57: =BF57 -> 25882.353 | BJ57: =BH57 -> 25882.353 | BL57: =BJ57*84/85 -> 25577.855 | BN57: =BL57 -> 25577.855 | BP57: =BN57 -> 25577.855 | BR57: =BP57 -> 25577.855 | BT57: =BR57 -> 25577.855 | BV57: =BT57 -> 25577.855 | BX57: =BV57 -> 25577.855 | BZ57: =BX57 -> 25577.855 | CB57: =BZ57*85/89 -> 24428.288 | CD57: =CB57 -> 24428.288
B58: Kotak Liquid Investments | P58: 5365853.7 | R58: 5121951.2 | T58: 6219512.2 | V58: 5252467.9 | X58: 4891060.4 | Z58: 4653168.9 | AB58: 4653168.9 | AC58: 0 | AD58: 4476826.7 | AE58: 0 | AF58: 2721617.4 | AH58: 2688826.8 | AJ58: 11724971 | AK58: 0 | AL58: 11724971 | AM58: 0 | AN58: 11274010 | AO58: 0 | AP58: 10934911 | AQ58: 0 | AR58: 10927400 | AS58: 0 | AT58: 11325903 | AU58: 0 | AV58: 10956344 | AW58: 0 | AX58: 10294414 | AY58: 0 | AZ58: 9863671.8 | BA58: 0 | BB58: 8818404.9 | BC58: 0 | BD58: 8579586.4 | BE58: 0 | BF58: 8054229.6 | BG58: 0 | BH58: 7732271.7 | BI58: 0 | BJ58: 7187197.3 | BK58: 0 | BL58: 6548758.1 | BM58: 0 | BN58: 5914580.8 | BO58: 0 | BP58: 5491817.1 | BQ58: 0 | BR58: 4966623.2 | BT58: 4345954.6 | BV58: =3823147.12258824-(1614318/85) -> 3804155.1 | BX58: =304791952.75/85-(34471974.3299996/85) -> 3180235 | BZ58: =251890104.75/85-405787.339176465+235 -> 2557860.7 | CB58: =1756004.00235295*85/89 -> 1677082.5 | CD58: 1661519.5
B59: Gross Burn | C59: =SUM(C24,C25,C26,C28,C27,C29,C37,C39,C38,C36,C40)-SUM(C22,C33,C34,C32) -> 56065.511 | D59: =SUM(D24,D25,D26,D28,D27,D29,D37,D39,D38,D36,D40)-SUM(D22,D33,D34,D32) -> 69483.914 | E59: =SUM(E24,E25,E26,E28,E27,E29,E37,E39,E38,E36,E40)-SUM(E22,E33,E34,E32) -> 62530.25 | F59: =SUM(F24,F25,F26,F28,F27,F29,F37,F39,F38,F36,F40)-SUM(F22,F33,F34,F32) -> 119242.04 | G59: =SUM(G24,G25,G26,G28,G27,G29,G37,G39,G38,G36,G40)-SUM(G22,G33,G34,G32) -> 157031.36 | H59: =SUM(H24,H25,H26,H28,H27,H29,H37,H39,H38,H36,H40)-SUM(H22,H33,H34,H32) -> 110658.62 | I59: =SUM(I24,I25,I26,I28,I27,I29,I37,I39,I38,I36,I40)-SUM(I22,I33,I34,I32) -> 187517.9 | J59: =SUM(J24,J25,J26,J28,J27,J29,J37,J39,J38,J36,J40)-SUM(J22,J33,J34,J32) -> 142172.95 | ... AN59: =SUM(AN24,AN25,AN26,AN28,AN27,AN29,AN37,AN39,AN38,AN36,AN40)-SUM(AN22,AN33,AN34,AN32) -> 514633.6 | AP59: =SUM(AP24,AP25,AP26,AP28,AP27,AP29,AP37,AP39,AP38,AP36,AP40)-SUM(AP22,AP33,AP34,AP32) -> -552030.82 | AR59: =SUM(AR24,AR25,AR26,AR28,AR27,AR29,AR37,AR39,AR38,AR36,AR40)-SUM(AR22,AR33,AR34,AR32) -> 307304.05 | AT59: =SUM(AT24,AT25,AT26,AT28,AT27,AT29,AT37,AT39,AT38,AT36,AT40)-SUM(AT22,AT33,AT34,AT32) -> 493660.15 | AV59: =SUM(AV24,AV25,AV26,AV28,AV27,AV29,AV37,AV39,AV38,AV36,AV40)-SUM(AV22,AV33,AV34,AV32) -> 359408.39 | AX59: =SUM(AX24,AX25,AX26,AX28,AX27,AX29,AX37,AX39,AX38,AX36,AX40)-SUM(AX22,AX33,AX34,AX32) -> 426897.01 | AZ59: =SUM(AZ24,AZ25,AZ26,AZ28,AZ27,AZ29,AZ37,AZ39,AZ38,AZ36,AZ40)-SUM(AZ22,AZ33,AZ34,AZ32) -> 542099.36 | BB59: =SUM(BB24,BB25,BB26,BB28,BB27,BB29,BB37,BB39,BB38,BB36,BB40)-SUM(BB22,BB33,BB34,BB32) -> 448374.57 | BD59: =SUM(BD24,BD25,BD26,BD28,BD27,BD29,BD37,BD39,BD38,BD36,BD40)-SUM(BD22,BD33,BD34,BD32) -> 123960.16 | BF59: =SUM(BF24,BF25,BF26,BF28,BF27,BF29,BF37,BF39,BF38,BF36,BF40)-SUM(BF22,BF33,BF34,BF32) -> 677279.64 | BH59: =SUM(BH24,BH25,BH26,BH28,BH27,BH29,BH37,BH39,BH38,BH36,BH40)-SUM(BH22,BH33,BH34,BH32) -> 342921.7 | BJ59: =SUM(BJ24,BJ25,BJ26,BJ28,BJ27,BJ29,BJ37,BJ39,BJ38,BJ36,BJ40)-SUM(BJ22,BJ33,BJ34,BJ32) -> 111315.33 | BL59: =SUM(BL24,BL25,BL26,BL28,BL27,BL29,BL37,BL39,BL40,BL38,BL36)-SUM(BL22,BL33,BL34,BL32) -> 744158.33 | BN59: =SUM(BN24,BN25,BN26,BN28,BN27,BN29,BN37,BN39,BN40,BN38,BN36)-SUM(BN22,BN33,BN34,BN32) -> 566984.95 | BP59: =SUM(BP24,BP25,BP26,BP28,BP27,BP29,BP37,BP39,BP38,BP36)-SUM(BP22,BP33,BP34,BP32) -> 272202.91 | BR59: =SUM(BR24,BR25,BR26,BR28,BR27,BR29,BR37,BR39,BR38,BR36)-SUM(BR22,BR33,BR34,BR32) -> 413302.88 | BT59: =SUM(BT24,BT25,BT26,BT28,BT27,BT29,BT37,BT39,BT38,BT36)-SUM(BT22,BT33,BT34,BT32) -> 239564.39 | BV59: =SUM(BV24,BV25,BV26,BV28,BV27,BV29,BV37,BV39,BV38,BV36)-SUM(BV22,BV33,BV34,BV32) -> 286862.9 | BX59: =SUM(BX24,BX25,BX26,BX28,BX27,BX29,BX37,BX39,BX40,BX38,BX36)-SUM(BX22,BX33,BX34,BX32) -> 158694.67 | BZ59: =SUM(BZ24,BZ25,BZ26,BZ28,BZ27,BZ29,BZ37,BZ39,BZ38,BZ36)-SUM(BZ22,BZ33,BZ34,BZ32) -> 690437.86 | CB59: =SUM(CB24,CB25,CB26,CB28,CB27,CB29,CB37,CB39,CB38,CB36)-SUM(CB22,CB33,CB34,CB32) -> 204677.8 | CD59: =SUM(CD24,CD25,CD26,CD28,CD27,CD29,CD37,CD39,CD38,CD36)-SUM(CD22,CD33,CD34,CD32) -> 395303.28
B61: Net Cash/Burn | C61: =C59+C33 -> 56065.511 | D61: =D59+D33 -> 69483.914 | E61: =E59+E33 -> 62530.25 | F61: =F59+F33 -> 119242.04 | G61: =G59+G33 -> 157031.36 | H61: =H59+H33 -> 110658.62 | I61: =I59+I33 -> 187517.9 | J61: =J59+J33 -> 142172.95 | ... BK61: =BK59+BK33 -> 0 | BL61: =BL59+BL33-BL40 -> 710091.4 | BM61: =BM59+BM33 -> 0 | BN61: =BN59+BN33-BN40 -> 487495.45 | BP61: =BP59+BP33-BP40 -> 272202.91 | BR61: =BR59+BR33-BR40 -> 413302.88 | BT61: =BT59+BT33-BT40 -> 239564.39 | BV61: =BV59+BV33-BV40 -> 286862.9 | BX61: =BX59+BX33-BX40 -> 118618.68 | BZ61: =BZ59+BZ33-BZ40 -> 690437.86 | CB61: =CB59+CB33-CB40+CB32 -> 204677.8 | CD61: =CD59+CD33-CD40 -> 395303.28
C63: =SUM(C43:C58)-C42 -> -4.6566129e-10 | D63: =SUM(D43:D58)-D42 -> 5.1222742e-09 | E63: =SUM(E43:E58)-E42 -> 4.6566129e-10 | F63: =SUM(F43:F58)-F42 -> -2.7939677e-09 | G63: =SUM(G43:G58)-G42 -> 2.7939677e-09 | H63: =SUM(H43:H58)-H42 -> 2.7939677e-09 | I63: =SUM(I43:I58)-I42 -> -5.5879354e-09 | J63: =SUM(J43:J58)-J42 -> 4.1909516e-09 | ... BP63: =SUM(BP43:BP58)-BP42 -> 0 | BR63: =SUM(BR43:BR58)-BR42 -> -0.0025882348 | BS63: =SUM(BS43:BS58)-BS42 -> 0 | BT63: =SUM(BT43:BT58)-BT42 -> -0.082117647 | BU63: =SUM(BU43:BU58)-BU42 -> 0 | BV63: =SUM(BV43:BV58)-BV42 -> -0.54 | BX63: =SUM(BX43:BX58)-BX42 -> 0 | BZ63: =SUM(BZ43:BZ58)-BZ42 -> -0.29 | CB63: =SUM(CB43:CB58)-CB42 -> -9.3132257e-10 | CD63: =SUM(CD43:CD58)-CD42 -> 1.8626451e-09
A389: 44742
A391: 44803
