Workbook

Sheet Working
B2: Weekday | C2: Average FTU | D2: Day factor | J2: Key Metrics | K2: 45748 | L2: 45778 | M2: 45809 | N2: 45839 | O2: 45870 | P2: 45901 | Q2: 45931 | R2: 45962 | S2: =EOMONTH(R2,1) -> 46022
B3: Monday | C3: 2606.6667 | D3: =C3/C$3 -> 1 | J3: Demand
B4: Tuesday | C4: 2470 | D4: =C4/C$3 -> 0.94757033
B5: Wednesday | C5: 2567 | D5: =C5/C$3 -> 0.98478261 | J5: MTU repeat rate | K5: ='Key Metrics'!F13/'Key Metrics'!#REF! -> #REF! | L5: ='Key Metrics'!G13/'Key Metrics'!F11 -> 0.67018616 | M5: ='Key Metrics'!H13/'Key Metrics'!G11 -> 0.60309138 | N5: ='Key Metrics'!I13/'Key Metrics'!H11 -> 0.60378781 | O5: ='Key Metrics'!J13/'Key Metrics'!I11 -> 0.61962328 | P5: ='Key Metrics'!K13/'Key Metrics'!J11 -> 0.56835913 | Q5: ='Key Metrics'!L13/'Key Metrics'!K11 -> 0.60449724 | R5: 0.57 | S5: 0.6
B6: Thursday | C6: 2624 | D6: =C6/C$3 -> 1.0066496
B7: Friday | C7: 2722.6667 | D7: =C7/C$3 -> 1.0445013
B8: Saturday | C8: 3350.3333 | D8: =C8/C$3 -> 1.2852941
B9: Sunday | C9: 3772.3333 | D9: =C9/C$3 -> 1.4471867
B11: Nov'25 | F11: Dec'25 | H11: 0.2
B12: Date | C12: Weekday | D12: FTU | F12: Date | G12: Weekday | H12: FTU
B13: 45962 | C13: Saturday | D13: 2978 | F13: 45992 | G13: =TEXT(F13, "dddd") -> Monday | H13: =D15*(1+H11) -> 2688
B14: =B13+1 -> 45963 | C14: Sunday | D14: 3547 | F14: =F13+1 -> 45993 | G14: =TEXT(F14, "dddd") -> Tuesday | H14: =H13*$D4 -> 2547.0691
B15: =B14+1 -> 45964 | C15: Monday | D15: 2240 | F15: =F14+1 -> 45994 | G15: =TEXT(F15, "dddd") -> Wednesday | H15: =H14*$D5 -> 2508.3093
B16: =B15+1 -> 45965 | C16: Tuesday | D16: 2072 | F16: =F15+1 -> 45995 | G16: =TEXT(F16, "dddd") -> Thursday | H16: =H15*$D6 -> 2524.9886
B17: =B16+1 -> 45966 | C17: =TEXT(B17, "dddd") -> Wednesday | D17: =ROUND($D$15*D5,0) -> 2206 | F17: =F16+1 -> 45996 | G17: =TEXT(F17, "dddd") -> Friday | H17: =H16*$D7 -> 2637.3538
B18: =B17+1 -> 45967 | C18: =TEXT(B18, "dddd") -> Thursday | D18: =ROUND($D$15*D6,0) -> 2255 | F18: =F17+1 -> 45997 | G18: =TEXT(F18, "dddd") -> Saturday | H18: =H17*$D8 -> 3389.7754
B19: =B18+1 -> 45968 | C19: =TEXT(B19, "dddd") -> Friday | D19: =ROUND($D$15*D7,0) -> 2340 | F19: =F18+1 -> 45998 | G19: =TEXT(F19, "dddd") -> Sunday | H19: =H18*$D9 -> 4905.6378
B20: =B19+1 -> 45969 | C20: =TEXT(B20, "dddd") -> Saturday | D20: =ROUND($D$15*D8,0) -> 2879 | F20: =F19+1 -> 45999 | G20: =TEXT(F20, "dddd") -> Monday | H20: =H13 -> 2688
B21: =B20+1 -> 45970 | C21: =TEXT(B21, "dddd") -> Sunday | D21: =ROUND($D$15*D9,0) -> 3242 | F21: =F20+1 -> 46000 | G21: =TEXT(F21, "dddd") -> Tuesday | H21: =H14 -> 2547.0691
B22: =B21+1 -> 45971 | C22: =TEXT(B22, "dddd") -> Monday | D22: =D15 -> 2240 | F22: =F21+1 -> 46001 | G22: =TEXT(F22, "dddd") -> Wednesday | H22: =H15 -> 2508.3093
B23: =B22+1 -> 45972 | C23: =TEXT(B23, "dddd") -> Tuesday | D23: =D16 -> 2072 | F23: =F22+1 -> 46002 | G23: =TEXT(F23, "dddd") -> Thursday | H23: =H16 -> 2524.9886
B24: =B23+1 -> 45973 | C24: =TEXT(B24, "dddd") -> Wednesday | D24: =D17 -> 2206 | F24: =F23+1 -> 46003 | G24: =TEXT(F24, "dddd") -> Friday | H24: =H17 -> 2637.3538
B25: =B24+1 -> 45974 | C25: =TEXT(B25, "dddd") -> Thursday | D25: =D18 -> 2255 | F25: =F24+1 -> 46004 | G25: =TEXT(F25, "dddd") -> Saturday | H25: =H18 -> 3389.7754
B26: =B25+1 -> 45975 | C26: =TEXT(B26, "dddd") -> Friday | D26: =D19 -> 2340 | F26: =F25+1 -> 46005 | G26: =TEXT(F26, "dddd") -> Sunday | H26: =H19 -> 4905.6378
B27: =B26+1 -> 45976 | C27: =TEXT(B27, "dddd") -> Saturday | D27: =D20 -> 2879 | F27: =F26+1 -> 46006 | G27: =TEXT(F27, "dddd") -> Monday | H27: =H20 -> 2688
B28: =B27+1 -> 45977 | C28: =TEXT(B28, "dddd") -> Sunday | D28: =D21 -> 3242 | F28: =F27+1 -> 46007 | G28: =TEXT(F28, "dddd") -> Tuesday | H28: =H21 -> 2547.0691
B29: =B28+1 -> 45978 | C29: =TEXT(B29, "dddd") -> Monday | D29: =D22 -> 2240 | F29: =F28+1 -> 46008 | G29: =TEXT(F29, "dddd") -> Wednesday | H29: =H22 -> 2508.3093
B30: =B29+1 -> 45979 | C30: =TEXT(B30, "dddd") -> Tuesday | D30: =D23 -> 2072 | F30: =F29+1 -> 46009 | G30: =TEXT(F30, "dddd") -> Thursday | H30: =H23 -> 2524.9886
B31: =B30+1 -> 45980 | C31: =TEXT(B31, "dddd") -> Wednesday | D31: =D24 -> 2206 | F31: =F30+1 -> 46010 | G31: =TEXT(F31, "dddd") -> Friday | H31: =H24 -> 2637.3538
B32: =B31+1 -> 45981 | C32: =TEXT(B32, "dddd") -> Thursday | D32: =D25 -> 2255 | F32: =F31+1 -> 46011 | G32: =TEXT(F32, "dddd") -> Saturday | H32: =H25 -> 3389.7754
B33: =B32+1 -> 45982 | C33: =TEXT(B33, "dddd") -> Friday | D33: =D26 -> 2340 | F33: =F32+1 -> 46012 | G33: =TEXT(F33, "dddd") -> Sunday | H33: =H26 -> 4905.6378
... B42: =B41+1 -> 45991 | C42: =TEXT(B42, "dddd") -> Sunday | D42: =D35 -> 3242 | F42: =F41+1 -> 46021 | G42: =TEXT(F42, "dddd") -> Tuesday | H42: =H35 -> 2547.0691
F43: =F42+1 -> 46022 | G43: =TEXT(F43, "dddd") -> Wednesday | H43: =H36 -> 2508.3093
B44: Total | D44: =SUM(D13:D43) -> 75461 | F44: Total | H44: =SUM(H13:H43) -> 92547.914

Sheet Key Metrics
C2: Actual | D2: Actual | E2: Actual | F2: Actual | G2: Actual | H2: Actual | I2: Actual | J2: Actual | K2: Actual | L2: Actual | M2: Actual | N2: Actual
B3: Key Metrics | C3: 45688 | D3: =EOMONTH(C3,1) -> 45716 | E3: =EOMONTH(D3,1) -> 45747 | F3: =EOMONTH(E3,1) -> 45777 | G3: =EOMONTH(F3,1) -> 45808 | H3: =EOMONTH(G3,1) -> 45838 | I3: =EOMONTH(H3,1) -> 45869 | J3: =EOMONTH(I3,1) -> 45900 | K3: =EOMONTH(J3,1) -> 45930 | ... N3: =EOMONTH(M3,1) -> 46022
F4: 506.96274 | G4: 1134.738 | H4: 1549.1958
B5: Annual Run Rate Revenue (USD Thousands) | C5: ='MIS P&L'!C7*12/88 -> 229.8297 | D5: ='MIS P&L'!D7*12/88 -> 239.00447 | E5: ='MIS P&L'!E7*12/88 -> 334.77175 | F5: ='MIS P&L'!F7*12/88 -> 460.87522 | G5: ='MIS P&L'!G7*12/88 -> 1031.6038 | H5: ='MIS P&L'!H7*12/88 -> 1408.3546 | I5: ='MIS P&L'!I7*12/88 -> 2035.9653 | J5: ='MIS P&L'!J7*12/88 -> 3757.6057 | ... N5: ='MIS P&L'!N7*12/88 -> 15923.098
B7: Micro markets | C7: 1 | D7: 2 | E7: 4 | F7: 7 | G7: 8 | H7: 15 | I7: 19 | J7: 26 | K7: 38 | L7: 51 | M7: 66 | N7: 86
B9: Demand
B11: Monthly Active Users * | C11: =SUM(C12:C13) -> 2763 | D11: =SUM(D12:D13) -> 3666 | E11: =SUM(E12:E13) -> 5437 | F11: =SUM(F12:F13) -> 7198 | G11: =SUM(G12:G13) -> 14686 | H11: =SUM(H12:H13) -> 21226 | I11: =SUM(I12:I13) -> 32013 | J11: =SUM(J12:J13) -> 54733 | ... N11: =SUM(N12:N13) -> 209901
B12: First time | C12: 966 | D12: 1583 | E12: 2682 | F12: 4037 | G12: 9862 | H12: 12369 | I12: 19197 | J12: 34897 | K12: 49119 | L12: 83204 | M12: 86837 | N12: 102395
B13: Repeat | C13: 1797 | D13: 2083 | E13: 2755 | F13: 3161 | G13: 4824 | H13: 8857 | I13: 12816 | J13: 19836 | K13: 31108 | L13: 48497 | M13: 74244 | N13: 107506
B14: Jobs | C14: =SUM(C15:C16) -> 6863 | D14: =SUM(D15:D16) -> 7519 | E14: =SUM(E15:E16) -> 10642 | F14: =SUM(F15:F16) -> 14980 | G14: =SUM(G15:G16) -> 35189 | H14: =SUM(H15:H16) -> 47211 | I14: =SUM(I15:I16) -> 68196 | J14: =SUM(J15:J16) -> 118808 | ... N14: =SUM(N15:N16) -> 518345
B15: First time | C15: 1665 | D15: 2439 | E15: 4093 | F15: 7056 | G15: 22591 | H15: 26771 | I15: 39036 | J15: 71090 | K15: 97264 | L15: 185159 | M15: 184371 | N15: 223401
B16: Repeat | C16: 5198 | D16: 5080 | E16: 6549 | F16: 7924 | G16: 12598 | H16: 20440 | I16: 29160 | J16: 47718 | K16: 70738 | L16: 123509 | M16: 191264 | N16: 294944
B17: Frequency | C17: =C14/C11 -> 2.4838943 | D17: =D14/D11 -> 2.0510093 | E17: =E14/E11 -> 1.9573294 | F17: =F14/F11 -> 2.0811336 | G17: =G14/G11 -> 2.3960915 | H17: =H14/H11 -> 2.2242062 | I17: =I14/I11 -> 2.1302596 | J17: =J14/J11 -> 2.1706831 | ... N17: =N14/N11 -> 2.4694737
B18: First Time | C18: =C15/C12 -> 1.7236025 | D18: =D15/D12 -> 1.5407454 | E18: =E15/E12 -> 1.5260999 | F18: =F15/F12 -> 1.7478325 | G18: =G15/G12 -> 2.2907118 | H18: =H15/H12 -> 2.1643625 | I18: =I15/I12 -> 2.0334427 | J18: =J15/J12 -> 2.0371379 | ... N18: =N15/N12 -> 2.1817569
B19: Repeat | C19: =C16/C13 -> 2.8925988 | D19: =D16/D13 -> 2.4387902 | E19: =E16/E13 -> 2.3771325 | F19: =F16/F13 -> 2.5068016 | G19: =G16/G13 -> 2.6115257 | H19: =H16/H13 -> 2.3077792 | I19: =I16/I13 -> 2.2752809 | J19: =J16/J13 -> 2.4056261 | ... N19: =N16/N13 -> 2.743512
B20: Jobs per Day | C20: =C14/30 -> 228.76667 | D20: =D14/30 -> 250.63333 | E20: =E14/30 -> 354.73333 | F20: =F14/30 -> 499.33333 | G20: =G14/(G$3-F$3) -> 1135.129 | H20: =H14/(H$3-G$3) -> 1573.7 | I20: =I14/(I$3-H$3) -> 2199.871 | J20: =J14/(J$3-I$3) -> 3832.5161 | K20: =K14/(K$3-J$3) -> 5600.0667 | L20: =L14/(L$3-K$3) -> 9957.0323 | M20: =M14/(M$3-L$3) -> 12521.167 | N20: =N14/(N$3-M$3) -> 16720.806
B21: First time | C21: =C15/30 -> 55.5 | D21: =D15/30 -> 81.3 | E21: =E15/30 -> 136.43333 | F21: =F15/30 -> 235.2 | G21: =G15/(G$3-F$3) -> 728.74194 | H21: =H15/(H$3-G$3) -> 892.36667 | I21: =I15/(I$3-H$3) -> 1259.2258 | J21: =J15/(J$3-I$3) -> 2293.2258 | K21: =K15/(K$3-J$3) -> 3242.1333 | L21: =L15/(L$3-K$3) -> 5972.871 | M21: =M15/(M$3-L$3) -> 6145.7 | N21: =N15/(N$3-M$3) -> 7206.4839
B22: Repeat | C22: =C16/30 -> 173.26667 | D22: =D16/30 -> 169.33333 | E22: =E16/30 -> 218.3 | F22: =F16/30 -> 264.13333 | G22: =G16/(G$3-F$3) -> 406.3871 | H22: =H16/(H$3-G$3) -> 681.33333 | I22: =I16/(I$3-H$3) -> 940.64516 | J22: =J16/(J$3-I$3) -> 1539.2903 | K22: =K16/(K$3-J$3) -> 2357.9333 | L22: =L16/(L$3-K$3) -> 3984.1613 | M22: =M16/(M$3-L$3) -> 6375.4667 | N22: =N16/(N$3-M$3) -> 9514.3226
B23: Hours | C23: =SUM(C24:C25) -> 9144.75 | D23: =SUM(D24:D25) -> 9603 | E23: =SUM(E24:E25) -> 13457.25 | F23: =SUM(F24:F25) -> 18463 | G23: =SUM(G24:G25) -> 41475.5 | H23: =SUM(H24:H25) -> 54875 | I23: =SUM(I24:I25) -> 79269.5 | J23: =SUM(J24:J25) -> 145034 | ... N23: =SUM(N24:N25) -> 648259.75
B24: First time | C24: 2163.75 | D24: 2948.5 | E24: 4872 | F24: 8340.25 | G24: 25539.5 | H24: 30253.75 | I24: 44115.5 | J24: 84742.75 | K24: 113683.75 | L24: 239537.75 | M24: 226326.75 | N24: =16322415/60 -> 272040.25
B25: Repeat | C25: 6981 | D25: 6654.5 | E25: 8585.25 | F25: 10122.75 | G25: 15936 | H25: 24621.25 | I25: 35154 | J25: 60291.25 | K25: 87714.25 | L25: 166153 | M25: 240733.67 | N25: 376219.5
B26: Hours per Day | C26: =SUM(C27:C28) -> 294.99194 | D26: =SUM(D27:D28) -> 342.96429 | E26: =SUM(E27:E28) -> 434.10484 | F26: =SUM(F27:F28) -> 615.43333 | G26: =SUM(G27:G28) -> 1337.9194 | H26: =SUM(H27:H28) -> 1829.1667 | I26: =SUM(I27:I28) -> 2557.0806 | J26: =SUM(J27:J28) -> 4678.5161 | ... N26: =SUM(N27:N28) -> 20911.605
B27: First time | C27: =C24/31 -> 69.798387 | D27: =D24/(D$3-C$3) -> 105.30357 | E27: =E24/(E$3-D$3) -> 157.16129 | F27: =F24/(F$3-E$3) -> 278.00833 | G27: =G24/(G$3-F$3) -> 823.85484 | H27: =H24/(H$3-G$3) -> 1008.4583 | I27: =I24/(I$3-H$3) -> 1423.0806 | J27: =J24/(J$3-I$3) -> 2733.6371 | K27: =K24/(K$3-J$3) -> 3789.4583 | ... N27: =N24/(N$3-M$3) -> 8775.4919
B28: Repeat | C28: =C25/31 -> 225.19355 | D28: =D25/(D$3-C$3) -> 237.66071 | E28: =E25/(E$3-D$3) -> 276.94355 | F28: =F25/(F$3-E$3) -> 337.425 | G28: =G25/(G$3-F$3) -> 514.06452 | H28: =H25/(H$3-G$3) -> 820.70833 | I28: =I25/(I$3-H$3) -> 1134 | J28: =J25/(J$3-I$3) -> 1944.879 | K28: =K25/(K$3-J$3) -> 2923.8083 | ... N28: =N25/(N$3-M$3) -> 12136.113
B29: Hours per Job | C29: =C23/C14 -> 1.3324712 | D29: =D23/D14 -> 1.2771645 | E29: =E23/E14 -> 1.2645414 | F29: =F23/F14 -> 1.23251 | G29: =G23/G14 -> 1.1786496 | H29: =H23/H14 -> 1.162335 | I29: =I23/I14 -> 1.1623776 | J29: =J23/J14 -> 1.2207427 | ... N29: =N23/N14 -> 1.2506337
B30: First time | C30: =C24/C15 -> 1.2995495 | D30: =D24/D15 -> 1.2088971 | E30: =E24/E15 -> 1.1903249 | F30: =F24/F15 -> 1.1820082 | G30: =G24/G15 -> 1.1305166 | H30: =H24/H15 -> 1.1300941 | I30: =I24/I15 -> 1.1301235 | J30: =J24/J15 -> 1.1920488 | ... N30: =N24/N15 -> 1.2177217
B31: Repeat | C31: =C25/C16 -> 1.3430165 | D31: =D25/D16 -> 1.3099409 | E31: =E25/E16 -> 1.3109253 | F31: =F25/F16 -> 1.2774798 | G31: =G25/G16 -> 1.2649627 | H31: =H25/H16 -> 1.2045621 | I31: =I25/I16 -> 1.2055556 | J31: =J25/J16 -> 1.2634907 | ... N31: =N25/N16 -> 1.2755625
B33: Supply
B35: Onboarded | C35: 37 | D35: 40 | E35: 109 | F35: 245 | G35: 333 | H35: 670 | I35: 678 | J35: 1032 | K35: 1564 | L35: 2123 | M35: 2760 | N35: 3343
B36: Active Experts | C36: =SUM(C37:C38) -> 121 | D36: =SUM(D37:D38) -> 150 | E36: =SUM(E37:E38) -> 224 | F36: =SUM(F37:F38) -> 386 | G36: =SUM(G37:G38) -> 637 | H36: =SUM(H37:H38) -> 1113 | I36: =SUM(I37:I38) -> 1566 | J36: =SUM(J37:J38) -> 2009 | ... N36: =SUM(N37:N38) -> 8423
B37: First Login experts | C37: 33 | D37: 46 | E37: 97 | F37: 210 | G37: 297 | H37: 582 | I37: 625 | J37: 812 | K37: 1481 | L37: 1838 | M37: 2487 | N37: 3061
B38: Repeat login experts | C38: 88 | D38: 104 | E38: 127 | F38: 176 | G38: 340 | H38: 531 | I38: 941 | J38: 1197 | K38: 1695 | L38: 2722 | M38: 3695 | N38: 5362
B40: Total Shifts | C40: 3374 | D40: 3698 | E40: 5350 | F40: 8602 | G40: 16535 | H40: 28634 | I40: 39739 | J40: 53626 | K40: 75747 | L40: 117432 | M40: 150778 | N40: 213124
B41: Total Shifts per Expert | C41: =C40/C36 -> 27.884298 | D41: =D40/D36 -> 24.653333 | E41: =E40/E36 -> 23.883929 | F41: =F40/F36 -> 22.284974 | G41: =G40/G36 -> 25.957614 | H41: =H40/H36 -> 25.726864 | I41: =I40/I36 -> 25.376117 | J41: =J40/J36 -> 26.692882 | ... N41: =N40/N36 -> 25.302624
B42: Present Shifts | C42: 2485 | D42: 2624 | E42: 3774 | F42: 6348 | G42: 10865 | H42: 19875 | I42: 27071 | J42: 36081 | K42: 53027 | L42: 82478 | M42: 110372 | N42: 160923
B43: Shifts per expert | C43: =C42/C36 -> 20.53719 | D43: =D42/D36 -> 17.493333 | E43: =E42/E36 -> 16.848214 | F43: =F42/F36 -> 16.445596 | G43: =G42/G36 -> 17.056515 | H43: =H42/H36 -> 17.857143 | I43: =I42/I36 -> 17.286718 | J43: =J42/J36 -> 17.959681 | ... N43: =N42/N36 -> 19.105188
B44: Attendence% | C44: =C42/C40 -> 0.73651452 | D44: =D42/D40 -> 0.70957274 | E44: =E42/E40 -> 0.70542056 | F44: =F42/F40 -> 0.73796791 | G44: =G42/G40 -> 0.65709102 | H44: =H42/H40 -> 0.69410491 | I44: =I42/I40 -> 0.68121996 | J44: =J42/J40 -> 0.67282661 | ... N44: =N42/N40 -> 0.75506747
B45: Shift hours | C45: 16935 | D45: 17886 | E45: 27198 | F45: 53875.81 | G45: 92848 | H45: 173757 | I45: 239593 | J45: 339942 | K45: 515685 | L45: 809604.52 | M45: 1100971 | N45: =96666701/60 -> 1611111.7
B46: Hours per shift | C46: =C45/C42 -> 6.8148893 | D46: =D45/D42 -> 6.816311 | E46: =E45/E42 -> 7.2066773 | F46: =F45/F42 -> 8.4870526 | G46: =G45/G42 -> 8.5456052 | H46: =H45/H42 -> 8.7424906 | I46: =I45/I42 -> 8.8505412 | J46: =J45/J42 -> 9.4216347 | ... N46: =N45/N42 -> 10.011693
B48: Utilization % | C48: =IFERROR(C23/C45,"") -> 0.53999114 | D48: =IFERROR(D23/D45,"") -> 0.53690037 | E48: =IFERROR(E23/E45,"") -> 0.49478822 | F48: =IFERROR(F23/F45,"") -> 0.34269554 | G48: =IFERROR(G23/G45,"") -> 0.44670321 | H48: =IFERROR(H23/H45,"") -> 0.31581461 | I48: =IFERROR(I23/I45,"") -> 0.33085065 | J48: =IFERROR(J23/J45,"") -> 0.42664337 | ... N48: =IFERROR(N23/N45,"") -> 0.40236798
B50: Expert Acquisition Cost | C50: =SUM(C51:C52) -> 11342.635 | D50: =SUM(D51:D52) -> 26127.917 | E50: =SUM(E51:E52) -> 12359.603 | F50: =SUM(F51:F52) -> 10371.719 | G50: =SUM(G51:G52) -> 11838.047 | H50: =SUM(H51:H52) -> 9709.9209 | I50: =SUM(I51:I52) -> 10096.205 | J50: =SUM(J51:J52) -> 8881.0788 | ... N50: =SUM(N51:N52) -> 6917.4877
B51: Training Centre Expenses | C51: ='MIS P&L'!C17/'Key Metrics'!C35*10^3 -> 4173.7314 | D51: ='MIS P&L'!D17/'Key Metrics'!D35*10^3 -> 13891.483 | E51: ='MIS P&L'!E17/'Key Metrics'!E35*10^3 -> 3473.3572 | F51: ='MIS P&L'!F17/'Key Metrics'!F35*10^3 -> 4373.9768 | G51: ='MIS P&L'!G17/'Key Metrics'!G35*10^3 -> 6371.0081 | H51: ='MIS P&L'!H17/'Key Metrics'!H35*10^3 -> 2744.9721 | I51: ='MIS P&L'!I17/'Key Metrics'!I35*10^3 -> 3141.8532 | J51: ='MIS P&L'!J17/'Key Metrics'!J35*10^3 -> 2321.3703 | ... N51: ='MIS P&L'!N17/'Key Metrics'!N35*10^3 -> 1644.7297
B52: Sourcing & Onboarding Cost | C52: ='MIS P&L'!C19/'Key Metrics'!C35*10^3 -> 7168.9032 | D52: ='MIS P&L'!D19/'Key Metrics'!D35*10^3 -> 12236.434 | E52: ='MIS P&L'!E19/'Key Metrics'!E35*10^3 -> 8886.2458 | F52: ='MIS P&L'!F19/'Key Metrics'!F35*10^3 -> 5997.7418 | G52: ='MIS P&L'!G19/'Key Metrics'!G35*10^3 -> 5467.039 | H52: ='MIS P&L'!H19/'Key Metrics'!H35*10^3 -> 6964.9488 | I52: ='MIS P&L'!I19/'Key Metrics'!I35*10^3 -> 6954.3515 | J52: ='MIS P&L'!J19/'Key Metrics'!J35*10^3 -> 6559.7085 | ... N52: ='MIS P&L'!N19/'Key Metrics'!N35*10^3 -> 5272.758
B54: Profitability
B56: GOV per Job | C56: ='MIS P&L'!C7*10^3/C14 -> 245.58033 | D56: ='MIS P&L'!D7*10^3/D14 -> 233.10273 | E56: ='MIS P&L'!E7*10^3/E14 -> 230.68904 | F56: ='MIS P&L'!F7*10^3/F14 -> 225.6176 | G56: ='MIS P&L'!G7*10^3/G14 -> 214.98465 | H56: ='MIS P&L'!H7*10^3/H14 -> 218.76117 | I56: ='MIS P&L'!I7*10^3/I14 -> 218.93384 | J56: ='MIS P&L'!J7*10^3/J14 -> 231.93535 | ... N56: ='MIS P&L'!N7*10^3/N14 -> 225.27349
B57: GOV per Hour | C57: ='MIS P&L'!C7*10^3/C23 -> 184.30442 | D57: ='MIS P&L'!D7*10^3/D23 -> 182.51582 | E57: ='MIS P&L'!E7*10^3/E23 -> 182.42901 | F57: ='MIS P&L'!F7*10^3/F23 -> 183.05539 | G57: ='MIS P&L'!G7*10^3/G23 -> 182.39912 | H57: ='MIS P&L'!H7*10^3/H23 -> 188.20836 | I57: ='MIS P&L'!I7*10^3/I23 -> 188.35002 | J57: ='MIS P&L'!J7*10^3/J23 -> 189.99528 | ... N57: ='MIS P&L'!N7*10^3/N23 -> 180.12747
B59: Cost per Job | C59: ='MIS P&L'!C8*10^3/C14 -> 191.8646 | D59: ='MIS P&L'!D8*10^3/D14 -> 240.53149 | E59: ='MIS P&L'!E8*10^3/E14 -> 223.42346 | F59: ='MIS P&L'!F8*10^3/F14 -> 311.50788 | G59: ='MIS P&L'!G8*10^3/G14 -> 287.74425 | H59: ='MIS P&L'!H8*10^3/H14 -> 343.01441 | I59: ='MIS P&L'!I8*10^3/I14 -> 304.96776 | J59: ='MIS P&L'!J8*10^3/J14 -> 293.73579 | ... N59: ='MIS P&L'!N8*10^3/N14 -> 261.2676
B60: Cost per Utilized Hour | C60: ='MIS P&L'!C8*10^3/C23 -> 143.99155 | D60: ='MIS P&L'!D8*10^3/D23 -> 188.33242 | E60: ='MIS P&L'!E8*10^3/E23 -> 176.68338 | F60: ='MIS P&L'!F8*10^3/F23 -> 252.74268 | G60: ='MIS P&L'!G8*10^3/G23 -> 244.13044 | H60: ='MIS P&L'!H8*10^3/H23 -> 295.10803 | I60: ='MIS P&L'!I8*10^3/I23 -> 262.36549 | J60: ='MIS P&L'!J8*10^3/J23 -> 240.62056 | ... N60: ='MIS P&L'!N8*10^3/N23 -> 208.90816
B61: Cost per Hour | C61: =C60*C48 -> 77.754163 | D61: =D60*D48 -> 101.11575 | E61: =E60*E48 -> 87.420857 | F61: =F60*F48 -> 86.61379 | G61: =G60*G48 -> 109.05385 | H61: =H60*H48 -> 93.199429 | I61: =I60*I48 -> 86.803794 | J61: =J60*J48 -> 102.65917 | ... N61: =N60*N48 -> 84.057955
B63: NOV 1 (Total Sales - Promo discounts) | M63: =('MIS P&L'!M7-'MIS P&L'!M11)/M14*10^3 -> 191.2879 | N63: =('MIS P&L'!N7-'MIS P&L'!N11)/N14*10^3 -> 185.74136
B64: NOV 1 per hour | M64: =M63/M29 -> 153.84397 | N64: =N63/N29 -> 148.51779
B66: NOV 2 (Total Sales - All discounts) | M66: =('MIS P&L'!M7-'MIS P&L'!M11-'MIS P&L'!M29)/M14*10^3 -> 115.63024 | N66: =('MIS P&L'!N7-'MIS P&L'!N11-'MIS P&L'!N29)/N14*10^3 -> 119.33035
B67: NOV 2 per hour | M67: =M66/M29 -> 92.996034 | N67: =N66/N29 -> 95.415901
B69: Gross Profit per Job | C69: ='MIS P&L'!C14*10^3/C14 -> 27.860882 | D69: ='MIS P&L'!D14*10^3/D14 -> -33.030516 | E69: ='MIS P&L'!E14*10^3/E14 -> -10.500657 | F69: ='MIS P&L'!F14*10^3/F14 -> -104.91298 | G69: ='MIS P&L'!G14*10^3/G14 -> -88.112971 | H69: ='MIS P&L'!H14*10^3/H14 -> -140.18964 | I69: ='MIS P&L'!I14*10^3/I14 -> -106.38027 | J69: ='MIS P&L'!J14*10^3/J14 -> -87.438103 | ... N69: ='MIS P&L'!N14*10^3/N14 -> -85.650543
B70: Gross Profit per Hour | C70: ='MIS P&L'!C14*10^3/C23 -> 20.909181 | D70: ='MIS P&L'!D14*10^3/D23 -> -25.862382 | E70: ='MIS P&L'!E14*10^3/E23 -> -8.3039247 | F70: ='MIS P&L'!F14*10^3/F23 -> -85.1214 | G70: ='MIS P&L'!G14*10^3/G23 -> -74.757564 | H70: ='MIS P&L'!H14*10^3/H23 -> -120.61035 | I70: ='MIS P&L'!I14*10^3/I23 -> -91.51955 | J70: ='MIS P&L'!J14*10^3/J23 -> -71.626971 | ... N70: ='MIS P&L'!N14*10^3/N23 -> -68.485713
B71: Gross Profit % | C71: =IFERROR(C69/C56,"") -> 0.11344916 | D71: =IFERROR(D69/D56,"") -> -0.1416994 | E71: =IFERROR(E69/E56,"") -> -0.045518663 | F71: =IFERROR(F69/F56,"") -> -0.46500352 | G71: =IFERROR(G69/G56,"") -> -0.40985703 | H71: =IFERROR(H69/H56,"") -> -0.64083419 | I71: =IFERROR(I69/I56,"") -> -0.48590146 | J71: =IFERROR(J69/J56,"") -> -0.37699343 | ... N71: =IFERROR(N69/N56,"") -> -0.38020694
B73: GST % | C73: ='MIS P&L'!C10/'MIS P&L'!C7 -> 0.066130885 | D73: ='MIS P&L'!D10/'MIS P&L'!D7 -> 0.061099341 | E73: ='MIS P&L'!E10/'MIS P&L'!E7 -> 0.059356317 | F73: ='MIS P&L'!F10/'MIS P&L'!F7 -> 0.064801162 | G73: ='MIS P&L'!G10/'MIS P&L'!G7 -> 0.065753298 | H73: ='MIS P&L'!H10/'MIS P&L'!H7 -> 0.065335753 | I73: ='MIS P&L'!I10/'MIS P&L'!I7 -> 0.066521906 | J73: ='MIS P&L'!J10/'MIS P&L'!J7 -> 0.066292917 | ... N73: ='MIS P&L'!N10/'MIS P&L'!N7 -> 0.043452205
B74: Promotional Discount % | C74: ='MIS P&L'!C11/'MIS P&L'!C7 -> 0.028297434 | D74: ='MIS P&L'!D11/'MIS P&L'!D7 -> 0.038981584 | E74: ='MIS P&L'!E11/'MIS P&L'!E7 -> 0.0089352604 | F74: ='MIS P&L'!F11/'MIS P&L'!F7 -> 0.0099149298 | G74: ='MIS P&L'!G11/'MIS P&L'!G7 -> 0.0026040652 | H74: ='MIS P&L'!H11/'MIS P&L'!H7 -> 0.0042435401 | I74: ='MIS P&L'!I11/'MIS P&L'!I7 -> 0.02329561 | J74: ='MIS P&L'!J11/'MIS P&L'!J7 -> 0.042440758 | ... N74: ='MIS P&L'!N11/'MIS P&L'!N7 -> 0.17548504
B76: Customer Acquisition Cost | C76: ='MIS P&L'!C26*10^3/C12 -> 907.00283 | D76: ='MIS P&L'!D26*10^3/D12 -> 835.69172 | E76: ='MIS P&L'!E26*10^3/E12 -> 592.10826 | F76: ='MIS P&L'!F26*10^3/F12 -> 653.07818 | G76: ='MIS P&L'!G26*10^3/G12 -> 629.81375 | H76: ='MIS P&L'!H26*10^3/H12 -> 847.20887 | I76: ='MIS P&L'!I26*10^3/I12 -> 886.84992 | J76: ='MIS P&L'!J26*10^3/J12 -> 1020.5879 | ... N76: ='MIS P&L'!N26*10^3/N12 -> 880.86646

Sheet RQSP Metrics
C2: Actual | D2: Actual | E2: Actual | F2: Actual | G2: Actual | H2: Actual | I2: Actual | J2: Actual | K2: Actual
B3: RQSP Metrics | C3: 45777 | D3: =EOMONTH(C3,1) -> 45808 | E3: =EOMONTH(D3,1) -> 45838 | F3: =EOMONTH(E3,1) -> 45869 | G3: =EOMONTH(F3,1) -> 45900 | H3: =EOMONTH(G3,1) -> 45930 | I3: =EOMONTH(H3,1) -> 45961 | J3: =EOMONTH(I3,1) -> 45991 | K3: =EOMONTH(J3,1) -> 46022
C4: 506.96274 | D4: 1134.738 | E4: 1549.1958
B5: Reliability
B6: Booking availability | G6: 0.887 | H6: 0.893 | I6: 0.814 | J6: 0.8637 | K6: 0.8845
B7: Fullfillment % | G7: 0.98289416 | H7: 0.99192785 | I7: 0.94681995 | J7: 0.994 | K7: 0.956
B9: Quality
B10: Average Rating | C10: 4.56 | D10: 4.52 | E10: 4.58 | F10: 4.63 | G10: 4.64 | H10: 4.64 | I10: 4.5710685 | J10: 4.59 | K10: 4.6039875
B11: 5 Rating % | C11: 0.77925834 | D11: 0.77925834 | E11: 0.7871776 | F11: 0.80329931 | G11: 0.8034 | H11: 0.84 | I11: 0.7795 | J11: 0.78625 | K11: 0.7953
B12: 4 Rating % | C12: 0.10226216 | D12: 0.0997 | E12: 0.0995796 | F12: 0.098554114 | G12: 0.0977 | H12: 0.1 | I12: 0.1069 | J12: 0.1047 | K12: 0.1002
B13: 3 Rating % | C13: 0.050924491 | D13: 0.054 | E13: 0.0546478 | F13: 0.049471968 | G13: 0.0492 | H13: 0.01 | I13: 0.0549 | J13: 0.05359 | K13: 0.0508
B14: 2 Rating % | C14: 0.030781944 | D14: 0.0305 | E14: 0.0223684 | F14: 0.01917216 | G14: 0.0202 | H14: 0.02 | I14: 0.0227 | J14: 0.02134 | K14: 0.0202
B15: 1 Rating % | C15: 0.036773061 | D15: 0.0401 | E15: 0.0362266 | F15: 0.029502445 | G15: 0.0296 | H15: 0.03 | I15: 0.0361 | J15: 0.03411 | K15: 0.0333
B17: Speed
B18: Median (P50)
B19: Booking to Check-in | C19: 19.31 | D19: 19.25 | E19: 19.22 | F19: 18.07 | G19: 18.12 | H19: 17.87 | I19: 19.58 | J19: 18.083333 | K19: 17.48333
B20: Booking to Allocation | C20: 0.02 | D20: 0.05 | E20: 0.12 | F20: 0.13 | G20: 0.12 | H20: 0.07 | I20: 0.05 | J20: 0.03 | K20: 0.05
B21: Allocation to Acceptance | C21: 1.18 | D21: 0.98 | E21: 0.48 | F21: 0.42 | G21: 0.4 | H21: 0.35 | I21: 0.4 | J21: 0.48 | K21: 0.37
B22: Acceptance to Arrival | C22: 10.18 | D22: 8.93 | E22: 8.43 | F22: 7.65 | G22: 7.08 | H22: 6.6 | I22: 7.35 | J22: 7.42 | K22: 7.58
B23: Arrival to Check-in | C23: 2.88 | D23: 5.52 | E23: 6.6 | F23: 6.9 | G23: 7.9 | H23: 8.62 | I23: 8.7 | J23: 7.12 | K23: 6.8
B25: 90th Percentile (P90)
B26: Booking to Check-in | C26: 45.6 | D26: 47 | E26: 37.49 | F26: 33.98 | G26: 36.35 | H26: 34.79 | I26: 42.68 | J26: 37.316667 | K26: 33.81667
B27: Booking to Allocation | C27: 12.932 | D27: 11.456 | E27: 8 | F27: 5.63 | G27: 6.07 | H27: 4.768 | I27: 7.03 | J27: 0.17 | K27: 7.08
B28: Allocation to Acceptance | C28: 10.957 | D28: 8.13 | E28: 3.03 | F28: 2.68 | G28: 2.68 | H28: 1.88 | I28: 4.1 | J28: 11.03 | K28: 2.1
B29: Acceptance to Arrival | C29: 22.953 | D29: 21.43 | E29: 18.52 | F29: 16.37 | G29: 15.38 | H29: 14.98 | I29: 16.78 | J29: 16.13 | K29: 16.33
B30: Arrival to Check-in | C30: 10.23 | D30: 13.744 | E30: 15.1 | F30: 15.754 | G30: 17.72 | H30: 19.55 | I30: 20.47 | J30: 16.5 | K30: 15.58
B32: Punctuality
B33: % Jobs On Time | C33: 0.451 | D33: 0.411 | E33: 0.465 | F33: 0.526 | G33: 0.533 | H33: 0.546 | I33: 0.444 | J33: =1-J34-J35 -> 0.5421261 | K33: =1-K34-K35 -> 0.6509
B34: % EOB (5-15) | C34: 0.21618196 | D34: 0.23169831 | E34: 0.26160168 | F34: 0.26449153 | G34: 0.23397414 | H34: 0.23865645 | I34: 0.2024272 | J34: 0.2114739 | K34: 0.206
B35: % EOB >15 | C35: 0.333111 | D35: 0.3571388 | E35: 0.2736958 | F35: 0.2095901 | G35: 0.2326695 | H35: 0.2158295 | I35: 0.3534045 | J35: 0.2464 | K35: 0.1431

Sheet Customer Cohorts - Overall 
B2: Customer Retention
B3: Month | C3: FTs | D3: 30 | E3: 60 | F3: 90 | G3: 120 | H3: 150 | I3: 180 | J3: 210 | K3: 240 | L3: 270 | M3: 300 | N3: 360 | Q3: The current rate reflects customers acquired in October who placed a second order within the same month. Since the 30-day period isn’t complete, retention is expected to improve.
B4: 45658 | C4: 997 | D4: 0.43 | E4: 0.34 | F4: 0.31 | G4: 0.3 | H4: 0.29 | I4: 0.29 | J4: 0.31 | K4: 0.29 | L4: 0.28 | M4: 0.31159 | N4: 0.29
B5: 45689 | C5: 1534 | D5: 0.39 | E5: 0.31 | F5: 0.28 | G5: 0.27 | H5: 0.28 | I5: 0.31 | J5: 0.29 | K5: 0.3 | L5: 0.3108 | M5: 0.28427
B6: 45717 | C6: 2546 | D6: 0.37 | E6: 0.24 | F6: 0.25 | G6: 0.24 | H6: 0.24 | I6: 0.26 | J6: 0.27 | K6: 0.27218 | L6: 0.25727
B7: 45748 | C7: 3787 | D7: 0.58 | E7: 0.28 | F7: 0.26 | G7: 0.27 | H7: 0.27 | I7: 0.27 | J7: 0.29403 | K7: 0.27099
B8: 45778 | C8: 9361 | D8: 0.79 | E8: 0.25 | F8: 0.25 | G8: 0.26 | H8: 0.26 | I8: 0.27266 | J8: 0.28148
B9: 45809 | C9: 11532 | D9: 0.76 | E9: 0.27 | F9: 0.26 | G9: 0.26 | H9: 0.27884 | I9: 0.27779
B10: 45839 | C10: 17911 | D10: 0.74 | E10: 0.26 | F10: 0.25 | G10: 0.26358 | H10: 0.26582
B11: 45870 | C11: 34709 | D11: 0.72 | E11: 0.27 | F11: 0.27896 | G11: 0.2767
B12: 45901 | C12: 48045 | D12: 0.68 | E12: 0.32081 | F12: 0.29341
B13: =EOMONTH(B12,1) -> 45961 | C13: 82760 | D13: 0.67978 | E13: 0.28012
B14: =EOMONTH(B13,1) -> 45991 | C14: ='Key Metrics'!M12 -> 86837 | D14: 0.71161
B15: =EOMONTH(B14,1) -> 46022 | C15: ='Key Metrics'!N12 -> 102395 | D15: 0.54132
B17: Booking Retention
B18: Month | C18: FTs | D18: 30 | E18: 60 | F18: 90 | G18: 120 | H18: 150 | I18: 180 | J18: 210 | K18: 240 | L18: 270 | M18: 300 | N18: 360
B19: 45658 | C19: 997 | D19: =D49*D4 -> 1.1126379 | E19: =E49*E4 -> 0.7923122 | F19: =F49*F4 -> 0.7107556 | G19: =G49*G4 -> 0.766782 | H19: =H49*H4 -> 0.77749 | I19: =I49*I4 -> 0.7239705 | J19: =J49*J4 -> 0.8138802 | K19: =K49*K4 -> 0.7485567 | ... N19: =N49*N4 -> 1.03907
B20: 45689 | C20: 1534 | D20: =D50*D5 -> 1.0026744 | E20: =E50*E5 -> 0.6840274 | F20: =F50*F5 -> 0.7183148 | G20: =G50*G5 -> 0.6794361 | H20: =H50*H5 -> 0.7075684 | I20: =I50*I5 -> 0.7781899 | J20: =J50*J5 -> 0.8611753 | K20: =K50*K5 -> 0.811464 | ... M20: =M50*M5 -> 0.9267202
B21: 45717 | C21: 2546 | D21: =D51*D6 -> 0.8894097 | E21: =E51*E6 -> 0.578736 | F21: =F51*F6 -> 0.5593975 | G21: =G51*G6 -> 0.5498784 | H21: =H51*H6 -> 0.5802432 | I21: =I51*I6 -> 0.7094334 | J21: =J51*J6 -> 0.7319106 | K21: =K51*K6 -> 0.83450388 | L21: =L51*L6 -> 0.78595985
B22: 45748 | C22: 3787 | D22: =D52*D7 -> 1.4608518 | E22: =E52*E7 -> 0.665434 | F22: =F52*F7 -> 0.5820932 | G22: =G52*G7 -> 0.6462666 | H22: =H52*H7 -> 0.7054992 | I22: =I52*I7 -> 0.7030287 | J22: =J52*J7 -> 0.88826463 | K22: =K52*K7 -> 0.8644581
B23: 45778 | C23: 9361 | D23: =D53*D8 -> 1.8961817 | E23: =E53*E8 -> 0.5591125 | F23: =F53*F8 -> 0.56955 | G23: =G53*G8 -> 0.6506058 | H23: =H53*H8 -> 0.63375 | I23: =I53*I8 -> 0.7579948 | J23: =J53*J8 -> 0.82952156
B24: 45809 | C24: 11532 | D24: =D54*D9 -> 1.7528336 | E24: =E54*E9 -> 0.6140502 | F24: =F54*F9 -> 0.6249074 | G24: =G54*G9 -> 0.6443554 | H24: =H54*H9 -> 0.74199324 | I24: =I54*I9 -> 0.77308957
B25: 45839 | C25: 17911 | D25: =D55*D10 -> 1.6568008 | E25: =E55*E10 -> 0.5914662 | F25: =F55*F10 -> 0.59315 | G25: =G55*G10 -> 0.7090302 | H25: =H55*H10 -> 0.75997938
B26: 45870 | C26: 34709 | D26: =D56*D11 -> 1.674972 | E26: =E56*E11 -> 0.6544314 | F26: =F56*F11 -> 0.71999576 | G26: =G56*G11 -> 0.7612017
B27: 45901 | C27: 48045 | D27: =D57*D12 -> 1.6156732 | E27: =E57*E12 -> 0.79657123 | F27: =F57*F12 -> 0.81157206
B28: =EOMONTH(B27,1) -> 45961 | C28: =C13 -> 82760 | D28: =D58*D13 -> 1.6457474 | E28: =E58*E13 -> 0.73279392
B29: =EOMONTH(B28,1) -> 45991 | C29: =C14 -> 86837 | D29: =D59*D14 -> 1.8416467
B30: =EOMONTH(B29,1) -> 46022 | C30: =C15 -> 102395 | D30: =D60*D15 -> 1.1535529
B32: Average Revenue Per User
B33: Month | C33: FTs | D33: 30 | E33: 60 | F33: 90 | G33: 120 | H33: 150 | I33: 180 | J33: 210 | K33: 240 | L33: 270 | M33: 300 | N33: 360
B34: 45658 | C34: 997 | D34: 622.73125 | E34: 560.463 | F34: 543.85099 | G34: 606.19668 | H34: 620.63602 | I34: 565.70819 | J34: 568.8386 | K34: 583.528 | L34: 671.151 | M34: 865.235 | N34: 844.297
B35: 45689 | C35: 1534 | D35: 602.35718 | E35: 505.71564 | F35: 599.69641 | G35: 561.19277 | H35: 543.49061 | I35: 514.66718 | J35: 669.117 | K35: 673.342 | L35: 748.577 | M35: 746.958
B36: 45717 | C36: 2546 | D36: 549.01505 | E36: 571.2223 | F36: 504.64815 | G36: 511.14697 | H36: 508.89439 | I36: 615.432 | J36: 665.233 | K36: 763.783 | L36: 726.243
B37: 45748 | C37: 3787 | D37: 546.37557 | E37: 527.6976 | F37: 497.86253 | G37: 495.7739 | H37: 589.072 | I37: 646.292 | J37: 707.75 | K37: 744.083
B38: 45778 | C38: 9361 | D38: 478.63597 | E38: 490.54682 | F38: 491.66711 | G38: 562.223 | H38: 601.551 | I38: 657.623 | J38: 659.977
B39: 45809 | C39: 11532 | D39: 457.11097 | E39: 478.47329 | F39: 533.887 | G39: 595.462 | H39: 602.881 | I39: 611.861
B40: 45839 | C40: 17911 | D40: 436.795 | E40: 518.266 | F40: 579.719 | G40: 638.087 | H40: 646.584
B41: 45870 | C41: 34709 | D41: 470.447 | E41: 591.007 | F41: 595.197 | G41: 616.558
B42: 45901 | C42: 48045 | D42: 515.24 | E42: 565.93 | F42: 613.512
B43: =B28 -> 45961 | C43: =C28 -> 82760 | D43: 536.756 | E43: 592.036
B44: =B29 -> 45991 | C44: =C29 -> 86837 | D44: 549.714
B45: =B30 -> 46022 | C45: =C30 -> 102395 | D45: 449.79
B47: Monthly Frequency
B48: Month | C48: FTs | D48: 30 | E48: 60 | F48: 90 | G48: 120 | H48: 150 | I48: 180 | J48: 210 | K48: 240 | L48: 270 | M48: 300 | N48: 360
B49: 45658 | C49: 997 | D49: 2.58753 | E49: 2.33033 | F49: 2.29276 | G49: 2.55594 | H49: 2.681 | I49: 2.49645 | J49: 2.62542 | K49: 2.58123 | L49: 2.6679 | M49: 3.465 | N49: 3.583
B50: 45689 | C50: 1534 | D50: 2.57096 | E50: 2.20654 | F50: 2.56541 | G50: 2.51643 | H50: 2.52703 | I50: 2.51029 | J50: 2.96957 | K50: 2.70488 | L50: 3.061 | M50: 3.26
B51: 45717 | C51: 2546 | D51: 2.40381 | E51: 2.4114 | F51: 2.23759 | G51: 2.29116 | H51: 2.41768 | I51: 2.72859 | J51: 2.71078 | K51: 3.066 | L51: 3.055
B52: 45748 | C52: 3787 | D52: 2.51871 | E52: 2.37655 | F52: 2.23882 | G52: 2.39358 | H52: 2.61296 | I52: 2.60381 | J52: 3.021 | K52: 3.19
B53: 45778 | C53: 9361 | D53: 2.40023 | E53: 2.23645 | F53: 2.2782 | G53: 2.50233 | H53: 2.4375 | I53: 2.78 | J53: 2.947
B54: 45809 | C54: 11532 | D54: 2.30636 | E54: 2.27426 | F54: 2.40349 | G54: 2.47829 | H54: 2.661 | I54: 2.783
B55: 45839 | C55: 17911 | D55: 2.23892 | E55: 2.27487 | F55: 2.3726 | G55: 2.69 | H55: 2.859
B56: 45870 | C56: 34709 | D56: 2.32635 | E56: 2.42382 | F56: 2.581 | G56: 2.751
B57: 45901 | C57: 48045 | D57: 2.37599 | E57: 2.483 | F57: 2.766
B58: =B43 -> 45961 | C58: =C43 -> 82760 | D58: 2.421 | E58: 2.616
B59: =B44 -> 45991 | C59: =C44 -> 86837 | D59: 2.588
B60: =B45 -> 46022 | C60: =C45 -> 102395 | D60: 2.131
B62: No of Orders by First Time Customers
B63: Month | C63: FTs | D63: 30 | E63: 60 | F63: 90 | G63: 120 | H63: 150 | I63: 180 | J63: 210 | K63: 240 | L63: 270 | M63: 300 | N63: 360
B64: 45658 | C64: 997 | D64: =C64*D4*D49 -> 1109.3 | E64: =D64*E4*E49 -> 878.91191 | F64: =E64*F4*F49 -> 624.69156 | G64: =F64*G4*G49 -> 479.00225 | H64: =G64*H4*H49 -> 372.41946 | I64: =H64*I4*I49 -> 269.6207 | J64: =I64*J4*J49 -> 219.43895 | K64: =J64*K4*K49 -> 164.2625 | ... N64: =M64*N4*N49 -> 137.65676
B65: 45689 | C65: 1534 | D65: =C65*D5*D50 -> 1538.1025 | E65: =D65*E5*E50 -> 1052.1043 | F65: =E65*F5*F50 -> 755.74207 | G65: =F65*G5*G50 -> 513.47845 | H65: =G65*H5*H50 -> 363.32112 | I65: =H65*I5*I50 -> 282.73283 | J65: =I65*J5*J50 -> 243.48253 | K65: =J65*K5*K50 -> 197.57731 | ... M65: =L65*M5*M50 -> 174.19273
B66: 45717 | C66: 2546 | D66: =C66*D6*D51 -> 2264.4371 | E66: =D66*E6*E51 -> 1310.5113 | F66: =E66*F6*F51 -> 733.09673 | G66: =F66*G6*G51 -> 403.11406 | H66: =G66*H6*H51 -> 233.90419 | I66: =H66*I6*I51 -> 165.93944 | J66: =I66*J6*J51 -> 121.45284 | K66: =J66*K6*K51 -> 101.35286 | L66: =K66*L6*L51 -> 79.659282
B67: 45748 | C67: 3787 | D67: =C67*D7*D52 -> 5532.2458 | E67: =D67*E7*E52 -> 3681.3444 | F67: =E67*F7*F52 -> 2142.8856 | G67: =F67*G7*G52 -> 1384.8754 | H67: =G67*H7*H52 -> 977.02846 | I67: =H67*I7*I52 -> 686.87905 | J67: =I67*J7*J52 -> 610.13036 | K67: =J67*K7*K52 -> 527.43214
B68: 45778 | C68: 9361 | D68: =C68*D8*D53 -> 17750.157 | E68: =D68*E8*E53 -> 9924.3346 | F68: =E68*F8*F53 -> 5652.4048 | G68: =F68*G8*G53 -> 3677.4873 | H68: =G68*H8*H53 -> 2330.6076 | I68: =H68*I8*I53 -> 1766.5884 | J68: =I68*J8*J53 -> 1465.4232
B69: 45809 | C69: 11532 | D69: =C69*D9*D54 -> 20213.677 | E69: =D69*E9*E54 -> 12412.212 | F69: =E69*F9*F54 -> 7756.4834 | G69: =F69*G9*G54 -> 4997.932 | H69: =G69*H9*H54 -> 3708.4317 | I69: =H69*I9*I54 -> 2866.9499
B70: 45839 | C70: 17911 | D70: =C70*D10*D55 -> 29674.959 | E70: =D70*E10*E55 -> 17551.735 | F70: =E70*F10*F55 -> 10410.812 | G70: =F70*G10*G55 -> 7381.58 | H70: =G70*H10*H55 -> 5609.8486
B71: 45870 | C71: 34709 | D71: =C71*D11*D56 -> 58136.603 | E71: =D71*E11*E56 -> 38046.419 | F71: =E71*F11*F56 -> 27393.26 | G71: =F71*G11*G56 -> 20851.796
B72: 45901 | C72: 48045 | D72: =C72*D12*D57 -> 77625.019 | E72: =D72*E12*E57 -> 61833.857 | F72: =E72*F12*F57 -> 50182.631
B73: =B58 -> 45961 | C73: =C58 -> 82760 | D73: =C73*D13*D58 -> 136202.05 | E73: =D73*E13*E58 -> 99808.036
B74: =B59 -> 45991 | C74: =C59 -> 86837 | D74: =C74*D14*D59 -> 159923.07
B75: =B60 -> 46022 | C75: =C60 -> 102395 | D75: =C75*D15*D60 -> 118118.05

Sheet Financials ->

Sheet MIS P&L
B2: Jobs | C2: ='Key Metrics'!C14 -> 6863 | D2: ='Key Metrics'!D14 -> 7519 | E2: ='Key Metrics'!E14 -> 10642 | F2: ='Key Metrics'!F14 -> 14980 | G2: ='Key Metrics'!G14 -> 35189 | H2: ='Key Metrics'!H14 -> 47211 | I2: ='Key Metrics'!I14 -> 68196 | J2: ='Key Metrics'!J14 -> 118808 | ... N2: ='Key Metrics'!N14 -> 518345
B3: Hours | C3: ='Key Metrics'!C23 -> 9144.75 | D3: ='Key Metrics'!D23 -> 9603 | E3: ='Key Metrics'!E23 -> 13457.25 | F3: ='Key Metrics'!F23 -> 18463 | G3: ='Key Metrics'!G23 -> 41475.5 | H3: ='Key Metrics'!H23 -> 54875 | I3: ='Key Metrics'!I23 -> 79269.5 | J3: ='Key Metrics'!J23 -> 145034 | ... N3: ='Key Metrics'!N23 -> 648259.75
B5: Profit & Loss Statement | C5: Actual | D5: Actual | E5: Actual | F5: Actual | G5: Actual | H5: Actual | I5: Actual | J5: Actual | K5: Actual | L5: Actual | M5: Actual | N5: Actual
B6: All Values (in INR Thousands) | C6: 45658 | D6: 45689 | E6: 45717 | F6: 45748 | G6: 45778 | H6: 45809 | I6: 45839 | J6: 45870 | K6: 45901 | L6: 45931 | M6: 45962 | N6: 45992
B7: Revenue | C7: =-SUMIF('TB 0125'!H:H,'MIS P&L'!B7,'TB 0125'!F:F)+C10 -> 1685.4178 | D7: =-SUMIF('TB 0225'!H:H,'MIS P&L'!B7,'TB 0225'!F:F)+D10 -> 1752.6994 | E7: =-SUMIF('TB 0325'!H:H,'MIS P&L'!B7,'TB 0325'!F:F)+E10 -> 2454.9928 | F7: =-SUMIF('TB 0425'!H:H,'MIS P&L'!B7,'TB 0425'!F:F)+F10 -> 3379.7516 | G7: =-SUMIF('TB 0525'!H:H,'MIS P&L'!B7,'TB 0525'!F:F)+G10-752 -> 7565.0949 | H7: =-SUMIF('TB 0625'!H:H,'MIS P&L'!B7,'TB 0625'!F:F)+H10 -> 10327.934 | I7: =-SUMIF('TB 0725'!H:H,'MIS P&L'!B7,'TB 0725'!F:F)+I10 -> 14930.412 | J7: =-SUMIF('TB 0825'!H:H,'MIS P&L'!B7,'TB 0825'!F:F)+J10 -> 27555.775 | K7: =-SUMIF('TB 0925'!H:H,'MIS P&L'!B7,'TB 0925'!F:F)+K10 -> 37606.66 | L7: =-SUMIF('TB 1025'!H:H,'MIS P&L'!B7,'TB 1025'!F:F)+L10 -> 74251.551 | M7: =-SUMIF('TB 1125'!H:H,'MIS P&L'!B7,'TB 1125'!F:F)+M10-'TB 1125'!P6/10^3 -> 84625.473 | N7: =-SUMIF('TB 1225'!H:H,'MIS P&L'!B7,'TB 1225'!F:F)+N10-('TB 1225'!P6-'TB 1225'!P7)/10^3 -> 116769.39
B8: Service Cost | C8: =SUMIF('TB 0125'!H:H,'MIS P&L'!B8,'TB 0125'!F:F) -> 1316.7668 | D8: =SUMIF('TB 0225'!H:H,'MIS P&L'!B8,'TB 0225'!F:F)+SUMIF('TB 0225'!H:H,"Service Cost - Retention Bonus",'TB 0225'!F:F) -> 1808.5563 | E8: =SUMIF('TB 0325'!H:H,'MIS P&L'!B8,'TB 0325'!F:F) -> 2377.6725 | F8: =SUMIF('TB 0425'!H:H,'MIS P&L'!B8,'TB 0425'!F:F) -> 4666.3881 | G8: =SUMIF('TB 0525'!H:H,'MIS P&L'!B8,'TB 0525'!F:F)+SUMIF('TB 0525'!H:H,"Service Cost - Retention Bonus",'TB 0525'!F:F) -> 10125.432 | H8: =SUMIF('TB 0625'!H:H,'MIS P&L'!B8,'TB 0625'!F:F) -> 16194.053 | I8: =SUMIF('TB 0725'!H:H,'MIS P&L'!B8,'TB 0725'!F:F) -> 20797.581 | J8: =SUMIF('TB 0825'!H:H,'MIS P&L'!B8,'TB 0825'!F:F) -> 34898.162 | K8: =SUMIF('TB 0925'!H:H,'MIS P&L'!B8,'TB 0925'!F:F) -> 42682.555 | L8: =SUMIF('TB 1025'!H:H,'MIS P&L'!B8,'TB 1025'!F:F) -> 80446.599 | M8: =SUMIF('TB 1125'!H:H,'MIS P&L'!B8,'TB 1125'!F:F)+1369000/10^3 -> 93364.573 | N8: =SUMIF('TB 1225'!H:H,'MIS P&L'!B8,'TB 1225'!F:F)+(2942373-123559)/10^3 -> 135426.75
B10: GST | C10: =111458.172629155/1000 -> 111.45817 | D10: =107088.778644068/1000 -> 107.08878 | E10: =145719.332747025/1000 -> 145.71933 | F10: 219.01183 | G10: =497429.94/10^3 -> 497.42994 | H10: =(679045.32-4262)/10^3 -> 674.78332 | I10: =993199.47 /10^3 -> 993.19947 | J10: 1826.7527 | K10: 2192.292 | L10: 3096.4967 | M10: =('TB 1125'!P5)/10^3 -> 3640.6934 | N10: =('TB 1225'!P5)/10^3 -> 5073.8874
B11: Promotional Discount | C11: =47693/1000 -> 47.693 | D11: =68323/1000 -> 68.323 | E11: =SUMIF('TB 0325'!H:H,'MIS P&L'!B11,'TB 0325'!F:F) -> 21.936 | F11: 33.51 | G11: 19.7 | H11: 43.827 | I11: 347.81305 | J11: 1169.488 | K11: 2266.901 | L11: 8631.1562 | M11: 12771.043 | N11: 20491.281
B12: Payment Gateway Cost | C12: =SUMIF('TB 0125'!H:H,'MIS P&L'!B12,'TB 0125'!F:F) -> 18.29068 | D12: =SUMIF('TB 0225'!H:H,'MIS P&L'!B12,'TB 0225'!F:F) -> 17.08784 | E12: =SUMIF('TB 0325'!H:H,'MIS P&L'!B12,'TB 0325'!F:F) -> 21.41301 | F12: =SUMIF('TB 0425'!H:H,'MIS P&L'!B12,'TB 0425'!F:F) -> 32.4381 | G12: =SUMIF('TB 0525'!H:H,'MIS P&L'!B12,'TB 0525'!F:F) -> 23.14003 | H12: =SUMIF('TB 0625'!H:H,'MIS P&L'!B12,'TB 0625'!F:F) -> 33.76314 | I12: =SUMIF('TB 0725'!H:H,'MIS P&L'!B12,'TB 0725'!F:F) -> 46.5271 | J12: =SUMIF('TB 0825'!H:H,'MIS P&L'!B12,'TB 0825'!F:F) -> 49.71843 | K12: =SUMIF('TB 0925'!H:H,'MIS P&L'!B12,'TB 0925'!F:F) -> 59.90393 | L12: =SUMIF('TB 1025'!H:H,'MIS P&L'!B12,'TB 1025'!F:F) -> 92.65611 | M12: =SUMIF('TB 1125'!H:H,'MIS P&L'!B12,'TB 1125'!F:F) -> 115.36249 | N12: =SUMIF('TB 1225'!H:H,'MIS P&L'!B12,'TB 1225'!F:F) -> 173.99614
B14: Gross Profit | C14: =C7-C8-C10-C11-C12 -> 191.20923 | D14: =D7-D8-D10-D11-D12 -> -248.35645 | E14: =E7-E8-E10-E11-E12 -> -111.74799 | F14: =F7-F8-F10-F11-F12 -> -1571.5964 | G14: =G7-G8-G10-G11-G12 -> -3100.6073 | H14: =H7-H8-H10-H11-H12 -> -6618.493 | I14: =I7-I8-I10-I11-I12 -> -7254.709 | J14: =J7-J8-J10-J11-J12 -> -10388.346 | ... N14: =N7-N8-N10-N11-N12 -> -44396.531
B15: Gross Profit % | C15: =C14/C7 -> 0.11344916 | D15: =D14/D7 -> -0.1416994 | E15: =E14/E7 -> -0.045518663 | F15: =F14/F7 -> -0.46500352 | G15: =G14/G7 -> -0.40985703 | H15: =H14/H7 -> -0.64083419 | I15: =I14/I7 -> -0.48590146 | J15: =J14/J7 -> -0.37699343 | ... N15: =N14/N7 -> -0.38020694
B17: Training Centre Expenses | C17: =SUMIF('TB 0125'!H:H,'MIS P&L'!B17,'TB 0125'!F:F)+'TB 0125'!R8 -> 154.42806 | D17: =SUMIF('TB 0225'!H:H,'MIS P&L'!B17,'TB 0225'!F:F)+'TB 0225'!P8 -> 555.65933 | E17: =SUMIF('TB 0325'!H:H,'MIS P&L'!B17,'TB 0325'!F:F)+'TB 0325'!P7 -> 378.59594 | F17: =SUMIF('TB 0425'!H:H,'MIS P&L'!B17,'TB 0425'!F:F)+'TB 0425'!R7 -> 1071.6243 | G17: =SUMIF('TB 0525'!H:H,'MIS P&L'!B17,'TB 0525'!F:F)+'TB 0525'!R4-28 -> 2121.5457 | H17: =SUMIF('TB 0625'!H:H,'MIS P&L'!B17,'TB 0625'!F:F)+'TB 0625'!M5 -> 1839.1313 | I17: =SUMIF('TB 0725'!H:H,'MIS P&L'!B17,'TB 0725'!F:F)+'TB 0725'!L5 -> 2130.1765 | J17: =SUMIF('TB 0825'!H:H,'MIS P&L'!B17,'TB 0825'!F:F)+'TB 0825'!L5 -> 2395.6542 | K17: =SUMIF('TB 0925'!H:H,'MIS P&L'!B17,'TB 0925'!F:F)+'TB 0925'!M6 -> 2327.5014 | L17: =SUMIF('TB 1025'!H:H,'MIS P&L'!B17,'TB 1025'!F:F)+'TB 1025'!M6 -> 4509.7977 | M17: =SUMIF('TB 1125'!H:H,'MIS P&L'!B17,'TB 1125'!F:F)+'TB 1125'!M6 -> 4659.3912 | N17: =SUMIF('TB 1225'!H:H,'MIS P&L'!B17,'TB 1225'!F:F)+'TB 1225'!M6 -> 5498.3315
B18: Managerial Cost | C18: =SUMIF('TB 0125'!H:H,'MIS P&L'!B18,'TB 0125'!F:F)+'TB 0125'!R4 -> 135.548 | D18: =SUMIF('TB 0225'!H:H,'MIS P&L'!B18,'TB 0225'!F:F)+'TB 0225'!P4 -> 249.681 | E18: =SUMIF('TB 0325'!H:H,'MIS P&L'!B18,'TB 0325'!F:F)+'TB 0325'!P3 -> 436.977 | F18: =SUMIF('TB 0425'!H:H,'MIS P&L'!B18,'TB 0425'!F:F)+'TB 0425'!R3 -> 913.946 | G18: =SUMIF('TB 0525'!H:H,'MIS P&L'!B18,'TB 0525'!F:F)+'TB 0525'!R6 -> 1372.664 | H18: =SUMIF('TB 0625'!H:H,'MIS P&L'!B18,'TB 0625'!F:F)+'TB 0625'!M6 -> 1974.5513 | I18: =SUMIF('TB 0725'!H:H,'MIS P&L'!B18,'TB 0725'!F:F)+'TB 0725'!L4 -> 2871.9352 | J18: =SUMIF('TB 0825'!H:H,'MIS P&L'!B18,'TB 0825'!F:F)+'TB 0825'!L4 -> 4358.6587 | K18: =SUMIF('TB 0925'!H:H,'MIS P&L'!B18,'TB 0925'!F:F)+'TB 0925'!M4 -> 5433.6316 | L18: =SUMIF('TB 1025'!H:H,'MIS P&L'!B18,'TB 1025'!F:F)+'TB 1025'!M4 -> 5889.8775 | M18: =SUMIF('TB 1125'!H:H,'MIS P&L'!B18,'TB 1125'!F:F)+'TB 1125'!M4 -> 5830.2844 | N18: =SUMIF('TB 1225'!H:H,'MIS P&L'!B18,'TB 1225'!F:F)+'TB 1225'!M4 -> 7442.0085
B19: Sourcing & Onboarding Cost | C19: =SUMIF('TB 0125'!H:H,'MIS P&L'!B19,'TB 0125'!F:F)+'TB 0125'!R7 -> 265.24942 | D19: =SUMIF('TB 0225'!H:H,'MIS P&L'!B19,'TB 0225'!F:F)+'TB 0225'!P7 -> 489.45735 | E19: =SUMIF('TB 0325'!H:H,'MIS P&L'!B19,'TB 0325'!F:F)+'TB 0325'!P6 -> 968.60079 | F19: =SUMIF('TB 0425'!H:H,'MIS P&L'!B19,'TB 0425'!F:F)+'TB 0425'!R6 -> 1469.4468 | G19: =SUMIF('TB 0525'!H:H,'MIS P&L'!B19,'TB 0525'!F:F)+'TB 0525'!R7 -> 1820.524 | H19: =SUMIF('TB 0625'!H:H,'MIS P&L'!B19,'TB 0625'!F:F)+'TB 0625'!M4 -> 4666.5157 | I19: =SUMIF('TB 0725'!H:H,'MIS P&L'!B19,'TB 0725'!F:F)+'TB 0725'!L6 -> 4715.0503 | J19: =SUMIF('TB 0825'!H:H,'MIS P&L'!B19,'TB 0825'!F:F)+'TB 0825'!L6 -> 6769.6192 | K19: =SUMIF('TB 0925'!H:H,'MIS P&L'!B19,'TB 0925'!F:F)+'TB 0925'!M5 -> 9609.5003 | L19: =SUMIF('TB 1025'!H:H,'MIS P&L'!B19,'TB 1025'!F:F)+'TB 1025'!M5 -> 13533.116 | M19: =SUMIF('TB 1125'!H:H,'MIS P&L'!B19,'TB 1125'!F:F)+'TB 1125'!M5-1369000/10^3 -> 13377.681 | N19: =SUMIF('TB 1225'!H:H,'MIS P&L'!B19,'TB 1225'!F:F)+'TB 1225'!M5-(2942373-123559)/10^3 -> 17626.83
B20: Customer Success Cost | C20: =SUMIF('TB 0125'!H:H,'MIS P&L'!B20,'TB 0125'!F:F)+'TB 0125'!R6 -> 77.612 | D20: =SUMIF('TB 0225'!H:H,'MIS P&L'!B20,'TB 0225'!F:F)+'TB 0225'!P6 -> 54 | E20: =SUMIF('TB 0325'!H:H,'MIS P&L'!B20,'TB 0325'!F:F)+'TB 0325'!P5 -> 214.423 | F20: =SUMIF('TB 0425'!H:H,'MIS P&L'!B20,'TB 0425'!F:F)+'TB 0425'!R5 -> 351.328 | G20: =SUMIF('TB 0525'!H:H,'MIS P&L'!B20,'TB 0525'!F:F)+'TB 0525'!R5 -> 622.162 | H20: =SUMIF('TB 0625'!H:H,'MIS P&L'!B20,'TB 0625'!F:F)+'TB 0625'!M7 -> 689.12637 | I20: =SUMIF('TB 0725'!H:H,'MIS P&L'!B20,'TB 0725'!F:F)+'TB 0725'!L7 -> 653.00077 | J20: =SUMIF('TB 0825'!H:H,'MIS P&L'!B20,'TB 0825'!F:F)+'TB 0825'!L7 -> 772.37655 | K20: =SUMIF('TB 0925'!H:H,'MIS P&L'!B20,'TB 0925'!F:F)+'TB 0925'!M3 -> 872.25708 | L20: =SUMIF('TB 1025'!H:H,'MIS P&L'!B20,'TB 1025'!F:F)+'TB 1025'!M3 -> 1664.9577 | M20: =SUMIF('TB 1125'!H:H,'MIS P&L'!B20,'TB 1125'!F:F)+'TB 1125'!M3 -> 2306.0512 | N20: =SUMIF('TB 1225'!H:H,'MIS P&L'!B20,'TB 1225'!F:F)+'TB 1225'!M3 -> 2942.72
B21: Operational Cost | C21: 0 | D21: 0 | E21: 0 | F21: =SUMIF('TB 0425'!H:H,'MIS P&L'!B21,'TB 0425'!F:F) -> 99.31976 | G21: =SUMIF('TB 0525'!H:H,'MIS P&L'!B21,'TB 0525'!F:F)+28 -> 468.69315 | H21: =SUMIF('TB 0625'!H:H,'MIS P&L'!B21,'TB 0625'!F:F) -> 1297.7536 | I21: =SUMIF('TB 0725'!H:H,'MIS P&L'!B21,'TB 0725'!F:F) -> 2435.4273 | J21: =SUMIF('TB 0825'!H:H,'MIS P&L'!B21,'TB 0825'!F:F) -> 1928.288 | K21: =SUMIF('TB 0925'!H:H,'MIS P&L'!B21,'TB 0925'!F:F) -> 725.32188 | L21: =SUMIF('TB 1025'!H:H,'MIS P&L'!B21,'TB 1025'!F:F) -> 1037.1374 | M21: =SUMIF('TB 1125'!H:H,'MIS P&L'!B21,'TB 1125'!F:F) -> 1046.1692 | N21: =SUMIF('TB 1225'!H:H,'MIS P&L'!B21,'TB 1225'!F:F) -> 725.16
B23: Operating Profit | C23: =C14-SUM(C17:C21) -> -441.62825 | D23: =D14-SUM(D17:D21) -> -1597.1541 | E23: =E14-SUM(E17:E21) -> -2110.3447 | F23: =F14-SUM(F17:F21) -> -5477.2612 | G23: =G14-SUM(G17:G21) -> -9506.1962 | H23: =H14-SUM(H17:H21) -> -17085.571 | I23: =I14-SUM(I17:I21) -> -20060.299 | J23: =J14-SUM(J17:J21) -> -26612.943 | ... N23: =N14-SUM(N17:N21) -> -78631.581
B24: Operating Profit % | C24: =C23/C7 -> -0.26202894 | D24: =D23/D7 -> -0.91125387 | E24: =E23/E7 -> -0.8596134 | F24: =F23/F7 -> -1.6206106 | G24: =G23/G7 -> -1.2565865 | H24: =H23/H7 -> -1.6543068 | I24: =I23/I7 -> -1.3435864 | J24: =J23/J7 -> -0.96578458 | ... N24: =N23/N7 -> -0.67339208
B26: Marketing Cost | C26: =SUM(C27:C29) -> 876.16473 | D26: =SUM(D27:D29) -> 1322.9 | E26: =SUM(E27:E29) -> 1588.0344 | F26: =SUM(F27:F29) -> 2636.4766 | G26: =SUM(G27:G29) -> 6211.2232 | H26: =SUM(H27:H29) -> 10479.127 | I26: =SUM(I27:I29) -> 17024.858 | J26: =SUM(J27:J29) -> 35615.457 | ... N26: =SUM(N27:N29) -> 90196.321
B27: Customer Acquisition Cost (Digital & BTL Marketing) | C27: =SUMIF('TB 0125'!H:H,'MIS P&L'!B27,'TB 0125'!F:F)+'TB 0125'!R5 -> 611.77973 | D27: =SUMIF('TB 0225'!H:H,'MIS P&L'!B27,'TB 0225'!F:F)+'TB 0225'!P5 -> 669.825 | E27: =SUMIF('TB 0325'!H:H,'MIS P&L'!B27,'TB 0325'!F:F)+'TB 0325'!P4 -> 863.641 | F27: =SUMIF('TB 0425'!H:H,'MIS P&L'!B27,'TB 0425'!F:F)+'TB 0425'!R4 -> 1339.3396 | G27: =SUMIF('TB 0525'!H:H,'MIS P&L'!B27,'TB 0525'!F:F) -> 3005.0652 | H27: =SUMIF('TB 0625'!H:H,'MIS P&L'!B27,'TB 0625'!F:F) -> 5817.5286 | I27: =SUMIF('TB 0725'!H:H,'MIS P&L'!B27,'TB 0725'!F:F) -> 7135.4089 | J27: =SUMIF('TB 0825'!H:H,'MIS P&L'!B27,'TB 0825'!F:F) -> 17875.963 | K27: =SUMIF('TB 0925'!H:H,'MIS P&L'!B27,'TB 0925'!F:F) -> 23474.935 | L27: =SUMIF('TB 1025'!H:H,'MIS P&L'!B27,'TB 1025'!F:F) -> 21563.45 | M27: =SUMIF('TB 1125'!H:H,'MIS P&L'!B27,'TB 1125'!F:F) -> 31021.673 | N27: =SUMIF('TB 1225'!H:H,'MIS P&L'!B27,'TB 1225'!F:F) -> 39731.204
B28: Branding Expense | C28: =SUMIF('TB 0125'!H:H,'MIS P&L'!B28,'TB 0125'!F:F) -> 81.59 | D28: =SUMIF('TB 0225'!H:H,'MIS P&L'!B28,'TB 0225'!F:F) -> 351.67 | E28: =SUMIF('TB 0325'!H:H,'MIS P&L'!B28,'TB 0325'!F:F) -> 68.02636 | F28: =SUMIF('TB 0425'!H:H,'MIS P&L'!B28,'TB 0425'!F:F) -> 427.385 | G28: =SUMIF('TB 0525'!H:H,'MIS P&L'!B28,'TB 0525'!F:F) -> 395 | H28: =SUMIF('TB 0625'!H:H,'MIS P&L'!B28,'TB 0625'!F:F) -> 576.15 | I28: =SUMIF('TB 0725'!H:H,'MIS P&L'!B28,'TB 0725'!F:F) -> 4461.049 | J28: =SUMIF('TB 0825'!H:H,'MIS P&L'!B28,'TB 0825'!F:F) -> 9270.918 | K28: =SUMIF('TB 0925'!H:H,'MIS P&L'!B28,'TB 0925'!F:F) -> 6044.993 | L28: =SUMIF('TB 1025'!H:H,'MIS P&L'!B28,'TB 1025'!F:F) -> 13300 | M28: =SUMIF('TB 1125'!H:H,'MIS P&L'!B28,'TB 1125'!F:F) -> 12253.526 | N28: =SUMIF('TB 1225'!H:H,'MIS P&L'!B28,'TB 1225'!F:F) -> 16041.3
B29: New User Discount (incl. Early Lifecycle Coupons & Referral Discount) | C29: =SUMIF('TB 0125'!H:H,'MIS P&L'!B29,'TB 0125'!F:F)+(79586/1000) -> 182.795 | D29: =SUMIF('TB 0225'!H:H,'MIS P&L'!B29,'TB 0225'!F:F)+(183118/1000) -> 301.405 | E29: =SUMIF('TB 0325'!H:H,'MIS P&L'!B29,'TB 0325'!F:F) -> 656.367 | F29: =SUMIF('TB 0425'!H:H,'MIS P&L'!B29,'TB 0425'!F:F)+(771680/1000) -> 869.752 | G29: =SUMIF('TB 0525'!H:H,'MIS P&L'!B29,'TB 0525'!F:F)+3344.989-752 -> 2811.158 | H29: =SUMIF('TB 0625'!H:H,'MIS P&L'!B29,'TB 0625'!F:F)+(5295962/10^3) -> 4085.448 | I29: =SUMIF('TB 0725'!H:H,'MIS P&L'!B29,'TB 0725'!F:F)+(6771408/10^3)+194.334 -> 5428.4001 | J29: =SUMIF('TB 0825'!H:H,'MIS P&L'!B29,'TB 0825'!F:F)+(9030.74944)+(34.71)+1714.962 -> 8468.5754 | K29: =SUMIF('TB 0925'!H:H,'MIS P&L'!B29,'TB 0925'!F:F)+(10998155/10^3)+4768.292 -> 13344.87 | L29: =SUMIF('TB 1025'!H:H,'MIS P&L'!B29,'TB 1025'!F:F)+(17286475.84/10^3)+14447.575 -> 28938.289 | M29: =('TB 1125'!S6/10^3)+SUMIF('TB 1125'!H:H,'MIS P&L'!B29,'TB 1125'!F:F)-'TB 1125'!P6/10^3+17129.742 -> 28419.663 | N29: =SUMIF('TB 1225'!H:H,'MIS P&L'!B29,'TB 1225'!F:F)+('TB 1225'!S6+'TB 1225'!S7)/10^3-('TB 1225'!P6-'TB 1225'!P7)/10^3+20790.947 -> 34423.818
B30: Employee Cost | C30: =SUM(C31:C32) -> 3092.8646 | D30: =SUM(D31:D32) -> 6606.2401 | E30: =SUM(E31:E32) -> 9142.0608 | F30: =SUM(F31:F32) -> 12823.778 | G30: =SUM(G31:G32) -> 16357.029 | H30: =SUM(H31:H32) -> 19256.697 | I30: =SUM(I31:I32) -> 22548.296 | J30: =SUM(J31:J32) -> 24500.942 | ... N30: =SUM(N31:N32) -> 45768.018
B31: Employee Cost | C31: =SUMIF('TB 0125'!H:H,'MIS P&L'!B30,'TB 0125'!F:F)+'TB 0125'!R3 -> 3092.8646 | D31: =SUMIF('TB 0225'!H:H,'MIS P&L'!B30,'TB 0225'!F:F)+'TB 0225'!P3 -> 4532.2401 | E31: =SUMIF('TB 0325'!H:H,'MIS P&L'!B30,'TB 0325'!F:F)+'TB 0325'!P8 -> 8965.1278 | F31: =SUMIF('TB 0425'!H:H,'MIS P&L'!B30,'TB 0425'!F:F)+'TB 0425'!R8 -> 12713.778 | G31: =SUMIF('TB 0525'!H:H,'MIS P&L'!B30,'TB 0525'!F:F)+'TB 0525'!R3 -> 15651.703 | H31: =SUMIF('TB 0625'!H:H,'MIS P&L'!B30,'TB 0625'!F:F)+'TB 0625'!M3+'TB 0625'!M8+'TB 0625'!M9 -> 19018.079 | I31: =SUMIF('TB 0725'!H:H,'MIS P&L'!B31,'TB 0725'!F:F)+'TB 0725'!L3+'TB 0725'!L8+'TB 0725'!L9 -> 21513.096 | J31: =SUMIF('TB 0825'!H:H,'MIS P&L'!B31,'TB 0825'!F:F)+'TB 0825'!L3+'TB 0825'!L8+'TB 0825'!L9 -> 24158.767 | K31: =SUMIF('TB 0925'!H:H,'MIS P&L'!B31,'TB 0925'!F:F)+'TB 0925'!M7+'TB 0925'!M8+'TB 0925'!M9 -> 26039.959 | L31: =SUMIF('TB 1025'!H:H,'MIS P&L'!B31,'TB 1025'!F:F)+'TB 1025'!M7+'TB 1025'!M8+'TB 1025'!M9 -> 35040.783 | M31: =SUMIF('TB 1125'!H:H,'MIS P&L'!B31,'TB 1125'!F:F)+'TB 1125'!M7+'TB 1125'!M8+'TB 1125'!M9 -> 39255.002 | N31: =SUMIF('TB 1225'!H:H,'MIS P&L'!B31,'TB 1225'!F:F)+'TB 1225'!M7+'TB 1225'!M8+'TB 1225'!M9 -> 45501.106
B32: Recruitment Cost | C32: 0 | D32: =SUMIF('TB 0225'!H:H,'MIS P&L'!B32,'TB 0225'!F:F) -> 2074 | E32: =SUMIF('TB 0325'!H:H,'MIS P&L'!B32,'TB 0325'!F:F) -> 176.933 | F32: =SUMIF('TB 0425'!H:H,'MIS P&L'!B32,'TB 0425'!F:F) -> 110 | G32: =SUMIF('TB 0525'!H:H,'MIS P&L'!B32,'TB 0525'!F:F) -> 705.326 | H32: =SUMIF('TB 0625'!H:H,'MIS P&L'!B32,'TB 0625'!F:F) -> 238.618 | I32: =SUMIF('TB 0725'!H:H,'MIS P&L'!B32,'TB 0725'!F:F) -> 1035.2 | J32: =SUMIF('TB 0825'!H:H,'MIS P&L'!B32,'TB 0825'!F:F) -> 342.175 | K32: =SUMIF('TB 0925'!H:H,'MIS P&L'!B32,'TB 0925'!F:F) -> 2 | L32: =SUMIF('TB 1025'!H:H,'MIS P&L'!B32,'TB 1025'!F:F) -> 147.942 | M32: =SUMIF('TB 1125'!H:H,'MIS P&L'!B32,'TB 1125'!F:F) -> 67.95 | N32: =SUMIF('TB 1225'!H:H,'MIS P&L'!B32,'TB 1225'!F:F) -> 266.912
B33: Tech Cost | C33: =SUMIF('TB 0125'!H:H,'MIS P&L'!B33,'TB 0125'!F:F) -> 373.25872 | D33: =SUMIF('TB 0225'!H:H,'MIS P&L'!B33,'TB 0225'!F:F) -> 518.67665 | E33: =SUMIF('TB 0325'!H:H,'MIS P&L'!B33,'TB 0325'!F:F) -> 549.93001 | F33: =SUMIF('TB 0425'!H:H,'MIS P&L'!B33,'TB 0425'!F:F) -> 1044.1697 | G33: =SUMIF('TB 0525'!H:H,'MIS P&L'!B33,'TB 0525'!F:F) -> 1383.7629 | H33: =SUMIF('TB 0625'!H:H,'MIS P&L'!B33,'TB 0625'!F:F) -> 1711.9282 | I33: =SUMIF('TB 0725'!H:H,'MIS P&L'!B33,'TB 0725'!F:F) -> 1849.1917 | J33: =SUMIF('TB 0825'!H:H,'MIS P&L'!B33,'TB 0825'!F:F) -> 2314.7726 | K33: =SUMIF('TB 0925'!H:H,'MIS P&L'!B33,'TB 0925'!F:F) -> 2765.2969 | L33: =SUMIF('TB 1025'!H:H,'MIS P&L'!B33,'TB 1025'!F:F) -> 3971.0149 | M33: =SUMIF('TB 1125'!H:H,'MIS P&L'!B33,'TB 1125'!F:F) -> 3401.2811 | N33: =SUMIF('TB 1225'!H:H,'MIS P&L'!B33,'TB 1225'!F:F) -> 2866.5096
B34: Other Costs | C34: =SUM(C35:C37) -> 487.48961 | D34: =SUM(D35:D37) -> 711.6444 | E34: =SUM(E35:E37) -> 860.95439 | F34: =SUM(F35:F37) -> 657.09742 | G34: =SUM(G35:G37) -> 1377.6578 | H34: =SUM(H35:H37) -> 1663.7004 | I34: =SUM(I35:I37) -> 2264.6548 | J34: =SUM(J35:J37) -> 2190.7756 | ... N34: =SUM(N35:N37) -> 5430.6649
B35: Professional Fees | C35: =SUMIF('TB 0125'!H:H,'MIS P&L'!B35,'TB 0125'!F:F) -> 109 | D35: =SUMIF('TB 0225'!H:H,'MIS P&L'!B35,'TB 0225'!F:F) -> 109 | E35: =SUMIF('TB 0325'!H:H,'MIS P&L'!B35,'TB 0325'!F:F) -> 237.58 | F35: =SUMIF('TB 0425'!H:H,'MIS P&L'!B35,'TB 0425'!F:F) -> 128.23 | G35: =SUMIF('TB 0525'!H:H,'MIS P&L'!B35,'TB 0525'!F:F) -> 440 | H35: =SUMIF('TB 0625'!H:H,'MIS P&L'!B35,'TB 0625'!F:F) -> 377.24 | I35: =SUMIF('TB 0725'!H:H,'MIS P&L'!B35,'TB 0725'!F:F) -> 750.95 | J35: =SUMIF('TB 0825'!H:H,'MIS P&L'!B35,'TB 0825'!F:F) -> 772.735 | K35: =SUMIF('TB 0925'!H:H,'MIS P&L'!B35,'TB 0925'!F:F) -> 794.13966 | L35: =SUMIF('TB 1025'!H:H,'MIS P&L'!B35,'TB 1025'!F:F) -> 1258.35 | M35: =SUMIF('TB 1125'!H:H,'MIS P&L'!B35,'TB 1125'!F:F) -> 2211.437 | N35: =SUMIF('TB 1225'!H:H,'MIS P&L'!B35,'TB 1225'!F:F) -> 3080.8271
B36: Office and Admin Expenses | C36: =SUMIF('TB 0125'!H:H,'MIS P&L'!B36,'TB 0125'!F:F) -> 295.994 | D36: =SUMIF('TB 0225'!H:H,'MIS P&L'!B36,'TB 0225'!F:F) -> 301.251 | E36: =SUMIF('TB 0325'!H:H,'MIS P&L'!B36,'TB 0325'!F:F) -> 586.42496 | F36: =SUMIF('TB 0425'!H:H,'MIS P&L'!B36,'TB 0425'!F:F) -> 466.89788 | G36: =SUMIF('TB 0525'!H:H,'MIS P&L'!B36,'TB 0525'!F:F) -> 814.74806 | H36: =SUMIF('TB 0625'!H:H,'MIS P&L'!B36,'TB 0625'!F:F) -> 1175.4557 | I36: =SUMIF('TB 0725'!H:H,'MIS P&L'!B36,'TB 0725'!F:F) -> 1349.8984 | J36: =SUMIF('TB 0825'!H:H,'MIS P&L'!B36,'TB 0825'!F:F) -> 1283.3703 | K36: =SUMIF('TB 0925'!H:H,'MIS P&L'!B36,'TB 0925'!F:F) -> 829.02504 | L36: =SUMIF('TB 1025'!H:H,'MIS P&L'!B36,'TB 1025'!F:F) -> 1607.0294 | M36: =SUMIF('TB 1125'!H:H,'MIS P&L'!B36,'TB 1125'!F:F) -> 2756.9744 | N36: =SUMIF('TB 1225'!H:H,'MIS P&L'!B36,'TB 1225'!F:F) -> 2293.5917
B37: Miscellaneous Expenses | C37: =SUMIF('TB 0125'!H:H,'MIS P&L'!B37,'TB 0125'!F:F) -> 82.49561 | D37: =SUMIF('TB 0225'!H:H,'MIS P&L'!B37,'TB 0225'!F:F) -> 301.3934 | E37: =SUMIF('TB 0325'!H:H,'MIS P&L'!B37,'TB 0325'!F:F) -> 36.94943 | F37: =SUMIF('TB 0425'!H:H,'MIS P&L'!B37,'TB 0425'!F:F) -> 61.96954 | G37: =SUMIF('TB 0525'!H:H,'MIS P&L'!B37,'TB 0525'!F:F) -> 122.90971 | H37: =SUMIF('TB 0625'!H:H,'MIS P&L'!B37,'TB 0625'!F:F) -> 111.00471 | I37: =SUMIF('TB 0725'!H:H,'MIS P&L'!B37,'TB 0725'!F:F) -> 163.80649 | J37: =SUMIF('TB 0825'!H:H,'MIS P&L'!B37,'TB 0825'!F:F) -> 134.67031 | K37: =SUMIF('TB 0925'!H:H,'MIS P&L'!B37,'TB 0925'!F:F) -> 282.65369 | L37: =SUMIF('TB 1025'!H:H,'MIS P&L'!B37,'TB 1025'!F:F) -> 82.52246 | M37: =SUMIF('TB 1125'!H:H,'MIS P&L'!B37,'TB 1125'!F:F) -> 43.1627 | N37: =SUMIF('TB 1225'!H:H,'MIS P&L'!B37,'TB 1225'!F:F) -> 56.24615
B39: Adjusted EBITDA | C39: =C23-C26-C30-C33-C34 -> -5271.4059 | D39: =D23-D26-D30-D33-D34 -> -10756.615 | E39: =E23-E26-E30-E33-E34 -> -14251.324 | F39: =F23-F26-F30-F33-F34 -> -22638.783 | G39: =G23-G26-G30-G33-G34 -> -34835.869 | H39: =H23-H26-H30-H33-H34 -> -50197.023 | I39: =I23-I26-I30-I33-I34 -> -63747.299 | J39: =J23-J26-J30-J33-J34 -> -91234.89 | ... N39: =N23-N26-N30-N33-N34 -> -222893.09
B40: EBITDA % | C40: =C39/C7 -> -3.1276552 | D40: =D39/D7 -> -6.1371706 | E40: =E39/E7 -> -5.8050371 | F40: =F39/F7 -> -6.6983571 | G40: =G39/G7 -> -4.6048159 | H40: =H39/H7 -> -4.8603162 | I40: =I39/I7 -> -4.2696276 | J40: =J39/J7 -> -3.3109172 | ... N40: =N39/N7 -> -1.9088316
B42: Fund Raising Expenses | C42: =SUMIF('TB 0125'!H:H,'MIS P&L'!B42,'TB 0125'!F:F) -> 1200.5 | D42: =SUMIF('TB 0225'!H:H,'MIS P&L'!B42,'TB 0225'!F:F) -> 502.26 | E42: =SUMIF('TB 0325'!H:H,'MIS P&L'!B42,'TB 0325'!F:F) -> 1515 | F42: =SUMIF('TB 0425'!H:H,'MIS P&L'!B42,'TB 0425'!F:F) -> 601 | G42: =SUMIF('TB 0525'!H:H,'MIS P&L'!B42,'TB 0525'!F:F) -> 148.5 | H42: =SUMIF('TB 0625'!H:H,'MIS P&L'!B42,'TB 0625'!F:F) -> 3184.84 | I42: =SUMIF('TB 0725'!H:H,'MIS P&L'!B42,'TB 0725'!F:F) -> 430.15 | J42: =SUMIF('TB 0825'!H:H,'MIS P&L'!B42,'TB 0825'!F:F) -> 0 | K42: =SUMIF('TB 0925'!H:H,'MIS P&L'!B42,'TB 0925'!F:F) -> 0 | L42: =SUMIF('TB 1025'!H:H,'MIS P&L'!B42,'TB 1025'!F:F) -> 0 | M42: =SUMIF('TB 1125'!H:H,'MIS P&L'!B42,'TB 1125'!F:F) -> 0 | N42: =SUMIF('TB 1225'!H:H,'MIS P&L'!B42,'TB 1225'!F:F) -> 0
B44: EBITDA | C44: =C39-C42 -> -6471.9059 | D44: =D39-D42 -> -11258.875 | E44: =E39-E42 -> -15766.324 | F44: =F39-F42 -> -23239.783 | G44: =G39-G42 -> -34984.369 | H44: =H39-H42 -> -53381.863 | I44: =I39-I42 -> -64177.449 | J44: =J39-J42 -> -91234.89 | ... N44: =N39-N42 -> -222893.09
B45: EBITDA % | C45: =C44/C7 -> -3.8399415 | D45: =D44/D7 -> -6.4237342 | E45: =E44/E7 -> -6.4221468 | F45: =F44/F7 -> -6.8761808 | G45: =G44/G7 -> -4.6244455 | H45: =H44/H7 -> -5.1686877 | I45: =I44/I7 -> -4.2984379 | J45: =J44/J7 -> -3.3109172 | ... N45: =N44/N7 -> -1.9088316
B47: Depreciation | C47: =SUMIF('TB 0125'!H:H,'MIS P&L'!B47,'TB 0125'!F:F) -> 68.039 | D47: =SUMIF('TB 0225'!H:H,'MIS P&L'!B47,'TB 0225'!F:F) -> 77.932 | E47: =SUMIF('TB 0325'!H:H,'MIS P&L'!B47,'TB 0325'!F:F) -> 160.17333 | F47: =SUMIF('TB 0425'!H:H,'MIS P&L'!B47,'TB 0425'!F:F) -> 213.09815 | G47: =SUMIF('TB 0525'!H:H,'MIS P&L'!B47,'TB 0525'!F:F) -> 266.90296 | H47: =SUMIF('TB 0625'!H:H,'MIS P&L'!B47,'TB 0625'!F:F) -> 293.91167 | I47: =SUMIF('TB 0725'!H:H,'MIS P&L'!B47,'TB 0725'!F:F) -> 338.10246 | J47: =SUMIF('TB 0825'!H:H,'MIS P&L'!B47,'TB 0825'!F:F) -> 395.112 | K47: =SUMIF('TB 0925'!H:H,'MIS P&L'!B47,'TB 0925'!F:F) -> 653.15802 | L47: =SUMIF('TB 1025'!H:H,'MIS P&L'!B47,'TB 1025'!F:F) -> 856.74808 | M47: =SUMIF('TB 1125'!H:H,'MIS P&L'!B47,'TB 1125'!F:F) -> 1006.8347 | N47: =SUMIF('TB 1225'!H:H,'MIS P&L'!B47,'TB 1225'!F:F) -> 1184.2885
B48: Interest Income | C48: =-SUMIF('TB 0125'!H:H,'MIS P&L'!B48,'TB 0125'!F:F) -> 530.43759 | D48: =-SUMIF('TB 0225'!H:H,'MIS P&L'!B48,'TB 0225'!F:F) -> 2475.789 | E48: =-SUMIF('TB 0325'!H:H,'MIS P&L'!B48,'TB 0325'!F:F) -> 3149.74 | F48: =-SUMIF('TB 0425'!H:H,'MIS P&L'!B48,'TB 0425'!F:F) -> 2627.8147 | G48: =-SUMIF('TB 0525'!H:H,'MIS P&L'!B48,'TB 0525'!F:F) -> 2553.0613 | H48: =-SUMIF('TB 0625'!H:H,'MIS P&L'!B48,'TB 0625'!F:F) -> 9875.7241 | I48: =-SUMIF('TB 0725'!H:H,'MIS P&L'!B48,'TB 0725'!F:F) -> 10016.751 | J48: =-SUMIF('TB 0825'!H:H,'MIS P&L'!B48,'TB 0825'!F:F) -> 9834.8399 | K48: =-SUMIF('TB 0925'!H:H,'MIS P&L'!B48,'TB 0925'!F:F) -> 10218.875 | L48: =-SUMIF('TB 1025'!H:H,'MIS P&L'!B48,'TB 1025'!F:F) -> 10608.585 | M48: =-SUMIF('TB 1125'!H:H,'MIS P&L'!B48,'TB 1125'!F:F) -> 17681.218 | N48: =-SUMIF('TB 1225'!H:H,'MIS P&L'!B48,'TB 1225'!F:F) -> 18913.496
B50: PBT | C50: =C44-C47+C48 -> -6009.5073 | D50: =D44-D47+D48 -> -8861.0183 | E50: =E44-E47+E48 -> -12776.758 | F50: =F44-F47+F48 -> -20825.066 | G50: =G44-G47+G48 -> -32698.211 | H50: =H44-H47+H48 -> -43800.051 | I50: =I44-I47+I48 -> -54498.801 | J50: =J44-J47+J48 -> -81795.162 | ... N50: =N44-N47+N48 -> -205163.89
B51: PBT % | C51: =C50/C7 -> -3.565589 | D51: =D50/D7 -> -5.0556406 | E51: =E50/E7 -> -5.2043972 | F51: =F50/F7 -> -6.1617151 | G51: =G50/G7 -> -4.3222472 | H51: =H50/H7 -> -4.2409307 | I51: =I50/I7 -> -3.6501873 | J51: =J50/J7 -> -2.9683492 | ... N51: =N50/N7 -> -1.7570006
B53: Tax | C53: 0 | D53: 0 | E53: 0 | F53: 0 | G53: 0 | H53: 0 | I53: 0 | J53: 0 | K53: =-SUMIF('TB 0925'!H:H,'MIS P&L'!B53,'TB 0925'!F:F) -> 0 | L53: 0 | M53: 0 | N53: 0
B55: PAT | C55: =C50-C53 -> -6009.5073 | D55: =D50-D53 -> -8861.0183 | E55: =E50-E53 -> -12776.758 | F55: =F50-F53 -> -20825.066 | G55: =G50-G53 -> -32698.211 | H55: =H50-H53 -> -43800.051 | I55: =I50-I53 -> -54498.801 | J55: =J50-J53 -> -81795.162 | ... N55: =N50-N53 -> -205163.89
B56: PAT % | C56: =C55/C7 -> -3.565589 | D56: =D55/D7 -> -5.0556406 | E56: =E55/E7 -> -5.2043972 | F56: =F55/F7 -> -6.1617151 | G56: =G55/G7 -> -4.3222472 | H56: =H55/H7 -> -4.2409307 | I56: =I55/I7 -> -3.6501873 | J56: =J55/J7 -> -2.9683492 | ... N56: =N55/N7 -> -1.7570006
B58: PAT ($ M) | C58: =C55/88/1000 -> -0.068289856 | D58: =D55/88/1000 -> -0.10069339 | E58: =E55/88/1000 -> -0.14519043 | F58: =F55/88/1000 -> -0.23664848 | G58: =G55/88/1000 -> -0.37157057 | H58: =H55/88/1000 -> -0.49772785 | I58: =I55/88/1000 -> -0.61930455 | J58: =J55/88/1000 -> -0.92949048 | ... M58: =M55/88/1000 -> -1.7641143 | N58: =N55/90/1000 -> -2.2795987
B59: Closing Cash ($ M) | F59: ='Cash Flow'!C38/88/1000 -> 5.2649187 | G59: ='Cash Flow'!D38/88/1000 -> 4.8940391 | H59: ='Cash Flow'!E38/88/1000 -> 22.825853 | I59: ='Cash Flow'!F38/88/1000 -> 22.127199 | J59: ='Cash Flow'!G38/88/1000 -> 21.448764 | K59: ='Cash Flow'!H38/88/1000 -> 20.465949 | L59: ='Cash Flow'!I38/88/1000 -> 33.886524 | M59: ='Cash Flow'!J38/88/1000 -> 47.439313
B60: Projected Runway | F60: =-F59/F58 -> 22.247845 | G60: =-G59/G58 -> 13.171224 | H60: =-H59/H58 -> 45.860107 | I60: =-I59/I58 -> 35.729107 | J60: =-J59/J58 -> 23.07583 | K60: =-K59/K58 -> 19.454458 | L60: =-L59/L58 -> 21.177906 | M60: =-M59/M58 -> 26.891292

Sheet Unit Economics
B2: Jobs per Day | C2: ='Key Metrics'!C20 -> 228.76667 | D2: ='Key Metrics'!D20 -> 250.63333 | E2: ='Key Metrics'!E20 -> 354.73333 | F2: ='Key Metrics'!F20 -> 499.33333 | G2: ='Key Metrics'!G20 -> 1135.129 | H2: ='Key Metrics'!H20 -> 1573.7 | I2: ='Key Metrics'!I20 -> 2199.871 | J2: ='Key Metrics'!J20 -> 3832.5161 | ... L2: ='Key Metrics'!L20 -> 9957.0323 | M2: ='Key Metrics'!#REF! -> #REF! | N2: ='Key Metrics'!M20 -> 12521.167 | O2: ='Key Metrics'!#REF! -> #REF! | P2: ='Key Metrics'!#REF! -> #REF! | Q2: ='Key Metrics'!#REF! -> #REF! | R2: ='Key Metrics'!#REF! -> #REF!
B3: Hrs per Day | C3: ='Key Metrics'!C26 -> 294.99194 | D3: ='Key Metrics'!D26 -> 342.96429 | E3: ='Key Metrics'!E26 -> 434.10484 | F3: ='Key Metrics'!F26 -> 615.43333 | G3: ='Key Metrics'!G26 -> 1337.9194 | H3: ='Key Metrics'!H26 -> 1829.1667 | I3: ='Key Metrics'!I26 -> 2557.0806 | J3: ='Key Metrics'!J26 -> 4678.5161 | ... L3: ='Key Metrics'!L26 -> 13086.798 | M3: ='Key Metrics'!#REF! -> #REF! | N3: ='Key Metrics'!M26 -> 15568.681 | O3: ='Key Metrics'!#REF! -> #REF! | P3: ='Key Metrics'!#REF! -> #REF! | Q3: ='Key Metrics'!#REF! -> #REF! | R3: ='Key Metrics'!#REF! -> #REF!
B5: Unit Economics | C5: Actual | D5: Actual | E5: Actual | F5: Actual | G5: Actual | H5: Actual | I5: Actual | J5: Actual | K5: Actual | L5: Actual | M5: Plan | N5: Actual | O5: Forecast | P5: Plan | Q5: Rev Forecast | R5: Plan
B6: All Values (in INR per Job) | C6: 45658 | D6: 45689 | E6: 45717 | F6: ='MIS P&L'!F6 -> 45748 | G6: ='MIS P&L'!G6 -> 45778 | H6: ='MIS P&L'!H6 -> 45809 | I6: ='MIS P&L'!I6 -> 45839 | J6: ='MIS P&L'!J6 -> 45870 | K6: ='MIS P&L'!K6 -> 45901 | L6: ='MIS P&L'!L6 -> 45931 | M6: =K6+31 -> 45932 | N6: ='MIS P&L'!M6 -> 45962 | O6: 45963 | P6: =M6+31 -> 45963 | Q6: 46022 | R6: =P6+31 -> 45994
B7: Revenue | C7: =('MIS P&L'!C7)*10^3/'MIS P&L'!C$2 -> 245.58033 | D7: =('MIS P&L'!D7)*10^3/'MIS P&L'!D$2 -> 233.10273 | E7: =('MIS P&L'!E7)*10^3/'MIS P&L'!E$2 -> 230.68904 | F7: =('MIS P&L'!F7)*10^3/'MIS P&L'!F$2 -> 225.6176 | G7: =('MIS P&L'!G7)*10^3/'MIS P&L'!G$2 -> 214.98465 | H7: =('MIS P&L'!H7)*10^3/'MIS P&L'!H$2 -> 218.76117 | I7: =('MIS P&L'!I7)*10^3/'MIS P&L'!I$2 -> 218.93384 | J7: =('MIS P&L'!J7)*10^3/'MIS P&L'!J$2 -> 231.93535 | ... L7: =('MIS P&L'!L7)*10^3/'MIS P&L'!L$2 -> 240.55474 | M7: =('MIS P&L'!#REF!)*10^3/'MIS P&L'!#REF! -> #REF! | N7: =('MIS P&L'!M7)*10^3/'MIS P&L'!M$2 -> 225.28644 | O7: =('MIS P&L'!#REF!)*10^3/'MIS P&L'!#REF! -> #REF! | P7: =('MIS P&L'!#REF!)*10^3/'MIS P&L'!#REF! -> #REF! | Q7: =('MIS P&L'!#REF!)*10^3/'MIS P&L'!#REF! -> #REF! | R7: =('MIS P&L'!#REF!)*10^3/'MIS P&L'!#REF! -> #REF!
B8: Service Cost | C8: =('MIS P&L'!C8)*10^3/'MIS P&L'!C$2 -> 191.8646 | D8: =('MIS P&L'!D8)*10^3/'MIS P&L'!D$2 -> 240.53149 | E8: =('MIS P&L'!E8)*10^3/'MIS P&L'!E$2 -> 223.42346 | F8: =('MIS P&L'!F8)*10^3/'MIS P&L'!F$2 -> 311.50788 | G8: =('MIS P&L'!G8)*10^3/'MIS P&L'!G$2 -> 287.74425 | H8: =('MIS P&L'!H8)*10^3/'MIS P&L'!H$2 -> 343.01441 | I8: =('MIS P&L'!I8)*10^3/'MIS P&L'!I$2 -> 304.96776 | J8: =('MIS P&L'!J8)*10^3/'MIS P&L'!J$2 -> 293.73579 | ... L8: =('MIS P&L'!L8)*10^3/'MIS P&L'!L$2 -> 260.62501 | M8: =('MIS P&L'!#REF!)*10^3/'MIS P&L'!#REF! -> #REF! | N8: =('MIS P&L'!M8)*10^3/'MIS P&L'!M$2 -> 248.55132 | O8: =('MIS P&L'!#REF!)*10^3/'MIS P&L'!#REF! -> #REF! | P8: =('MIS P&L'!#REF!)*10^3/'MIS P&L'!#REF! -> #REF! | Q8: =('MIS P&L'!#REF!)*10^3/'MIS P&L'!#REF! -> #REF! | R8: =('MIS P&L'!#REF!)*10^3/'MIS P&L'!#REF! -> #REF!
B10: GST | C10: =('MIS P&L'!C10)*10^3/'MIS P&L'!C$2 -> 16.240445 | D10: =('MIS P&L'!D10)*10^3/'MIS P&L'!D$2 -> 14.242423 | E10: =('MIS P&L'!E10)*10^3/'MIS P&L'!E$2 -> 13.692852 | F10: =('MIS P&L'!F10)*10^3/'MIS P&L'!F$2 -> 14.620283 | G10: =('MIS P&L'!G10)*10^3/'MIS P&L'!G$2 -> 14.13595 | H10: =('MIS P&L'!H10)*10^3/'MIS P&L'!H$2 -> 14.292926 | I10: =('MIS P&L'!I10)*10^3/'MIS P&L'!I$2 -> 14.563896 | J10: =('MIS P&L'!J10)*10^3/'MIS P&L'!J$2 -> 15.375671 | ... L10: =('MIS P&L'!L10)*10^3/'MIS P&L'!L$2 -> 10.031803 | M10: =('MIS P&L'!#REF!)*10^3/'MIS P&L'!#REF! -> #REF! | N10: =('MIS P&L'!M10)*10^3/'MIS P&L'!M$2 -> 9.6921039 | O10: =('MIS P&L'!#REF!)*10^3/'MIS P&L'!#REF! -> #REF! | P10: =('MIS P&L'!#REF!)*10^3/'MIS P&L'!#REF! -> #REF! | Q10: =('MIS P&L'!#REF!)*10^3/'MIS P&L'!#REF! -> #REF! | R10: =('MIS P&L'!#REF!)*10^3/'MIS P&L'!#REF! -> #REF!
B11: Promotions & Discounts | C11: =('MIS P&L'!C11)*10^3/'MIS P&L'!C$2 -> 6.9492933 | D11: =('MIS P&L'!D11)*10^3/'MIS P&L'!D$2 -> 9.0867137 | E11: =('MIS P&L'!E11)*10^3/'MIS P&L'!E$2 -> 2.0612667 | F11: =('MIS P&L'!F11)*10^3/'MIS P&L'!F$2 -> 2.2369826 | G11: =('MIS P&L'!G11)*10^3/'MIS P&L'!G$2 -> 0.55983404 | H11: =('MIS P&L'!H11)*10^3/'MIS P&L'!H$2 -> 0.92832179 | I11: =('MIS P&L'!I11)*10^3/'MIS P&L'!I$2 -> 5.1001972 | J11: =('MIS P&L'!J11)*10^3/'MIS P&L'!J$2 -> 9.8435122 | ... L11: =('MIS P&L'!L11)*10^3/'MIS P&L'!L$2 -> 27.962588 | M11: =('MIS P&L'!#REF!)*10^3/'MIS P&L'!#REF! -> #REF! | N11: =('MIS P&L'!M11)*10^3/'MIS P&L'!M$2 -> 33.998544 | O11: =('MIS P&L'!#REF!)*10^3/'MIS P&L'!#REF! -> #REF! | P11: =('MIS P&L'!#REF!)*10^3/'MIS P&L'!#REF! -> #REF! | Q11: =('MIS P&L'!#REF!)*10^3/'MIS P&L'!#REF! -> #REF! | R11: =('MIS P&L'!#REF!)*10^3/'MIS P&L'!#REF! -> #REF!
B12: Payment Gateway Cost | C12: =('MIS P&L'!C12)*10^3/'MIS P&L'!C$2 -> 2.6651144 | D12: =('MIS P&L'!D12)*10^3/'MIS P&L'!D$2 -> 2.2726214 | E12: =('MIS P&L'!E12)*10^3/'MIS P&L'!E$2 -> 2.0121227 | F12: =('MIS P&L'!F12)*10^3/'MIS P&L'!F$2 -> 2.1654272 | G12: =('MIS P&L'!G12)*10^3/'MIS P&L'!G$2 -> 0.65759271 | H12: =('MIS P&L'!H12)*10^3/'MIS P&L'!H$2 -> 0.7151541 | I12: =('MIS P&L'!I12)*10^3/'MIS P&L'!I$2 -> 0.68225556 | J12: =('MIS P&L'!J12)*10^3/'MIS P&L'!J$2 -> 0.41847712 | ... L12: =('MIS P&L'!L12)*10^3/'MIS P&L'!L$2 -> 0.30018049 | M12: =('MIS P&L'!#REF!)*10^3/'MIS P&L'!#REF! -> #REF! | N12: =('MIS P&L'!M12)*10^3/'MIS P&L'!M$2 -> 0.30711326 | O12: =('MIS P&L'!#REF!)*10^3/'MIS P&L'!#REF! -> #REF! | P12: =('MIS P&L'!#REF!)*10^3/'MIS P&L'!#REF! -> #REF! | Q12: =('MIS P&L'!#REF!)*10^3/'MIS P&L'!#REF! -> #REF! | R12: =('MIS P&L'!#REF!)*10^3/'MIS P&L'!#REF! -> #REF!
B14: Gross Profit | C14: =C7-C8-C10-C11-C12 -> 27.860882 | D14: =D7-D8-D10-D11-D12 -> -33.030516 | E14: =E7-E8-E10-E11-E12 -> -10.500657 | F14: =F7-F8-F10-F11-F12 -> -104.91298 | G14: =G7-G8-G10-G11-G12 -> -88.112971 | H14: =H7-H8-H10-H11-H12 -> -140.18964 | I14: =I7-I8-I10-I11-I12 -> -106.38027 | J14: =J7-J8-J10-J11-J12 -> -87.438103 | ... R14: =R7-R8-R10-R11-R12 -> #REF!
B15: Gross Profit % | C15: =C14/C7 -> 0.11344916 | D15: =D14/D7 -> -0.1416994 | E15: =E14/E7 -> -0.045518663 | F15: =F14/F7 -> -0.46500352 | G15: =G14/G7 -> -0.40985703 | H15: =H14/H7 -> -0.64083419 | I15: =I14/I7 -> -0.48590146 | J15: =J14/J7 -> -0.37699343 | ... R15: =R14/R7 -> #REF!
B17: Training Centre Expenses | C17: =('MIS P&L'!C17)*10^3/'MIS P&L'!C$2 -> 22.501539 | D17: =('MIS P&L'!D17)*10^3/'MIS P&L'!D$2 -> 73.900696 | E17: =('MIS P&L'!E17)*10^3/'MIS P&L'!E$2 -> 35.575638 | F17: =('MIS P&L'!F17)*10^3/'MIS P&L'!F$2 -> 71.537003 | G17: =('MIS P&L'!G17)*10^3/'MIS P&L'!G$2 -> 60.290025 | H17: =('MIS P&L'!H17)*10^3/'MIS P&L'!H$2 -> 38.955568 | I17: =('MIS P&L'!I17)*10^3/'MIS P&L'!I$2 -> 31.236091 | J17: =('MIS P&L'!J17)*10^3/'MIS P&L'!J$2 -> 20.164081 | ... L17: =('MIS P&L'!L17)*10^3/'MIS P&L'!L$2 -> 14.610512 | M17: =('MIS P&L'!#REF!)*10^3/'MIS P&L'!#REF! -> #REF! | N17: =('MIS P&L'!M17)*10^3/'MIS P&L'!M$2 -> 12.404039 | O17: =('MIS P&L'!#REF!)*10^3/'MIS P&L'!#REF! -> #REF! | P17: =('MIS P&L'!#REF!)*10^3/'MIS P&L'!#REF! -> #REF! | Q17: =('MIS P&L'!#REF!)*10^3/'MIS P&L'!#REF! -> #REF! | R17: =('MIS P&L'!#REF!)*10^3/'MIS P&L'!#REF! -> #REF!
B18: Managerial Cost | C18: =('MIS P&L'!C18)*10^3/'MIS P&L'!C$2 -> 19.750546 | D18: =('MIS P&L'!D18)*10^3/'MIS P&L'!D$2 -> 33.206676 | E18: =('MIS P&L'!E18)*10^3/'MIS P&L'!E$2 -> 41.061549 | F18: =('MIS P&L'!F18)*10^3/'MIS P&L'!F$2 -> 61.011081 | G18: =('MIS P&L'!G18)*10^3/'MIS P&L'!G$2 -> 39.008326 | H18: =('MIS P&L'!H18)*10^3/'MIS P&L'!H$2 -> 41.823967 | I18: =('MIS P&L'!I18)*10^3/'MIS P&L'!I$2 -> 42.112957 | J18: =('MIS P&L'!J18)*10^3/'MIS P&L'!J$2 -> 36.686576 | ... L18: =('MIS P&L'!L18)*10^3/'MIS P&L'!L$2 -> 19.081594 | M18: =('MIS P&L'!#REF!)*10^3/'MIS P&L'!#REF! -> #REF! | N18: =('MIS P&L'!M18)*10^3/'MIS P&L'!M$2 -> 15.521143 | O18: =('MIS P&L'!#REF!)*10^3/'MIS P&L'!#REF! -> #REF! | P18: =('MIS P&L'!#REF!)*10^3/'MIS P&L'!#REF! -> #REF! | Q18: =('MIS P&L'!#REF!)*10^3/'MIS P&L'!#REF! -> #REF! | R18: =('MIS P&L'!#REF!)*10^3/'MIS P&L'!#REF! -> #REF!
B19: Sourcing & Onboarding Cost | C19: =('MIS P&L'!C19)*10^3/'MIS P&L'!C$2 -> 38.649194 | D19: =('MIS P&L'!D19)*10^3/'MIS P&L'!D$2 -> 65.09607 | E19: =('MIS P&L'!E19)*10^3/'MIS P&L'!E$2 -> 91.0168 | F19: =('MIS P&L'!F19)*10^3/'MIS P&L'!F$2 -> 98.093909 | G19: =('MIS P&L'!G19)*10^3/'MIS P&L'!G$2 -> 51.735599 | H19: =('MIS P&L'!H19)*10^3/'MIS P&L'!H$2 -> 98.843823 | I19: =('MIS P&L'!I19)*10^3/'MIS P&L'!I$2 -> 69.13969 | J19: =('MIS P&L'!J19)*10^3/'MIS P&L'!J$2 -> 56.979489 | ... L19: =('MIS P&L'!L19)*10^3/'MIS P&L'!L$2 -> 43.843598 | M19: =('MIS P&L'!#REF!)*10^3/'MIS P&L'!#REF! -> #REF! | N19: =('MIS P&L'!M19)*10^3/'MIS P&L'!M$2 -> 35.61351 | O19: =('MIS P&L'!#REF!)*10^3/'MIS P&L'!#REF! -> #REF! | P19: =('MIS P&L'!#REF!)*10^3/'MIS P&L'!#REF! -> #REF! | Q19: =('MIS P&L'!#REF!)*10^3/'MIS P&L'!#REF! -> #REF! | R19: =('MIS P&L'!#REF!)*10^3/'MIS P&L'!#REF! -> #REF!
B20: Customer Success Cost | C20: =('MIS P&L'!C20)*10^3/'MIS P&L'!C$2 -> 11.308757 | D20: =('MIS P&L'!D20)*10^3/'MIS P&L'!D$2 -> 7.1818061 | E20: =('MIS P&L'!E20)*10^3/'MIS P&L'!E$2 -> 20.14875 | F20: =('MIS P&L'!F20)*10^3/'MIS P&L'!F$2 -> 23.453138 | G20: =('MIS P&L'!G20)*10^3/'MIS P&L'!G$2 -> 17.680582 | H20: =('MIS P&L'!H20)*10^3/'MIS P&L'!H$2 -> 14.596733 | I20: =('MIS P&L'!I20)*10^3/'MIS P&L'!I$2 -> 9.575353 | J20: =('MIS P&L'!J20)*10^3/'MIS P&L'!J$2 -> 6.5010483 | ... L20: =('MIS P&L'!L20)*10^3/'MIS P&L'!L$2 -> 5.394008 | M20: =('MIS P&L'!#REF!)*10^3/'MIS P&L'!#REF! -> #REF! | N20: =('MIS P&L'!M20)*10^3/'MIS P&L'!M$2 -> 6.1390745 | O20: =('MIS P&L'!#REF!)*10^3/'MIS P&L'!#REF! -> #REF! | P20: =('MIS P&L'!#REF!)*10^3/'MIS P&L'!#REF! -> #REF! | Q20: =('MIS P&L'!#REF!)*10^3/'MIS P&L'!#REF! -> #REF! | R20: =('MIS P&L'!#REF!)*10^3/'MIS P&L'!#REF! -> #REF!
B21: Other Operational Cost | C21: =('MIS P&L'!C21)*10^3/'MIS P&L'!C$2 -> 0 | D21: =('MIS P&L'!D21)*10^3/'MIS P&L'!D$2 -> 0 | E21: =('MIS P&L'!E21)*10^3/'MIS P&L'!E$2 -> 0 | F21: =('MIS P&L'!F21)*10^3/'MIS P&L'!F$2 -> 6.6301575 | G21: =('MIS P&L'!G21)*10^3/'MIS P&L'!G$2 -> 13.319309 | H21: =('MIS P&L'!H21)*10^3/'MIS P&L'!H$2 -> 27.488373 | I21: =('MIS P&L'!I21)*10^3/'MIS P&L'!I$2 -> 35.712172 | J21: =('MIS P&L'!J21)*10^3/'MIS P&L'!J$2 -> 16.230288 | ... L21: =('MIS P&L'!L21)*10^3/'MIS P&L'!L$2 -> 3.3600418 | M21: =('MIS P&L'!#REF!)*10^3/'MIS P&L'!#REF! -> #REF! | N21: =('MIS P&L'!M21)*10^3/'MIS P&L'!M$2 -> 2.7850686 | O21: =('MIS P&L'!#REF!)*10^3/'MIS P&L'!#REF! -> #REF! | P21: =('MIS P&L'!#REF!)*10^3/'MIS P&L'!#REF! -> #REF! | Q21: =('MIS P&L'!#REF!)*10^3/'MIS P&L'!#REF! -> #REF! | R21: =('MIS P&L'!#REF!)*10^3/'MIS P&L'!#REF! -> #REF!
B23: Operating Profit | C23: =C14-SUM(C17:C20) -> -64.349155 | D23: =D14-SUM(D17:D20) -> -212.41576 | E23: =E14-SUM(E17:E20) -> -198.30339 | F23: =F14-SUM(F17:F21) -> -365.63827 | G23: =G14-SUM(G17:G21) -> -270.14681 | H23: =H14-SUM(H17:H21) -> -361.8981 | I23: =I14-SUM(I17:I21) -> -294.15653 | J23: =J14-SUM(J17:J21) -> -223.99959 | K23: =K14-SUM(K17:K21) -> -170.01705 | L23: =L14-SUM(L17:L21) -> -144.65459 | M23: =M14-SUM(M17:M21) -> #REF! | ... R23: =R14-SUM(R17:R21) -> #REF!
B24: Operating Profit % | C24: =C23/C7 -> -0.26202894 | D24: =D23/D7 -> -0.91125387 | E24: =E23/E7 -> -0.8596134 | F24: =F23/F7 -> -1.6206106 | G24: =G23/G7 -> -1.2565865 | H24: =H23/H7 -> -1.6543068 | I24: =I23/I7 -> -1.3435864 | J24: =J23/J7 -> -0.96578458 | ... R24: =R23/R7 -> #REF!
B26: Marketing Cost | C26: ='MIS P&L'!C26*10^3/'MIS P&L'!C$2 -> 127.66498 | D26: ='MIS P&L'!D26*10^3/'MIS P&L'!D$2 -> 175.94095 | E26: ='MIS P&L'!E26*10^3/'MIS P&L'!E$2 -> 149.2233 | F26: ='MIS P&L'!F26*10^3/'MIS P&L'!F$2 -> 175.99977 | G26: ='MIS P&L'!G26*10^3/'MIS P&L'!G$2 -> 176.51036 | H26: ='MIS P&L'!H26*10^3/'MIS P&L'!H$2 -> 221.96366 | I26: ='MIS P&L'!I26*10^3/'MIS P&L'!I$2 -> 249.64599 | J26: ='MIS P&L'!J26*10^3/'MIS P&L'!J$2 -> 299.77322 | ... L26: ='MIS P&L'!L26*10^3/'MIS P&L'!L$2 -> 206.7002 | M26: ='MIS P&L'!#REF!*10^3/'MIS P&L'!#REF! -> #REF! | N26: ='MIS P&L'!M26*10^3/'MIS P&L'!M$2 -> 190.8631 | O26: ='MIS P&L'!#REF!*10^3/'MIS P&L'!#REF! -> #REF! | P26: ='MIS P&L'!#REF!*10^3/'MIS P&L'!#REF! -> #REF! | Q26: ='MIS P&L'!#REF!*10^3/'MIS P&L'!#REF! -> #REF! | R26: ='MIS P&L'!#REF!*10^3/'MIS P&L'!#REF! -> #REF!
B27: Employee Cost | C27: ='MIS P&L'!C30*10^3/'MIS P&L'!C$2 -> 450.65782 | D27: ='MIS P&L'!D30*10^3/'MIS P&L'!D$2 -> 878.60621 | E27: ='MIS P&L'!E30*10^3/'MIS P&L'!E$2 -> 859.05477 | F27: ='MIS P&L'!F30*10^3/'MIS P&L'!F$2 -> 856.05995 | G27: ='MIS P&L'!G30*10^3/'MIS P&L'!G$2 -> 464.83358 | H27: ='MIS P&L'!H30*10^3/'MIS P&L'!H$2 -> 407.88581 | I27: ='MIS P&L'!I30*10^3/'MIS P&L'!I$2 -> 330.63956 | J27: ='MIS P&L'!J30*10^3/'MIS P&L'!J$2 -> 206.223 | ... L27: ='MIS P&L'!L30*10^3/'MIS P&L'!L$2 -> 114.00186 | M27: ='MIS P&L'!#REF!*10^3/'MIS P&L'!#REF! -> #REF! | N27: ='MIS P&L'!M30*10^3/'MIS P&L'!M$2 -> 104.68394 | O27: ='MIS P&L'!#REF!*10^3/'MIS P&L'!#REF! -> #REF! | P27: ='MIS P&L'!#REF!*10^3/'MIS P&L'!#REF! -> #REF! | Q27: ='MIS P&L'!#REF!*10^3/'MIS P&L'!#REF! -> #REF! | R27: ='MIS P&L'!#REF!*10^3/'MIS P&L'!#REF! -> #REF!
B28: Tech Cost | C28: ='MIS P&L'!C33*10^3/'MIS P&L'!C$2 -> 54.387108 | D28: ='MIS P&L'!D33*10^3/'MIS P&L'!D$2 -> 68.982132 | E28: ='MIS P&L'!E33*10^3/'MIS P&L'!E$2 -> 51.675438 | F28: ='MIS P&L'!F33*10^3/'MIS P&L'!F$2 -> 69.704251 | G28: ='MIS P&L'!G33*10^3/'MIS P&L'!G$2 -> 39.323733 | H28: ='MIS P&L'!H33*10^3/'MIS P&L'!H$2 -> 36.261215 | I28: ='MIS P&L'!I33*10^3/'MIS P&L'!I$2 -> 27.115838 | J28: ='MIS P&L'!J33*10^3/'MIS P&L'!J$2 -> 19.483306 | ... L28: ='MIS P&L'!L33*10^3/'MIS P&L'!L$2 -> 12.865004 | M28: ='MIS P&L'!#REF!*10^3/'MIS P&L'!#REF! -> #REF! | N28: ='MIS P&L'!M33*10^3/'MIS P&L'!M$2 -> 9.0547504 | O28: ='MIS P&L'!#REF!*10^3/'MIS P&L'!#REF! -> #REF! | P28: ='MIS P&L'!#REF!*10^3/'MIS P&L'!#REF! -> #REF! | Q28: ='MIS P&L'!#REF!*10^3/'MIS P&L'!#REF! -> #REF! | R28: ='MIS P&L'!#REF!*10^3/'MIS P&L'!#REF! -> #REF!
B29: Other Costs | C29: ='MIS P&L'!C34*10^3/'MIS P&L'!C$2 -> 71.031562 | D29: ='MIS P&L'!D34*10^3/'MIS P&L'!D$2 -> 94.64615 | E29: ='MIS P&L'!E34*10^3/'MIS P&L'!E$2 -> 80.901559 | F29: ='MIS P&L'!F34*10^3/'MIS P&L'!F$2 -> 43.864981 | G29: ='MIS P&L'!G34*10^3/'MIS P&L'!G$2 -> 39.150239 | H29: ='MIS P&L'!H34*10^3/'MIS P&L'!H$2 -> 35.239678 | I29: ='MIS P&L'!I34*10^3/'MIS P&L'!I$2 -> 33.208031 | J29: ='MIS P&L'!J34*10^3/'MIS P&L'!J$2 -> 18.43963 | ... L29: ='MIS P&L'!L34*10^3/'MIS P&L'!L$2 -> 9.5503968 | M29: ='MIS P&L'!#REF!*10^3/'MIS P&L'!#REF! -> #REF! | N29: ='MIS P&L'!M34*10^3/'MIS P&L'!M$2 -> 13.341606 | O29: ='MIS P&L'!#REF!*10^3/'MIS P&L'!#REF! -> #REF! | P29: ='MIS P&L'!#REF!*10^3/'MIS P&L'!#REF! -> #REF! | Q29: ='MIS P&L'!#REF!*10^3/'MIS P&L'!#REF! -> #REF! | R29: ='MIS P&L'!#REF!*10^3/'MIS P&L'!#REF! -> #REF!
B31: Adjusted EBITDA | C31: =C23-C26-C27-C28-C29 -> -768.09062 | D31: =D23-D26-D27-D28-D29 -> -1430.5912 | E31: =E23-E26-E27-E28-E29 -> -1339.1585 | F31: =F23-F26-F27-F28-F29 -> -1511.2672 | G31: =G23-G26-G27-G28-G29 -> -989.96473 | H31: =H23-H26-H27-H28-H29 -> -1063.2485 | I31: =I23-I26-I27-I28-I29 -> -934.76596 | J31: =J23-J26-J27-J28-J29 -> -767.91874 | ... R31: =R23-R26-R27-R28-R29 -> #REF!
B32: EBITDA % | C32: =C31/C7 -> -3.1276552 | D32: =D31/D7 -> -6.1371706 | E32: =E31/E7 -> -5.8050371 | F32: =F31/F7 -> -6.6983571 | G32: =G31/G7 -> -4.6048159 | H32: =H31/H7 -> -4.8603162 | I32: =I31/I7 -> -4.2696276 | J32: =J31/J7 -> -3.3109172 | ... R32: =R31/R7 -> #REF!
B34: Fund Raising Expenses | C34: ='MIS P&L'!C42*10^3/'MIS P&L'!C$2 -> 174.9235 | D34: ='MIS P&L'!D42*10^3/'MIS P&L'!D$2 -> 66.798776 | E34: ='MIS P&L'!E42*10^3/'MIS P&L'!E$2 -> 142.36046 | F34: ='MIS P&L'!F42*10^3/'MIS P&L'!F$2 -> 40.12016 | G34: ='MIS P&L'!G42*10^3/'MIS P&L'!G$2 -> 4.2200688 | H34: ='MIS P&L'!H42*10^3/'MIS P&L'!H$2 -> 67.459702 | I34: ='MIS P&L'!I42*10^3/'MIS P&L'!I$2 -> 6.3075547 | J34: ='MIS P&L'!J42*10^3/'MIS P&L'!J$2 -> 0 | ... L34: ='MIS P&L'!L42*10^3/'MIS P&L'!L$2 -> 0 | M34: ='MIS P&L'!#REF!*10^3/'MIS P&L'!#REF! -> #REF! | N34: ='MIS P&L'!M42*10^3/'MIS P&L'!M$2 -> 0 | O34: ='MIS P&L'!#REF!*10^3/'MIS P&L'!#REF! -> #REF! | P34: ='MIS P&L'!#REF!*10^3/'MIS P&L'!#REF! -> #REF! | Q34: ='MIS P&L'!#REF!*10^3/'MIS P&L'!#REF! -> #REF! | R34: ='MIS P&L'!#REF!*10^3/'MIS P&L'!#REF! -> #REF!
B36: EBITDA | C36: =C31-C34 -> -943.01412 | D36: =D31-D34 -> -1497.39 | E36: =E31-E34 -> -1481.5189 | F36: =F31-F34 -> -1551.3874 | G36: =G31-G34 -> -994.1848 | H36: =H31-H34 -> -1130.7082 | I36: =I31-I34 -> -941.07351 | J36: =J31-J34 -> -767.91874 | ... R36: =R31-R34 -> #REF!
B37: EBITDA % | C37: =C36/C7 -> -3.8399415 | D37: =D36/D7 -> -6.4237342 | E37: =E36/E7 -> -6.4221468 | F37: =F36/F7 -> -6.8761808 | G37: =G36/G7 -> -4.6244455 | H37: =H36/H7 -> -5.1686877 | I37: =I36/I7 -> -4.2984379 | J37: =J36/J7 -> -3.3109172 | ... R37: =R36/R7 -> #REF!
B39: Depreciation | C39: ='MIS P&L'!C47*10^3/'MIS P&L'!C$2 -> 9.9138861 | D39: ='MIS P&L'!D47*10^3/'MIS P&L'!D$2 -> 10.364676 | E39: ='MIS P&L'!E47*10^3/'MIS P&L'!E$2 -> 15.051055 | F39: ='MIS P&L'!F47*10^3/'MIS P&L'!F$2 -> 14.225511 | G39: ='MIS P&L'!G47*10^3/'MIS P&L'!G$2 -> 7.5848407 | H39: ='MIS P&L'!H47*10^3/'MIS P&L'!H$2 -> 6.2254913 | I39: ='MIS P&L'!I47*10^3/'MIS P&L'!I$2 -> 4.9578049 | J39: ='MIS P&L'!J47*10^3/'MIS P&L'!J$2 -> 3.3256346 | ... L39: ='MIS P&L'!L47*10^3/'MIS P&L'!L$2 -> 2.7756297 | M39: ='MIS P&L'!#REF!*10^3/'MIS P&L'!#REF! -> #REF! | N39: ='MIS P&L'!M47*10^3/'MIS P&L'!M$2 -> 2.6803539 | O39: ='MIS P&L'!#REF!*10^3/'MIS P&L'!#REF! -> #REF! | P39: ='MIS P&L'!#REF!*10^3/'MIS P&L'!#REF! -> #REF! | Q39: ='MIS P&L'!#REF!*10^3/'MIS P&L'!#REF! -> #REF! | R39: ='MIS P&L'!#REF!*10^3/'MIS P&L'!#REF! -> #REF!
B40: Interest Income | C40: ='MIS P&L'!C48 *10^3/'MIS P&L'!C$2 -> 77.289464 | D40: ='MIS P&L'!D48 *10^3/'MIS P&L'!D$2 -> 329.27105 | E40: ='MIS P&L'!E48 *10^3/'MIS P&L'!E$2 -> 295.97256 | F40: ='MIS P&L'!F48 *10^3/'MIS P&L'!F$2 -> 175.42154 | G40: ='MIS P&L'!G48 *10^3/'MIS P&L'!G$2 -> 72.552823 | H40: ='MIS P&L'!H48 *10^3/'MIS P&L'!H$2 -> 209.18269 | I40: ='MIS P&L'!I48 *10^3/'MIS P&L'!I$2 -> 146.8818 | J40: ='MIS P&L'!J48 *10^3/'MIS P&L'!J$2 -> 82.779273 | ... L40: ='MIS P&L'!L48 *10^3/'MIS P&L'!L$2 -> 34.368919 | M40: ='MIS P&L'!#REF! *10^3/'MIS P&L'!#REF! -> #REF! | N40: ='MIS P&L'!M48 *10^3/'MIS P&L'!M$2 -> 47.070209 | O40: ='MIS P&L'!#REF! *10^3/'MIS P&L'!#REF! -> #REF! | P40: ='MIS P&L'!#REF! *10^3/'MIS P&L'!#REF! -> #REF! | Q40: ='MIS P&L'!#REF! *10^3/'MIS P&L'!#REF! -> #REF! | R40: ='MIS P&L'!#REF! *10^3/'MIS P&L'!#REF! -> #REF!
B42: PBT | C42: =C36-C39+C40 -> -875.63854 | D42: =D36-D39+D40 -> -1178.4836 | E42: =E36-E39+E40 -> -1200.5974 | F42: =F36-F39+F40 -> -1390.1914 | G42: =G36-G39+G40 -> -929.21682 | H42: =H36-H39+H40 -> -927.75097 | I42: =I36-I39+I40 -> -799.14952 | J42: =J36-J39+J40 -> -688.4651 | ... R42: =R36-R39+R40 -> #REF!
B43: PBT % | C43: =C42/C7 -> -3.565589 | D43: =D42/D7 -> -5.0556406 | E43: =E42/E7 -> -5.2043972 | F43: =F42/F7 -> -6.1617151 | G43: =G42/G7 -> -4.3222472 | H43: =H42/H7 -> -4.2409307 | I43: =I42/I7 -> -3.6501873 | J43: =J42/J7 -> -2.9683492 | ... R43: =R42/R7 -> #REF!
B45: Tax | C45: ='MIS P&L'!C53 *10^3/'MIS P&L'!C$2 -> 0 | D45: ='MIS P&L'!D53 *10^3/'MIS P&L'!D$2 -> 0 | E45: ='MIS P&L'!E53 *10^3/'MIS P&L'!E$2 -> 0 | F45: ='MIS P&L'!F53 *10^3/'MIS P&L'!F$2 -> 0 | G45: ='MIS P&L'!G53 *10^3/'MIS P&L'!G$2 -> 0 | H45: ='MIS P&L'!H53 *10^3/'MIS P&L'!H$2 -> 0 | I45: ='MIS P&L'!I53 *10^3/'MIS P&L'!I$2 -> 0 | J45: ='MIS P&L'!J53 *10^3/'MIS P&L'!J$2 -> 0 | ... L45: ='MIS P&L'!L53 *10^3/'MIS P&L'!L$2 -> 0 | M45: ='MIS P&L'!#REF! *10^3/'MIS P&L'!#REF! -> #REF! | N45: ='MIS P&L'!M53 *10^3/'MIS P&L'!M$2 -> 0 | O45: ='MIS P&L'!#REF! *10^3/'MIS P&L'!#REF! -> #REF! | P45: ='MIS P&L'!#REF! *10^3/'MIS P&L'!#REF! -> #REF! | Q45: ='MIS P&L'!#REF! *10^3/'MIS P&L'!#REF! -> #REF! | R45: ='MIS P&L'!#REF! *10^3/'MIS P&L'!#REF! -> #REF!
B47: PAT | C47: =C42-C45 -> -875.63854 | D47: =D42-D45 -> -1178.4836 | E47: =E42-E45 -> -1200.5974 | F47: =F42-F45 -> -1390.1914 | G47: =G42-G45 -> -929.21682 | H47: =H42-H45 -> -927.75097 | I47: =I42-I45 -> -799.14952 | J47: =J42-J45 -> -688.4651 | ... R47: =R42-R45 -> #REF!
B48: PAT % | C48: =C47/C7 -> -3.565589 | D48: =D47/D7 -> -5.0556406 | E48: =E47/E7 -> -5.2043972 | F48: =F47/F7 -> -6.1617151 | G48: =G47/G7 -> -4.3222472 | H48: =H47/H7 -> -4.2409307 | I48: =I47/I7 -> -3.6501873 | J48: =J47/J7 -> -2.9683492 | ... R48: =R47/R7 -> #REF!

Sheet BS
B2: Balance Sheet
B3: All Values (in INR Thousands) | C3: 45352 | D3: 45383 | E3: 45413 | F3: 45444 | G3: 45474 | H3: 45505 | I3: 45536 | J3: 45566 | K3: 45597 | L3: 45627 | M3: 45658 | N3: 45689 | O3: 45717 | P3: 45748 | Q3: 45778 | R3: 45809 | S3: 45839 | T3: 45870 | U3: 45901 | V3: 45931 | W3: 45962 | X3: 45992
B5: Equity & Liabilities
B7: Shareholder's Funds | C7: -1805.7439 | D7: =SUM(D8:D9) -> #REF! | E7: =SUM(E8:E9) -> #REF! | F7: =SUM(F8:F9) -> #REF! | G7: =SUM(G8:G9) -> #REF! | H7: =SUM(H8:H9) -> #REF! | I7: =SUM(I8:I9) -> #REF! | J7: =SUM(J8:J9) -> #REF! | K7: =SUM(K8:K9) -> #REF! | ... X7: =SUM(X8:X9) -> 3944770.4
B8: Share Capital | C8: 100 | D8: =-SUMIF('TB 0424'!G:G,BS!B8,'TB 0424'!D:D) -> 100 | E8: =-SUMIF('TB 0524'!G:G,BS!B8,'TB 0524'!D:D) -> 4307.01 | F8: =-SUMIF('TB 0624'!G:G,BS!B8,'TB 0624'!D:D) -> 4307.01 | G8: =-SUMIF('TB 0724'!G:G,BS!B8,'TB 0724'!D:D) -> 4307.01 | H8: =-SUMIF('TB 0824'!G:G,BS!B8,'TB 0824'!D:D) -> 4307.01 | I8: =-SUMIF('TB 1024'!K:K,BS!B8,'TB 1024'!H:H) -> 4307.01 | J8: =-SUMIF('TB 1024'!K:K,BS!B8,'TB 1024'!H:H) -> 4307.01 | K8: =-SUMIF('TB 1124'!H:H,BS!B8,'TB 1124'!F:F) -> 4307.01 | L8: =-SUMIF('TB 1224'!H:H,BS!B8,'TB 1224'!F:F) -> 4307.01 | M8: =-SUMIF('TB 0125'!H:H,BS!B8,'TB 0125'!F:F) -> 9441.62 | N8: =-SUMIF('TB 0225'!H:H,BS!B8,'TB 0225'!F:F) -> 9441.62 | O8: =-SUMIF('TB 0325'!H:H,BS!B8,'TB 0325'!F:F) -> 9441.62 | P8: =-SUMIF('TB 0425'!H:H,BS!B8,'TB 0425'!F:F) -> 9441.62 | Q8: =-SUMIF('TB 0525'!H:H,BS!B8,'TB 0525'!F:F) -> 9441.62 | R8: =-SUMIF('TB 0625'!H:H,BS!B8,'TB 0625'!F:F) -> 15958.12 | S8: =-SUMIF('TB 0725'!H:H,BS!B8,'TB 0725'!F:F) -> 15958.12 | T8: =-SUMIF('TB 0825'!H:H,BS!B8,'TB 0825'!F:F) -> 15958.12 | U8: =-SUMIF('TB 0925'!H:H,BS!B8,'TB 0925'!F:F) -> 15958.12 | V8: =-SUMIF('TB 1025'!H:H,BS!B8,'TB 1025'!F:F) -> 15958.12 | W8: =-SUMIF('TB 1125'!H:H,BS!B8,'TB 1125'!F:F) -> 19705.016 | X8: =-SUMIF('TB 1225'!H:H,BS!B8,'TB 1225'!F:F) -> 19627.43
B9: Reserves & Surplus | C9: -1905.7439 | D9: =-SUMIF('TB 0424'!G:G,BS!B9,'TB 0424'!D:D)+'MIS P&L'!#REF! -> #REF! | E9: =-SUMIF('TB 0524'!G:G,BS!B9,'TB 0524'!D:D)+'MIS P&L'!#REF! -> #REF! | F9: =-SUMIF('TB 0624'!G:G,BS!B9,'TB 0624'!D:D)+'MIS P&L'!#REF! -> #REF! | G9: =-SUMIF('TB 0724'!G:G,BS!B9,'TB 0724'!D:D)+'MIS P&L'!#REF! -> #REF! | H9: =-SUMIF('TB 0824'!G:G,BS!B9,'TB 0824'!D:D)+'MIS P&L'!#REF! -> #REF! | I9: =H9+'MIS P&L'!#REF! -> #REF! | J9: =I9+'MIS P&L'!#REF! -> #REF! | K9: =J9+'MIS P&L'!#REF! -> #REF! | L9: =K9+'MIS P&L'!#REF! -> #REF! | M9: =-SUMIF('TB 0125'!H:H,BS!B9,'TB 0125'!F:F)+'MIS P&L'!C55 -> 511307.94 | N9: =-SUMIF('TB 0225'!H:H,BS!B9,'TB 0225'!F:F)+'MIS P&L'!D55 -> 502445.31 | O9: =-SUMIF('TB 0325'!H:H,BS!B9,'TB 0325'!F:F)+'MIS P&L'!E55 -> 489663.48 | P9: =-SUMIF('TB 0425'!H:H,BS!B9,'TB 0425'!F:F)+'MIS P&L'!F55 -> 467154.43 | Q9: =-SUMIF('TB 0525'!H:H,BS!B9,'TB 0525'!F:F)+'MIS P&L'!G55 -> 434456.22 | R9: =-SUMIF('TB 0625'!H:H,BS!B9,'TB 0625'!F:F)+'MIS P&L'!H55 -> 2007721.1 | S9: =-SUMIF('TB 0725'!H:H,BS!B9,'TB 0725'!F:F)+'MIS P&L'!I55 -> 1953222.3 | T9: =-SUMIF('TB 0825'!H:H,BS!B9,'TB 0825'!F:F)+'MIS P&L'!J55 -> 1871427.1 | U9: =-SUMIF('TB 0925'!H:H,BS!B9,'TB 0925'!F:F)+'MIS P&L'!K55 -> 1778851.8 | V9: =-SUMIF('TB 1025'!H:H,BS!B9,'TB 1025'!F:F)+'MIS P&L'!L55 -> 2938853.1 | W9: =-SUMIF('TB 1125'!H:H,BS!B9,'TB 1125'!F:F)+'MIS P&L'!M55 -> 4132047.6 | X9: =-SUMIF('TB 1225'!H:H,BS!B9,'TB 1225'!F:F)+'MIS P&L'!N55 -> 3925143
B11: Non-Current Liabilities | C11: 1509.234 | D11: =SUM(D12:D15) -> 3065.4085 | E11: =SUM(E12:E15) -> 261.76786 | F11: =SUM(F12:F15) -> 261.76786 | G11: =SUM(G12:G15) -> 261.76786 | H11: =SUM(H12:H15) -> 261.76786 | I11: =SUM(I12:I15) -> 0 | J11: =SUM(J12:J15) -> 0 | K11: =SUM(K12:K15) -> 0 | ... X11: =SUM(X12:X15) -> 548.984
B12: Long-term Borrowings | C12: 1509.234 | D12: =-SUMIF('TB 0424'!G:G,BS!B12,'TB 0424'!D:D) -> 3065.4085 | E12: =-SUMIF('TB 0524'!G:G,BS!B12,'TB 0524'!D:D) -> 261.76786 | F12: =-SUMIF('TB 0624'!G:G,BS!B12,'TB 0624'!D:D) -> 261.76786 | G12: =-SUMIF('TB 0724'!G:G,BS!B12,'TB 0724'!D:D) -> 261.76786 | H12: =-SUMIF('TB 0824'!G:G,BS!B12,'TB 0824'!D:D) -> 261.76786 | I12: =-SUMIF('TB 0924'!G:G,BS!B12,'TB 0924'!D:D) -> 0 | J12: =-SUMIF('TB 1024'!K:K,BS!B12,'TB 1024'!H:H) -> 0 | K12: =-SUMIF('TB 1124'!H:H,BS!B12,'TB 1124'!F:F) -> 0 | L12: =-SUMIF('TB 1224'!H:H,BS!B12,'TB 1224'!F:F) -> 0 | M12: =-SUMIF('TB 0125'!H:H,BS!B12,'TB 0125'!F:F) -> 0 | N12: =-SUMIF('TB 0225'!H:H,BS!B12,'TB 0225'!F:F) -> 0 | O12: =-SUMIF('TB 0325'!H:H,BS!B12,'TB 0325'!F:F) -> 0 | P12: =-SUMIF('TB 0425'!H:H,BS!B12,'TB 0425'!F:F) -> 0 | Q12: =-SUMIF('TB 0525'!H:H,BS!B12,'TB 0525'!F:F) -> 0 | R12: =-SUMIF('TB 0625'!H:H,BS!B12,'TB 0625'!F:F) -> 0 | S12: =-SUMIF('TB 0725'!H:H,BS!B12,'TB 0725'!F:F) -> 0 | T12: =-SUMIF('TB 0825'!H:H,BS!B12,'TB 0825'!F:F) -> 0 | U12: =-SUMIF('TB 0925'!H:H,BS!B12,'TB 0925'!F:F) -> 0 | V12: =-SUMIF('TB 1025'!H:H,BS!B12,'TB 1025'!F:F) -> 0 | W12: =-SUMIF('TB 1125'!H:H,BS!B12,'TB 1125'!F:F) -> 0 | X12: =-SUMIF('TB 1225'!H:H,BS!B12,'TB 1225'!F:F) -> 0
B13: Deferred Tax Liabilities | C13: 0 | D13: =-SUMIF('TB 0424'!G:G,BS!B13,'TB 0424'!D:D) -> 0 | E13: =-SUMIF('TB 0524'!G:G,BS!B13,'TB 0524'!D:D) -> 0 | F13: =-SUMIF('TB 0624'!G:G,BS!B13,'TB 0624'!D:D) -> 0 | G13: =-SUMIF('TB 0724'!G:G,BS!B13,'TB 0724'!D:D) -> 0 | H13: =-SUMIF('TB 0824'!G:G,BS!B13,'TB 0824'!D:D) -> 0 | I13: =-SUMIF('TB 0924'!G:G,BS!B13,'TB 0924'!D:D) -> 0 | J13: =-SUMIF('TB 1024'!K:K,BS!B13,'TB 1024'!H:H) -> 0 | K13: =-SUMIF('TB 1124'!H:H,BS!B13,'TB 1124'!F:F) -> 0 | L13: =-SUMIF('TB 1224'!H:H,BS!B13,'TB 1224'!F:F) -> 0 | M13: =-SUMIF('TB 0125'!H:H,BS!B13,'TB 0125'!F:F) -> 0 | N13: =-SUMIF('TB 0225'!H:H,BS!B13,'TB 0225'!F:F) -> 0 | O13: =-SUMIF('TB 0325'!H:H,BS!B13,'TB 0325'!F:F) -> 0 | P13: =-SUMIF('TB 0425'!H:H,BS!B13,'TB 0425'!F:F) -> 0 | Q13: =-SUMIF('TB 0525'!H:H,BS!B13,'TB 0525'!F:F) -> 0 | R13: =-SUMIF('TB 0625'!H:H,BS!B13,'TB 0625'!F:F) -> 0 | S13: =-SUMIF('TB 0725'!H:H,BS!B13,'TB 0725'!F:F) -> 0 | T13: =-SUMIF('TB 0825'!H:H,BS!B13,'TB 0825'!F:F) -> 0 | U13: =-SUMIF('TB 0925'!H:H,BS!B13,'TB 0925'!F:F) -> 0 | V13: =-SUMIF('TB 1025'!H:H,BS!B13,'TB 1025'!F:F) -> 0 | W13: =-SUMIF('TB 1125'!H:H,BS!B13,'TB 1125'!F:F) -> 0 | X13: =-SUMIF('TB 1225'!H:H,BS!B13,'TB 1225'!F:F) -> 0
B14: Other Long-term Liabilities | C14: 0 | D14: =-SUMIF('TB 0424'!G:G,BS!B14,'TB 0424'!D:D) -> 0 | E14: =-SUMIF('TB 0524'!G:G,BS!B14,'TB 0524'!D:D) -> 0 | F14: =-SUMIF('TB 0624'!G:G,BS!B14,'TB 0624'!D:D) -> 0 | G14: =-SUMIF('TB 0724'!G:G,BS!B14,'TB 0724'!D:D) -> 0 | H14: =-SUMIF('TB 0824'!G:G,BS!B14,'TB 0824'!D:D) -> 0 | I14: =-SUMIF('TB 0924'!G:G,BS!B14,'TB 0924'!D:D) -> 0 | J14: =-SUMIF('TB 1024'!K:K,BS!B14,'TB 1024'!H:H) -> 0 | K14: =-SUMIF('TB 1124'!H:H,BS!B14,'TB 1124'!F:F) -> 0 | L14: =-SUMIF('TB 1224'!H:H,BS!B14,'TB 1224'!F:F) -> 0 | M14: =-SUMIF('TB 0125'!H:H,BS!B14,'TB 0125'!F:F) -> 0 | N14: =-SUMIF('TB 0225'!H:H,BS!B14,'TB 0225'!F:F) -> 0 | O14: =-SUMIF('TB 0325'!H:H,BS!B14,'TB 0325'!F:F) -> 0 | P14: =-SUMIF('TB 0425'!H:H,BS!B14,'TB 0425'!F:F) -> 0 | Q14: =-SUMIF('TB 0525'!H:H,BS!B14,'TB 0525'!F:F) -> 0 | R14: =-SUMIF('TB 0625'!H:H,BS!B14,'TB 0625'!F:F) -> 0 | S14: =-SUMIF('TB 0725'!H:H,BS!B14,'TB 0725'!F:F) -> 0 | T14: =-SUMIF('TB 0825'!H:H,BS!B14,'TB 0825'!F:F) -> 0 | U14: =-SUMIF('TB 0925'!H:H,BS!B14,'TB 0925'!F:F) -> 0 | V14: =-SUMIF('TB 1025'!H:H,BS!B14,'TB 1025'!F:F) -> 0 | W14: =-SUMIF('TB 1125'!H:H,BS!B14,'TB 1125'!F:F) -> 0 | X14: =-SUMIF('TB 1225'!H:H,BS!B14,'TB 1225'!F:F) -> 0
B15: Long-term Provisions | C15: 0 | D15: =-SUMIF('TB 0424'!G:G,BS!B15,'TB 0424'!D:D) -> 0 | E15: =-SUMIF('TB 0524'!G:G,BS!B15,'TB 0524'!D:D) -> 0 | F15: =-SUMIF('TB 0624'!G:G,BS!B15,'TB 0624'!D:D) -> 0 | G15: =-SUMIF('TB 0724'!G:G,BS!B15,'TB 0724'!D:D) -> 0 | H15: =-SUMIF('TB 0824'!G:G,BS!B15,'TB 0824'!D:D) -> 0 | I15: =-SUMIF('TB 0924'!G:G,BS!B15,'TB 0924'!D:D) -> 0 | J15: =-SUMIF('TB 1024'!K:K,BS!B15,'TB 1024'!H:H) -> 0 | K15: =-SUMIF('TB 1124'!H:H,BS!B15,'TB 1124'!F:F) -> 0 | L15: =-SUMIF('TB 1224'!H:H,BS!B15,'TB 1224'!F:F) -> 0 | M15: =-SUMIF('TB 0125'!H:H,BS!B15,'TB 0125'!F:F) -> 0 | N15: =-SUMIF('TB 0225'!H:H,BS!B15,'TB 0225'!F:F) -> 0 | O15: =-SUMIF('TB 0325'!H:H,BS!B15,'TB 0325'!F:F) -> 0 | P15: =-SUMIF('TB 0425'!H:H,BS!B15,'TB 0425'!F:F) -> 548.984 | Q15: =-SUMIF('TB 0525'!H:H,BS!B15,'TB 0525'!F:F) -> 548.984 | R15: =-SUMIF('TB 0625'!H:H,BS!B15,'TB 0625'!F:F) -> 548.984 | S15: =-SUMIF('TB 0725'!H:H,BS!B15,'TB 0725'!F:F) -> 548.984 | T15: =-SUMIF('TB 0825'!H:H,BS!B15,'TB 0825'!F:F) -> 548.984 | U15: =-SUMIF('TB 0925'!H:H,BS!B15,'TB 0925'!F:F) -> 548.984 | V15: =-SUMIF('TB 1025'!H:H,BS!B15,'TB 1025'!F:F) -> 548.984 | W15: =-SUMIF('TB 1125'!H:H,BS!B15,'TB 1125'!F:F) -> 548.984 | X15: =-SUMIF('TB 1225'!H:H,BS!B15,'TB 1225'!F:F) -> 548.984
B17: Current Liabilities | C17: 1012.025 | D17: =SUM(D18:D21) -> 1018.4789 | E17: =SUM(E18:E21) -> 1605.2266 | F17: =SUM(F18:F21) -> 1607.3874 | G17: =SUM(G18:G21) -> 1173.285 | H17: =SUM(H18:H21) -> 1326.3147 | I17: =SUM(I18:I21) -> 1877.3625 | J17: =SUM(J18:J21) -> 1887.9561 | K17: =SUM(K18:K21) -> 1780.2449 | ... X17: =SUM(X18:X21) -> 276426.75
B18: Short-term Borrowings | C18: 0 | D18: =-SUMIF('TB 0424'!G:G,BS!B18,'TB 0424'!D:D) -> 0 | E18: =-SUMIF('TB 0524'!G:G,BS!B18,'TB 0524'!D:D) -> 0 | F18: =-SUMIF('TB 0624'!G:G,BS!B18,'TB 0624'!D:D) -> 0 | G18: =-SUMIF('TB 0724'!G:G,BS!B18,'TB 0724'!D:D) -> 0 | H18: =-SUMIF('TB 0824'!G:G,BS!B18,'TB 0824'!D:D) -> 0 | I18: =-SUMIF('TB 0924'!G:G,BS!B18,'TB 0924'!D:D) -> 0 | J18: =-SUMIF('TB 1024'!K:K,BS!B18,'TB 1024'!H:H) -> 0 | K18: =-SUMIF('TB 1124'!H:H,BS!B18,'TB 1124'!F:F) -> 0 | L18: =-SUMIF('TB 1224'!H:H,BS!B18,'TB 1224'!F:F) -> 0 | M18: =-SUMIF('TB 0125'!H:H,BS!B18,'TB 0125'!F:F) -> 0 | N18: =-SUMIF('TB 0225'!H:H,BS!B18,'TB 0225'!F:F) -> 0 | O18: =-SUMIF('TB 0325'!H:H,BS!B18,'TB 0325'!F:F) -> 0 | P18: =-SUMIF('TB 0425'!H:H,BS!B18,'TB 0425'!F:F) -> 0 | Q18: =-SUMIF('TB 0525'!H:H,BS!B18,'TB 0525'!F:F) -> 0 | R18: =-SUMIF('TB 0625'!H:H,BS!B18,'TB 0625'!F:F) -> 0 | S18: =-SUMIF('TB 0725'!H:H,BS!B18,'TB 0725'!F:F) -> 0 | T18: =-SUMIF('TB 0825'!H:H,BS!B18,'TB 0825'!F:F) -> 0 | U18: =-SUMIF('TB 0925'!H:H,BS!B18,'TB 0925'!F:F) -> 0 | V18: =-SUMIF('TB 1025'!H:H,BS!B18,'TB 1025'!F:F) -> 0 | W18: =-SUMIF('TB 1125'!H:H,BS!B18,'TB 1125'!F:F) -> 0 | X18: =-SUMIF('TB 1225'!H:H,BS!B18,'TB 1225'!F:F) -> 0
B19: Trade Payables | C19: 551.291 | D19: =-SUMIF('TB 0424'!G:G,BS!B19,'TB 0424'!D:D) -> 496.062 | E19: =-SUMIF('TB 0524'!G:G,BS!B19,'TB 0524'!D:D) -> 352.27859 | F19: =-SUMIF('TB 0624'!G:G,BS!B19,'TB 0624'!D:D) -> 708.47586 | G19: =-SUMIF('TB 0724'!G:G,BS!B19,'TB 0724'!D:D) -> 327.17807 | H19: =-SUMIF('TB 0824'!G:G,BS!B19,'TB 0824'!D:D) -> 343.65628 | I19: =-SUMIF('TB 0924'!G:G,BS!B19,'TB 0924'!D:D)-8.697 -> 634.84113 | J19: =-SUMIF('TB 1024'!K:K,BS!B19,'TB 1024'!H:H) -> 926.48742 | K19: =-SUMIF('TB 1124'!H:H,BS!B19,'TB 1124'!F:F) -> 965.18671 | L19: =-SUMIF('TB 1224'!H:H,BS!B19,'TB 1224'!F:F) -> 1394.6618 | M19: =-SUMIF('TB 0125'!H:H,BS!B19,'TB 0125'!F:F) -> 1668.2542 | N19: =-SUMIF('TB 0225'!H:H,BS!B19,'TB 0225'!F:F) -> 3501.9218 | O19: =-SUMIF('TB 0325'!H:H,BS!B19,'TB 0325'!F:F) -> 6166.399 | P19: =-SUMIF('TB 0425'!H:H,BS!B19,'TB 0425'!F:F) -> 7721.7208 | Q19: =-SUMIF('TB 0525'!H:H,BS!B19,'TB 0525'!F:F) -> 12865.928 | R19: =-SUMIF('TB 0625'!H:H,BS!B19,'TB 0625'!F:F) -> 16542.411 | S19: =-SUMIF('TB 0725'!H:H,BS!B19,'TB 0725'!F:F) -> 21924.406 | T19: =-SUMIF('TB 0825'!H:H,BS!B19,'TB 0825'!F:F) -> 33091.814 | U19: =-SUMIF('TB 0925'!H:H,BS!B19,'TB 0925'!F:F) -> 51150.455 | V19: =-SUMIF('TB 1025'!H:H,BS!B19,'TB 1025'!F:F) -> 80730.005 | W19: =-SUMIF('TB 1125'!H:H,BS!B19,'TB 1125'!F:F) -> 116424.2 | X19: =-SUMIF('TB 1225'!H:H,BS!B19,'TB 1225'!F:F) -> 163006.14
B20: Other Current Liabilities | C20: 435.734 | D20: =-SUMIF('TB 0424'!G:G,BS!B20,'TB 0424'!D:D) -> 397.41689 | E20: =-SUMIF('TB 0524'!G:G,BS!B20,'TB 0524'!D:D) -> 1057.798 | F20: =-SUMIF('TB 0624'!G:G,BS!B20,'TB 0624'!D:D) -> 873.91152 | G20: =-SUMIF('TB 0724'!G:G,BS!B20,'TB 0724'!D:D) -> 821.10692 | H20: =-SUMIF('TB 0824'!G:G,BS!B20,'TB 0824'!D:D) -> 957.65841 | I20: =-SUMIF('TB 0924'!G:G,BS!B20,'TB 0924'!D:D) -> 1217.5214 | J20: =-SUMIF('TB 1024'!K:K,BS!B20,'TB 1024'!H:H)+('Raw TB'!E160/1000)+3 -> 936.46863 | K20: =-SUMIF('TB 1124'!H:H,BS!B20,'TB 1124'!F:F) -> 579.07988 | L20: =-SUMIF('TB 1224'!H:H,BS!B20,'TB 1224'!F:F) -> 538.27763 | M20: =-SUMIF('TB 0125'!H:H,BS!B20,'TB 0125'!F:F) -> 878.75247 | N20: =-SUMIF('TB 0225'!H:H,BS!B20,'TB 0225'!F:F) -> 1498.7551 | O20: =-SUMIF('TB 0325'!H:H,BS!B20,'TB 0325'!F:F) -> 1749.2525 | P20: =-SUMIF('TB 0425'!H:H,BS!B20,'TB 0425'!F:F) -> 3911.1356 | Q20: =-SUMIF('TB 0525'!H:H,BS!B20,'TB 0525'!F:F) -> 5425.7485 | R20: =-SUMIF('TB 0625'!H:H,BS!B20,'TB 0625'!F:F) -> 10550.319 | S20: =-SUMIF('TB 0725'!H:H,BS!B20,'TB 0725'!F:F) -> 9255.7159 | T20: =-SUMIF('TB 0825'!H:H,BS!B20,'TB 0825'!F:F) -> 10246.463 | U20: =-SUMIF('TB 0925'!H:H,BS!B20,'TB 0925'!F:F) -> 13676.538 | V20: =-SUMIF('TB 1025'!H:H,BS!B20,'TB 1025'!F:F) -> 17307.733 | W20: =-SUMIF('TB 1125'!H:H,BS!B20,'TB 1125'!F:F) -> 26266.12 | X20: =-SUMIF('TB 1225'!H:H,BS!B20,'TB 1225'!F:F) -> 30623.952
B21: Short-term Provisions | C21: 25 | D21: =-SUMIF('TB 0424'!G:G,BS!B21,'TB 0424'!D:D) -> 125 | E21: =-SUMIF('TB 0524'!G:G,BS!B21,'TB 0524'!D:D) -> 195.15 | F21: =-SUMIF('TB 0624'!G:G,BS!B21,'TB 0624'!D:D) -> 25 | G21: =-SUMIF('TB 0724'!G:G,BS!B21,'TB 0724'!D:D) -> 25 | H21: =-SUMIF('TB 0824'!G:G,BS!B21,'TB 0824'!D:D) -> 25 | I21: =-SUMIF('TB 0924'!G:G,BS!B21,'TB 0924'!D:D) -> 25 | J21: =-SUMIF('TB 1024'!K:K,BS!B21,'TB 1024'!H:H) -> 25 | K21: =-SUMIF('TB 1124'!H:H,BS!B21,'TB 1124'!F:F) -> 235.97827 | L21: =-SUMIF('TB 1224'!H:H,BS!B21,'TB 1224'!F:F) -> 55.6456 | M21: =-SUMIF('TB 0125'!H:H,BS!B21,'TB 0125'!F:F) -> 21.177 | N21: =-SUMIF('TB 0225'!H:H,BS!B21,'TB 0225'!F:F) -> 19.2 | O21: =-SUMIF('TB 0325'!H:H,BS!B21,'TB 0325'!F:F) -> 131.6 | P21: =-SUMIF('TB 0425'!H:H,BS!B21,'TB 0425'!F:F) -> 137.549 | Q21: =-SUMIF('TB 0525'!H:H,BS!B21,'TB 0525'!F:F) -> 184.997 | R21: =-SUMIF('TB 0625'!H:H,BS!B21,'TB 0625'!F:F) -> 6157.8194 | S21: =-SUMIF('TB 0725'!H:H,BS!B21,'TB 0725'!F:F) -> 2950.5266 | T21: =-SUMIF('TB 0825'!H:H,BS!B21,'TB 0825'!F:F) -> 31374.754 | U21: =-SUMIF('TB 0925'!H:H,BS!B21,'TB 0925'!F:F) -> 38891.496 | V21: =-SUMIF('TB 1025'!H:H,BS!B21,'TB 1025'!F:F) -> 62557.269 | W21: =-SUMIF('TB 1125'!H:H,BS!B21,'TB 1125'!F:F) -> 49806.905 | X21: =-SUMIF('TB 1225'!H:H,BS!B21,'TB 1225'!F:F) -> 82796.656
B23: TOTAL | C23: 715.5151 | D23: =D7+D11+D17 -> #REF! | E23: =E7+E11+E17 -> #REF! | F23: =F7+F11+F17 -> #REF! | G23: =G7+G11+G17 -> #REF! | H23: =H7+H11+H17 -> #REF! | I23: =I7+I11+I17 -> #REF! | J23: =J7+J11+J17 -> #REF! | K23: =K7+K11+K17 -> #REF! | ... X23: =X7+X11+X17 -> 4221746.1
V24: =V23-V43 -> 0
B25: Assets
B27: Non-Current Assets | C27: 150 | D27: =SUM(D28:D33) -> 461 | E27: =SUM(E28:E33) -> 503.1129 | F27: =SUM(F28:F33) -> 785.76557 | G27: =SUM(G28:G33) -> 2989.7887 | H27: =SUM(H28:H33) -> 2941.5163 | I27: =SUM(I28:I33) -> 3230.1353 | J27: =SUM(J28:J33) -> 3193.6392 | K27: =SUM(K28:K33) -> 3184.4312 | ... X27: =SUM(X28:X33) -> 59797.92
B28: Property, Plant & Equipment | C28: 0 | D28: =SUMIF('TB 0424'!G:G,BS!B28,'TB 0424'!D:D) -> 0 | E28: =SUMIF('TB 0524'!G:G,BS!B28,'TB 0524'!D:D) -> 42.1129 | F28: =SUMIF('TB 0624'!G:G,BS!B28,'TB 0624'!D:D) -> 40.4699 | G28: =SUMIF('TB 0724'!G:G,BS!B28,'TB 0724'!D:D) -> 857.30306 | H28: =SUMIF('TB 0824'!G:G,BS!B28,'TB 0824'!D:D) -> 821.84066 | I28: =SUMIF('TB 0924'!G:G,BS!B28,'TB 0924'!D:D) -> 774.26966 | J28: =SUMIF('TB 1024'!K:K,BS!B28,'TB 1024'!H:H) -> 750.58352 | K28: =SUMIF('TB 1124'!H:H,BS!B28,'TB 1124'!F:F) -> 754.18552 | L28: =SUMIF('TB 1224'!H:H,BS!B28,'TB 1224'!F:F) -> 740.17081 | M28: =SUMIF('TB 0125'!H:H,BS!B28,'TB 0125'!F:F) -> 2123.1732 | N28: =SUMIF('TB 0225'!H:H,BS!B28,'TB 0225'!F:F) -> 4433.3041 | O28: =SUMIF('TB 0325'!H:H,BS!B28,'TB 0325'!F:F) -> 6690.8508 | P28: =SUMIF('TB 0425'!H:H,BS!B28,'TB 0425'!F:F) -> 8283.0508 | Q28: =SUMIF('TB 0525'!H:H,BS!B28,'TB 0525'!F:F) -> 9793.0554 | R28: =SUMIF('TB 0625'!H:H,BS!B28,'TB 0625'!F:F) -> 10722.163 | S28: =SUMIF('TB 0725'!H:H,BS!B28,'TB 0725'!F:F) -> 11908.648 | T28: =SUMIF('TB 0825'!H:H,BS!B28,'TB 0825'!F:F) -> 20742.382 | U28: =SUMIF('TB 0925'!H:H,BS!B28,'TB 0925'!F:F) -> 26358.47 | V28: =SUMIF('TB 1025'!H:H,BS!B28,'TB 1025'!F:F) -> 32009.48 | W28: =SUMIF('TB 1125'!H:H,BS!B28,'TB 1125'!F:F) -> 35382.53 | X28: =SUMIF('TB 1225'!H:H,BS!B28,'TB 1225'!F:F) -> 41307.52
B29: Intangible Assets | C29: 0 | D29: =SUMIF('TB 0424'!G:G,BS!B29,'TB 0424'!D:D) -> 0 | E29: =SUMIF('TB 0524'!G:G,BS!B29,'TB 0524'!D:D) -> 0 | F29: =SUMIF('TB 0624'!G:G,BS!B29,'TB 0624'!D:D) -> 284.29567 | G29: =SUMIF('TB 0724'!G:G,BS!B29,'TB 0724'!D:D) -> 1521.4857 | H29: =SUMIF('TB 0824'!G:G,BS!B29,'TB 0824'!D:D) -> 1508.6757 | I29: =SUMIF('TB 0924'!G:G,BS!B29,'TB 0924'!D:D) -> 1495.8657 | J29: =SUMIF('TB 1024'!K:K,BS!B29,'TB 1024'!H:H) -> 1483.0557 | K29: =SUMIF('TB 1124'!H:H,BS!B29,'TB 1124'!F:F) -> 1470.2457 | L29: =SUMIF('TB 1224'!H:H,BS!B29,'TB 1224'!F:F) -> 1457.4357 | M29: =SUMIF('TB 0125'!H:H,BS!B29,'TB 0125'!F:F) -> 1444.6257 | N29: =SUMIF('TB 0225'!H:H,BS!B29,'TB 0225'!F:F) -> 1431.8157 | O29: =SUMIF('TB 0325'!H:H,BS!B29,'TB 0325'!F:F) -> 1425.0189 | P29: =SUMIF('TB 0425'!H:H,BS!B29,'TB 0425'!F:F) -> 0 | Q29: =SUMIF('TB 0525'!H:H,BS!B29,'TB 0525'!F:F) -> 0 | R29: =SUMIF('TB 0625'!H:H,BS!B29,'TB 0625'!F:F) -> 0 | S29: =SUMIF('TB 0725'!H:H,BS!B29,'TB 0725'!F:F) -> 0 | T29: =SUMIF('TB 0825'!H:H,BS!B29,'TB 0825'!F:F) -> 0 | U29: =SUMIF('TB 0925'!H:H,BS!B29,'TB 0925'!F:F) -> -848.49468 | V29: =SUMIF('TB 1025'!H:H,BS!B29,'TB 1025'!F:F) -> 0 | W29: =SUMIF('TB 1125'!H:H,BS!B29,'TB 1125'!F:F) -> 0 | X29: =SUMIF('TB 1225'!H:H,BS!B29,'TB 1225'!F:F) -> 0
B30: Non-current Investments | C30: 0 | D30: =SUMIF('TB 0424'!G:G,BS!B30,'TB 0424'!D:D) -> 0 | E30: =SUMIF('TB 0524'!G:G,BS!B30,'TB 0524'!D:D) -> 0 | F30: =SUMIF('TB 0624'!G:G,BS!B30,'TB 0624'!D:D) -> 0 | G30: =SUMIF('TB 0724'!G:G,BS!B30,'TB 0724'!D:D) -> 0 | H30: =SUMIF('TB 0824'!G:G,BS!B30,'TB 0824'!D:D) -> 0 | I30: =SUMIF('TB 0924'!G:G,BS!B30,'TB 0924'!D:D) -> 0 | J30: =SUMIF('TB 1024'!K:K,BS!B30,'TB 1024'!H:H) -> 0 | K30: =SUMIF('TB 1124'!H:H,BS!B30,'TB 1124'!F:F) -> 0 | L30: =SUMIF('TB 1224'!H:H,BS!B30,'TB 1224'!F:F) -> 0 | M30: =SUMIF('TB 0125'!H:H,BS!B30,'TB 0125'!F:F) -> 0 | N30: =SUMIF('TB 0225'!H:H,BS!B30,'TB 0225'!F:F) -> 0 | O30: =SUMIF('TB 0325'!H:H,BS!B30,'TB 0325'!F:F) -> 0 | P30: =SUMIF('TB 0425'!H:H,BS!B30,'TB 0425'!F:F) -> 0 | Q30: =SUMIF('TB 0525'!H:H,BS!B30,'TB 0525'!F:F) -> 0 | R30: =SUMIF('TB 0625'!H:H,BS!B30,'TB 0625'!F:F) -> 0 | S30: =SUMIF('TB 0725'!H:H,BS!B30,'TB 0725'!F:F) -> 0 | T30: =SUMIF('TB 0825'!H:H,BS!B30,'TB 0825'!F:F) -> 0 | U30: =SUMIF('TB 0925'!H:H,BS!B30,'TB 0925'!F:F) -> 0 | V30: =SUMIF('TB 1025'!H:H,BS!B30,'TB 1025'!F:F) -> 0 | W30: =SUMIF('TB 1125'!H:H,BS!B30,'TB 1125'!F:F) -> 0 | X30: =SUMIF('TB 1225'!H:H,BS!B30,'TB 1225'!F:F) -> 0
B31: Deferred Tax Assets | C31: 0 | D31: =SUMIF('TB 0424'!G:G,BS!B31,'TB 0424'!D:D) -> 0 | E31: =SUMIF('TB 0524'!G:G,BS!B31,'TB 0524'!D:D) -> 0 | F31: =SUMIF('TB 0624'!G:G,BS!B31,'TB 0624'!D:D) -> 0 | G31: =SUMIF('TB 0724'!G:G,BS!B31,'TB 0724'!D:D) -> 0 | H31: =SUMIF('TB 0824'!G:G,BS!B31,'TB 0824'!D:D) -> 0 | I31: =SUMIF('TB 0924'!G:G,BS!B31,'TB 0924'!D:D) -> 0 | J31: =SUMIF('TB 1024'!K:K,BS!B31,'TB 1024'!H:H) -> 0 | K31: =SUMIF('TB 1124'!H:H,BS!B31,'TB 1124'!F:F) -> 0 | L31: =SUMIF('TB 1224'!H:H,BS!B31,'TB 1224'!F:F) -> 0 | M31: =SUMIF('TB 0125'!H:H,BS!B31,'TB 0125'!F:F) -> 0 | N31: =SUMIF('TB 0225'!H:H,BS!B31,'TB 0225'!F:F) -> 0 | O31: =SUMIF('TB 0325'!H:H,BS!B31,'TB 0325'!F:F) -> 0 | P31: =SUMIF('TB 0425'!H:H,BS!B31,'TB 0425'!F:F) -> 0 | Q31: =SUMIF('TB 0525'!H:H,BS!B31,'TB 0525'!F:F) -> 0 | R31: =SUMIF('TB 0625'!H:H,BS!B31,'TB 0625'!F:F) -> 0 | S31: =SUMIF('TB 0725'!H:H,BS!B31,'TB 0725'!F:F) -> 0 | T31: =SUMIF('TB 0825'!H:H,BS!B31,'TB 0825'!F:F) -> 0 | U31: =SUMIF('TB 0925'!H:H,BS!B31,'TB 0925'!F:F) -> 0 | V31: =SUMIF('TB 1025'!H:H,BS!B31,'TB 1025'!F:F) -> 0 | W31: =SUMIF('TB 1125'!H:H,BS!B31,'TB 1125'!F:F) -> 0 | X31: =SUMIF('TB 1225'!H:H,BS!B31,'TB 1225'!F:F) -> 0
B32: Long-term Loans & Advances | C32: 150 | D32: =SUMIF('TB 0424'!G:G,BS!B32,'TB 0424'!D:D) -> 461 | E32: =SUMIF('TB 0524'!G:G,BS!B32,'TB 0524'!D:D) -> 461 | F32: =SUMIF('TB 0624'!G:G,BS!B32,'TB 0624'!D:D) -> 461 | G32: =SUMIF('TB 0724'!G:G,BS!B32,'TB 0724'!D:D) -> 611 | H32: =SUMIF('TB 0824'!G:G,BS!B32,'TB 0824'!D:D) -> 611 | I32: =SUMIF('TB 0924'!G:G,BS!B32,'TB 0924'!D:D) -> 960 | J32: =SUMIF('TB 1024'!K:K,BS!B32,'TB 1024'!H:H) -> 960 | K32: =SUMIF('TB 1124'!H:H,BS!B32,'TB 1124'!F:F) -> 960 | L32: =SUMIF('TB 1224'!H:H,BS!B32,'TB 1224'!F:F) -> 1080 | M32: =SUMIF('TB 0125'!H:H,BS!B32,'TB 0125'!F:F) -> 1680 | N32: =SUMIF('TB 0225'!H:H,BS!B32,'TB 0225'!F:F) -> 1680 | O32: =SUMIF('TB 0325'!H:H,BS!B32,'TB 0325'!F:F) -> 4196 | P32: =SUMIF('TB 0425'!H:H,BS!B32,'TB 0425'!F:F) -> 0 | Q32: =SUMIF('TB 0525'!H:H,BS!B32,'TB 0525'!F:F) -> 0 | R32: =SUMIF('TB 0625'!H:H,BS!B32,'TB 0625'!F:F) -> 0 | S32: =SUMIF('TB 0725'!H:H,BS!B32,'TB 0725'!F:F) -> 0 | T32: =SUMIF('TB 0825'!H:H,BS!B32,'TB 0825'!F:F) -> 0 | U32: =SUMIF('TB 0925'!H:H,BS!B32,'TB 0925'!F:F) -> 0 | V32: =SUMIF('TB 1025'!H:H,BS!B32,'TB 1025'!F:F) -> 0 | W32: =SUMIF('TB 1125'!H:H,BS!B32,'TB 1125'!F:F) -> 0 | X32: =SUMIF('TB 1225'!H:H,BS!B32,'TB 1225'!F:F) -> 0
B33: Other Non-current Assets | C33: 0 | D33: =SUMIF('TB 0424'!G:G,BS!B33,'TB 0424'!D:D) -> 0 | E33: =SUMIF('TB 0524'!G:G,BS!B33,'TB 0524'!D:D) -> 0 | F33: =SUMIF('TB 0624'!G:G,BS!B33,'TB 0624'!D:D) -> 0 | G33: =SUMIF('TB 0724'!G:G,BS!B33,'TB 0724'!D:D) -> 0 | H33: =SUMIF('TB 0824'!G:G,BS!B33,'TB 0824'!D:D) -> 0 | I33: =SUMIF('TB 0924'!G:G,BS!B33,'TB 0924'!D:D) -> 0 | J33: =SUMIF('TB 1024'!K:K,BS!B33,'TB 1024'!H:H) -> 0 | K33: =SUMIF('TB 1124'!H:H,BS!B33,'TB 1124'!F:F) -> 0 | L33: =SUMIF('TB 1224'!H:H,BS!B33,'TB 1224'!F:F) -> 0 | M33: =SUMIF('TB 0125'!H:H,BS!B33,'TB 0125'!F:F) -> 0 | N33: =SUMIF('TB 0225'!H:H,BS!B33,'TB 0225'!F:F) -> 0 | O33: =SUMIF('TB 0325'!H:H,BS!B33,'TB 0325'!F:F) -> 0 | P33: =SUMIF('TB 0425'!H:H,BS!B33,'TB 0425'!F:F) -> 4989 | Q33: =SUMIF('TB 0525'!H:H,BS!B33,'TB 0525'!F:F) -> 6092 | R33: =SUMIF('TB 0625'!H:H,BS!B33,'TB 0625'!F:F) -> 7521.4 | S33: =SUMIF('TB 0725'!H:H,BS!B33,'TB 0725'!F:F) -> 8204.4 | T33: =SUMIF('TB 0825'!H:H,BS!B33,'TB 0825'!F:F) -> 8841.4 | U33: =SUMIF('TB 0925'!H:H,BS!B33,'TB 0925'!F:F) -> 10992.4 | V33: =SUMIF('TB 1025'!H:H,BS!B33,'TB 1025'!F:F) -> 15715.4 | W33: =SUMIF('TB 1125'!H:H,BS!B33,'TB 1125'!F:F) -> 15705.4 | X33: =SUMIF('TB 1225'!H:H,BS!B33,'TB 1225'!F:F) -> 18490.4
B35: Current Assets | C35: 565.5151 | D35: =SUM(D36:D41) -> 521.6599 | E35: =SUM(E36:E41) -> 74511.118 | F35: =SUM(F36:F41) -> 71394.431 | G35: =SUM(G36:G41) -> 66157.545 | H35: =SUM(H36:H41) -> 63282.38 | I35: =SUM(I36:I41) -> 59885.662 | J35: =SUM(J36:J41) -> 56672.879 | K35: =SUM(K36:K41) -> 53479.349 | ... X35: =SUM(X36:X41) -> 4161948.2
B36: Current Investments | C36: 0 | D36: =SUMIF('TB 0424'!G:G,BS!B36,'TB 0424'!D:D) -> 0 | E36: =SUMIF('TB 0524'!G:G,BS!B36,'TB 0524'!D:D) -> 72000 | F36: =SUMIF('TB 0624'!G:G,BS!B36,'TB 0624'!D:D) -> 70000 | G36: =SUMIF('TB 0724'!G:G,BS!B36,'TB 0724'!D:D) -> 64502.214 | H36: =SUMIF('TB 0824'!G:G,BS!B36,'TB 0824'!D:D) -> 60000 | I36: =SUMIF('TB 0924'!G:G,BS!B36,'TB 0924'!D:D) -> 57000 | J36: =SUMIF('TB 1024'!K:K,BS!B36,'TB 1024'!H:H) -> 53500 | K36: =SUMIF('TB 1124'!H:H,BS!B36,'TB 1124'!F:F) -> 50000 | L36: =SUMIF('TB 1224'!H:H,BS!B36,'TB 1224'!F:F) -> 47000 | M36: =SUMIF('TB 0125'!H:H,BS!B36,'TB 0125'!F:F) -> 511500 | N36: =SUMIF('TB 0225'!H:H,BS!B36,'TB 0225'!F:F) -> 498000 | O36: =SUMIF('TB 0325'!H:H,BS!B36,'TB 0325'!F:F) -> 478000 | P36: =SUMIF('TB 0425'!H:H,BS!B36,'TB 0425'!F:F) -> 452000 | Q36: =SUMIF('TB 0525'!H:H,BS!B36,'TB 0525'!F:F) -> 415000 | R36: =SUMIF('TB 0625'!H:H,BS!B36,'TB 0625'!F:F) -> 1979500 | S36: =SUMIF('TB 0725'!H:H,BS!B36,'TB 0725'!F:F) -> 1942000 | T36: =SUMIF('TB 0825'!H:H,BS!B36,'TB 0825'!F:F) -> 1872012.9 | U36: =SUMIF('TB 0925'!H:H,BS!B36,'TB 0925'!F:F) -> 1797198.2 | V36: =SUMIF('TB 1025'!H:H,BS!B36,'TB 1025'!F:F) -> 1650468.6 | W36: =SUMIF('TB 1125'!H:H,BS!B36,'TB 1125'!F:F) -> 4173443.6 | X36: =SUMIF('TB 1225'!H:H,BS!B36,'TB 1225'!F:F) -> 3963942.5
B37: Inventories | C37: 0 | D37: =SUMIF('TB 0424'!G:G,BS!B37,'TB 0424'!D:D) -> 0 | E37: =SUMIF('TB 0524'!G:G,BS!B37,'TB 0524'!D:D) -> 0 | F37: =SUMIF('TB 0624'!G:G,BS!B37,'TB 0624'!D:D) -> 0 | G37: =SUMIF('TB 0724'!G:G,BS!B37,'TB 0724'!D:D) -> 0 | H37: =SUMIF('TB 0824'!G:G,BS!B37,'TB 0824'!D:D) -> 0 | I37: =SUMIF('TB 0924'!G:G,BS!B37,'TB 0924'!D:D) -> 0 | J37: =SUMIF('TB 1024'!K:K,BS!B37,'TB 1024'!H:H) -> 0 | K37: =SUMIF('TB 1124'!H:H,BS!B37,'TB 1124'!F:F) -> 0 | L37: =SUMIF('TB 1224'!H:H,BS!B37,'TB 1224'!F:F) -> 0 | M37: =SUMIF('TB 0125'!H:H,BS!B37,'TB 0125'!F:F) -> 0 | N37: =SUMIF('TB 0225'!H:H,BS!B37,'TB 0225'!F:F) -> 0 | O37: =SUMIF('TB 0325'!H:H,BS!B37,'TB 0325'!F:F) -> 0 | P37: =SUMIF('TB 0425'!H:H,BS!B37,'TB 0425'!F:F) -> 0 | Q37: =SUMIF('TB 0525'!H:H,BS!B37,'TB 0525'!F:F) -> 0 | R37: =SUMIF('TB 0625'!H:H,BS!B37,'TB 0625'!F:F) -> 0 | S37: =SUMIF('TB 0725'!H:H,BS!B37,'TB 0725'!F:F) -> 0 | T37: =SUMIF('TB 0825'!H:H,BS!B37,'TB 0825'!F:F) -> 0 | U37: =SUMIF('TB 0925'!H:H,BS!B37,'TB 0925'!F:F) -> 0 | V37: =SUMIF('TB 1025'!H:H,BS!B37,'TB 1025'!F:F) -> 0 | W37: =SUMIF('TB 1125'!H:H,BS!B37,'TB 1125'!F:F) -> 0 | X37: =SUMIF('TB 1225'!H:H,BS!B37,'TB 1225'!F:F) -> 0
B38: Trade Receivables | C38: 0 | D38: =SUMIF('TB 0424'!G:G,BS!B38,'TB 0424'!D:D) -> 0 | E38: =SUMIF('TB 0524'!G:G,BS!B38,'TB 0524'!D:D) -> 16.97903 | F38: =SUMIF('TB 0624'!G:G,BS!B38,'TB 0624'!D:D) -> 54.96598 | G38: =SUMIF('TB 0724'!G:G,BS!B38,'TB 0724'!D:D) -> 12.73977 | H38: =SUMIF('TB 0824'!G:G,BS!B38,'TB 0824'!D:D) -> 33.84598 | I38: =SUMIF('TB 0924'!G:G,BS!B38,'TB 0924'!D:D) -> 39.04079 | J38: =SUMIF('TB 1024'!K:K,BS!B38,'TB 1024'!H:H)+('Raw TB'!D159/1000)-57.85846 -> 76.48125 | K38: =SUMIF('TB 1124'!H:H,BS!B38,'TB 1124'!F:F) -> 42.42715 | L38: =SUMIF('TB 1224'!H:H,BS!B38,'TB 1224'!F:F) -> 53.18298 | M38: =SUMIF('TB 0125'!H:H,BS!B38,'TB 0125'!F:F) -> 57.74493 | N38: =SUMIF('TB 0225'!H:H,BS!B38,'TB 0225'!F:F) -> 59.03632 | O38: =SUMIF('TB 0325'!H:H,BS!B38,'TB 0325'!F:F) -> 129.22068 | P38: =SUMIF('TB 0425'!H:H,BS!B38,'TB 0425'!F:F) -> 79.57419 | Q38: =SUMIF('TB 0525'!H:H,BS!B38,'TB 0525'!F:F) -> 350.37062 | R38: =SUMIF('TB 0625'!H:H,BS!B38,'TB 0625'!F:F) -> 556.1828 | S38: =SUMIF('TB 0725'!H:H,BS!B38,'TB 0725'!F:F) -> 181.86937 | T38: =SUMIF('TB 0825'!H:H,BS!B38,'TB 0825'!F:F) -> 1084.2103 | U38: =SUMIF('TB 0925'!H:H,BS!B38,'TB 0925'!F:F) -> 1355.8121 | V38: =SUMIF('TB 1025'!H:H,BS!B38,'TB 1025'!F:F) -> 680.33862 | W38: =SUMIF('TB 1125'!H:H,BS!B38,'TB 1125'!F:F) -> 3013.317 | X38: =SUMIF('TB 1225'!H:H,BS!B38,'TB 1225'!F:F) -> 1224.37
B39: Cash & Cash Equivalents | C39: 468.08582 | D39: =SUMIF('TB 0424'!G:G,BS!B39,'TB 0424'!D:D) -> 354.35406 | E39: =SUMIF('TB 0524'!G:G,BS!B39,'TB 0524'!D:D) -> 2024.1879 | F39: =SUMIF('TB 0624'!G:G,BS!B39,'TB 0624'!D:D) -> 627.2803 | G39: =SUMIF('TB 0724'!G:G,BS!B39,'TB 0724'!D:D) -> 581.8522 | H39: =SUMIF('TB 0824'!G:G,BS!B39,'TB 0824'!D:D) -> 1896.0085 | I39: =SUMIF('TB 0924'!G:G,BS!B39,'TB 0924'!D:D) -> 1529.1704 | J39: =SUMIF('TB 1024'!K:K,BS!B39,'TB 1024'!H:H) -> 1567.3858 | K39: =SUMIF('TB 1124'!H:H,BS!B39,'TB 1124'!F:F) -> 1939.9963 | L39: =SUMIF('TB 1224'!H:H,BS!B39,'TB 1224'!F:F) -> 1611.7121 | M39: =SUMIF('TB 0125'!H:H,BS!B39,'TB 0125'!F:F) -> 3325.1475 | N39: =SUMIF('TB 0225'!H:H,BS!B39,'TB 0225'!F:F) -> 5801.5587 | O39: =SUMIF('TB 0325'!H:H,BS!B39,'TB 0325'!F:F) -> 7334.7525 | P39: =SUMIF('TB 0425'!H:H,BS!B39,'TB 0425'!F:F) -> 11312.843 | Q39: =SUMIF('TB 0525'!H:H,BS!B39,'TB 0525'!F:F) -> 15675.441 | R39: =SUMIF('TB 0625'!H:H,BS!B39,'TB 0625'!F:F) -> 29175.034 | S39: =SUMIF('TB 0725'!H:H,BS!B39,'TB 0725'!F:F) -> 5193.4857 | T39: =SUMIF('TB 0825'!H:H,BS!B39,'TB 0825'!F:F) -> 15478.375 | U39: =SUMIF('TB 0925'!H:H,BS!B39,'TB 0925'!F:F) -> 3805.2395 | V39: =SUMIF('TB 1025'!H:H,BS!B39,'TB 1025'!F:F) -> 1331545.5 | W39: =SUMIF('TB 1125'!H:H,BS!B39,'TB 1125'!F:F) -> 1215.9606 | X39: =SUMIF('TB 1225'!H:H,BS!B39,'TB 1225'!F:F) -> 42514.249
B40: Short-term Loans & Advances | C40: 0 | D40: =SUMIF('TB 0424'!G:G,BS!B40,'TB 0424'!D:D) -> 0 | E40: =SUMIF('TB 0524'!G:G,BS!B40,'TB 0524'!D:D) -> 0 | F40: =SUMIF('TB 0624'!G:G,BS!B40,'TB 0624'!D:D) -> 0 | G40: =SUMIF('TB 0724'!G:G,BS!B40,'TB 0724'!D:D) -> 0 | H40: =SUMIF('TB 0824'!G:G,BS!B40,'TB 0824'!D:D) -> 0 | I40: =SUMIF('TB 0924'!G:G,BS!B40,'TB 0924'!D:D) -> 0 | J40: =SUMIF('TB 1024'!K:K,BS!B40,'TB 1024'!H:H) -> 0 | K40: =SUMIF('TB 1124'!H:H,BS!B40,'TB 1124'!F:F) -> 0 | L40: =SUMIF('TB 1224'!H:H,BS!B40,'TB 1224'!F:F) -> 0 | M40: =SUMIF('TB 0125'!H:H,BS!B40,'TB 0125'!F:F) -> 0 | N40: =SUMIF('TB 0225'!H:H,BS!B40,'TB 0225'!F:F) -> 0 | O40: =SUMIF('TB 0325'!H:H,BS!B40,'TB 0325'!F:F) -> 0 | P40: =SUMIF('TB 0425'!H:H,BS!B40,'TB 0425'!F:F) -> 0 | Q40: =SUMIF('TB 0525'!H:H,BS!B40,'TB 0525'!F:F) -> 0 | R40: =SUMIF('TB 0625'!H:H,BS!B40,'TB 0625'!F:F) -> 0 | S40: =SUMIF('TB 0725'!H:H,BS!B40,'TB 0725'!F:F) -> 0 | T40: =SUMIF('TB 0825'!H:H,BS!B40,'TB 0825'!F:F) -> 0 | U40: =SUMIF('TB 0925'!H:H,BS!B40,'TB 0925'!F:F) -> 0 | V40: =SUMIF('TB 1025'!H:H,BS!B40,'TB 1025'!F:F) -> 0 | W40: =SUMIF('TB 1125'!H:H,BS!B40,'TB 1125'!F:F) -> 0 | X40: =SUMIF('TB 1225'!H:H,BS!B40,'TB 1225'!F:F) -> 0
B41: Other Current Assets | C41: 97.42928 | D41: =SUMIF('TB 0424'!G:G,BS!B41,'TB 0424'!D:D) -> 167.30584 | E41: =SUMIF('TB 0524'!G:G,BS!B41,'TB 0524'!D:D) -> 469.9513 | F41: =SUMIF('TB 0624'!G:G,BS!B41,'TB 0624'!D:D) -> 712.18499 | G41: =SUMIF('TB 0724'!G:G,BS!B41,'TB 0724'!D:D) -> 1060.7388 | H41: =SUMIF('TB 0824'!G:G,BS!B41,'TB 0824'!D:D) -> 1352.5252 | I41: =SUMIF('TB 0924'!G:G,BS!B41,'TB 0924'!D:D) -> 1317.4508 | J41: =SUMIF('TB 1024'!K:K,BS!B41,'TB 1024'!H:H) -> 1529.0124 | K41: =SUMIF('TB 1124'!H:H,BS!B41,'TB 1124'!F:F) -> 1496.9254 | L41: =SUMIF('TB 1224'!H:H,BS!B41,'TB 1224'!F:F) -> 1825.8358 | M41: =SUMIF('TB 0125'!H:H,BS!B41,'TB 0125'!F:F) -> 3187.0561 | N41: =SUMIF('TB 0225'!H:H,BS!B41,'TB 0225'!F:F) -> 5501.0955 | O41: =SUMIF('TB 0325'!H:H,BS!B41,'TB 0325'!F:F) -> 9376.5058 | P41: =SUMIF('TB 0425'!H:H,BS!B41,'TB 0425'!F:F) -> 12250.969 | Q41: =SUMIF('TB 0525'!H:H,BS!B41,'TB 0525'!F:F) -> 16012.628 | R41: =SUMIF('TB 0625'!H:H,BS!B41,'TB 0625'!F:F) -> 30003.953 | S41: =SUMIF('TB 0725'!H:H,BS!B41,'TB 0725'!F:F) -> 36371.628 | T41: =SUMIF('TB 0825'!H:H,BS!B41,'TB 0825'!F:F) -> 44487.992 | U41: =SUMIF('TB 0925'!H:H,BS!B41,'TB 0925'!F:F) -> 60215.672 | V41: =SUMIF('TB 1025'!H:H,BS!B41,'TB 1025'!F:F) -> 85535.902 | W41: =SUMIF('TB 1125'!H:H,BS!B41,'TB 1125'!F:F) -> 116037.98 | X41: =SUMIF('TB 1225'!H:H,BS!B41,'TB 1225'!F:F) -> 154267.05
B43: TOTAL | C43: 715.5151 | D43: =D27+D35 -> 982.6599 | E43: =E27+E35 -> 75014.231 | F43: =F27+F35 -> 72180.197 | G43: =G27+G35 -> 69147.333 | H43: =H27+H35 -> 66223.896 | I43: =I27+I35 -> 63115.797 | J43: =J27+J35 -> 59866.519 | K43: =K27+K35 -> 56663.78 | ... X43: =X27+X35 -> 4221746.1

Sheet Cash Flow
B2: Cash Flow Statement
B3: All Values (in INR Thousands) | C3: 45748 | D3: 45778 | E3: 45809 | F3: 45839 | G3: 45870 | H3: 45901 | I3: 45931 | J3: 45962 | K3: 45992
B5: A. Cash flow from operating activities
B6: Loss before taxation | C6: -20732.043 | D6: ='MIS P&L'!G55 -> -32698.211 | E6: ='MIS P&L'!H55 -> -43800.051 | F6: ='MIS P&L'!I55 -> -54498.801 | G6: ='MIS P&L'!J55 -> -81795.162 | H6: ='MIS P&L'!K55 -> -92575.36 | I6: ='MIS P&L'!L55 -> -140807.79 | J6: ='MIS P&L'!M55 -> -155242.06 | K6: ='MIS P&L'!N55 -> -205163.89
B7: Adjustments for:
B8: Depreciation | C8: ='MIS P&L'!F47 -> 213.09815 | D8: ='MIS P&L'!G47 -> 266.90296 | E8: ='MIS P&L'!H47 -> 293.91167 | F8: ='MIS P&L'!I47 -> 338.10246 | G8: ='MIS P&L'!J47 -> 395.112 | H8: ='MIS P&L'!K47 -> 653.15802 | I8: ='MIS P&L'!L47 -> 856.74808 | J8: ='MIS P&L'!M47 -> 1006.8347 | K8: ='MIS P&L'!N47 -> 1184.2885
B9: Interest income | C9: =-'MIS P&L'!F48 -> -2627.8147 | D9: =-'MIS P&L'!G48 -> -2553.0613 | E9: =-'MIS P&L'!H48 -> -9875.7241 | F9: =-'MIS P&L'!I48 -> -10016.751 | G9: =-'MIS P&L'!J48 -> -9834.8399 | H9: =-'MIS P&L'!K48 -> -10218.875 | I9: =-'MIS P&L'!L48 -> -10608.585 | J9: =-'MIS P&L'!M48 -> -17681.218 | K9: =-'MIS P&L'!N48 -> -18913.496
B10: Operating cash flow before working capital changes | C10: =SUM(C6:C9) -> -23146.759 | D10: =SUM(D6:D9) -> -34984.369 | E10: =SUM(E6:E9) -> -53381.863 | F10: =SUM(F6:F9) -> -64177.449 | G10: =SUM(G6:G9) -> -91234.89 | H10: =SUM(H6:H9) -> -102141.08 | I10: =SUM(I6:I9) -> -150559.62 | J10: =SUM(J6:J9) -> -171916.45 | K10: =SUM(K6:K9) -> -222893.09
B12: Working capital changes:
B13: (Increase) in Trade Receivables | C13: =BS!O38-BS!P38 -> 49.64649 | D13: =BS!P38-BS!Q38 -> -270.79643 | E13: =BS!Q38-BS!R38 -> -205.81218 | F13: =BS!R38-BS!S38 -> 374.31343 | G13: =BS!S38-BS!T38 -> -902.34089 | H13: =BS!T38-BS!U38 -> -271.60187 | I13: =BS!U38-BS!V38 -> 675.47351 | J13: =BS!V38-BS!W38 -> -2332.9784 | K13: =BS!W38-BS!X38 -> 1788.9471
B14: (Decrease)/Increase in Trade Payables | C14: =BS!P19-BS!O19 -> 1555.3218 | D14: =BS!Q19-BS!P19 -> 5144.2071 | E14: =BS!R19-BS!Q19 -> 3676.4829 | F14: =BS!S19-BS!R19 -> 5381.9954 | G14: =BS!T19-BS!S19 -> 11167.407 | H14: =BS!U19-BS!T19 -> 18058.642 | I14: =BS!V19-BS!U19 -> 29579.55 | J14: =BS!W19-BS!V19 -> 35694.199 | K14: =BS!X19-BS!W19 -> 46581.938
B15: (Decrease)/Increase in Other Current Liabilities | C15: =-BS!O20+BS!P20 -> 2161.8832 | D15: =-BS!P20+BS!Q20 -> 1514.6129 | E15: =-BS!Q20+BS!R20 -> 5124.5701 | F15: =-BS!R20+BS!S20 -> -1294.6027 | G15: =-BS!S20+BS!T20 -> 990.74732 | H15: =-BS!T20+BS!U20 -> 3430.0747 | I15: =-BS!U20+BS!V20 -> 3631.1951 | J15: =-BS!V20+BS!W20 -> 8958.3866 | K15: =-BS!W20+BS!X20 -> 4357.8322
B16: (Decrease)/Increase in Short Term Provisions | C16: =-BS!O21+BS!P21 -> 5.949 | D16: =-BS!P21+BS!Q21 -> 47.448 | E16: =-BS!Q21+BS!R21 -> 5972.8224 | F16: =-BS!R21+BS!S21 -> -3207.2928 | G16: =-BS!S21+BS!T21 -> 28424.227 | H16: =-BS!T21+BS!U21 -> 7516.7421 | I16: =-BS!U21+BS!V21 -> 23665.773 | J16: =-BS!V21+BS!W21 -> -12750.363 | K16: =-BS!W21+BS!X21 -> 32989.751
B17: (Increase)/Decrease in Other Current Assets | C17: =BS!O41-BS!P41 -> -2874.4629 | D17: =BS!P41-BS!Q41 -> -3761.6594 | E17: =BS!Q41-BS!R41 -> -13991.325 | F17: =BS!R41-BS!S41 -> -6367.6754 | G17: =BS!S41-BS!T41 -> -8116.3633 | H17: =BS!T41-BS!U41 -> -15727.68 | I17: =BS!U41-BS!V41 -> -25320.23 | J17: =BS!V41-BS!W41 -> -30502.082 | K17: =BS!W41-BS!X41 -> -38229.063
B18: (Increase) in Long term advances | C18: =BS!O32-BS!P33 -> -793 | D18: =BS!P33-BS!Q33 -> -1103 | E18: =BS!Q33-BS!R33 -> -1429.4 | F18: =BS!R33-BS!S33 -> -683 | G18: =BS!S33-BS!T33 -> -637 | H18: =BS!T33-BS!U33 -> -2151 | I18: =BS!U33-BS!V33 -> -4723 | J18: =BS!V33-BS!W33 -> 10 | K18: =BS!W33-BS!X33 -> -2785
B19: Cash generated from operations | C19: =SUM(C10:C18) -> -23041.422 | D19: =SUM(D10:D18) -> -33413.557 | E19: =SUM(E10:E18) -> -54234.525 | F19: =SUM(F10:F18) -> -69973.711 | G19: =SUM(G10:G18) -> -60308.212 | H19: =SUM(H10:H18) -> -91285.901 | I19: =SUM(I10:I18) -> -123050.86 | J19: =SUM(J10:J18) -> -172839.28 | K19: =SUM(K10:K18) -> -178188.69
B20: Taxes Paid | C20: 0 | D20: 0 | E20: 0 | F20: 0 | G20: 0 | H20: 0 | I20: 0 | J20: 0 | K20: 0
B21: Net Cash Flow from/(used in) Operating Activities | C21: =SUM(C19:C20) -> -23041.422 | D21: =SUM(D19:D20) -> -33413.557 | E21: =SUM(E19:E20) -> -54234.525 | F21: =SUM(F19:F20) -> -69973.711 | G21: =SUM(G19:G20) -> -60308.212 | H21: =SUM(H19:H20) -> -91285.901 | I21: =SUM(I19:I20) -> -123050.86 | J21: =SUM(J19:J20) -> -172839.28 | K21: =SUM(K19:K20) -> -178188.69
B23: B. Cash flows from investing activities
B24: (Increase)/Decrease in Current Investments | C24: =BS!O36-BS!P36 -> 26000 | D24: =BS!P36-BS!Q36 -> 37000 | E24: =BS!Q36-BS!R36 -> -1564500 | F24: =BS!R36-BS!S36 -> 37500 | G24: =BS!S36-BS!T36 -> 69987.107 | H24: =BS!T36-BS!U36 -> 74814.643 | I24: =BS!U36-BS!V36 -> 146729.65 | J24: =BS!V36-BS!W36 -> -2522975 | K24: =BS!W36-BS!X36 -> 209501.05
B25: Interest income from Fixed Deposit | C25: ='MIS P&L'!F48 -> 2627.8147 | D25: ='MIS P&L'!G48 -> 2553.0613 | E25: ='MIS P&L'!H48 -> 9875.7241 | F25: ='MIS P&L'!I48 -> 10016.751 | G25: ='MIS P&L'!J48 -> 9834.8399 | H25: ='MIS P&L'!K48 -> 10218.875 | I25: ='MIS P&L'!L48 -> 10608.585 | J25: ='MIS P&L'!M48 -> 17681.218 | K25: ='MIS P&L'!N48 -> 18913.496
B26: Purchase of Fixed assets | C26: =-((SUMIF('TB 0425'!J:J,'Cash Flow'!B26,'TB 0425'!F:F)-SUMIF('TB 0325'!I:I,'Cash Flow'!B26,'TB 0325'!F:F))) -> -1608.302 | D26: =-((SUMIF('TB 0525'!I:I,'Cash Flow'!B26,'TB 0525'!F:F)-SUMIF('TB 0425'!J:J,'Cash Flow'!B26,'TB 0425'!F:F))) -> -1776.9076 | E26: =-((SUMIF('TB 0625'!I:I,'Cash Flow'!B26,'TB 0625'!F:F)-SUMIF('TB 0525'!I:I,'Cash Flow'!B26,'TB 0525'!F:F))) -> -1223.019 | F26: =-((SUMIF('TB 0725'!I:I,'Cash Flow'!B26,'TB 0725'!F:F)-SUMIF('TB 0625'!I:I,'Cash Flow'!B26,'TB 0625'!F:F))) -> -1524.588 | G26: =-((SUMIF('TB 0825'!I:I,'Cash Flow'!B26,'TB 0825'!F:F)-SUMIF('TB 0725'!I:I,'Cash Flow'!B26,'TB 0725'!F:F))) -> -9228.846 | H26: =-((SUMIF('TB 0925'!I:I,'Cash Flow'!B26,'TB 0925'!F:F)-SUMIF('TB 0825'!I:I,'Cash Flow'!B26,'TB 0825'!F:F))) -> -5420.751 | I26: =-((SUMIF('TB 1025'!I:I,'Cash Flow'!B26,'TB 1025'!F:F)-SUMIF('TB 0925'!I:I,'Cash Flow'!B26,'TB 0925'!F:F))) -> -7356.2532 | J26: =-(SUMIF('TB 1125'!I:I,'Cash Flow'!B26,'TB 1125'!F:F)-SUMIF('TB 1025'!I:I,'Cash Flow'!B26,'TB 1025'!F:F)) -> -4379.884 | K26: =-(SUMIF('TB 1225'!I:I,'Cash Flow'!B26,'TB 1225'!F:F)-SUMIF('TB 1125'!I:I,'Cash Flow'!B26,'TB 1125'!F:F)) -> -7109.279
B27: Net Cash Flow from / (used in) Investing Activities | C27: =SUM(C24:C26) -> 27019.513 | D27: =SUM(D24:D26) -> 37776.154 | E27: =SUM(E24:E26) -> -1555847.3 | F27: =SUM(F24:F26) -> 45992.163 | G27: =SUM(G24:G26) -> 70593.101 | H27: =SUM(H24:H26) -> 79612.767 | I27: =SUM(I24:I26) -> 149981.99 | J27: =SUM(J24:J26) -> -2509673.7 | K27: =SUM(K24:K26) -> 221305.27
B29: C. Cash flows from financing activities
B30: Proceeds from issue of Share Capital | C30: 0 | D30: 0 | E30: 1623581.4 | F30: 0 | G30: 0 | H30: 0 | I30: =-'TB 1025'!F96 -> 1300809.2 | J30: =('TB 1125'!D96*1/1000)+(-'TB 1125'!C171*1/1000)-3 -> 1352183.4 | K30: =-('TB 1225'!F171) -> -1818.29
B32: Net Cash Flow from / (used in) Financing Activities | C32: =SUM(C30:C31) -> 0 | D32: =SUM(D30:D31) -> 0 | E32: =SUM(E30:E31) -> 1623581.4 | F32: =SUM(F30:F31) -> 0 | G32: =SUM(G30:G31) -> 0 | H32: =SUM(H30:H31) -> 0 | I32: =SUM(I30:I31) -> 1300809.2 | J32: =SUM(J30:J31) -> 1352183.4 | K32: =SUM(K30:K31) -> -1818.29
B34: Net Increase/(Decrease) in cash and cash equivalents | C34: =C21+C27+C32 -> 3978.091 | D34: =D21+D27+D32 -> 4362.597 | E34: =E21+E27+E32 -> 13499.593 | F34: =F21+F27+F32 -> -23981.548 | G34: =G21+G27+G32 -> 10284.889 | H34: =H21+H27+H32 -> -11673.134 | I34: =I21+I27+I32 -> 1327740.3 | J34: =J21+J27+J32 -> -1330329.6 | K34: =K21+K27+K32 -> 41298.289
B35: Cash and cash equivalents at previous month | C35: =BS!O39 -> 7334.7525 | D35: =BS!P39 -> 11312.843 | E35: =BS!Q39 -> 15675.441 | F35: =BS!R39 -> 29175.034 | G35: =BS!S39 -> 5193.4857 | H35: =BS!T39 -> 15478.375 | I35: =BS!U39 -> 3805.2395 | J35: =BS!V39 -> 1331545.5 | K35: =BS!W39 -> 1215.9606
B36: Cash and cash equivalents at end of period | C36: =SUM(C34:C35) -> 11312.844 | D36: =SUM(D34:D35) -> 15675.441 | E36: =SUM(E34:E35) -> 29175.034 | F36: =SUM(F34:F35) -> 5193.4857 | G36: =SUM(G34:G35) -> 15478.375 | H36: =SUM(H34:H35) -> 3805.2405 | I36: =SUM(I34:I35) -> 1331545.5 | J36: =SUM(J34:J35) -> 1215.9606 | K36: =SUM(K34:K35) -> 42514.25
B37: FD Balances at end of period | C37: =BS!P36 -> 452000 | D37: =BS!Q36 -> 415000 | E37: =BS!R36 -> 1979500 | F37: =BS!S36 -> 1942000 | G37: =BS!T36 -> 1872012.9 | H37: =BS!U36 -> 1797198.2 | I37: =BS!V36 -> 1650468.6 | J37: =BS!W36 -> 4173443.6 | K37: =BS!X36 -> 3963942.5
B38: Closing Bank Balance | C38: =SUM(C36:C37) -> 463312.84 | D38: =SUM(D36:D37) -> 430675.44 | E38: =SUM(E36:E37) -> 2008675 | F38: =SUM(F36:F37) -> 1947193.5 | G38: =SUM(G36:G37) -> 1887491.3 | H38: =SUM(H36:H37) -> 1801003.5 | I38: =SUM(I36:I37) -> 2982014.1 | J38: =SUM(J36:J37) -> 4174659.6 | K38: =SUM(K36:K37) -> 4006456.8

Sheet Raw TB 1125
A1: Account | C1: Opening Balance | D1: Debit | E1: Credit | F1: Closing Balance | G1: Vlookup
A3: Assets | B3: =TRIM(A3) -> Assets
A4: Accounts Receivable | B4: =TRIM(A4) -> Accounts Receivable | C4: 37891105 | D4: 47811279 | E4: 82689067 | F4: 3013317 | G4: =VLOOKUP(B4,'TB 1125'!A:A,1,0) -> Accounts Receivable
A5: Accrued Interest | B5: =TRIM(A5) -> Accrued Interest | C5: 44549174 | D5: 60436186 | E5: 44549174 | F5: 60436186 | G5: =VLOOKUP(B5,'TB 1125'!A:A,1,0) -> Accrued Interest
A6: Accumulated Amortization on Leasehold Improvement | B6: =TRIM(A6) -> Accumulated Amortization on Leasehold Improvement | C6: -1139002.1 | D6: 0 | E6: 343755.54 | F6: -1482757.6 | G6: =VLOOKUP(B6,'TB 1125'!A:A,1,0) -> Accumulated Amortization on Leasehold Improvement
A7: Accumulated Depreciation on Computer and Laptops | B7: =TRIM(A7) -> Accumulated Depreciation on Computer and Laptops | C7: -2065810.3 | D7: 0 | E7: 634271.45 | F7: -2700081.8 | G7: =VLOOKUP(B7,'TB 1125'!A:A,1,0) -> Accumulated Depreciation on Computer and Laptops
A8: Accumulated Depreciation on Furniture & Equipment | B8: =TRIM(A8) -> Accumulated Depreciation on Furniture & Equipment | C8: -87026.18 | D8: 0 | E8: 11003.51 | F8: -98029.69 | G8: =VLOOKUP(B8,'TB 1125'!A:A,1,0) -> Accumulated Depreciation on Furniture & Equipment
A9: Accumulated Depreciation on Office Equipment | B9: =TRIM(A9) -> Accumulated Depreciation on Office Equipment | C9: -99018.23 | D9: 0 | E9: 17804.24 | F9: -116822.47 | G9: =VLOOKUP(B9,'TB 1125'!A:A,1,0) -> Accumulated Depreciation on Office Equipment
A10: Advance to Vendors | B10: =TRIM(A10) -> Advance to Vendors | C10: 8263651.8 | D10: 839774.54 | E10: 347360 | F10: 8756066.4 | G10: =VLOOKUP(B10,'TB 1125'!A:A,1,0) -> Advance to Vendors
A11: Amazon Wallet | B11: =TRIM(A11) -> Amazon Wallet | C11: 305.98 | D11: 0 | E11: 0 | F11: 305.98 | G11: =VLOOKUP(B11,'TB 1125'!A:A,1,0) -> Amazon Wallet
A12: Axis Bank 1655 | B12: =TRIM(A12) -> Axis Bank 1655 | C12: 11810.34 | D12: 0 | E12: 0 | F12: 11810.34 | G12: =VLOOKUP(B12,'TB 1125'!A:A,1,0) -> Axis Bank 1655
A13: Computer and Laptops | B13: =TRIM(A13) -> Computer and Laptops | C13: 21313987 | D13: 4210884 | E13: 0 | F13: 25524871 | G13: =VLOOKUP(B13,'TB 1125'!A:A,1,0) -> Computer and Laptops
A14: Expert Inventory | B14: =TRIM(A14) -> Expert Inventory | C14: 1489288 | D14: 3398794 | E14: 1577281.3 | F14: 3310800.7 | G14: =VLOOKUP(B14,'TB 1125'!A:A,1,0) -> Expert Inventory
A15: Furniture and Equipment | B15: =TRIM(A15) -> Furniture and Equipment | C15: 704611.34 | D15: 0 | E15: 0 | F15: 704611.34 | G15: =VLOOKUP(B15,'TB 1125'!A:A,1,0) -> Furniture and Equipment
... A18: ICICI 7454 | B18: =TRIM(A18) -> ICICI 7454 | C18: 0 | D18: 800000000 | E18: 800000000 | F18: 0 | G18: =VLOOKUP(B18,'TB 1125'!A:A,1,0) -> ICICI 7454
A19: Input Tax Credits | B19: =TRIM(A19) -> Input Tax Credits | C19: 0 | D19: 0 | E19: 0 | F19: 0
A20: Input CGST | B20: =TRIM(A20) -> Input CGST | C20: 11231923 | D20: 4509931.9 | E20: 8117.75 | F20: 15733737 | G20: =VLOOKUP(B20,'TB 1125'!A:A,1,0) -> Input CGST
A21: Input IGST | B21: =TRIM(A21) -> Input IGST | C21: 6483602.6 | D21: 5521606.9 | E21: 1879447.8 | F21: 10125762 | G21: =VLOOKUP(B21,'TB 1125'!A:A,1,0) -> Input IGST
A22: Input SGST | B22: =TRIM(A22) -> Input SGST | C22: 11163565 | D22: 4509931.9 | E22: 8117.75 | F22: 15665379 | G22: =VLOOKUP(B22,'TB 1125'!A:A,1,0) -> Input SGST
A23: Total for Input Tax Credits | B23: =TRIM(A23) -> Total for Input Tax Credits | C23: 28879091 | D23: 14541471 | E23: 1895683.3 | F23: 41524878
B24: =TRIM(A24)
A25: Investments | B25: =TRIM(A25) -> Investments | C25: 0 | D25: 0 | E25: 0 | F25: 0
A26: ABSL Floating Rate Fund | B26: =TRIM(A26) -> ABSL Floating Rate Fund | C26: 0 | D26: 79996000 | E26: 0 | F26: 79996000 | G26: =VLOOKUP(B26,'TB 1125'!A:A,1,0) -> ABSL Floating Rate Fund
A27: Aditya Birla Sun Life Money Manager Fund | B27: =TRIM(A27) -> Aditya Birla Sun Life Money Manager Fund | C27: 0 | D27: 59997000 | E27: 0 | F27: 59997000 | G27: =VLOOKUP(B27,'TB 1125'!A:A,1,0) -> Aditya Birla Sun Life Money Manager Fund
A28: Axis Liquid Fund | B28: =TRIM(A28) -> Axis Liquid Fund | C28: 0 | D28: 99995000 | E28: 0 | F28: 99995000 | G28: =VLOOKUP(B28,'TB 1125'!A:A,1,0) -> Axis Liquid Fund
A29: Fixed Deposit 318213005918 | B29: =TRIM(A29) -> Fixed Deposit 318213005918 | C29: 0 | D29: 248500000 | E29: 0 | F29: 248500000 | G29: =VLOOKUP(B29,'TB 1125'!A:A,1,0) -> Fixed Deposit 318213005918
A30: Fixed Deposit 318213005919 | B30: =TRIM(A30) -> Fixed Deposit 318213005919 | C30: 0 | D30: 248500000 | E30: 0 | F30: 248500000 | G30: =VLOOKUP(B30,'TB 1125'!A:A,1,0) -> Fixed Deposit 318213005919
A31: Fixed Deposit 318213005920 | B31: =TRIM(A31) -> Fixed Deposit 318213005920 | C31: 0 | D31: 248500000 | E31: 0 | F31: 248500000 | G31: =VLOOKUP(B31,'TB 1125'!A:A,1,0) -> Fixed Deposit 318213005920
A32: Fixed Deposit 318213005922 | B32: =TRIM(A32) -> Fixed Deposit 318213005922 | C32: 0 | D32: 54500000 | E32: 0 | F32: 54500000 | G32: =VLOOKUP(B32,'TB 1125'!A:A,1,0) -> Fixed Deposit 318213005922
A33: Fixed Deposit 50301170464152 | B33: =TRIM(A33) -> Fixed Deposit 50301170464152 | C33: 50000000 | D33: 0 | E33: 50000000 | F33: 0 | G33: =VLOOKUP(B33,'TB 1125'!A:A,1,0) -> Fixed Deposit 50301170464152
A34: Fixed Deposit 50301170464596 | B34: =TRIM(A34) -> Fixed Deposit 50301170464596 | C34: 100000000 | D34: 0 | E34: 0 | F34: 100000000 | G34: =VLOOKUP(B34,'TB 1125'!A:A,1,0) -> Fixed Deposit 50301170464596
A35: Fixed Deposit 50301170464942 | B35: =TRIM(A35) -> Fixed Deposit 50301170464942 | C35: 150000000 | D35: 0 | E35: 0 | F35: 150000000 | G35: =VLOOKUP(B35,'TB 1125'!A:A,1,0) -> Fixed Deposit 50301170464942
A36: Fixed Deposit 50301170465320 | B36: =TRIM(A36) -> Fixed Deposit 50301170465320 | C36: 300000000 | D36: 0 | E36: 0 | F36: 300000000 | G36: =VLOOKUP(B36,'TB 1125'!A:A,1,0) -> Fixed Deposit 50301170465320
A37: Fixed Deposit 50301242721572 | B37: =TRIM(A37) -> Fixed Deposit 50301242721572 | C37: 0 | D37: 5200000 | E37: 0 | F37: 5200000 | G37: =VLOOKUP(B37,'TB 1125'!A:A,1,0) -> Fixed Deposit 50301242721572
... A59: UTI Liquid Fund | B59: =TRIM(A59) -> UTI Liquid Fund | C59: 0 | D59: 79996000 | E59: 0 | F59: 79996000 | G59: =VLOOKUP(B59,'TB 1125'!A:A,1,0) -> UTI Liquid Fund
A60: Total for Investments | B60: =TRIM(A60) -> Total for Investments | C60: 1.6504686e+09 | D60: 3.377975e+09 | E60: 855000000 | F60: 4.1734436e+09
B61: =TRIM(A61)
A62: Kotak Mahindra Bank 0429 | B62: =TRIM(A62) -> Kotak Mahindra Bank 0429 | C62: 1300809153 | D62: 1353927099 | E62: 2654736252 | F62: 0 | G62: =VLOOKUP(B62,'TB 1125'!A:A,1,0) -> Kotak Mahindra Bank 0429
A63: Kotak Mahindra Bank 9942 | B63: =TRIM(A63) -> Kotak Mahindra Bank 9942 | C63: 1000000 | D63: 3512687718 | E63: 3513387718 | F63: 300000 | G63: =VLOOKUP(B63,'TB 1125'!A:A,1,0) -> Kotak Mahindra Bank 9942
A64: Kotak Mahindra Bank 9966 | B64: =TRIM(A64) -> Kotak Mahindra Bank 9966 | C64: 29251923 | D64: 6.7757566e+08 | E64: 7.0661816e+08 | F64: 209417.22 | G64: =VLOOKUP(B64,'TB 1125'!A:A,1,0) -> Kotak Mahindra Bank 9966
A65: Leasehold Improvement | B65: =TRIM(A65) -> Leasehold Improvement | C65: 12860897 | D65: 0 | E65: 0 | F65: 12860897 | G65: =VLOOKUP(B65,'TB 1125'!A:A,1,0) -> Leasehold Improvement
A66: Office Equipment | B66: =TRIM(A66) -> Office Equipment | C66: 520841.58 | D66: 169000 | E66: 0 | F66: 689841.58 | G66: =VLOOKUP(B66,'TB 1125'!A:A,1,0) -> Office Equipment
A67: Prepaid - Consumption | B67: =TRIM(A67) -> Prepaid - Consumption | C67: 1222814 | D67: 0 | E67: 0 | F67: 1222814 | G67: =VLOOKUP(B67,'TB 1125'!A:A,1,0) -> Prepaid - Consumption
A68: Prepaid Expense - Asset | B68: =TRIM(A68) -> Prepaid Expense - Asset | C68: 1326433.4 | D68: 0 | E68: 250391.67 | F68: 1076041.7 | G68: =VLOOKUP(B68,'TB 1125'!A:A,1,0) -> Prepaid Expense - Asset
A69: Prepaid Expenses | B69: =TRIM(A69) -> Prepaid Expenses | C69: 45327019 | D69: 10016667 | E69: 5536023 | F69: 49807663 | G69: =VLOOKUP(B69,'TB 1125'!A:A,1,0) -> Prepaid Expenses
A70: Receipt from Customers | B70: =TRIM(A70) -> Receipt from Customers | C70: -37210767 | D70: 81827860 | E70: 44617093 | F70: 0 | G70: =VLOOKUP(B70,'TB 1125'!A:A,1,0) -> Receipt from Customers
A71: Reverse Charge Tax Input but not due | B71: =TRIM(A71) -> Reverse Charge Tax Input but not due | C71: 2254508.8 | D71: 525642.79 | E71: 0 | F71: 2780151.6 | G71: =VLOOKUP(B71,'TB 1125'!A:A,1,0) -> Reverse Charge Tax Input but not due
A72: Security Deposit | B72: =TRIM(A72) -> Security Deposit | C72: 15715400 | D72: 40000 | E72: 50000 | F72: 15705400 | G72: =VLOOKUP(B72,'TB 1125'!A:A,1,0) -> Security Deposit
A73: Slaash Technologies - Control Account | B73: =TRIM(A73) -> Slaash Technologies - Control Account | C73: 0 | D73: 277200 | E73: 277200 | F73: 0 | G73: =VLOOKUP(B73,'TB 1125'!A:A,1,0) -> Slaash Technologies - Control Account
... A75: Virtu Travels - Control Account | B75: =TRIM(A75) -> Virtu Travels - Control Account | C75: 0 | D75: 368955 | E75: 368955 | F75: 0 | G75: =VLOOKUP(B75,'TB 1125'!A:A,1,0) -> Virtu Travels - Control Account
A76: Liabilities | B76: =TRIM(A76) -> Liabilities
A77: Accounts Payable | B77: =TRIM(A77) -> Accounts Payable | C77: -52884681 | D77: 78743954 | E77: 1.0680334e+08 | F77: -80944071 | G77: =VLOOKUP(B77,'TB 1125'!A:A,1,0) -> Accounts Payable
A78: Advance from B2C Customer | B78: =TRIM(A78) -> Advance from B2C Customer | C78: -4574135.7 | D78: 9431001.7 | E78: 10438196 | F78: -5581330 | G78: =VLOOKUP(B78,'TB 1125'!A:A,1,0) -> Advance from B2C Customer
A79: App Wallet | B79: =TRIM(A79) -> App Wallet | C79: -1963787.3 | D79: 127411 | E79: 299705 | F79: -2136081.3 | G79: =VLOOKUP(B79,'TB 1125'!A:A,1,0) -> App Wallet
A80: Employee Reimbursements | B80: =TRIM(A80) -> Employee Reimbursements | C80: 494297.59 | D80: 0 | E80: 0 | F80: 494297.59 | G80: =VLOOKUP(B80,'TB 1125'!A:A,1,0) -> Employee Reimbursements
A81: Employee Salaries Payable | B81: =TRIM(A81) -> Employee Salaries Payable | C81: -1562915 | D81: 30710373 | E81: 30088903 | F81: -941444.61 | G81: =VLOOKUP(B81,'TB 1125'!A:A,1,0) -> Employee Salaries Payable
A82: Expert Joining Bonus Payable | B82: =TRIM(A82) -> Expert Joining Bonus Payable | C82: -1373346 | D82: 1231526.6 | E82: 1260150 | F82: -1401969.4 | G82: =VLOOKUP(B82,'TB 1125'!A:A,1,0) -> Expert Joining Bonus Payable
A83: Expert Referral Bonus Payable | B83: =TRIM(A83) -> Expert Referral Bonus Payable | C83: 0 | D83: 3346943 | E83: 3361793 | F83: -14850 | G83: =VLOOKUP(B83,'TB 1125'!A:A,1,0) -> Expert Referral Bonus Payable
A84: Expert Retention Bonus Payable | B84: =TRIM(A84) -> Expert Retention Bonus Payable | C84: 0 | D84: 0 | E84: 6676440 | F84: -6676440 | G84: =VLOOKUP(B84,'TB 1125'!A:A,1,0) -> Expert Retention Bonus Payable
A85: Expert Service Cost Payable | B85: =TRIM(A85) -> Expert Service Cost Payable | C85: -71783997 | D85: 77434366 | E85: 89521347 | F85: -83870977 | G85: =VLOOKUP(B85,'TB 1125'!A:A,1,0) -> Expert Service Cost Payable
A86: GST Payable | B86: =TRIM(A86) -> GST Payable | C86: 0 | D86: 0 | E86: 0 | F86: 0
A87: Output CGST | B87: =TRIM(A87) -> Output CGST | C87: -1768190.4 | D87: 1607548.9 | E87: 1894627.9 | F87: -2055269.3 | G87: =VLOOKUP(B87,'TB 1125'!A:A,1,0) -> Output CGST
A88: Output IGST | B88: =TRIM(A88) -> Output IGST | C88: -202818.5 | D88: 349343 | E88: 377080.93 | F88: -230556.43 | G88: =VLOOKUP(B88,'TB 1125'!A:A,1,0) -> Output IGST
A89: Output SGST | B89: =TRIM(A89) -> Output SGST | C89: -1768188.4 | D89: 1607548.9 | E89: 1894627.9 | F89: -2055267.3 | G89: =VLOOKUP(B89,'TB 1125'!A:A,1,0) -> Output SGST
A90: Total for GST Payable | B90: =TRIM(A90) -> Total for GST Payable | C90: -3739197.3 | D90: 3564440.9 | E90: 4166336.6 | F90: -4341093.1
B91: =TRIM(A91)
A92: Professional Tax | B92: =TRIM(A92) -> Professional Tax | C92: -39000 | D92: 39200 | E92: 38000 | F92: -37800 | G92: =VLOOKUP(B92,'TB 1125'!A:A,1,0) -> Professional Tax
A93: Provident Fund | B93: =TRIM(A93) -> Provident Fund | C93: 0 | D93: 0 | E93: 0 | F93: 0 | G93: =VLOOKUP(B93,'TB 1125'!A:A,1,0) -> Provident Fund
A94: Provident Fund - Employee | B94: =TRIM(A94) -> Provident Fund - Employee | C94: -447570 | D94: 452538 | E94: 464708 | F94: -459740 | G94: =VLOOKUP(B94,'TB 1125'!A:A,1,0) -> Provident Fund - Employee
A95: Provident Fund - Employer | B95: =TRIM(A95) -> Provident Fund - Employer | C95: -447570 | D95: 452538 | E95: 464708 | F95: -459740 | G95: =VLOOKUP(B95,'TB 1125'!A:A,1,0) -> Provident Fund - Employer
A96: Total for Provident Fund | B96: =TRIM(A96) -> Total for Provident Fund | C96: -895140 | D96: 905076 | E96: 929416 | F96: -919480
B97: =TRIM(A97)
A98: Provision for Customer Acquisition Cost | B98: =TRIM(A98) -> Provision for Customer Acquisition Cost | C98: -13575425 | D98: 13575425 | E98: 12411398 | F98: -12411398 | G98: =VLOOKUP(B98,'TB 1125'!A:A,1,0) -> Provision for Customer Acquisition Cost
A99: Provision for Gratuity - LT | B99: =TRIM(A99) -> Provision for Gratuity - LT | C99: -548984 | D99: 0 | E99: 0 | F99: -548984 | G99: =VLOOKUP(B99,'TB 1125'!A:A,1,0) -> Provision for Gratuity - LT
A100: Provision for Gratuity - ST | B100: =TRIM(A100) -> Provision for Gratuity - ST | C100: -1269 | D100: 0 | E100: 0 | F100: -1269 | G100: =VLOOKUP(B100,'TB 1125'!A:A,1,0) -> Provision for Gratuity - ST
A101: Provision for Marketing Expense | B101: =TRIM(A101) -> Provision for Marketing Expense | C101: -15670233 | D101: 15670233 | E101: 24366217 | F101: -24366217 | G101: =VLOOKUP(B101,'TB 1125'!A:A,1,0) -> Provision for Marketing Expense
A102: Provision for Other Cost | B102: =TRIM(A102) -> Provision for Other Cost | C102: -21677125 | D102: 21677125 | E102: 8038850 | F102: -8038850 | G102: =VLOOKUP(B102,'TB 1125'!A:A,1,0) -> Provision for Other Cost
A103: Provision for Professional Fees | B103: =TRIM(A103) -> Provision for Professional Fees | C103: -70000 | D103: 70000 | E103: 1316320 | F103: -1316320 | G103: =VLOOKUP(B103,'TB 1125'!A:A,1,0) -> Provision for Professional Fees
A104: Provision for Rent Expense | B104: =TRIM(A104) -> Provision for Rent Expense | C104: -188100 | D104: 188100 | E104: 16916 | F104: -16916 | G104: =VLOOKUP(B104,'TB 1125'!A:A,1,0) -> Provision for Rent Expense
A105: Provision for Service Cost | B105: =TRIM(A105) -> Provision for Service Cost | C105: -400000 | D105: 400000 | E105: 134790 | F105: -134790 | G105: =VLOOKUP(B105,'TB 1125'!A:A,1,0) -> Provision for Service Cost
A106: Provision for Software Expense | B106: =TRIM(A106) -> Provision for Software Expense | C106: -3153866.8 | D106: 3153866.8 | E106: 3714772.3 | F106: -3714772.3 | G106: =VLOOKUP(B106,'TB 1125'!A:A,1,0) -> Provision for Software Expense
A107: Provision for Staff Welfare Expense | B107: =TRIM(A107) -> Provision for Staff Welfare Expense | C107: -821927.03 | D107: 821927.03 | E107: 2414260 | F107: -2414260 | G107: =VLOOKUP(B107,'TB 1125'!A:A,1,0) -> Provision for Staff Welfare Expense
A108: Provision for TC Expense | B108: =TRIM(A108) -> Provision for TC Expense | C108: -154572.91 | D108: 154572.91 | E108: 842113 | F108: -842113 | G108: =VLOOKUP(B108,'TB 1125'!A:A,1,0) -> Provision for TC Expense
A109: TDS Payable | B109: =TRIM(A109) -> TDS Payable | C109: -6067609.7 | D109: 6340985 | E109: 8041773.7 | F109: -7768398.4 | G109: =VLOOKUP(B109,'TB 1125'!A:A,1,0) -> TDS Payable
A110: Variable Salary Payable | B110: =TRIM(A110) -> Variable Salary Payable | C110: -2699443 | D110: 0 | E110: 0 | F110: -2699443 | G110: =VLOOKUP(B110,'TB 1125'!A:A,1,0) -> Variable Salary Payable
A111: Equities | B111: =TRIM(A111) -> Equities
A112: Current Year Earnings | B112: =TRIM(A112) -> Current Year Earnings | C112: 4.6015869e+08 | D112: 0 | E112: 0 | F112: 4.6015869e+08 | G112: =VLOOKUP(B112,'TB 1125'!A:A,1,0) -> Current Year Earnings
A113: ESOP Outstanding Reserve | B113: =TRIM(A113) -> ESOP Outstanding Reserve | C113: -1245691 | D113: 0 | E113: 0 | F113: -1245691 | G113: =VLOOKUP(B113,'TB 1125'!A:A,1,0) -> ESOP Outstanding Reserve
A114: Owner's Equity | B114: =TRIM(A114) -> Owner's Equity | C114: -100000 | D114: 0 | E114: 0 | F114: -100000 | G114: =VLOOKUP(B114,'TB 1125'!A:A,1,0) -> Owner's Equity
A115: BERTELSMANN NEDERLAND B.V. | B115: =TRIM(A115) -> BERTELSMANN NEDERLAND B.V. | C115: 0 | D115: 0 | E115: 2798700 | F115: -2798700 | G115: =VLOOKUP(B115,'TB 1125'!A:A,1,0) -> BERTELSMANN NEDERLAND B.V.
A116: Elevation Capital III Limited ESC | B116: =TRIM(A116) -> Elevation Capital III Limited ESC | C116: -10 | D116: 0 | E116: 0 | F116: -10 | G116: =VLOOKUP(B116,'TB 1125'!A:A,1,0) -> Elevation Capital III Limited ESC
A117: Elevation Capital III Limited PSC | B117: =TRIM(A117) -> Elevation Capital III Limited PSC | C117: -5463300 | D117: 0 | E117: 0 | F117: -5463300 | G117: =VLOOKUP(B117,'TB 1125'!A:A,1,0) -> Elevation Capital III Limited PSC
A118: ELEVATION CAPITAL VIII LIMITED | B118: =TRIM(A118) -> ELEVATION CAPITAL VIII LIMITED | C118: 0 | D118: 0 | E118: 1097500 | F118: -1097500 | G118: =VLOOKUP(B118,'TB 1125'!A:A,1,0) -> ELEVATION CAPITAL VIII LIMITED
A119: Gaurav Munjal | B119: =TRIM(A119) -> Gaurav Munjal | C119: -10800 | D119: 0 | E119: 0 | F119: -10800 | G119: =VLOOKUP(B119,'TB 1125'!A:A,1,0) -> Gaurav Munjal
A120: Lightspeed India Partners IV LLC | B120: =TRIM(A120) -> Lightspeed India Partners IV LLC | C120: -3772700 | D120: 0 | E120: 1097500 | F120: -4870200 | G120: =VLOOKUP(B120,'TB 1125'!A:A,1,0) -> Lightspeed India Partners IV LLC
A121: Nexus Ventures VII Holdings LLC ESC | B121: =TRIM(A121) -> Nexus Ventures VII Holdings LLC ESC | C121: -10 | D121: 0 | E121: 0 | F121: -10 | G121: =VLOOKUP(B121,'TB 1125'!A:A,1,0) -> Nexus Ventures VII Holdings LLC ESC
A122: Nexus Ventures VII Holdings LLC PSC | B122: =TRIM(A122) -> Nexus Ventures VII Holdings LLC PSC | C122: -6497900 | D122: 0 | E122: 493900 | F122: -6991800 | G122: =VLOOKUP(B122,'TB 1125'!A:A,1,0) -> Nexus Ventures VII Holdings LLC PSC
A123: Niraj Singh | B123: =TRIM(A123) -> Niraj Singh | C123: -16200 | D123: 0 | E123: 0 | F123: -16200 | G123: =VLOOKUP(B123,'TB 1125'!A:A,1,0) -> Niraj Singh
... A130: Vidit Aatrey | B130: =TRIM(A130) -> Vidit Aatrey | C130: -37800 | D130: 0 | E130: 0 | F130: -37800 | G130: =VLOOKUP(B130,'TB 1125'!A:A,1,0) -> Vidit Aatrey
A131: Total for Owner's Equity | B131: =TRIM(A131) -> Total for Owner's Equity | C131: -2.1786607e+09 | D131: 0 | E131: 2654736252 | F131: -4.833397e+09
...

Sheet Raw TB 1225
A1: Account | C1: Opening Balance | D1: Debit | E1: Credit | F1: Closing Balance | G1: Vlookup
A3: Assets | B3: =TRIM(A3) -> Assets
A4: Accounts Receivable | B4: =TRIM(A4) -> Accounts Receivable | C4: 3013317 | D4: 66113310 | E4: 66969391 | F4: 2157235.5 | G4: =VLOOKUP(B4,'TB 1225'!A:A,1,0) -> Accounts Receivable
A5: Accrued Interest | B5: =TRIM(A5) -> Accrued Interest | C5: 60436186 | D5: 75481262 | E5: 60436186 | F5: 75481262 | G5: =VLOOKUP(B5,'TB 1225'!A:A,1,0) -> Accrued Interest
A6: Accumulated Amortization on Leasehold Improvement | B6: =TRIM(A6) -> Accumulated Amortization on Leasehold Improvement | C6: -1482757.6 | D6: 0 | E6: 462364.89 | F6: -1945122.5 | G6: =VLOOKUP(B6,'TB 1225'!A:A,1,0) -> Accumulated Amortization on Leasehold Improvement
A7: Accumulated Depreciation on Computer and Laptops | B7: =TRIM(A7) -> Accumulated Depreciation on Computer and Laptops | C7: -2700081.8 | D7: 0 | E7: 691820.18 | F7: -3391901.9 | G7: =VLOOKUP(B7,'TB 1225'!A:A,1,0) -> Accumulated Depreciation on Computer and Laptops
A8: Accumulated Depreciation on Furniture & Equipment | B8: =TRIM(A8) -> Accumulated Depreciation on Furniture & Equipment | C8: -98029.69 | D8: 0 | E8: 11370.3 | F8: -109399.99 | G8: =VLOOKUP(B8,'TB 1225'!A:A,1,0) -> Accumulated Depreciation on Furniture & Equipment
A9: Accumulated Depreciation on Office Equipment | B9: =TRIM(A9) -> Accumulated Depreciation on Office Equipment | C9: -116822.47 | D9: 0 | E9: 18733.17 | F9: -135555.64 | G9: =VLOOKUP(B9,'TB 1225'!A:A,1,0) -> Accumulated Depreciation on Office Equipment
A10: Advance to Vendors | B10: =TRIM(A10) -> Advance to Vendors | C10: 8756066.4 | D10: 11524661 | E10: 99062.88 | F10: 20181664 | G10: =VLOOKUP(B10,'TB 1225'!A:A,1,0) -> Advance to Vendors
A11: Amazon Wallet | B11: =TRIM(A11) -> Amazon Wallet | C11: 305.98 | D11: 0 | E11: 0 | F11: 305.98 | G11: =VLOOKUP(B11,'TB 1225'!A:A,1,0) -> Amazon Wallet
A12: Axis Bank 1655 | B12: =TRIM(A12) -> Axis Bank 1655 | C12: 11810.34 | D12: 3131680 | E12: 2916665.3 | F12: 226825.06 | G12: =VLOOKUP(B12,'TB 1225'!A:A,1,0) -> Axis Bank 1655
A13: Computer and Laptops | B13: =TRIM(A13) -> Computer and Laptops | C13: 25524871 | D13: 330880 | E13: 0 | F13: 25855751 | G13: =VLOOKUP(B13,'TB 1225'!A:A,1,0) -> Computer and Laptops
A14: Expert Inventory | B14: =TRIM(A14) -> Expert Inventory | C14: 3400180.7 | D14: 10206713 | E14: 8231916 | F14: 5374977.7 | G14: =VLOOKUP(B14,'TB 1225'!A:A,1,0) -> Expert Inventory
A15: Furniture and Equipment | B15: =TRIM(A15) -> Furniture and Equipment | C15: 704611.34 | D15: 0 | E15: 0 | F15: 704611.34 | G15: =VLOOKUP(B15,'TB 1225'!A:A,1,0) -> Furniture and Equipment
... A17: HDFC Bank 9531 | B17: =TRIM(A17) -> HDFC Bank 9531 | C17: 449633.35 | D17: 1080430.8 | E17: 1406225.6 | F17: 123838.5 | G17: =VLOOKUP(B17,'TB 1225'!A:A,1,0) -> HDFC Bank 9531
A18: Input Tax Credits | B18: =TRIM(A18) -> Input Tax Credits | C18: 0 | D18: 0 | E18: 0 | F18: 0
A19: Input CGST | B19: =TRIM(A19) -> Input CGST | C19: 15716937 | D19: 4065386.1 | E19: 0 | F19: 19782323 | G19: =VLOOKUP(B19,'TB 1225'!A:A,1,0) -> Input CGST
A20: Input IGST | B20: =TRIM(A20) -> Input IGST | C20: 10163831 | D20: 3645771.8 | E20: 2009906 | F20: 11799696 | G20: =VLOOKUP(B20,'TB 1225'!A:A,1,0) -> Input IGST
A21: Input SGST | B21: =TRIM(A21) -> Input SGST | C21: 15648579 | D21: 4065386.1 | E21: 0 | F21: 19713965 | G21: =VLOOKUP(B21,'TB 1225'!A:A,1,0) -> Input SGST
A22: Total for Input Tax Credits | B22: =TRIM(A22) -> Total for Input Tax Credits | C22: 41529347 | D22: 11776544 | E22: 2009906 | F22: 51295985
B23: =TRIM(A23)
A24: Investments | B24: =TRIM(A24) -> Investments | C24: 0 | D24: 0 | E24: 0 | F24: 0
A25: ABSL Floating Rate Fund | B25: =TRIM(A25) -> ABSL Floating Rate Fund | C25: 79996000 | D25: 0 | E25: 0 | F25: 79996000 | G25: =VLOOKUP(B25,'TB 1225'!A:A,1,0) -> ABSL Floating Rate Fund
A26: Aditya Birla Sun Life Money Manager Fund | B26: =TRIM(A26) -> Aditya Birla Sun Life Money Manager Fund | C26: 59997000 | D26: 0 | E26: 0 | F26: 59997000 | G26: =VLOOKUP(B26,'TB 1225'!A:A,1,0) -> Aditya Birla Sun Life Money Manager Fund
A27: Axis Liquid Fund | B27: =TRIM(A27) -> Axis Liquid Fund | C27: 99995000 | D27: 0 | E27: 0 | F27: 99995000 | G27: =VLOOKUP(B27,'TB 1225'!A:A,1,0) -> Axis Liquid Fund
A28: Fixed Deposit 318213005918 | B28: =TRIM(A28) -> Fixed Deposit 318213005918 | C28: 248500000 | D28: 0 | E28: 0 | F28: 248500000 | G28: =VLOOKUP(B28,'TB 1225'!A:A,1,0) -> Fixed Deposit 318213005918
A29: Fixed Deposit 318213005919 | B29: =TRIM(A29) -> Fixed Deposit 318213005919 | C29: 248500000 | D29: 0 | E29: 0 | F29: 248500000 | G29: =VLOOKUP(B29,'TB 1225'!A:A,1,0) -> Fixed Deposit 318213005919
A30: Fixed Deposit 318213005920 | B30: =TRIM(A30) -> Fixed Deposit 318213005920 | C30: 248500000 | D30: 0 | E30: 0 | F30: 248500000 | G30: =VLOOKUP(B30,'TB 1225'!A:A,1,0) -> Fixed Deposit 318213005920
A31: Fixed Deposit 318213005922 | B31: =TRIM(A31) -> Fixed Deposit 318213005922 | C31: 54500000 | D31: 0 | E31: 0 | F31: 54500000 | G31: =VLOOKUP(B31,'TB 1225'!A:A,1,0) -> Fixed Deposit 318213005922
A32: Fixed Deposit 50301170464596 | B32: =TRIM(A32) -> Fixed Deposit 50301170464596 | C32: 100000000 | D32: 0 | E32: 100000000 | F32: 0 | G32: =VLOOKUP(B32,'TB 1225'!A:A,1,0) -> Fixed Deposit 50301170464596
A33: Fixed Deposit 50301170464942 | B33: =TRIM(A33) -> Fixed Deposit 50301170464942 | C33: 150000000 | D33: 0 | E33: 0 | F33: 150000000 | G33: =VLOOKUP(B33,'TB 1225'!A:A,1,0) -> Fixed Deposit 50301170464942
A34: Fixed Deposit 50301170465320 | B34: =TRIM(A34) -> Fixed Deposit 50301170465320 | C34: 300000000 | D34: 0 | E34: 0 | F34: 300000000 | G34: =VLOOKUP(B34,'TB 1225'!A:A,1,0) -> Fixed Deposit 50301170465320
A35: Fixed Deposit 50301242721572 | B35: =TRIM(A35) -> Fixed Deposit 50301242721572 | C35: 5200000 | D35: 0 | E35: 0 | F35: 5200000 | G35: =VLOOKUP(B35,'TB 1225'!A:A,1,0) -> Fixed Deposit 50301242721572
A36: Fixed Deposit 50301242791241 | B36: =TRIM(A36) -> Fixed Deposit 50301242791241 | C36: 247400000 | D36: 0 | E36: 0 | F36: 247400000 | G36: =VLOOKUP(B36,'TB 1225'!A:A,1,0) -> Fixed Deposit 50301242791241
... A58: UTI Liquid Fund | B58: =TRIM(A58) -> UTI Liquid Fund | C58: 79996000 | D58: 0 | E58: 69491402 | F58: 10504599 | G58: =VLOOKUP(B58,'TB 1225'!A:A,1,0) -> UTI Liquid Fund
A59: Total for Investments | B59: =TRIM(A59) -> Total for Investments | C59: 4.1734436e+09 | D59: 3.2098835e+08 | E59: 5.304894e+08 | F59: 3.9639425e+09
B60: =TRIM(A60)
A61: Kotak Mahindra Bank 9942 | B61: =TRIM(A61) -> Kotak Mahindra Bank 9942 | C61: 300000 | D61: 4.3124098e+08 | E61: 3.9314098e+08 | F61: 38400000 | G61: =VLOOKUP(B61,'TB 1225'!A:A,1,0) -> Kotak Mahindra Bank 9942
A62: Kotak Mahindra Bank 9966 | B62: =TRIM(A62) -> Kotak Mahindra Bank 9966 | C62: 209417.22 | D62: 4.7240692e+08 | E62: 4.6901227e+08 | F62: 3604072.9 | G62: =VLOOKUP(B62,'TB 1225'!A:A,1,0) -> Kotak Mahindra Bank 9966
A63: Leasehold Improvement | B63: =TRIM(A63) -> Leasehold Improvement | C63: 12860897 | D63: 6766884 | E63: 0 | F63: 19627781 | G63: =VLOOKUP(B63,'TB 1225'!A:A,1,0) -> Leasehold Improvement
A64: Office Equipment | B64: =TRIM(A64) -> Office Equipment | C64: 689841.58 | D64: 11515 | E64: 0 | F64: 701356.58 | G64: =VLOOKUP(B64,'TB 1225'!A:A,1,0) -> Office Equipment
A65: Prepaid - Consumption | B65: =TRIM(A65) -> Prepaid - Consumption | C65: 1222814 | D65: 0 | E65: 0 | F65: 1222814 | G65: =VLOOKUP(B65,'TB 1225'!A:A,1,0) -> Prepaid - Consumption
A66: Prepaid Expense - Asset | B66: =TRIM(A66) -> Prepaid Expense - Asset | C66: 1076041.7 | D66: 1100595 | E66: 250391.67 | F66: 1926245 | G66: =VLOOKUP(B66,'TB 1225'!A:A,1,0) -> Prepaid Expense - Asset
A67: Prepaid Expenses | B67: =TRIM(A67) -> Prepaid Expenses | C67: 49712663 | D67: 5162370.1 | E67: 7958920.8 | F67: 46916112 | G67: =VLOOKUP(B67,'TB 1225'!A:A,1,0) -> Prepaid Expenses
A68: RazorpayX Lite | B68: =TRIM(A68) -> RazorpayX Lite | C68: 0 | D68: 90000 | E68: 0 | F68: 90000 | G68: =VLOOKUP(B68,'TB 1225'!A:A,1,0) -> RazorpayX Lite
A69: Receipt from Customers | B69: =TRIM(A69) -> Receipt from Customers | C69: 0 | D69: 65831102 | E69: 68763968 | F69: -2932865.5 | G69: =VLOOKUP(B69,'TB 1225'!A:A,1,0) -> Receipt from Customers
A70: Reverse Charge Tax Input but not due | B70: =TRIM(A70) -> Reverse Charge Tax Input but not due | C70: 2780151.6 | D70: 470256.88 | E70: 0 | F70: 3250408.5 | G70: =VLOOKUP(B70,'TB 1225'!A:A,1,0) -> Reverse Charge Tax Input but not due
A71: Security Deposit | B71: =TRIM(A71) -> Security Deposit | C71: 15705400 | D71: 2785000 | E71: 0 | F71: 18490400 | G71: =VLOOKUP(B71,'TB 1225'!A:A,1,0) -> Security Deposit
A72: TDS Receivable | B72: =TRIM(A72) -> TDS Receivable | C72: 1271832.7 | D72: 0 | E72: 0 | F72: 1271832.7 | G72: =VLOOKUP(B72,'TB 1225'!A:A,1,0) -> TDS Receivable
A73: Virtu Travels - Control Account | B73: =TRIM(A73) -> Virtu Travels - Control Account | C73: 0 | D73: 0 | E73: 36025 | F73: -36025 | G73: =VLOOKUP(B73,'TB 1225'!A:A,1,0) -> Virtu Travels - Control Account
A74: Liabilities | B74: =TRIM(A74) -> Liabilities
A75: Accounts Payable | B75: =TRIM(A75) -> Accounts Payable | C75: -80942920 | D75: 88692880 | E75: 92676329 | F75: -84926369 | G75: =VLOOKUP(B75,'TB 1225'!A:A,1,0) -> Accounts Payable
A76: Advance from B2C Customer | B76: =TRIM(A76) -> Advance from B2C Customer | C76: -5581330 | D76: 13280943 | E76: 14842946 | F76: -7143332.8 | G76: =VLOOKUP(B76,'TB 1225'!A:A,1,0) -> Advance from B2C Customer
A77: App Wallet | B77: =TRIM(A77) -> App Wallet | C77: -2136081.3 | D77: 342395 | E77: 445723 | F77: -2239409.3 | G77: =VLOOKUP(B77,'TB 1225'!A:A,1,0) -> App Wallet
A78: Compensation Payable for Damages | B78: =TRIM(A78) -> Compensation Payable for Damages | C78: 0 | D78: 51660 | E78: 51660 | F78: 0
A79: Employee Reimbursements | B79: =TRIM(A79) -> Employee Reimbursements | C79: 494297.59 | D79: 128231.35 | E79: 128231.35 | F79: 494297.59 | G79: =VLOOKUP(B79,'TB 1225'!A:A,1,0) -> Employee Reimbursements
A80: Employee Salaries Payable | B80: =TRIM(A80) -> Employee Salaries Payable | C80: -941444.61 | D80: 34499743 | E80: 34435409 | F80: -877110.61 | G80: =VLOOKUP(B80,'TB 1225'!A:A,1,0) -> Employee Salaries Payable
A81: Expert Joining Bonus Payable | B81: =TRIM(A81) -> Expert Joining Bonus Payable | C81: -1401969.4 | D81: 1305197.4 | E81: 1976890 | F81: -2073662 | G81: =VLOOKUP(B81,'TB 1225'!A:A,1,0) -> Expert Joining Bonus Payable
A82: Expert Referral Bonus Payable | B82: =TRIM(A82) -> Expert Referral Bonus Payable | C82: -14850 | D82: 2928039 | E82: 2949697 | F82: -36508 | G82: =VLOOKUP(B82,'TB 1225'!A:A,1,0) -> Expert Referral Bonus Payable
A83: Expert Retention Bonus Payable | B83: =TRIM(A83) -> Expert Retention Bonus Payable | C83: -6676440 | D83: 268235 | E83: 268235 | F83: -6676440 | G83: =VLOOKUP(B83,'TB 1225'!A:A,1,0) -> Expert Retention Bonus Payable
A84: Expert Service Cost Payable | B84: =TRIM(A84) -> Expert Service Cost Payable | C84: -83870977 | D84: 89243771 | E84: 1.2825851e+08 | F84: -1.2288572e+08 | G84: =VLOOKUP(B84,'TB 1225'!A:A,1,0) -> Expert Service Cost Payable
A85: GST Payable | B85: =TRIM(A85) -> GST Payable | C85: 0 | D85: 0 | E85: 0 | F85: 0
A86: Output CGST | B86: =TRIM(A86) -> Output CGST | C86: -2055269.3 | D86: 1780559 | E86: 2585849.3 | F86: -2860559.6 | G86: =VLOOKUP(B86,'TB 1225'!A:A,1,0) -> Output CGST
A87: Output IGST | B87: =TRIM(A87) -> Output IGST | C87: -230556.43 | D87: 621696 | E87: 372445.7 | F87: 18693.87 | G87: =VLOOKUP(B87,'TB 1225'!A:A,1,0) -> Output IGST
A88: Output SGST | B88: =TRIM(A88) -> Output SGST | C88: -2055267.3 | D88: 1780559 | E88: 2585849.3 | F88: -2860557.6 | G88: =VLOOKUP(B88,'TB 1225'!A:A,1,0) -> Output SGST
A89: Total for GST Payable | B89: =TRIM(A89) -> Total for GST Payable | C89: -4341093.1 | D89: 4182814 | E89: 5544144.2 | F89: -5702423.3
B90: =TRIM(A90)
A91: LWF - Employee | B91: =TRIM(A91) -> LWF - Employee | C91: 0 | D91: 0 | E91: 8275 | F91: -8275 | G91: =VLOOKUP(B91,'TB 1225'!A:A,1,0) -> LWF - Employee
A92: LWF - Employer | B92: =TRIM(A92) -> LWF - Employer | C92: 0 | D92: 0 | E92: 18625 | F92: -18625 | G92: =VLOOKUP(B92,'TB 1225'!A:A,1,0) -> LWF - Employer
A93: NPS Employer | B93: =TRIM(A93) -> NPS Employer | C93: 0 | D93: 0 | E93: 74603 | F93: -74603 | G93: =VLOOKUP(B93,'TB 1225'!A:A,1,0) -> NPS Employer
A94: Professional Tax | B94: =TRIM(A94) -> Professional Tax | C94: -37800 | D94: 38005.9 | E94: 40200 | F94: -39994.1 | G94: =VLOOKUP(B94,'TB 1225'!A:A,1,0) -> Professional Tax
A95: Provident Fund | B95: =TRIM(A95) -> Provident Fund | C95: 0 | D95: 0 | E95: 0 | F95: 0 | G95: =VLOOKUP(B95,'TB 1225'!A:A,1,0) -> Provident Fund
A96: Provident Fund - Employee | B96: =TRIM(A96) -> Provident Fund - Employee | C96: -459740 | D96: 468309 | E96: 492087 | F96: -483518 | G96: =VLOOKUP(B96,'TB 1225'!A:A,1,0) -> Provident Fund - Employee
A97: Provident Fund - Employer | B97: =TRIM(A97) -> Provident Fund - Employer | C97: -459740 | D97: 468309 | E97: 492087 | F97: -483518 | G97: =VLOOKUP(B97,'TB 1225'!A:A,1,0) -> Provident Fund - Employer
A98: Total for Provident Fund | B98: =TRIM(A98) -> Total for Provident Fund | C98: -919480 | D98: 936618 | E98: 984174 | F98: -967036
B99: =TRIM(A99)
A100: Provision for Customer Acquisition Cost | B100: =TRIM(A100) -> Provision for Customer Acquisition Cost | C100: -11411398 | D100: 11411398 | E100: 28063800 | F100: -28063800 | G100: =VLOOKUP(B100,'TB 1225'!A:A,1,0) -> Provision for Customer Acquisition Cost
A101: Provision for Gratuity - LT | B101: =TRIM(A101) -> Provision for Gratuity - LT | C101: -548984 | D101: 0 | E101: 0 | F101: -548984 | G101: =VLOOKUP(B101,'TB 1225'!A:A,1,0) -> Provision for Gratuity - LT
A102: Provision for Gratuity - ST | B102: =TRIM(A102) -> Provision for Gratuity - ST | C102: -1269 | D102: 0 | E102: 0 | F102: -1269 | G102: =VLOOKUP(B102,'TB 1225'!A:A,1,0) -> Provision for Gratuity - ST
A103: Provision for Marketing Expense | B103: =TRIM(A103) -> Provision for Marketing Expense | C103: -22866217 | D103: 22866217 | E103: 26805889 | F103: -26805889 | G103: =VLOOKUP(B103,'TB 1225'!A:A,1,0) -> Provision for Marketing Expense
A104: Provision for Other Cost | B104: =TRIM(A104) -> Provision for Other Cost | C104: -8038850 | D104: 8038850 | E104: =15284991.25+100000 -> 15384991 | F104: =-15284991.25-100000 -> -15384991 | G104: =VLOOKUP(B104,'TB 1225'!A:A,1,0) -> Provision for Other Cost
A105: Provision for Professional Fees | B105: =TRIM(A105) -> Provision for Professional Fees | C105: -366320 | D105: 366320 | E105: 580000 | F105: -580000 | G105: =VLOOKUP(B105,'TB 1225'!A:A,1,0) -> Provision for Professional Fees
A106: Provision for Rent Expense | B106: =TRIM(A106) -> Provision for Rent Expense | C106: -16916 | D106: 16916 | E106: 24416 | F106: -24416 | G106: =VLOOKUP(B106,'TB 1225'!A:A,1,0) -> Provision for Rent Expense
A107: Provision for Service Cost | B107: =TRIM(A107) -> Provision for Service Cost | C107: -134790 | D107: 134790 | E107: 134790 | F107: -134790 | G107: =VLOOKUP(B107,'TB 1225'!A:A,1,0) -> Provision for Service Cost
A108: Provision for Software Expense | B108: =TRIM(A108) -> Provision for Software Expense | C108: -3714772.3 | D108: 3714772 | E108: 4002027 | F108: -4002027.3 | G108: =VLOOKUP(B108,'TB 1225'!A:A,1,0) -> Provision for Software Expense
A109: Provision for Staff Welfare Expense | B109: =TRIM(A109) -> Provision for Staff Welfare Expense | C109: -2414260 | D109: 2414260 | E109: 5892118 | F109: -5892118 | G109: =VLOOKUP(B109,'TB 1225'!A:A,1,0) -> Provision for Staff Welfare Expense
A110: Provision for TC Expense | B110: =TRIM(A110) -> Provision for TC Expense | C110: -842113 | D110: 842113 | E110: 1907356 | F110: -1907356 | G110: =VLOOKUP(B110,'TB 1225'!A:A,1,0) -> Provision for TC Expense
A111: TDS Payable | B111: =TRIM(A111) -> TDS Payable | C111: -7768398.4 | D111: 8040832 | E111: 8646414.3 | F111: -8373980.7 | G111: =VLOOKUP(B111,'TB 1225'!A:A,1,0) -> TDS Payable
A112: Variable Salary Payable | B112: =TRIM(A112) -> Variable Salary Payable | C112: -2699443 | D112: 0 | E112: 0 | F112: -2699443 | G112: =VLOOKUP(B112,'TB 1225'!A:A,1,0) -> Variable Salary Payable
A113: Equities | B113: =TRIM(A113) -> Equities
A114: Current Year Earnings | B114: =TRIM(A114) -> Current Year Earnings | C114: 6.239862e+08 | D114: 0 | E114: 0 | F114: 6.239862e+08 | G114: =VLOOKUP(B114,'TB 1225'!A:A,1,0) -> Current Year Earnings
A115: ESOP Outstanding Reserve | B115: =TRIM(A115) -> ESOP Outstanding Reserve | C115: -1245691 | D115: 0 | E115: 0 | F115: -1245691 | G115: =VLOOKUP(B115,'TB 1225'!A:A,1,0) -> ESOP Outstanding Reserve
A116: Owner's Equity | B116: =TRIM(A116) -> Owner's Equity | C116: -100000 | D116: 0 | E116: 0 | F116: -100000 | G116: =VLOOKUP(B116,'TB 1225'!A:A,1,0) -> Owner's Equity
A117: BERTELSMANN NEDERLAND B.V. | B117: =TRIM(A117) -> BERTELSMANN NEDERLAND B.V. | C117: -2798700 | D117: 0 | E117: 0 | F117: -2798700 | G117: =VLOOKUP(B117,'TB 1225'!A:A,1,0) -> BERTELSMANN NEDERLAND B.V.
A118: Elevation Capital III Limited ESC | B118: =TRIM(A118) -> Elevation Capital III Limited ESC | C118: -10 | D118: 0 | E118: 0 | F118: -10 | G118: =VLOOKUP(B118,'TB 1225'!A:A,1,0) -> Elevation Capital III Limited ESC
A119: Elevation Capital III Limited PSC | B119: =TRIM(A119) -> Elevation Capital III Limited PSC | C119: -5463300 | D119: 0 | E119: 0 | F119: -5463300 | G119: =VLOOKUP(B119,'TB 1225'!A:A,1,0) -> Elevation Capital III Limited PSC
A120: ELEVATION CAPITAL VIII LIMITED | B120: =TRIM(A120) -> ELEVATION CAPITAL VIII LIMITED | C120: -1097500 | D120: 0 | E120: 0 | F120: -1097500 | G120: =VLOOKUP(B120,'TB 1225'!A:A,1,0) -> ELEVATION CAPITAL VIII LIMITED
A121: Gaurav Munjal | B121: =TRIM(A121) -> Gaurav Munjal | C121: -10800 | D121: 0 | E121: 0 | F121: -10800 | G121: =VLOOKUP(B121,'TB 1225'!A:A,1,0) -> Gaurav Munjal
A122: Lightspeed India Partners IV LLC | B122: =TRIM(A122) -> Lightspeed India Partners IV LLC | C122: -4870200 | D122: 0 | E122: 0 | F122: -4870200 | G122: =VLOOKUP(B122,'TB 1225'!A:A,1,0) -> Lightspeed India Partners IV LLC
A123: Nexus Ventures VII Holdings LLC ESC | B123: =TRIM(A123) -> Nexus Ventures VII Holdings LLC ESC | C123: -10 | D123: 0 | E123: 0 | F123: -10 | G123: =VLOOKUP(B123,'TB 1225'!A:A,1,0) -> Nexus Ventures VII Holdings LLC ESC
...

Sheet TB 1225
B1: =SUBTOTAL(9,B3:B1048576) -> 3013317 | C1: =SUBTOTAL(9,C3:C1048576) -> 1.3194441e+08 | D1: =SUBTOTAL(9,D3:D1048576) -> 1.3573336e+08 | E1: =SUBTOTAL(9,E3:E1048576) -> 1224370 | F1: =SUBTOTAL(9,F3:F1048576) -> 1224.37
A2: Particulars | B2: Opening | C2: Debit | D2: Credit | E2: Closing | F2: INR in '000 | G2: Head | H2: Tag | K2: Employee cost Headwise | L2: Amount | M2: In '000 | O2: Revenue | R2: Discount | U2: New user Discount
A3: Accounts Receivable | B3: =SUMIF('Raw TB 1225'!$B:$B,'TB 1225'!$A3,'Raw TB 1225'!C:C) -> 3013317 | C3: =SUMIF('Raw TB 1225'!$B:$B,'TB 1225'!$A3,'Raw TB 1225'!D:D) -> 66113310 | D3: =SUMIF('Raw TB 1225'!$B:$B,'TB 1225'!$A3,'Raw TB 1225'!E:E) -> 66969391 | E3: =SUMIF('Raw TB 1225'!$B:$B,'TB 1225'!$A3,'Raw TB 1225'!F:F) -> 2157235.5 | F3: =E3/10^3 -> 2157.2355 | G3: BSA | H3: Trade Receivables | K3: Customer Success Cost | L3: 92283 | M3: =L3/10^3 -> 92.283 | O3: Particular | P3: Amount | R3: Particular | S3: Amount | U3: Particular | V3: Amount
A4: Accrued Interest | B4: =SUMIF('Raw TB 1225'!$B:$B,'TB 1225'!$A4,'Raw TB 1225'!C:C) -> 60436186 | C4: =SUMIF('Raw TB 1225'!$B:$B,'TB 1225'!$A4,'Raw TB 1225'!D:D) -> 75481262 | D4: =SUMIF('Raw TB 1225'!$B:$B,'TB 1225'!$A4,'Raw TB 1225'!E:E) -> 60436186 | E4: =SUMIF('Raw TB 1225'!$B:$B,'TB 1225'!$A4,'Raw TB 1225'!F:F) -> 75481262 | F4: =E4/10^3 -> 75481.262 | G4: BSA | H4: Other Current Assets | K4: Manegerial Cost | L4: 1842219 | M4: =L4/10^3 -> 1842.219 | O4: As Books | P4: 1.2168612e+08 | R4: Total Discount | S4: 62141532 | U4: From discount | V4: =S6 -> 20859296
A5: Accumulated Amortization on Leasehold Improvement | B5: =SUMIF('Raw TB 1225'!$B:$B,'TB 1225'!$A5,'Raw TB 1225'!C:C) -> -1482757.6 | C5: =SUMIF('Raw TB 1225'!$B:$B,'TB 1225'!$A5,'Raw TB 1225'!D:D) -> 0 | D5: =SUMIF('Raw TB 1225'!$B:$B,'TB 1225'!$A5,'Raw TB 1225'!E:E) -> 462364.89 | E5: =SUMIF('Raw TB 1225'!$B:$B,'TB 1225'!$A5,'Raw TB 1225'!F:F) -> -1945122.5 | F5: =E5/10^3 -> -1945.1225 | G5: BSA | H5: Property, Plant & Equipment | K5: Sourcing and Onboarding | L5: 1188507 | M5: =L5/10^3 -> 1188.507 | O5: GST | P5: 5073887.4 | R5: Promotional discount | S5: 41282228 | U5: Offer pack | V5: -9988940.8
A6: Accumulated Depreciation on Computer and Laptops | B6: =SUMIF('Raw TB 1225'!$B:$B,'TB 1225'!$A6,'Raw TB 1225'!C:C) -> -2700081.8 | C6: =SUMIF('Raw TB 1225'!$B:$B,'TB 1225'!$A6,'Raw TB 1225'!D:D) -> 0 | D6: =SUMIF('Raw TB 1225'!$B:$B,'TB 1225'!$A6,'Raw TB 1225'!E:E) -> 691820.18 | E6: =SUMIF('Raw TB 1225'!$B:$B,'TB 1225'!$A6,'Raw TB 1225'!F:F) -> -3391901.9 | F6: =E6/10^3 -> -3391.9019 | G6: BSA | H6: Property, Plant & Equipment | K6: Training Centre Expenses | L6: 789156 | M6: =L6/10^3 -> 789.156 | O6: Offer pack income | P6: 11825541 | R6: CAC | S6: 20859296 | U6: Promo
A7: Accumulated Depreciation on Furniture & Equipment | B7: =SUMIF('Raw TB 1225'!$B:$B,'TB 1225'!$A7,'Raw TB 1225'!C:C) -> -98029.69 | C7: =SUMIF('Raw TB 1225'!$B:$B,'TB 1225'!$A7,'Raw TB 1225'!D:D) -> 0 | D7: =SUMIF('Raw TB 1225'!$B:$B,'TB 1225'!$A7,'Raw TB 1225'!E:E) -> 11370.3 | E7: =SUMIF('Raw TB 1225'!$B:$B,'TB 1225'!$A7,'Raw TB 1225'!F:F) -> -109399.99 | F7: =E7/10^3 -> -109.39999 | G7: BSA | H7: Property, Plant & Equipment | K7: Employee Cost | L7: =36471796-11000 -> 36460796 | M7: =L7/10^3 -> 36460.796 | O7: offer pack forfeiture | P7: 1834914.1 | R7: Difference | S7: =S4-S5-S6 -> 8.5 | U7: Total | V7: =SUM(V4:V6) -> 10870355
A8: Accumulated Depreciation on Office Equipment | B8: =SUMIF('Raw TB 1225'!$B:$B,'TB 1225'!$A8,'Raw TB 1225'!C:C) -> -116822.47 | C8: =SUMIF('Raw TB 1225'!$B:$B,'TB 1225'!$A8,'Raw TB 1225'!D:D) -> 0 | D8: =SUMIF('Raw TB 1225'!$B:$B,'TB 1225'!$A8,'Raw TB 1225'!E:E) -> 18733.17 | E8: =SUMIF('Raw TB 1225'!$B:$B,'TB 1225'!$A8,'Raw TB 1225'!F:F) -> -135555.64 | F8: =E8/10^3 -> -135.55564 | G8: BSA | H8: Property, Plant & Equipment | K8: Consultant | L8: =625000+1596399.52+741000 -> 2962399.5 | M8: =L8/10^3 -> 2962.3995 | O8: As per MIS | P8: =P4+P5-P6+P7 -> 1.1676938e+08 | R8: Promotional discount | S8: =S5 -> 41282228 | U8: New user Discount | V8: =V7 -> 10870355
A9: Advance to Vendors | B9: =SUMIF('Raw TB 1225'!$B:$B,'TB 1225'!$A9,'Raw TB 1225'!C:C) -> 8756066.4 | C9: =SUMIF('Raw TB 1225'!$B:$B,'TB 1225'!$A9,'Raw TB 1225'!D:D) -> 11524661 | D9: =SUMIF('Raw TB 1225'!$B:$B,'TB 1225'!$A9,'Raw TB 1225'!E:E) -> 99062.88 | E9: =SUMIF('Raw TB 1225'!$B:$B,'TB 1225'!$A9,'Raw TB 1225'!F:F) -> 20181664 | F9: =E9/10^3 -> 20181.664 | G9: BSA | H9: Other Current Assets | K9: Intern | L9: 128807 | M9: =L9/10^3 -> 128.807
A10: Amazon Wallet | B10: =SUMIF('Raw TB 1225'!$B:$B,'TB 1225'!$A10,'Raw TB 1225'!C:C) -> 305.98 | C10: =SUMIF('Raw TB 1225'!$B:$B,'TB 1225'!$A10,'Raw TB 1225'!D:D) -> 0 | D10: =SUMIF('Raw TB 1225'!$B:$B,'TB 1225'!$A10,'Raw TB 1225'!E:E) -> 0 | E10: =SUMIF('Raw TB 1225'!$B:$B,'TB 1225'!$A10,'Raw TB 1225'!F:F) -> 305.98 | F10: =E10/10^3 -> 0.30598 | G10: BSA | H10: Other Current Assets | L10: =SUM(L3:L9) -> 43464168 | M10: =SUM(M3:M9) -> 43464.168
A11: Axis Bank 1655 | B11: =SUMIF('Raw TB 1225'!$B:$B,'TB 1225'!$A11,'Raw TB 1225'!C:C) -> 11810.34 | C11: =SUMIF('Raw TB 1225'!$B:$B,'TB 1225'!$A11,'Raw TB 1225'!D:D) -> 3131680 | D11: =SUMIF('Raw TB 1225'!$B:$B,'TB 1225'!$A11,'Raw TB 1225'!E:E) -> 2916665.3 | E11: =SUMIF('Raw TB 1225'!$B:$B,'TB 1225'!$A11,'Raw TB 1225'!F:F) -> 226825.06 | F11: =E11/10^3 -> 226.82506 | G11: BSA | H11: Cash & Cash Equivalents | L11: =L10-E106-E124 -> 0
A12: Computer and Laptops | B12: =SUMIF('Raw TB 1225'!$B:$B,'TB 1225'!$A12,'Raw TB 1225'!C:C) -> 25524871 | C12: =SUMIF('Raw TB 1225'!$B:$B,'TB 1225'!$A12,'Raw TB 1225'!D:D) -> 330880 | D12: =SUMIF('Raw TB 1225'!$B:$B,'TB 1225'!$A12,'Raw TB 1225'!E:E) -> 0 | E12: =SUMIF('Raw TB 1225'!$B:$B,'TB 1225'!$A12,'Raw TB 1225'!F:F) -> 25855751 | F12: =E12/10^3 -> 25855.751 | G12: BSA | H12: Property, Plant & Equipment | I12: Purchase of Fixed assets
A13: Expert Inventory | B13: =SUMIF('Raw TB 1225'!$B:$B,'TB 1225'!$A13,'Raw TB 1225'!C:C) -> 3400180.7 | C13: =SUMIF('Raw TB 1225'!$B:$B,'TB 1225'!$A13,'Raw TB 1225'!D:D) -> 10206713 | D13: =SUMIF('Raw TB 1225'!$B:$B,'TB 1225'!$A13,'Raw TB 1225'!E:E) -> 8231916 | E13: =SUMIF('Raw TB 1225'!$B:$B,'TB 1225'!$A13,'Raw TB 1225'!F:F) -> 5374977.7 | F13: =E13/10^3 -> 5374.9777 | G13: BSA | H13: Other Current Assets
A14: Furniture and Equipment | B14: =SUMIF('Raw TB 1225'!$B:$B,'TB 1225'!$A14,'Raw TB 1225'!C:C) -> 704611.34 | C14: =SUMIF('Raw TB 1225'!$B:$B,'TB 1225'!$A14,'Raw TB 1225'!D:D) -> 0 | D14: =SUMIF('Raw TB 1225'!$B:$B,'TB 1225'!$A14,'Raw TB 1225'!E:E) -> 0 | E14: =SUMIF('Raw TB 1225'!$B:$B,'TB 1225'!$A14,'Raw TB 1225'!F:F) -> 704611.34 | F14: =E14/10^3 -> 704.61134 | G14: BSA | H14: Property, Plant & Equipment | I14: Purchase of Fixed assets
A15: HDFC Bank 6899 | B15: =SUMIF('Raw TB 1225'!$B:$B,'TB 1225'!$A15,'Raw TB 1225'!C:C) -> 245099.7 | C15: =SUMIF('Raw TB 1225'!$B:$B,'TB 1225'!$A15,'Raw TB 1225'!D:D) -> 1.9121684e+08 | D15: =SUMIF('Raw TB 1225'!$B:$B,'TB 1225'!$A15,'Raw TB 1225'!E:E) -> 1.9140043e+08 | E15: =SUMIF('Raw TB 1225'!$B:$B,'TB 1225'!$A15,'Raw TB 1225'!F:F) -> 61512.8 | F15: =E15/10^3 -> 61.5128 | G15: BSA | H15: Cash & Cash Equivalents
A16: HDFC Bank 9531 | B16: =SUMIF('Raw TB 1225'!$B:$B,'TB 1225'!$A16,'Raw TB 1225'!C:C) -> 449633.35 | C16: =SUMIF('Raw TB 1225'!$B:$B,'TB 1225'!$A16,'Raw TB 1225'!D:D) -> 1080430.8 | D16: =SUMIF('Raw TB 1225'!$B:$B,'TB 1225'!$A16,'Raw TB 1225'!E:E) -> 1406225.6 | E16: =SUMIF('Raw TB 1225'!$B:$B,'TB 1225'!$A16,'Raw TB 1225'!F:F) -> 123838.5 | F16: =E16/10^3 -> 123.8385 | G16: BSA | H16: Cash & Cash Equivalents
A17: Input CGST | B17: =SUMIF('Raw TB 1225'!$B:$B,'TB 1225'!$A17,'Raw TB 1225'!C:C) -> 15716937 | C17: =SUMIF('Raw TB 1225'!$B:$B,'TB 1225'!$A17,'Raw TB 1225'!D:D) -> 4065386.1 | D17: =SUMIF('Raw TB 1225'!$B:$B,'TB 1225'!$A17,'Raw TB 1225'!E:E) -> 0 | E17: =SUMIF('Raw TB 1225'!$B:$B,'TB 1225'!$A17,'Raw TB 1225'!F:F) -> 19782323 | F17: =E17/10^3 -> 19782.323 | G17: BSA | H17: Other Current Assets
A18: Input IGST | B18: =SUMIF('Raw TB 1225'!$B:$B,'TB 1225'!$A18,'Raw TB 1225'!C:C) -> 10163831 | C18: =SUMIF('Raw TB 1225'!$B:$B,'TB 1225'!$A18,'Raw TB 1225'!D:D) -> 3645771.8 | D18: =SUMIF('Raw TB 1225'!$B:$B,'TB 1225'!$A18,'Raw TB 1225'!E:E) -> 2009906 | E18: =SUMIF('Raw TB 1225'!$B:$B,'TB 1225'!$A18,'Raw TB 1225'!F:F) -> 11799696 | F18: =E18/10^3 -> 11799.696 | G18: BSA | H18: Other Current Assets
A19: Input SGST | B19: =SUMIF('Raw TB 1225'!$B:$B,'TB 1225'!$A19,'Raw TB 1225'!C:C) -> 15648579 | C19: =SUMIF('Raw TB 1225'!$B:$B,'TB 1225'!$A19,'Raw TB 1225'!D:D) -> 4065386.1 | D19: =SUMIF('Raw TB 1225'!$B:$B,'TB 1225'!$A19,'Raw TB 1225'!E:E) -> 0 | E19: =SUMIF('Raw TB 1225'!$B:$B,'TB 1225'!$A19,'Raw TB 1225'!F:F) -> 19713965 | F19: =E19/10^3 -> 19713.965 | G19: BSA | H19: Other Current Assets
A20: Aditya Birla Sun Life Money Manager Fund | B20: =SUMIF('Raw TB 1225'!$B:$B,'TB 1225'!$A20,'Raw TB 1225'!C:C) -> 59997000 | C20: =SUMIF('Raw TB 1225'!$B:$B,'TB 1225'!$A20,'Raw TB 1225'!D:D) -> 0 | D20: =SUMIF('Raw TB 1225'!$B:$B,'TB 1225'!$A20,'Raw TB 1225'!E:E) -> 0 | E20: =SUMIF('Raw TB 1225'!$B:$B,'TB 1225'!$A20,'Raw TB 1225'!F:F) -> 59997000 | F20: =E20/10^3 -> 59997 | G20: BSA | H20: Current Investments
A21: Fixed Deposit 50301170464152 | B21: =SUMIF('Raw TB 1225'!$B:$B,'TB 1225'!$A21,'Raw TB 1225'!C:C) -> 0 | C21: =SUMIF('Raw TB 1225'!$B:$B,'TB 1225'!$A21,'Raw TB 1225'!D:D) -> 0 | D21: =SUMIF('Raw TB 1225'!$B:$B,'TB 1225'!$A21,'Raw TB 1225'!E:E) -> 0 | E21: =SUMIF('Raw TB 1225'!$B:$B,'TB 1225'!$A21,'Raw TB 1225'!F:F) -> 0 | F21: =E21/10^3 -> 0 | G21: BSA | H21: Current Investments
A22: Fixed Deposit 50301170464596 | B22: =SUMIF('Raw TB 1225'!$B:$B,'TB 1225'!$A22,'Raw TB 1225'!C:C) -> 100000000 | C22: =SUMIF('Raw TB 1225'!$B:$B,'TB 1225'!$A22,'Raw TB 1225'!D:D) -> 0 | D22: =SUMIF('Raw TB 1225'!$B:$B,'TB 1225'!$A22,'Raw TB 1225'!E:E) -> 100000000 | E22: =SUMIF('Raw TB 1225'!$B:$B,'TB 1225'!$A22,'Raw TB 1225'!F:F) -> 0 | F22: =E22/10^3 -> 0 | G22: BSA | H22: Current Investments
A23: Fixed Deposit 50301170464942 | B23: =SUMIF('Raw TB 1225'!$B:$B,'TB 1225'!$A23,'Raw TB 1225'!C:C) -> 150000000 | C23: =SUMIF('Raw TB 1225'!$B:$B,'TB 1225'!$A23,'Raw TB 1225'!D:D) -> 0 | D23: =SUMIF('Raw TB 1225'!$B:$B,'TB 1225'!$A23,'Raw TB 1225'!E:E) -> 0 | E23: =SUMIF('Raw TB 1225'!$B:$B,'TB 1225'!$A23,'Raw TB 1225'!F:F) -> 150000000 | F23: =E23/10^3 -> 150000 | G23: BSA | H23: Current Investments
A24: Fixed Deposit 50301170465320 | B24: =SUMIF('Raw TB 1225'!$B:$B,'TB 1225'!$A24,'Raw TB 1225'!C:C) -> 300000000 | C24: =SUMIF('Raw TB 1225'!$B:$B,'TB 1225'!$A24,'Raw TB 1225'!D:D) -> 0 | D24: =SUMIF('Raw TB 1225'!$B:$B,'TB 1225'!$A24,'Raw TB 1225'!E:E) -> 0 | E24: =SUMIF('Raw TB 1225'!$B:$B,'TB 1225'!$A24,'Raw TB 1225'!F:F) -> 300000000 | F24: =E24/10^3 -> 300000 | G24: BSA | H24: Current Investments
A25: Fixed Deposit 9349969993 | B25: =SUMIF('Raw TB 1225'!$B:$B,'TB 1225'!$A25,'Raw TB 1225'!C:C) -> 100000000 | C25: =SUMIF('Raw TB 1225'!$B:$B,'TB 1225'!$A25,'Raw TB 1225'!D:D) -> 0 | D25: =SUMIF('Raw TB 1225'!$B:$B,'TB 1225'!$A25,'Raw TB 1225'!E:E) -> 0 | E25: =SUMIF('Raw TB 1225'!$B:$B,'TB 1225'!$A25,'Raw TB 1225'!F:F) -> 100000000 | F25: =E25/10^3 -> 100000 | G25: BSA | H25: Current Investments
A26: Fixed Deposit 9349970005 | B26: =SUMIF('Raw TB 1225'!$B:$B,'TB 1225'!$A26,'Raw TB 1225'!C:C) -> 150000000 | C26: =SUMIF('Raw TB 1225'!$B:$B,'TB 1225'!$A26,'Raw TB 1225'!D:D) -> 0 | D26: =SUMIF('Raw TB 1225'!$B:$B,'TB 1225'!$A26,'Raw TB 1225'!E:E) -> 0 | E26: =SUMIF('Raw TB 1225'!$B:$B,'TB 1225'!$A26,'Raw TB 1225'!F:F) -> 150000000 | F26: =E26/10^3 -> 150000 | G26: BSA | H26: Current Investments
... A37: Kotak Mahindra Bank 9942 | B37: =SUMIF('Raw TB 1225'!$B:$B,'TB 1225'!$A37,'Raw TB 1225'!C:C) -> 300000 | C37: =SUMIF('Raw TB 1225'!$B:$B,'TB 1225'!$A37,'Raw TB 1225'!D:D) -> 4.3124098e+08 | D37: =SUMIF('Raw TB 1225'!$B:$B,'TB 1225'!$A37,'Raw TB 1225'!E:E) -> 3.9314098e+08 | E37: =SUMIF('Raw TB 1225'!$B:$B,'TB 1225'!$A37,'Raw TB 1225'!F:F) -> 38400000 | F37: =E37/10^3 -> 38400 | G37: BSA | H37: Cash & Cash Equivalents
A38: Kotak Mahindra Bank 9966 | B38: =SUMIF('Raw TB 1225'!$B:$B,'TB 1225'!$A38,'Raw TB 1225'!C:C) -> 209417.22 | C38: =SUMIF('Raw TB 1225'!$B:$B,'TB 1225'!$A38,'Raw TB 1225'!D:D) -> 4.7240692e+08 | D38: =SUMIF('Raw TB 1225'!$B:$B,'TB 1225'!$A38,'Raw TB 1225'!E:E) -> 4.6901227e+08 | E38: =SUMIF('Raw TB 1225'!$B:$B,'TB 1225'!$A38,'Raw TB 1225'!F:F)+8000 -> 3612072.9 | F38: =E38/10^3 -> 3612.0729 | G38: BSA | H38: Cash & Cash Equivalents
A39: Leasehold Improvement | B39: =SUMIF('Raw TB 1225'!$B:$B,'TB 1225'!$A39,'Raw TB 1225'!C:C) -> 12860897 | C39: =SUMIF('Raw TB 1225'!$B:$B,'TB 1225'!$A39,'Raw TB 1225'!D:D) -> 6766884 | D39: =SUMIF('Raw TB 1225'!$B:$B,'TB 1225'!$A39,'Raw TB 1225'!E:E) -> 0 | E39: =SUMIF('Raw TB 1225'!$B:$B,'TB 1225'!$A39,'Raw TB 1225'!F:F) -> 19627781 | F39: =E39/10^3 -> 19627.781 | G39: BSA | H39: Property, Plant & Equipment | I39: Purchase of Fixed assets
A40: Office Equipment | B40: =SUMIF('Raw TB 1225'!$B:$B,'TB 1225'!$A40,'Raw TB 1225'!C:C) -> 689841.58 | C40: =SUMIF('Raw TB 1225'!$B:$B,'TB 1225'!$A40,'Raw TB 1225'!D:D) -> 11515 | D40: =SUMIF('Raw TB 1225'!$B:$B,'TB 1225'!$A40,'Raw TB 1225'!E:E) -> 0 | E40: =SUMIF('Raw TB 1225'!$B:$B,'TB 1225'!$A40,'Raw TB 1225'!F:F) -> 701356.58 | F40: =E40/10^3 -> 701.35658 | G40: BSA | H40: Property, Plant & Equipment | I40: Purchase of Fixed assets
A41: Prepaid - Consumption | B41: =SUMIF('Raw TB 1225'!$B:$B,'TB 1225'!$A41,'Raw TB 1225'!C:C) -> 1222814 | C41: =SUMIF('Raw TB 1225'!$B:$B,'TB 1225'!$A41,'Raw TB 1225'!D:D) -> 0 | D41: =SUMIF('Raw TB 1225'!$B:$B,'TB 1225'!$A41,'Raw TB 1225'!E:E) -> 0 | E41: =SUMIF('Raw TB 1225'!$B:$B,'TB 1225'!$A41,'Raw TB 1225'!F:F) -> 1222814 | F41: =E41/10^3 -> 1222.814 | G41: BSA | H41: Other Current Assets
A42: Prepaid Expense - Asset | B42: =SUMIF('Raw TB 1225'!$B:$B,'TB 1225'!$A42,'Raw TB 1225'!C:C) -> 1076041.7 | C42: =SUMIF('Raw TB 1225'!$B:$B,'TB 1225'!$A42,'Raw TB 1225'!D:D) -> 1100595 | D42: =SUMIF('Raw TB 1225'!$B:$B,'TB 1225'!$A42,'Raw TB 1225'!E:E) -> 250391.67 | E42: =SUMIF('Raw TB 1225'!$B:$B,'TB 1225'!$A42,'Raw TB 1225'!F:F) -> 1926245 | F42: =E42/10^3 -> 1926.245 | G42: BSA | H42: Other Current Assets
A43: Prepaid Expenses | B43: =SUMIF('Raw TB 1225'!$B:$B,'TB 1225'!$A43,'Raw TB 1225'!C:C) -> 49712663 | C43: =SUMIF('Raw TB 1225'!$B:$B,'TB 1225'!$A43,'Raw TB 1225'!D:D) -> 5162370.1 | D43: =SUMIF('Raw TB 1225'!$B:$B,'TB 1225'!$A43,'Raw TB 1225'!E:E) -> 7958920.8 | E43: =SUMIF('Raw TB 1225'!$B:$B,'TB 1225'!$A43,'Raw TB 1225'!F:F) -> 46916112 | F43: =E43/10^3 -> 46916.112 | G43: BSA | H43: Trade Payables
A44: Receipt from Customers | B44: =SUMIF('Raw TB 1225'!$B:$B,'TB 1225'!$A44,'Raw TB 1225'!C:C) -> 0 | C44: =SUMIF('Raw TB 1225'!$B:$B,'TB 1225'!$A44,'Raw TB 1225'!D:D) -> 65831102 | D44: =SUMIF('Raw TB 1225'!$B:$B,'TB 1225'!$A44,'Raw TB 1225'!E:E) -> 68763968 | E44: =SUMIF('Raw TB 1225'!$B:$B,'TB 1225'!$A44,'Raw TB 1225'!F:F)+2000000 -> -932865.51 | F44: =E44/10^3 -> -932.86551 | G44: BSA | H44: Trade Receivables
A45: Reverse Charge Tax Input but not due | B45: =SUMIF('Raw TB 1225'!$B:$B,'TB 1225'!$A45,'Raw TB 1225'!C:C) -> 2780151.6 | C45: =SUMIF('Raw TB 1225'!$B:$B,'TB 1225'!$A45,'Raw TB 1225'!D:D) -> 470256.88 | D45: =SUMIF('Raw TB 1225'!$B:$B,'TB 1225'!$A45,'Raw TB 1225'!E:E) -> 0 | E45: =SUMIF('Raw TB 1225'!$B:$B,'TB 1225'!$A45,'Raw TB 1225'!F:F) -> 3250408.5 | F45: =E45/10^3 -> 3250.4085 | G45: BSA | H45: Other Current Assets
A46: Security Deposit | B46: =SUMIF('Raw TB 1225'!$B:$B,'TB 1225'!$A46,'Raw TB 1225'!C:C) -> 15705400 | C46: =SUMIF('Raw TB 1225'!$B:$B,'TB 1225'!$A46,'Raw TB 1225'!D:D) -> 2785000 | D46: =SUMIF('Raw TB 1225'!$B:$B,'TB 1225'!$A46,'Raw TB 1225'!E:E) -> 0 | E46: =SUMIF('Raw TB 1225'!$B:$B,'TB 1225'!$A46,'Raw TB 1225'!F:F) -> 18490400 | F46: =E46/10^3 -> 18490.4 | G46: BSA | H46: Other Non-current Assets
A47: TDS Receivable | B47: =SUMIF('Raw TB 1225'!$B:$B,'TB 1225'!$A47,'Raw TB 1225'!C:C) -> 1271832.7 | C47: =SUMIF('Raw TB 1225'!$B:$B,'TB 1225'!$A47,'Raw TB 1225'!D:D) -> 0 | D47: =SUMIF('Raw TB 1225'!$B:$B,'TB 1225'!$A47,'Raw TB 1225'!E:E) -> 0 | E47: =SUMIF('Raw TB 1225'!$B:$B,'TB 1225'!$A47,'Raw TB 1225'!F:F) -> 1271832.7 | F47: =E47/10^3 -> 1271.8327 | G47: BSA | H47: Other Current Assets
A48: Accounts Payable | B48: =SUMIF('Raw TB 1225'!$B:$B,'TB 1225'!$A48,'Raw TB 1225'!C:C) -> -80942920 | C48: =SUMIF('Raw TB 1225'!$B:$B,'TB 1225'!$A48,'Raw TB 1225'!D:D) -> 88692880 | D48: =SUMIF('Raw TB 1225'!$B:$B,'TB 1225'!$A48,'Raw TB 1225'!E:E) -> 92676329 | E48: =SUMIF('Raw TB 1225'!$B:$B,'TB 1225'!$A48,'Raw TB 1225'!F:F) -> -84926369 | F48: =E48/10^3 -> -84926.369 | G48: BSL | H48: Trade Payables
A49: Advance from B2C Customer | B49: =SUMIF('Raw TB 1225'!$B:$B,'TB 1225'!$A49,'Raw TB 1225'!C:C) -> -5581330 | C49: =SUMIF('Raw TB 1225'!$B:$B,'TB 1225'!$A49,'Raw TB 1225'!D:D) -> 13280943 | D49: =SUMIF('Raw TB 1225'!$B:$B,'TB 1225'!$A49,'Raw TB 1225'!E:E) -> 14842946 | E49: =SUMIF('Raw TB 1225'!$B:$B,'TB 1225'!$A49,'Raw TB 1225'!F:F)-2000000 -> -9143332.8 | F49: =E49/10^3 -> -9143.3328 | G49: BSL | H49: Other Current Liabilities
A50: App Wallet | B50: =SUMIF('Raw TB 1225'!$B:$B,'TB 1225'!$A50,'Raw TB 1225'!C:C) -> -2136081.3 | C50: =SUMIF('Raw TB 1225'!$B:$B,'TB 1225'!$A50,'Raw TB 1225'!D:D) -> 342395 | D50: =SUMIF('Raw TB 1225'!$B:$B,'TB 1225'!$A50,'Raw TB 1225'!E:E) -> 445723 | E50: =SUMIF('Raw TB 1225'!$B:$B,'TB 1225'!$A50,'Raw TB 1225'!F:F) -> -2239409.3 | F50: =E50/10^3 -> -2239.4093 | G50: BSL | H50: Other Current Liabilities
A51: Employee Reimbursements | B51: =SUMIF('Raw TB 1225'!$B:$B,'TB 1225'!$A51,'Raw TB 1225'!C:C) -> 494297.59 | C51: =SUMIF('Raw TB 1225'!$B:$B,'TB 1225'!$A51,'Raw TB 1225'!D:D) -> 128231.35 | D51: =SUMIF('Raw TB 1225'!$B:$B,'TB 1225'!$A51,'Raw TB 1225'!E:E) -> 128231.35 | E51: =SUMIF('Raw TB 1225'!$B:$B,'TB 1225'!$A51,'Raw TB 1225'!F:F) -> 494297.59 | F51: =E51/10^3 -> 494.29759 | G51: BSL | H51: Other Current Liabilities
A52: Employee Salaries Payable | B52: =SUMIF('Raw TB 1225'!$B:$B,'TB 1225'!$A52,'Raw TB 1225'!C:C) -> -941444.61 | C52: =SUMIF('Raw TB 1225'!$B:$B,'TB 1225'!$A52,'Raw TB 1225'!D:D) -> 34499743 | D52: =SUMIF('Raw TB 1225'!$B:$B,'TB 1225'!$A52,'Raw TB 1225'!E:E) -> 34435409 | E52: =SUMIF('Raw TB 1225'!$B:$B,'TB 1225'!$A52,'Raw TB 1225'!F:F) -> -877110.61 | F52: =E52/10^3 -> -877.11061 | G52: BSL | H52: Other Current Liabilities
A53: ESI - Employee | B53: =SUMIF('Raw TB 1225'!$B:$B,'TB 1225'!$A53,'Raw TB 1225'!C:C) -> 0 | C53: =SUMIF('Raw TB 1225'!$B:$B,'TB 1225'!$A53,'Raw TB 1225'!D:D) -> 0 | D53: =SUMIF('Raw TB 1225'!$B:$B,'TB 1225'!$A53,'Raw TB 1225'!E:E) -> 0 | E53: =SUMIF('Raw TB 1225'!$B:$B,'TB 1225'!$A53,'Raw TB 1225'!F:F) -> 0 | F53: =E53/10^3 -> 0 | G53: BSL | H53: Other Current Liabilities
A54: ESI - Employer | B54: =SUMIF('Raw TB 1225'!$B:$B,'TB 1225'!$A54,'Raw TB 1225'!C:C) -> 0 | C54: =SUMIF('Raw TB 1225'!$B:$B,'TB 1225'!$A54,'Raw TB 1225'!D:D) -> 0 | D54: =SUMIF('Raw TB 1225'!$B:$B,'TB 1225'!$A54,'Raw TB 1225'!E:E) -> 0 | E54: =SUMIF('Raw TB 1225'!$B:$B,'TB 1225'!$A54,'Raw TB 1225'!F:F) -> 0 | F54: =E54/10^3 -> 0 | G54: BSL | H54: Other Current Liabilities
A55: Expert Joining Bonus Payable | B55: =SUMIF('Raw TB 1225'!$B:$B,'TB 1225'!$A55,'Raw TB 1225'!C:C) -> -1401969.4 | C55: =SUMIF('Raw TB 1225'!$B:$B,'TB 1225'!$A55,'Raw TB 1225'!D:D) -> 1305197.4 | D55: =SUMIF('Raw TB 1225'!$B:$B,'TB 1225'!$A55,'Raw TB 1225'!E:E) -> 1976890 | E55: =SUMIF('Raw TB 1225'!$B:$B,'TB 1225'!$A55,'Raw TB 1225'!F:F) -> -2073662 | F55: =E55/10^3 -> -2073.662 | G55: BSL | H55: Trade Payables
A56: Expert Referral Bonus Payable | B56: =SUMIF('Raw TB 1225'!$B:$B,'TB 1225'!$A56,'Raw TB 1225'!C:C) -> -14850 | C56: =SUMIF('Raw TB 1225'!$B:$B,'TB 1225'!$A56,'Raw TB 1225'!D:D) -> 2928039 | D56: =SUMIF('Raw TB 1225'!$B:$B,'TB 1225'!$A56,'Raw TB 1225'!E:E) -> 2949697 | E56: =SUMIF('Raw TB 1225'!$B:$B,'TB 1225'!$A56,'Raw TB 1225'!F:F) -> -36508 | F56: =E56/10^3 -> -36.508 | G56: BSL | H56: Trade Payables
A57: Expert Retention Bonus Payable | B57: =SUMIF('Raw TB 1225'!$B:$B,'TB 1225'!$A57,'Raw TB 1225'!C:C) -> -6676440 | C57: =SUMIF('Raw TB 1225'!$B:$B,'TB 1225'!$A57,'Raw TB 1225'!D:D) -> 268235 | D57: =SUMIF('Raw TB 1225'!$B:$B,'TB 1225'!$A57,'Raw TB 1225'!E:E) -> 268235 | E57: =SUMIF('Raw TB 1225'!$B:$B,'TB 1225'!$A57,'Raw TB 1225'!F:F) -> -6676440 | F57: =E57/10^3 -> -6676.44 | G57: BSL | H57: Other Current Liabilities
A58: Expert Service Cost Payable | B58: =SUMIF('Raw TB 1225'!$B:$B,'TB 1225'!$A58,'Raw TB 1225'!C:C) -> -83870977 | C58: =SUMIF('Raw TB 1225'!$B:$B,'TB 1225'!$A58,'Raw TB 1225'!D:D) -> 89243771 | D58: =SUMIF('Raw TB 1225'!$B:$B,'TB 1225'!$A58,'Raw TB 1225'!E:E) -> 1.2825851e+08 | E58: =SUMIF('Raw TB 1225'!$B:$B,'TB 1225'!$A58,'Raw TB 1225'!F:F) -> -1.2288572e+08 | F58: =E58/10^3 -> -122885.72 | G58: BSL | H58: Trade Payables
A59: Expert Yulu Bonus Payable | B59: =SUMIF('Raw TB 1225'!$B:$B,'TB 1225'!$A59,'Raw TB 1225'!C:C) -> 0 | C59: =SUMIF('Raw TB 1225'!$B:$B,'TB 1225'!$A59,'Raw TB 1225'!D:D) -> 0 | D59: =SUMIF('Raw TB 1225'!$B:$B,'TB 1225'!$A59,'Raw TB 1225'!E:E) -> 0 | E59: =SUMIF('Raw TB 1225'!$B:$B,'TB 1225'!$A59,'Raw TB 1225'!F:F) -> 0 | F59: =E59/10^3 -> 0 | G59: BSL | H59: Trade Payables
A60: Output CGST | B60: =SUMIF('Raw TB 1225'!$B:$B,'TB 1225'!$A60,'Raw TB 1225'!C:C) -> -2055269.3 | C60: =SUMIF('Raw TB 1225'!$B:$B,'TB 1225'!$A60,'Raw TB 1225'!D:D) -> 1780559 | D60: =SUMIF('Raw TB 1225'!$B:$B,'TB 1225'!$A60,'Raw TB 1225'!E:E) -> 2585849.3 | E60: =SUMIF('Raw TB 1225'!$B:$B,'TB 1225'!$A60,'Raw TB 1225'!F:F) -> -2860559.6 | F60: =E60/10^3 -> -2860.5596 | G60: BSL | H60: Other Current Assets
A61: Output IGST | B61: =SUMIF('Raw TB 1225'!$B:$B,'TB 1225'!$A61,'Raw TB 1225'!C:C) -> -230556.43 | C61: =SUMIF('Raw TB 1225'!$B:$B,'TB 1225'!$A61,'Raw TB 1225'!D:D) -> 621696 | D61: =SUMIF('Raw TB 1225'!$B:$B,'TB 1225'!$A61,'Raw TB 1225'!E:E) -> 372445.7 | E61: =SUMIF('Raw TB 1225'!$B:$B,'TB 1225'!$A61,'Raw TB 1225'!F:F) -> 18693.87 | F61: =E61/10^3 -> 18.69387 | G61: BSL | H61: Other Current Assets
... A95: Retained Earnings | B95: =SUMIF('Raw TB 1225'!$B:$B,'TB 1225'!$A95,'Raw TB 1225'!C:C) -> 58903867 | C95: =SUMIF('Raw TB 1225'!$B:$B,'TB 1225'!$A95,'Raw TB 1225'!D:D) -> 0 | D95: =SUMIF('Raw TB 1225'!$B:$B,'TB 1225'!$A95,'Raw TB 1225'!E:E) -> 0 | E95: =SUMIF('Raw TB 1225'!$B:$B,'TB 1225'!$A95,'Raw TB 1225'!F:F) -> 58903867 | F95: =E95/10^3 -> 58903.867 | G95: BSL | H95: Reserves & Surplus
A96: Share Application Money Pending Allotment | B96: =SUMIF('Raw TB 1225'!$B:$B,'TB 1225'!$A96,'Raw TB 1225'!C:C) -> 0 | C96: =SUMIF('Raw TB 1225'!$B:$B,'TB 1225'!$A96,'Raw TB 1225'!D:D) -> 0 | D96: =SUMIF('Raw TB 1225'!$B:$B,'TB 1225'!$A96,'Raw TB 1225'!E:E) -> 0 | E96: =SUMIF('Raw TB 1225'!$B:$B,'TB 1225'!$A96,'Raw TB 1225'!F:F) -> 0 | F96: =E96/10^3 -> 0 | G96: BSL | H96: Reserves & Surplus | I96: Proceeds from issue of Share Capital
A97: FD Interest Income | B97: =SUMIF('Raw TB 1225'!$B:$B,'TB 1225'!$A97,'Raw TB 1225'!C:C) -> 0 | C97: =SUMIF('Raw TB 1225'!$B:$B,'TB 1225'!$A97,'Raw TB 1225'!D:D) -> 60536186 | D97: =SUMIF('Raw TB 1225'!$B:$B,'TB 1225'!$A97,'Raw TB 1225'!E:E) -> 78930787 | E97: =SUMIF('Raw TB 1225'!$B:$B,'TB 1225'!$A97,'Raw TB 1225'!F:F) -> -18394601 | F97: =E97/10^3 -> -18394.601 | G97: PLI | H97: Interest Income
A98: Gain or Loss on Mutual Fund Investment | B98: =SUMIF('Raw TB 1225'!$B:$B,'TB 1225'!$A98,'Raw TB 1225'!C:C) -> 0 | C98: =SUMIF('Raw TB 1225'!$B:$B,'TB 1225'!$A98,'Raw TB 1225'!D:D) -> 0 | D98: =SUMIF('Raw TB 1225'!$B:$B,'TB 1225'!$A98,'Raw TB 1225'!E:E) -> 518894.79 | E98: =SUMIF('Raw TB 1225'!$B:$B,'TB 1225'!$A98,'Raw TB 1225'!F:F) -> -518894.79 | F98: =E98/10^3 -> -518.89479 | G98: PLI | H98: Interest Income
A99: Audit Fees | B99: =SUMIF('Raw TB 1225'!$B:$B,'TB 1225'!$A99,'Raw TB 1225'!C:C) -> 0 | C99: =SUMIF('Raw TB 1225'!$B:$B,'TB 1225'!$A99,'Raw TB 1225'!D:D) -> 0 | D99: =SUMIF('Raw TB 1225'!$B:$B,'TB 1225'!$A99,'Raw TB 1225'!E:E) -> 0 | E99: =SUMIF('Raw TB 1225'!$B:$B,'TB 1225'!$A99,'Raw TB 1225'!F:F) -> 0 | F99: =E99/10^3 -> 0 | G99: PLE | H99: Professional Fees
A100: Bank Fees and Charges | B100: =SUMIF('Raw TB 1225'!$B:$B,'TB 1225'!$A100,'Raw TB 1225'!C:C) -> 0 | C100: =SUMIF('Raw TB 1225'!$B:$B,'TB 1225'!$A100,'Raw TB 1225'!D:D) -> 34583.53 | D100: =SUMIF('Raw TB 1225'!$B:$B,'TB 1225'!$A100,'Raw TB 1225'!E:E) -> 0 | E100: =SUMIF('Raw TB 1225'!$B:$B,'TB 1225'!$A100,'Raw TB 1225'!F:F) -> 34583.53 | F100: =E100/10^3 -> 34.58353 | G100: PLE | H100: Miscellaneous Expenses
A101: Branding Expense | B101: =SUMIF('Raw TB 1225'!$B:$B,'TB 1225'!$A101,'Raw TB 1225'!C:C) -> 0 | C101: =SUMIF('Raw TB 1225'!$B:$B,'TB 1225'!$A101,'Raw TB 1225'!D:D) -> 13097300 | D101: =SUMIF('Raw TB 1225'!$B:$B,'TB 1225'!$A101,'Raw TB 1225'!E:E) -> 5660500 | E101: =SUMIF('Raw TB 1225'!$B:$B,'TB 1225'!$A101,'Raw TB 1225'!F:F) -> 7436800 | F101: =E101/10^3 -> 7436.8 | G101: PLE | H101: Branding Expense
A102: Brokerage Charges | B102: =SUMIF('Raw TB 1225'!$B:$B,'TB 1225'!$A102,'Raw TB 1225'!C:C) -> 0 | C102: =SUMIF('Raw TB 1225'!$B:$B,'TB 1225'!$A102,'Raw TB 1225'!D:D) -> 0 | D102: =SUMIF('Raw TB 1225'!$B:$B,'TB 1225'!$A102,'Raw TB 1225'!E:E) -> 0 | E102: =SUMIF('Raw TB 1225'!$B:$B,'TB 1225'!$A102,'Raw TB 1225'!F:F) -> 0 | F102: =E102/10^3 -> 0 | G102: PLE | H102: Training Centre Expenses
A103: Customer Acquisition Cost | B103: =SUMIF('Raw TB 1225'!$B:$B,'TB 1225'!$A103,'Raw TB 1225'!C:C) -> 0 | C103: =SUMIF('Raw TB 1225'!$B:$B,'TB 1225'!$A103,'Raw TB 1225'!D:D) -> 31517833 | D103: =SUMIF('Raw TB 1225'!$B:$B,'TB 1225'!$A103,'Raw TB 1225'!E:E) -> 5941406 | E103: =SUMIF('Raw TB 1225'!$B:$B,'TB 1225'!$A103,'Raw TB 1225'!F:F) -> 25576427 | F103: =E103/10^3 -> 25576.427 | G103: PLE | H103: Customer Acquisition Cost (Digital & BTL Marketing)
A104: Customer Success Cost | B104: =SUMIF('Raw TB 1225'!$B:$B,'TB 1225'!$A104,'Raw TB 1225'!C:C) -> 0 | C104: =SUMIF('Raw TB 1225'!$B:$B,'TB 1225'!$A104,'Raw TB 1225'!D:D) -> 3470481 | D104: =SUMIF('Raw TB 1225'!$B:$B,'TB 1225'!$A104,'Raw TB 1225'!E:E) -> 643044 | E104: =SUMIF('Raw TB 1225'!$B:$B,'TB 1225'!$A104,'Raw TB 1225'!F:F) -> 2827437 | F104: =E104/10^3 -> 2827.437 | G104: PLE | H104: Customer Success Cost
A105: Depreciation and Amortization | B105: =SUMIF('Raw TB 1225'!$B:$B,'TB 1225'!$A105,'Raw TB 1225'!C:C) -> 0 | C105: =SUMIF('Raw TB 1225'!$B:$B,'TB 1225'!$A105,'Raw TB 1225'!D:D) -> 1184288.5 | D105: =SUMIF('Raw TB 1225'!$B:$B,'TB 1225'!$A105,'Raw TB 1225'!E:E) -> 0 | E105: =SUMIF('Raw TB 1225'!$B:$B,'TB 1225'!$A105,'Raw TB 1225'!F:F) -> 1184288.5 | F105: =E105/10^3 -> 1184.2885 | G105: PLE | H105: Depreciation
A106: Employer PF Expense | B106: =SUMIF('Raw TB 1225'!$B:$B,'TB 1225'!$A106,'Raw TB 1225'!C:C) -> 0 | C106: =SUMIF('Raw TB 1225'!$B:$B,'TB 1225'!$A106,'Raw TB 1225'!D:D) -> 492087 | D106: =SUMIF('Raw TB 1225'!$B:$B,'TB 1225'!$A106,'Raw TB 1225'!E:E) -> 0 | E106: =SUMIF('Raw TB 1225'!$B:$B,'TB 1225'!$A106,'Raw TB 1225'!F:F) -> 492087 | F106: =E106/10^3 -> 492.087 | G106: PLE
A107: PF Admin Expense | B107: =SUMIF('Raw TB 1225'!$B:$B,'TB 1225'!$A107,'Raw TB 1225'!C:C) -> 0 | C107: =SUMIF('Raw TB 1225'!$B:$B,'TB 1225'!$A107,'Raw TB 1225'!D:D) -> 34950 | D107: =SUMIF('Raw TB 1225'!$B:$B,'TB 1225'!$A107,'Raw TB 1225'!E:E) -> 0 | E107: =SUMIF('Raw TB 1225'!$B:$B,'TB 1225'!$A107,'Raw TB 1225'!F:F) -> 34950 | F107: =E107/10^3 -> 34.95 | G107: PLE | H107: Employee Cost
A108: Staff Welfare Expense | B108: =SUMIF('Raw TB 1225'!$B:$B,'TB 1225'!$A108,'Raw TB 1225'!C:C) -> 0 | C108: =SUMIF('Raw TB 1225'!$B:$B,'TB 1225'!$A108,'Raw TB 1225'!D:D) -> 7721708.3 | D108: =SUMIF('Raw TB 1225'!$B:$B,'TB 1225'!$A108,'Raw TB 1225'!E:E) -> 2419814 | E108: =SUMIF('Raw TB 1225'!$B:$B,'TB 1225'!$A108,'Raw TB 1225'!F:F) -> 5301894.3 | F108: =E108/10^3 -> 5301.8943 | G108: PLE | H108: Employee Cost
A109: Variable Salary | B109: =SUMIF('Raw TB 1225'!$B:$B,'TB 1225'!$A109,'Raw TB 1225'!C:C) -> 0 | C109: =SUMIF('Raw TB 1225'!$B:$B,'TB 1225'!$A109,'Raw TB 1225'!D:D) -> 0 | D109: =SUMIF('Raw TB 1225'!$B:$B,'TB 1225'!$A109,'Raw TB 1225'!E:E) -> 0 | E109: =SUMIF('Raw TB 1225'!$B:$B,'TB 1225'!$A109,'Raw TB 1225'!F:F) -> 0 | F109: =E109/10^3 -> 0 | G109: PLE | H109: Employee Cost
A110: Employee Cost | B110: =SUMIF('Raw TB 1225'!$B:$B,'TB 1225'!$A110,'Raw TB 1225'!C:C) -> 0 | C110: =SUMIF('Raw TB 1225'!$B:$B,'TB 1225'!$A110,'Raw TB 1225'!D:D) -> 0 | D110: =SUMIF('Raw TB 1225'!$B:$B,'TB 1225'!$A110,'Raw TB 1225'!E:E) -> 0 | E110: =SUMIF('Raw TB 1225'!$B:$B,'TB 1225'!$A110,'Raw TB 1225'!F:F) -> 0 | F110: =E110/10^3 -> 0 | G110: PLE | H110: Employee Cost
A111: Expert Retention Bonus | B111: =SUMIF('Raw TB 1225'!$B:$B,'TB 1225'!$A111,'Raw TB 1225'!C:C) -> 0 | C111: =SUMIF('Raw TB 1225'!$B:$B,'TB 1225'!$A111,'Raw TB 1225'!D:D) -> 367000 | D111: =SUMIF('Raw TB 1225'!$B:$B,'TB 1225'!$A111,'Raw TB 1225'!E:E) -> 90250 | E111: =SUMIF('Raw TB 1225'!$B:$B,'TB 1225'!$A111,'Raw TB 1225'!F:F) -> 276750 | F111: =E111/10^3 -> 276.75 | G111: PLE | H111: Service Cost
A112: Expert Welfare Cost | B112: =SUMIF('Raw TB 1225'!$B:$B,'TB 1225'!$A112,'Raw TB 1225'!C:C) -> 0 | C112: =SUMIF('Raw TB 1225'!$B:$B,'TB 1225'!$A112,'Raw TB 1225'!D:D) -> 66509.49 | D112: =SUMIF('Raw TB 1225'!$B:$B,'TB 1225'!$A112,'Raw TB 1225'!E:E) -> 44540 | E112: =SUMIF('Raw TB 1225'!$B:$B,'TB 1225'!$A112,'Raw TB 1225'!F:F) -> 21969.49 | F112: =E112/10^3 -> 21.96949 | G112: PLE | H112: Service Cost
A113: Foreign Exchange Gain or Loss | B113: =SUMIF('Raw TB 1225'!$B:$B,'TB 1225'!$A113,'Raw TB 1225'!C:C) -> 0 | C113: =SUMIF('Raw TB 1225'!$B:$B,'TB 1225'!$A113,'Raw TB 1225'!D:D) -> 1030.25 | D113: =SUMIF('Raw TB 1225'!$B:$B,'TB 1225'!$A113,'Raw TB 1225'!E:E) -> 0 | E113: =SUMIF('Raw TB 1225'!$B:$B,'TB 1225'!$A113,'Raw TB 1225'!F:F) -> 1030.25 | F113: =E113/10^3 -> 1.03025 | G113: PLI | H113: Miscellaneous Expenses
A114: Hood Rent Expense | B114: =SUMIF('Raw TB 1225'!$B:$B,'TB 1225'!$A114,'Raw TB 1225'!C:C) -> 0 | C114: =SUMIF('Raw TB 1225'!$B:$B,'TB 1225'!$A114,'Raw TB 1225'!D:D) -> 601760 | D114: =SUMIF('Raw TB 1225'!$B:$B,'TB 1225'!$A114,'Raw TB 1225'!E:E) -> 173100 | E114: =SUMIF('Raw TB 1225'!$B:$B,'TB 1225'!$A114,'Raw TB 1225'!F:F) -> 428660 | F114: =E114/10^3 -> 428.66 | G114: PLE | H114: Operational Cost
A115: Managerial Cost | B115: =SUMIF('Raw TB 1225'!$B:$B,'TB 1225'!$A115,'Raw TB 1225'!C:C) -> 0 | C115: =SUMIF('Raw TB 1225'!$B:$B,'TB 1225'!$A115,'Raw TB 1225'!D:D) -> 5599789.5 | D115: =SUMIF('Raw TB 1225'!$B:$B,'TB 1225'!$A115,'Raw TB 1225'!E:E) -> 0 | E115: =SUMIF('Raw TB 1225'!$B:$B,'TB 1225'!$A115,'Raw TB 1225'!F:F) -> 5599789.5 | F115: =E115/10^3 -> 5599.7895 | G115: PLE | H115: Managerial Cost
A116: Office and Admin Expense | B116: =SUMIF('Raw TB 1225'!$B:$B,'TB 1225'!$A116,'Raw TB 1225'!C:C) -> 0 | C116: =SUMIF('Raw TB 1225'!$B:$B,'TB 1225'!$A116,'Raw TB 1225'!D:D) -> 157337 | D116: =SUMIF('Raw TB 1225'!$B:$B,'TB 1225'!$A116,'Raw TB 1225'!E:E) -> 16916 | E116: =SUMIF('Raw TB 1225'!$B:$B,'TB 1225'!$A116,'Raw TB 1225'!F:F) -> 140421 | F116: =E116/10^3 -> 140.421 | G116: PLE | H116: Office and Admin Expenses
A117: Office Rent Expense | B117: =SUMIF('Raw TB 1225'!$B:$B,'TB 1225'!$A117,'Raw TB 1225'!C:C) -> 0 | C117: =SUMIF('Raw TB 1225'!$B:$B,'TB 1225'!$A117,'Raw TB 1225'!D:D) -> 2153170.7 | D117: =SUMIF('Raw TB 1225'!$B:$B,'TB 1225'!$A117,'Raw TB 1225'!E:E) -> 0 | E117: =SUMIF('Raw TB 1225'!$B:$B,'TB 1225'!$A117,'Raw TB 1225'!F:F) -> 2153170.7 | F117: =E117/10^3 -> 2153.1707 | G117: PLE | H117: Office and Admin Expenses
A118: Operational Expense | B118: =SUMIF('Raw TB 1225'!$B:$B,'TB 1225'!$A118,'Raw TB 1225'!C:C) -> 0 | C118: =SUMIF('Raw TB 1225'!$B:$B,'TB 1225'!$A118,'Raw TB 1225'!D:D) -> 993891 | D118: =SUMIF('Raw TB 1225'!$B:$B,'TB 1225'!$A118,'Raw TB 1225'!E:E) -> 697391 | E118: =SUMIF('Raw TB 1225'!$B:$B,'TB 1225'!$A118,'Raw TB 1225'!F:F) -> 296500 | F118: =E118/10^3 -> 296.5 | G118: PLE | H118: Operational Cost
A119: Other Cost | B119: =SUMIF('Raw TB 1225'!$B:$B,'TB 1225'!$A119,'Raw TB 1225'!C:C) -> 0 | C119: =SUMIF('Raw TB 1225'!$B:$B,'TB 1225'!$A119,'Raw TB 1225'!D:D) -> 13185.45 | D119: =SUMIF('Raw TB 1225'!$B:$B,'TB 1225'!$A119,'Raw TB 1225'!E:E) -> 0 | E119: =SUMIF('Raw TB 1225'!$B:$B,'TB 1225'!$A119,'Raw TB 1225'!F:F)-8000 -> 5185.45 | F119: =E119/10^3 -> 5.18545 | G119: PLE | H119: Miscellaneous Expenses
A120: Other Expenses | B120: =SUMIF('Raw TB 1225'!$B:$B,'TB 1225'!$A120,'Raw TB 1225'!C:C) -> 0 | C120: =SUMIF('Raw TB 1225'!$B:$B,'TB 1225'!$A120,'Raw TB 1225'!D:D) -> 3.09 | D120: =SUMIF('Raw TB 1225'!$B:$B,'TB 1225'!$A120,'Raw TB 1225'!E:E) -> 5.59 | E120: =SUMIF('Raw TB 1225'!$B:$B,'TB 1225'!$A120,'Raw TB 1225'!F:F) -> -2.5 | F120: =E120/10^3 -> -0.0025 | G120: PLE | H120: Miscellaneous Expenses
A121: Professional Fees | B121: =SUMIF('Raw TB 1225'!$B:$B,'TB 1225'!$A121,'Raw TB 1225'!C:C) -> 0 | C121: =SUMIF('Raw TB 1225'!$B:$B,'TB 1225'!$A121,'Raw TB 1225'!D:D) -> 2571663.1 | D121: =SUMIF('Raw TB 1225'!$B:$B,'TB 1225'!$A121,'Raw TB 1225'!E:E) -> 41320 | E121: =SUMIF('Raw TB 1225'!$B:$B,'TB 1225'!$A121,'Raw TB 1225'!F:F) -> 2530343.1 | F121: =E121/10^3 -> 2530.3431 | G121: PLE | H121: Professional Fees
A122: Rates and Taxes | B122: =SUMIF('Raw TB 1225'!$B:$B,'TB 1225'!$A122,'Raw TB 1225'!C:C) -> 0 | C122: =SUMIF('Raw TB 1225'!$B:$B,'TB 1225'!$A122,'Raw TB 1225'!D:D) -> 12249.42 | D122: =SUMIF('Raw TB 1225'!$B:$B,'TB 1225'!$A122,'Raw TB 1225'!E:E) -> 0 | E122: =SUMIF('Raw TB 1225'!$B:$B,'TB 1225'!$A122,'Raw TB 1225'!F:F) -> 12249.42 | F122: =E122/10^3 -> 12.24942 | G122: PLE | H122: Miscellaneous Expenses
A123: Recruitment Charges | B123: =SUMIF('Raw TB 1225'!$B:$B,'TB 1225'!$A123,'Raw TB 1225'!C:C) -> 0 | C123: =SUMIF('Raw TB 1225'!$B:$B,'TB 1225'!$A123,'Raw TB 1225'!D:D) -> 266912 | D123: =SUMIF('Raw TB 1225'!$B:$B,'TB 1225'!$A123,'Raw TB 1225'!E:E) -> 0 | E123: =SUMIF('Raw TB 1225'!$B:$B,'TB 1225'!$A123,'Raw TB 1225'!F:F) -> 266912 | F123: =E123/10^3 -> 266.912 | G123: PLE | H123: Recruitment Cost
A124: Salaries and Employee Wages | B124: =SUMIF('Raw TB 1225'!$B:$B,'TB 1225'!$A124,'Raw TB 1225'!C:C) -> 0 | C124: =SUMIF('Raw TB 1225'!$B:$B,'TB 1225'!$A124,'Raw TB 1225'!D:D) -> 42983081 | D124: =SUMIF('Raw TB 1225'!$B:$B,'TB 1225'!$A124,'Raw TB 1225'!E:E) -> 11000 | E124: =SUMIF('Raw TB 1225'!$B:$B,'TB 1225'!$A124,'Raw TB 1225'!F:F) -> 42972081 | F124: =E124/10^3 -> 42972.081 | G124: PLE
A125: Service Cost | B125: =SUMIF('Raw TB 1225'!$B:$B,'TB 1225'!$A125,'Raw TB 1225'!C:C) -> 0 | C125: =SUMIF('Raw TB 1225'!$B:$B,'TB 1225'!$A125,'Raw TB 1225'!D:D) -> 1.3230922e+08 | D125: =SUMIF('Raw TB 1225'!$B:$B,'TB 1225'!$A125,'Raw TB 1225'!E:E) -> 0 | E125: =SUMIF('Raw TB 1225'!$B:$B,'TB 1225'!$A125,'Raw TB 1225'!F:F) -> 1.3230922e+08 | F125: =E125/10^3 -> 132309.22 | G125: PLE | H125: Service Cost
A126: Software Expense | B126: =SUMIF('Raw TB 1225'!$B:$B,'TB 1225'!$A126,'Raw TB 1225'!C:C) -> 0 | C126: =SUMIF('Raw TB 1225'!$B:$B,'TB 1225'!$A126,'Raw TB 1225'!D:D) -> 7038832.6 | D126: =SUMIF('Raw TB 1225'!$B:$B,'TB 1225'!$A126,'Raw TB 1225'!E:E) -> 4172323 | E126: =SUMIF('Raw TB 1225'!$B:$B,'TB 1225'!$A126,'Raw TB 1225'!F:F) -> 2866509.6 | F126: =E126/10^3 -> 2866.5096 | G126: PLE | H126: Tech Cost
A127: Sourcing and Onboarding Expense | B127: =SUMIF('Raw TB 1225'!$B:$B,'TB 1225'!$A127,'Raw TB 1225'!C:C) -> 0 | C127: =SUMIF('Raw TB 1225'!$B:$B,'TB 1225'!$A127,'Raw TB 1225'!D:D) -> 22335291 | D127: =SUMIF('Raw TB 1225'!$B:$B,'TB 1225'!$A127,'Raw TB 1225'!E:E) -> 3078154 | E127: =SUMIF('Raw TB 1225'!$B:$B,'TB 1225'!$A127,'Raw TB 1225'!F:F) -> 19257137 | F127: =E127/10^3 -> 19257.137 | G127: PLE | H127: Sourcing & Onboarding Cost
A128: Training Centre Expense | B128: =SUMIF('Raw TB 1225'!$B:$B,'TB 1225'!$A128,'Raw TB 1225'!C:C) -> 0 | C128: =SUMIF('Raw TB 1225'!$B:$B,'TB 1225'!$A128,'Raw TB 1225'!D:D) -> 2998895.5 | D128: =SUMIF('Raw TB 1225'!$B:$B,'TB 1225'!$A128,'Raw TB 1225'!E:E) -> 583841 | E128: =SUMIF('Raw TB 1225'!$B:$B,'TB 1225'!$A128,'Raw TB 1225'!F:F) -> 2415054.5 | F128: =E128/10^3 -> 2415.0545 | G128: PLE | H128: Training Centre Expenses
A129: Training Centre Rent Expense | B129: =SUMIF('Raw TB 1225'!$B:$B,'TB 1225'!$A129,'Raw TB 1225'!C:C) -> 0 | C129: =SUMIF('Raw TB 1225'!$B:$B,'TB 1225'!$A129,'Raw TB 1225'!D:D) -> 2552393 | D129: =SUMIF('Raw TB 1225'!$B:$B,'TB 1225'!$A129,'Raw TB 1225'!E:E) -> 258272 | E129: =SUMIF('Raw TB 1225'!$B:$B,'TB 1225'!$A129,'Raw TB 1225'!F:F) -> 2294121 | F129: =E129/10^3 -> 2294.121 | G129: PLE | H129: Training Centre Expenses
A130: Provision for Professional Fees | B130: =SUMIF('Raw TB 1225'!$B:$B,'TB 1225'!$A130,'Raw TB 1225'!C:C) -> -366320 | C130: =SUMIF('Raw TB 1225'!$B:$B,'TB 1225'!$A130,'Raw TB 1225'!D:D) -> 366320 | D130: =SUMIF('Raw TB 1225'!$B:$B,'TB 1225'!$A130,'Raw TB 1225'!E:E) -> 580000 | E130: =SUMIF('Raw TB 1225'!$B:$B,'TB 1225'!$A130,'Raw TB 1225'!F:F) -> -580000 | F130: =E130/10^3 -> -580 | G130: BSL | H130: Short-term Provisions
A131: Payment Gateway Cost | B131: =SUMIF('Raw TB 1225'!$B:$B,'TB 1225'!$A131,'Raw TB 1225'!C:C) -> 0 | C131: =SUMIF('Raw TB 1225'!$B:$B,'TB 1225'!$A131,'Raw TB 1225'!D:D) -> 170755.86 | D131: =SUMIF('Raw TB 1225'!$B:$B,'TB 1225'!$A131,'Raw TB 1225'!E:E) -> 0 | E131: =SUMIF('Raw TB 1225'!$B:$B,'TB 1225'!$A131,'Raw TB 1225'!F:F) -> 170755.86 | F131: =E131/10^3 -> 170.75586 | G131: PLE | H131: Payment Gateway Cost
A132: Provision for Service Cost | B132: =SUMIF('Raw TB 1225'!$B:$B,'TB 1225'!$A132,'Raw TB 1225'!C:C) -> -134790 | C132: =SUMIF('Raw TB 1225'!$B:$B,'TB 1225'!$A132,'Raw TB 1225'!D:D) -> 134790 | D132: =SUMIF('Raw TB 1225'!$B:$B,'TB 1225'!$A132,'Raw TB 1225'!E:E) -> 134790 | E132: =SUMIF('Raw TB 1225'!$B:$B,'TB 1225'!$A132,'Raw TB 1225'!F:F) -> -134790 | F132: =E132/10^3 -> -134.79 | G132: BSL | H132: Short-term Provisions
A133: Additional Charges | B133: =SUMIF('Raw TB 1225'!$B:$B,'TB 1225'!$A133,'Raw TB 1225'!C:C) -> 0 | C133: =SUMIF('Raw TB 1225'!$B:$B,'TB 1225'!$A133,'Raw TB 1225'!D:D) -> 0 | D133: =SUMIF('Raw TB 1225'!$B:$B,'TB 1225'!$A133,'Raw TB 1225'!E:E) -> 9 | E133: =SUMIF('Raw TB 1225'!$B:$B,'TB 1225'!$A133,'Raw TB 1225'!F:F) -> -9 | F133: =E133/10^3 -> -0.009 | G133: PLI | H133: Revenue
A134: Convenience and Platform Fee | B134: =SUMIF('Raw TB 1225'!$B:$B,'TB 1225'!$A134,'Raw TB 1225'!C:C) -> 0 | C134: =SUMIF('Raw TB 1225'!$B:$B,'TB 1225'!$A134,'Raw TB 1225'!D:D) -> 0 | D134: =SUMIF('Raw TB 1225'!$B:$B,'TB 1225'!$A134,'Raw TB 1225'!E:E) -> 21216169 | E134: =SUMIF('Raw TB 1225'!$B:$B,'TB 1225'!$A134,'Raw TB 1225'!F:F) -> -21216169 | F134: =E134/10^3 -> -21216.169 | G134: PLI | H134: Revenue
A135: Discount | B135: =SUMIF('Raw TB 1225'!$B:$B,'TB 1225'!$A135,'Raw TB 1225'!C:C) -> 0 | C135: =SUMIF('Raw TB 1225'!$B:$B,'TB 1225'!$A135,'Raw TB 1225'!D:D) -> 62141533 | D135: =SUMIF('Raw TB 1225'!$B:$B,'TB 1225'!$A135,'Raw TB 1225'!E:E) -> 0 | E135: =SUMIF('Raw TB 1225'!$B:$B,'TB 1225'!$A135,'Raw TB 1225'!F:F) -> 62141533 | F135: =E135/10^3 -> 62141.533 | G135: PLE
A136: Extension Fees | B136: =SUMIF('Raw TB 1225'!$B:$B,'TB 1225'!$A136,'Raw TB 1225'!C:C) -> 0 | C136: =SUMIF('Raw TB 1225'!$B:$B,'TB 1225'!$A136,'Raw TB 1225'!D:D) -> 0 | D136: =SUMIF('Raw TB 1225'!$B:$B,'TB 1225'!$A136,'Raw TB 1225'!E:E) -> 2399586.8 | E136: =SUMIF('Raw TB 1225'!$B:$B,'TB 1225'!$A136,'Raw TB 1225'!F:F) -> -2399586.8 | F136: =E136/10^3 -> -2399.5868 | G136: PLI | H136: Revenue
A137: Forfeiture Income | B137: =SUMIF('Raw TB 1225'!$B:$B,'TB 1225'!$A137,'Raw TB 1225'!C:C) -> 0 | C137: =SUMIF('Raw TB 1225'!$B:$B,'TB 1225'!$A137,'Raw TB 1225'!D:D) -> 600000 | D137: =SUMIF('Raw TB 1225'!$B:$B,'TB 1225'!$A137,'Raw TB 1225'!E:E) -> 600000 | E137: =SUMIF('Raw TB 1225'!$B:$B,'TB 1225'!$A137,'Raw TB 1225'!F:F) -> 0 | F137: =E137/10^3 -> 0 | G137: PLI | H137: Revenue
A138: Maestro Revenue | B138: =SUMIF('Raw TB 1225'!$B:$B,'TB 1225'!$A138,'Raw TB 1225'!C:C) -> 0 | C138: =SUMIF('Raw TB 1225'!$B:$B,'TB 1225'!$A138,'Raw TB 1225'!D:D) -> 0 | D138: =SUMIF('Raw TB 1225'!$B:$B,'TB 1225'!$A138,'Raw TB 1225'!E:E) -> 84864677 | E138: =SUMIF('Raw TB 1225'!$B:$B,'TB 1225'!$A138,'Raw TB 1225'!F:F) -> -84864677 | F138: =E138/10^3 -> -84864.677 | G138: PLI | H138: Revenue
A139: Offer Pack Income | B139: =SUMIF('Raw TB 1225'!$B:$B,'TB 1225'!$A139,'Raw TB 1225'!C:C) -> 0 | C139: =SUMIF('Raw TB 1225'!$B:$B,'TB 1225'!$A139,'Raw TB 1225'!D:D) -> 0 | D139: =SUMIF('Raw TB 1225'!$B:$B,'TB 1225'!$A139,'Raw TB 1225'!E:E) -> 11825541 | E139: =SUMIF('Raw TB 1225'!$B:$B,'TB 1225'!$A139,'Raw TB 1225'!F:F) -> -11825541 | F139: =E139/10^3 -> -11825.541 | G139: PLI | H139: Revenue
A140: Platform Fees | B140: =SUMIF('Raw TB 1225'!$B:$B,'TB 1225'!$A140,'Raw TB 1225'!C:C) -> 0 | C140: =SUMIF('Raw TB 1225'!$B:$B,'TB 1225'!$A140,'Raw TB 1225'!D:D) -> 0 | D140: =SUMIF('Raw TB 1225'!$B:$B,'TB 1225'!$A140,'Raw TB 1225'!E:E) -> 902007 | E140: =SUMIF('Raw TB 1225'!$B:$B,'TB 1225'!$A140,'Raw TB 1225'!F:F) -> -902007 | F140: =E140/10^3 -> -902.007 | G140: PLI | H140: Revenue
A141: Save Surge | B141: =SUMIF('Raw TB 1225'!$B:$B,'TB 1225'!$A141,'Raw TB 1225'!C:C) -> 0 | C141: =SUMIF('Raw TB 1225'!$B:$B,'TB 1225'!$A141,'Raw TB 1225'!D:D) -> 0 | D141: =SUMIF('Raw TB 1225'!$B:$B,'TB 1225'!$A141,'Raw TB 1225'!E:E) -> 0 | E141: =SUMIF('Raw TB 1225'!$B:$B,'TB 1225'!$A141,'Raw TB 1225'!F:F) -> 0 | F141: =E141/10^3 -> 0 | G141: PLI | H141: Revenue
A142: Surge Fees | B142: =SUMIF('Raw TB 1225'!$B:$B,'TB 1225'!$A142,'Raw TB 1225'!C:C) -> 0 | C142: =SUMIF('Raw TB 1225'!$B:$B,'TB 1225'!$A142,'Raw TB 1225'!D:D) -> 0 | D142: =SUMIF('Raw TB 1225'!$B:$B,'TB 1225'!$A142,'Raw TB 1225'!E:E) -> 409090 | E142: =SUMIF('Raw TB 1225'!$B:$B,'TB 1225'!$A142,'Raw TB 1225'!F:F) -> -409090 | F142: =E142/10^3 -> -409.09 | G142: PLI | H142: Revenue
A143: New User Discount | B143: =SUMIF('Raw TB 1225'!$B:$B,'TB 1225'!$A143,'Raw TB 1225'!C:C) -> 0 | C143: =SUMIF('Raw TB 1225'!$B:$B,'TB 1225'!$A143,'Raw TB 1225'!D:D) -> 3331601 | D143: =SUMIF('Raw TB 1225'!$B:$B,'TB 1225'!$A143,'Raw TB 1225'!E:E) -> 567408 | E143: =SUMIF('Raw TB 1225'!$B:$B,'TB 1225'!$A143,'Raw TB 1225'!F:F) -> 2764193 | F143: =E143/10^3 -> 2764.193 | G143: PLI | H143: New User Discount (incl. Early Lifecycle Coupons & Referral Discount)
...

Sheet TB 1125
B1: =SUBTOTAL(9,B3:B1048576) -> -2.3841858e-07 | C1: =SUBTOTAL(9,C3:C1048576) -> 1.379168e+10 | D1: =SUBTOTAL(9,D3:D1048576) -> 1.379168e+10 | E1: =SUBTOTAL(9,E3:E1048576) -> -9.3877316e-07 | F1: =SUBTOTAL(9,F3:F1048576) -> 1.1041266e-09 | H1: 17681218 | I1: =-E1+H1 -> 17681218
A2: Particulars | B2: Opening | C2: Debit | D2: Credit | E2: Closing | F2: INR in '000 | G2: Head | H2: Tag | K2: Employee cost Headwise | L2: Amount | M2: In '000 | O2: Revenue | R2: Discount | U2: New user Discount
