Workbook
Name _: #REF!
Name _?: #REF!
Name _??: #REF!
Name _???: #REF!
Name _????: #REF!
Name _?????????: #REF!
Name _??_???: #REF!
Name _?_??: #REF!
Name __: {#N/A,#N/A,FALSE,"Cash Flows";#N/A,#N/A,FALSE,"Fixed Assets";#N/A,#N/A,FALSE,"Balance Sheet";#N/A,#N/A,FALSE,"P & L"}
Name __?: #REF!
Name __??: #REF!
Name __???: #REF!
Name __????: #REF!
Name __?????????: #REF!
Name __??_???: #REF!
Name __?_??: #REF!
Name ___?: #REF!
Name ___??: #REF!
Name ___???: #REF!
Name ___????: #REF!
Name ___?????????: #REF!
Name ___??_???: #REF!
Name ___?_??: #REF!
Name ____?: #REF!
Name ____??: #REF!
Name ____???: #REF!
Name ____????: #REF!
Name ____?????????: #REF!
Name ____??_???: #REF!
Name ____?_??: #REF!
Name _____?: #REF!
Name _____??: #REF!
Name _____???: #REF!
Name _____????: #REF!
Name _____?????????: #REF!
Name _____??_???: #REF!
Name _____?_??: #REF!
Name ______?: #REF!
Name ______??: #REF!
Name ______???: #REF!
Name ______????: #REF!
Name ______?????????: #REF!
Name ______??_???: #REF!
Name ______?_??: #REF!
Name _______?: #REF!
Name _______??: #REF!
Name _______???: #REF!
Name _______????: #REF!
Name _______?????????: #REF!
Name _______??_???: #REF!
Name _______?_??: #REF!
Name ________?: #REF!
Name ________??: #REF!
Name ________???: #REF!
Name ________????: #REF!
Name ________?????????: #REF!
Name ________??_???: #REF!
Name ________?_??: #REF!
Name _________?: #REF!
Name _________??: #REF!

Sheet Revised MIS Template - KPIs
B2: Business KPIs | C2: Unit | D2: 45658 | E2: =EDATE(D2,1) -> 45689 | F2: =EDATE(E2,1) -> 45717 | G2: =EDATE(F2,1) -> 45748 | H2: =EDATE(G2,1) -> 45778 | I2: =EDATE(H2,1) -> 45809 | J2: =EDATE(I2,1) -> 45839 | K2: =EDATE(J2,1) -> 45870 | L2: =EDATE(K2,1) -> 45901 | ... P2: =EDATE(O2,1) -> 46023
B3: Consolidated Summary
B4: Net AUM (incl. interest) | C4: INR Cr | D4: =SUM(D5:D7) -> 1488.35 | E4: =SUM(E5:E7) -> 1719.41 | F4: =SUM(F5:F7) -> 1873.89 | G4: =SUM(G5:G7) -> 2123.78 | H4: =SUM(H5:H7) -> 2348.76 | I4: =SUM(I5:I7) -> 2660.1017 | J4: =SUM(J5:J7) -> 2849.167 | K4: =SUM(K5:K7) -> 3050.6097 | ... O4: =SUM(O5:O7) -> 4179.1953 | P4: =P5+P6+P7 -> 4538.6755
B5: Total FD AUM | C5: INR Cr | D5: 1439.89 | E5: 1639.58 | F5: 1755.19 | G5: 1940.5 | H5: 2086.05 | I5: 2298.3017 | J5: 2360.197 | K5: 2422.6797 | L5: 2576 | M5: 2634.4371 | N5: 2675 | O5: 2777.2616 | P5: 2835.867
B6: Total Bonds AUM | C6: INR Cr | D6: 48.46 | E6: 79.83 | F6: 118.7 | G6: 183.28 | H6: 262.71 | I6: 361.8 | J6: 488.97 | K6: 627.93 | L6: 750.06 | M6: 948.13321 | N6: 1145 | O6: 1366.5109 | P6: 1625.19
B7: Total G/S AUM | C7: INR Cr | L7: 0.2002143 | M7: 7.1120649 | N7: 15.166943 | O7: 35.422771 | P7: 77.6185
B9: Gross Inflows | C9: INR Cr | D9: =SUM(D10:D12) -> 241.44198 | E9: =SUM(E10:E12) -> 272.45407 | F9: =SUM(F10:F12) -> 247.8979 | G9: =SUM(G10:G12) -> 301.70248 | H9: =SUM(H10:H12) -> 301.8032 | I9: =SUM(I10:I12) -> 347.98853 | J9: =SUM(J10:J12) -> 365.93385 | K9: =SUM(K10:K12) -> 333.76508 | ... P9: =SUM(P10:P12) -> 582.27721
B10: FD inflows | C10: INR Cr | D10: =D62 -> 215.70354 | E10: =E62 -> 240.69784 | F10: =F62 -> 201.83473 | G10: =G62 -> 237.00088 | H10: =H62 -> 211.15243 | I10: =I62 -> 237.38944 | J10: =J62 -> 216.50432 | K10: =K62 -> 186.19292 | ... P10: =P62 -> 226.80795
B11: Bond inflows | C11: INR Cr | D11: =D105 -> 25.738444 | E11: =E105 -> 31.756236 | F11: =F105 -> 46.063175 | G11: =G105 -> 64.701603 | H11: =H105 -> 90.650764 | I11: =I105 -> 110.5991 | J11: =J105 -> 149.42952 | K11: =K105 -> 147.57216 | ... P11: =P105 -> 305.86326
B12: G/S inflows | C12: INR Cr | D12: =D127 -> 0 | E12: =E127 -> 0 | F12: =F127 -> 0 | G12: =G127 -> 0 | H12: =H127 -> 0 | I12: =I127 -> 0 | J12: =J127 -> 0 | K12: =K127 -> 0 | ... O12: =O127 -> 20.782346 | P12: 49.606
B14: Net Inflows (change in AUM) | C14: # | E14: =SUM(E15:E17) -> 231.06 | F14: =SUM(F15:F17) -> 154.48 | G14: =SUM(G15:G17) -> 249.89 | H14: =SUM(H15:H17) -> 224.98 | I14: =SUM(I15:I17) -> 311.34172 | J14: =SUM(J15:J17) -> 189.06529 | K14: =SUM(K15:K17) -> 201.44269 | L14: =SUM(L15:L17) -> 275.65051 | ... P14: =SUM(P15:P17) -> 359.48016
B15: Net FD inflows | C15: # | E15: =E5-D5 -> 199.69 | F15: =F5-E5 -> 115.61 | G15: =G5-F5 -> 185.31 | H15: =H5-G5 -> 145.55 | I15: =I5-H5 -> 212.25172 | J15: =J5-I5 -> 61.895291 | K15: =K5-J5 -> 62.482688 | L15: =L5-K5 -> 153.3203 | ... P15: =P5-O5 -> 58.605355
B16: Net Bond inflows | C16: # | E16: =E6-D6 -> 31.37 | F16: =F6-E6 -> 38.87 | G16: =G6-F6 -> 64.58 | H16: =H6-G6 -> 79.43 | I16: =I6-H6 -> 99.09 | J16: =J6-I6 -> 127.17 | K16: =K6-J6 -> 138.96 | L16: =L6-K6 -> 122.13 | ... P16: =P6-O6 -> 258.67908
B17: Net G/S inflows | C17: # | E17: =E7-D7 -> 0 | F17: =F7-E7 -> 0 | G17: =G7-F7 -> 0 | H17: =H7-G7 -> 0 | I17: =I7-H7 -> 0 | J17: =J7-I7 -> 0 | K17: =K7-J7 -> 0 | L17: =L7-K7 -> 0.2002143 | ... P17: =P7-O7 -> 42.195729
B19: # active users (AUM > 0) (last day of the month) | C19: # | D19: 61029 | E19: 68015 | F19: 73172 | G19: 76490 | H19: 82402 | I19: 94446 | J19: 101464 | K19: 108039 | L19: 115949 | M19: 126902 | N19: 136630 | O19: 149919 | P19: =P138 -> 170161
B21: # transacting users (TD) | C21: # | D21: =D22+D23 -> 20202 | E21: =E22+E23 -> 21958 | F21: =F22+F23 -> 23305 | G21: =G22+G23 -> 25771 | H21: =H22+H23 -> 27574 | I21: =I22+I23 -> 31694 | J21: =J22+J23 -> 31939 | K21: =K22+K23 -> 32291 | ... P21: =P22+P23 -> 73322
B22: # new transacting users | C22: # | D22: 9507 | E22: 9372 | F22: 8618 | G22: 8860 | H22: 9522 | I22: 11579 | J22: 10661 | K22: 10530 | L22: 13773 | M22: 17555 | N22: 17808 | O22: 19639 | P22: 27437
B23: # repeat transacting users | C23: # | D23: 10695 | E23: 12586 | F23: 14687 | G23: 16911 | H23: 18052 | I23: 20115 | J23: 21278 | K23: 21761 | L23: 24115 | M23: 27916 | N23: 30558 | O23: 37607 | P23: 45885
B25: # transactions (platform) | C25: # | D25: =SUM(D26:D28) -> 39883 | E25: =SUM(E26:E28) -> 41965 | F25: =SUM(F26:F28) -> 43181 | G25: =SUM(G26:G28) -> 48079 | H25: =SUM(H26:H28) -> 51654 | I25: =SUM(I26:I28) -> 60199 | J25: =SUM(J26:J28) -> 54403 | K25: =SUM(K26:K28) -> 55651 | ... P25: =SUM(P26:P28) -> 205829
B26: # FD transactions | C26: # | D26: =D57 -> 35300 | E26: =E57 -> 37254 | F26: =F57 -> 37250 | G26: =G57 -> 41066 | H26: =H57 -> 42376 | I26: =I57 -> 48851 | J26: =J57 -> 40964 | K26: =K57 -> 42223 | ... P26: =P57 -> 58928
B27: # Bond transactions | C27: # | D27: =D100 -> 4583 | E27: =E100 -> 4711 | F27: =F100 -> 5931 | G27: =G100 -> 7013 | H27: =H100 -> 9278 | I27: =I100 -> 11348 | J27: =J100 -> 13439 | K27: =K100 -> 13428 | ... P27: =P100 -> 29112
B28: # G/S transactions | C28: # | D28: =D125 -> 0 | E28: =E125 -> 0 | F28: =F125 -> 0 | G28: =G125 -> 0 | H28: =H125 -> 0 | I28: =I125 -> 0 | J28: =J125 -> 0 | K28: =K125 -> 0 | ... P28: =P125 -> 117789
B30: ATS (platform) | C30: INR L | D30: =IFERROR(D9*10^2/D25,"") -> 0.60537568 | E30: =IFERROR(E9*10^2/E25,"") -> 0.6492412 | F30: =IFERROR(F9*10^2/F25,"") -> 0.57409023 | G30: =IFERROR(G9*10^2/G25,"") -> 0.62751406 | H30: =IFERROR(H9*10^2/H25,"") -> 0.58427846 | I30: =IFERROR(I9*10^2/I25,"") -> 0.57806364 | J30: =IFERROR(J9*10^2/J25,"") -> 0.67263542 | K30: =IFERROR(K9*10^2/K25,"") -> 0.59974678 | ... P30: =IFERROR(P9*10^2/P25,"") -> 0.28289367
B31: FD ATS | C31: INR L | D31: =IFERROR(D10*10^2/D26,"") -> 0.61105818 | E31: =IFERROR(E10*10^2/E26,"") -> 0.64609931 | F31: =IFERROR(F10*10^2/F26,"") -> 0.5418382 | G31: =IFERROR(G10*10^2/G26,"") -> 0.57712191 | H31: =IFERROR(H10*10^2/H26,"") -> 0.49828307 | I31: =IFERROR(I10*10^2/I26,"") -> 0.48594591 | J31: =IFERROR(J10*10^2/J26,"") -> 0.5285234 | K31: =IFERROR(K10*10^2/K26,"") -> 0.44097512 | ... P31: =IFERROR(P10*10^2/P26,"") -> 0.38488996
B32: Bond ATS | C32: INR L | D32: =IFERROR(D11*10^2/D27,"") -> 0.5616069 | E32: =IFERROR(E11*10^2/E27,"") -> 0.67408694 | F32: =IFERROR(F11*10^2/F27,"") -> 0.77665108 | G32: =IFERROR(G11*10^2/G27,"") -> 0.92259522 | H32: =IFERROR(H11*10^2/H27,"") -> 0.9770507 | I32: =IFERROR(I11*10^2/I27,"") -> 0.97461312 | J32: =IFERROR(J11*10^2/J27,"") -> 1.1119095 | K32: =IFERROR(K11*10^2/K27,"") -> 1.0989884 | ... P32: =IFERROR(P11*10^2/P27,"") -> 1.0506432
B33: G/S ATS | C33: INR L | D33: =IFERROR(D12*10^2/D28,"") | E33: =IFERROR(E12*10^2/E28,"") | F33: =IFERROR(F12*10^2/F28,"") | G33: =IFERROR(G12*10^2/G28,"") | H33: =IFERROR(H12*10^2/H28,"") | I33: =IFERROR(I12*10^2/I28,"") | J33: =IFERROR(J12*10^2/J28,"") | K33: =IFERROR(K12*10^2/K28,"") | ... P33: =IFERROR(P12*10^2/P28,"") -> 0.042114289
B35: AUM/User (platform) | C35: INR L | D35: =IFERROR(D9*10^2/D166,"") -> 1.195139 | E35: =IFERROR(E9*10^2/E166,"") -> 1.2407964 | F35: =IFERROR(F9*10^2/F166,"") -> 1.0637112 | G35: =IFERROR(G9*10^2/G166,"") -> 1.1707054 | H35: =IFERROR(H9*10^2/H166,"") -> 1.0945209 | I35: =IFERROR(I9*10^2/I166,"") -> 1.0979634 | J35: =IFERROR(J9*10^2/J166,"") -> 1.1457273 | K35: =IFERROR(K9*10^2/K166,"") -> 1.0336164 | ... P35: =IFERROR(P9*10^2/P166,"") -> 0.79413711
B36: FD AUM/User | C36: INR L | D36: =IFERROR(D10*10^2/D167,"") -> 1.1750479 | E36: =IFERROR(E10*10^2/E167,"") -> 1.2027074 | F36: =IFERROR(F10*10^2/F167,"") -> 0.97363593 | G36: =IFERROR(G10*10^2/G167,"") -> 1.0480736 | H36: =IFERROR(H10*10^2/H167,"") -> 0.89304869 | I36: =IFERROR(I10*10^2/I167,"") -> 0.88019813 | J36: =IFERROR(J10*10^2/J167,"") -> 0.86122886 | K36: =IFERROR(K10*10^2/K167,"") -> 0.72019852 | ... P36: =IFERROR(P10*10^2/P167,"") -> 0.58408991
B37: Bond AUM/User | C37: INR L | D37: =IFERROR(D11*10^2/D168,"") -> 1.0370042 | E37: =IFERROR(E11*10^2/E168,"") -> 1.1770287 | F37: =IFERROR(F11*10^2/F168,"") -> 1.3282346 | G37: =IFERROR(G11*10^2/G168,"") -> 1.6252601 | H37: =IFERROR(H11*10^2/H168,"") -> 1.7681054 | I37: =IFERROR(I11*10^2/I168,"") -> 1.7661944 | J37: =IFERROR(J11*10^2/J168,"") -> 1.9064752 | K37: =IFERROR(K11*10^2/K168,"") -> 1.9600499 | ... P37: =IFERROR(P11*10^2/P168,"") -> 1.8099488
B38: G/S AUM/User | C38: INR L | D38: =IFERROR(D12*10^2/D169,"") | E38: =IFERROR(E12*10^2/E169,"") | F38: =IFERROR(F12*10^2/F169,"") | G38: =IFERROR(G12*10^2/G169,"") | H38: =IFERROR(H12*10^2/H169,"") | I38: =IFERROR(I12*10^2/I169,"") | J38: =IFERROR(J12*10^2/J169,"") | K38: =IFERROR(K12*10^2/K169,"") | ... P38: =IFERROR(P12*10^2/P169,"") -> 0.24558642
B40: Net AUM/Active User | C40: INR L | D40: =D4/D19*100 -> 2.4387586 | E40: =E4/E19*100 -> 2.5279865 | F40: =F4/F19*100 -> 2.5609386 | G40: =G4/G19*100 -> 2.776546 | H40: =H4/H19*100 -> 2.8503677 | I40: =I4/I19*100 -> 2.8165319 | J40: =J4/J19*100 -> 2.8080571 | K40: =K4/K19*100 -> 2.823619 | ... P40: =P4/P19*100 -> 2.667283
B41: % MoM growth of key metrics
B42: Net AUM | E42: =IFERROR(E4/D4-1,"") -> 0.15524574 | F42: =IFERROR(F4/E4-1,"") -> 0.089844772 | G42: =IFERROR(G4/F4-1,"") -> 0.13335361 | H42: =IFERROR(H4/G4-1,"") -> 0.10593376 | I42: =IFERROR(I4/H4-1,"") -> 0.13255578 | J42: =IFERROR(J4/I4-1,"") -> 0.071074459 | K42: =IFERROR(K4/J4-1,"") -> 0.070702309 | L42: =IFERROR(L4/K4-1,"") -> 0.090359155 | ... P42: =IFERROR(P4/O4-1,"") -> 0.086016597
B43: Gross inflow | E43: =IFERROR(E9/D9-1,"") -> 0.1284453 | F43: =IFERROR(F9/E9-1,"") -> -0.090129566 | G43: =IFERROR(G9/F9-1,"") -> 0.21704331 | H43: =IFERROR(H9/G9-1,"") -> 0.0003338097 | I43: =IFERROR(I9/H9-1,"") -> 0.1530313 | J43: =IFERROR(J9/I9-1,"") -> 0.051568695 | K43: =IFERROR(K9/J9-1,"") -> -0.087908695 | L43: =IFERROR(L9/K9-1,"") -> 0.10582348 | ... P43: =IFERROR(P9/O9-1,"") -> 0.11791122
B44: Net Inflow | E44: =IFERROR(E14/D14-1,"") | F44: =IFERROR(F14/E14-1,"") -> -0.33142907 | G44: =IFERROR(G14/F14-1,"") -> 0.6176204 | H44: =IFERROR(H14/G14-1,"") -> -0.099683861 | I44: =IFERROR(I14/H14-1,"") -> 0.383864 | J44: =IFERROR(J14/I14-1,"") -> -0.39274027 | K44: =IFERROR(K14/J14-1,"") -> 0.065466257 | L44: =IFERROR(L14/K14-1,"") -> 0.36838183 | ... P44: =IFERROR(P14/O14-1,"") -> 0.044914214
B45: Active users | E45: =IFERROR(E19/D19-1,"") -> 0.11447017 | F45: =IFERROR(F19/E19-1,"") -> 0.07582151 | G45: =IFERROR(G19/F19-1,"") -> 0.045345214 | H45: =IFERROR(H19/G19-1,"") -> 0.077291149 | I45: =IFERROR(I19/H19-1,"") -> 0.1461615 | J45: =IFERROR(J19/I19-1,"") -> 0.074307011 | K45: =IFERROR(K19/J19-1,"") -> 0.064801309 | L45: =IFERROR(L19/K19-1,"") -> 0.073214302 | ... P45: =IFERROR(P19/O19-1,"") -> 0.13501958
B46: Transacting users | E46: =IFERROR(E21/D21-1,"") -> 0.086922087 | F46: =IFERROR(F21/E21-1,"") -> 0.061344385 | G46: =IFERROR(G21/F21-1,"") -> 0.1058142 | H46: =IFERROR(H21/G21-1,"") -> 0.069962361 | I46: =IFERROR(I21/H21-1,"") -> 0.14941612 | J46: =IFERROR(J21/I21-1,"") -> 0.0077301697 | K46: =IFERROR(K21/J21-1,"") -> 0.011021009 | L46: =IFERROR(L21/K21-1,"") -> 0.17333003 | ... P46: =IFERROR(P21/O21-1,"") -> 0.28082311
B47: ATS | E47: =E30/D30-1 -> 0.072460001 | F47: =F30/E30-1 -> -0.115752 | G47: =G30/F30-1 -> 0.093058237 | H47: =H30/G30-1 -> -0.06889981 | I47: =I30/H30-1 -> -0.01063674 | J47: =J30/I30-1 -> 0.16360098 | K47: =K30/J30-1 -> -0.10836277 | L47: =L30/K30-1 -> -0.0041397143 | ... P47: =P30/O30-1 -> -0.29088358
B48: Net AUM/Active User | E48: =E40/D40-1 -> 0.036587405 | F48: =F40/E40-1 -> 0.013034934 | G48: =G40/F40-1 -> 0.08419075 | H48: =H40/G40-1 -> 0.026587623 | I48: =I40/H40-1 -> -0.011870681 | J48: =J40/I40-1 -> -0.0030089652 | K48: =K40/J40-1 -> 0.0055418795 | L48: =L40/K40-1 -> 0.015975237 | ... P48: =P40/O40-1 -> -0.043173687
B50: FD | D50: 45658 | E50: =EDATE(D50,1) -> 45689 | F50: =EDATE(E50,1) -> 45717 | G50: =EDATE(F50,1) -> 45748 | H50: =EDATE(G50,1) -> 45778 | I50: =EDATE(H50,1) -> 45809 | J50: =EDATE(I50,1) -> 45839 | K50: =EDATE(J50,1) -> 45870 | L50: =EDATE(K50,1) -> 45901 | ... P50: =EDATE(O50,1) -> 46023
B51: # registered users | C51: # | D51: 321340 | E51: 278365 | F51: 309811 | G51: 250954 | H51: 219708 | I51: 248478 | J51: 228344 | K51: 208505 | L51: 224443 | M51: 244165 | N51: 233087 | O51: 268160 | P51: 246327
B52: # D0 Booking Initiated Users | C52: # | D52: 116265 | E52: 104857 | F52: 101680 | G52: 79543 | H52: 71415 | I52: 95663 | J52: 95863 | K52: 79398 | L52: 93580 | M52: 106003 | N52: 88945 | O52: 108548 | P52: 103653
B53: # users (PS) | C53: # | D53: 20373 | E53: 21838 | F53: 22603 | G53: 24303 | H53: 25286 | I53: 28662 | J53: 26953 | K53: 27461 | L53: 32170 | M53: 35417 | N53: 36052 | O53: 37931 | P53: 40393
B54: # users (TD) | C54: # | D54: 18357 | E54: 20013 | F54: 20730 | G54: 22613 | H54: 23644 | I54: 26970 | J54: 25139 | K54: 25853 | L54: 30260 | M54: 32866 | N54: 33545 | O54: 35804 | P54: 38831
B55: # auto renewed users (TD) | D55: 166 | E55: 98 | F55: 357 | G55: 460 | H55: 334 | I55: 265 | J55: 844 | K55: 638 | L55: 1257 | M55: 2085 | N55: 1428 | O55: 2930 | P55: 2931
B56: # new users (TD) | C56: # | D56: 8861 | E56: 8735 | F56: 7767 | G56: 8257 | H56: 8438 | I56: 10122 | J56: 8454 | K56: 8503 | L56: 11695 | M56: 13504 | N56: 12374 | O56: 12395 | P56: 14801
B57: # FDs booked (TD) | C57: # | D57: 35300 | E57: 37254 | F57: 37250 | G57: 41066 | H57: 42376 | I57: 48851 | J57: 40964 | K57: 42223 | L57: 47396 | M57: 50383 | N57: 51692 | O57: 55148 | P57: 58928
B59: Gross FD bookings | C59: INR Cr | D59: 229.17226 | E59: 254.13404 | F59: 206.79613 | G59: 239.49056 | H59: 215.31302 | I59: 240.90556 | J59: 214.90391 | K59: 182.7498 | L59: 194.45896 | M59: 186.19919 | N59: 183.01267 | O59: 195.73365 | P59: =2036150700/10^7 -> 203.61507
B60: vKYC failure | C60: INR Cr | D60: =11.6156719+3.82 -> 15.435672 | E60: =12.1178671+2.63 -> 14.747867 | F60: 12.730368 | G60: 13.456419 | H60: 13.047945 | I60: 12.021625 | J60: 15.888558 | K60: 11.592855 | L60: 11.543298 | M60: 13.654616 | N60: 13.481708 | O60: 13.113278 | P60: =104471153/10^7 -> 10.447115
B61: Renewed | C61: INR Cr | D61: 1.9669521 | E61: 1.3116617 | F61: 7.7689684 | G61: 10.966737 | H61: 8.887354 | I61: 8.5055054 | J61: 17.488976 | K61: 15.035975 | L61: 21.442607 | M61: 29.133166 | N61: 29.313921 | O61: 38.071443 | P61: =33.64 -> 33.64
B62: Net FD bookings | C62: INR Cr | D62: =D59-D60+D61 -> 215.70354 | E62: =E59-E60+E61 -> 240.69784 | F62: =F59-F60+F61 -> 201.83473 | G62: =G59-G60+G61 -> 237.00088 | H62: =H59-H60+H61 -> 211.15243 | I62: =I59-I60+I61 -> 237.38944 | J62: =J59-J60+J61 -> 216.50432 | K62: =K59-K60+K61 -> 186.19292 | ... P62: =P59-P60+P61 -> 226.80795
B63: FD booked by New users (TD) | C63: INR Cr | P63: =765703789/10^7 -> 76.570379
B64: FD booked by Repeat users (TD) | C64: INR Cr | P64: =P59-P60-P63 -> 116.59758
B66: Opening FD AUM | C66: INR Cr | D66: 1226.3 | E66: =D70 -> 1389.3356 | F66: =E70 -> 1581.6737 | G66: =F70 -> 1715.0616 | H66: =G70 -> 1868.6271 | I66: =H70 -> 2009.0095 | J66: =I70 -> 2180.5157 | K66: =J70 -> 2299.4196 | L66: =K70 -> 2390.9004 | ... P66: =O70 -> 2646.0458
B67: Net FD bookings | C67: INR Cr | D67: =D62 -> 215.70354 | E67: =E62 -> 240.69784 | F67: =F62 -> 201.83473 | G67: =G62 -> 237.00088 | H67: =H62 -> 211.15243 | I67: =I62 -> 237.38944 | J67: =J62 -> 216.50432 | K67: =K62 -> 186.19292 | ... P67: =P62 -> 226.80795
B68: Withdrawal | C68: INR Cr | D68: 37.544061 | E68: 36.24308 | F68: 37.229095 | G68: 40.623444 | H68: 40.687688 | I68: 38.950324 | J68: 42.527294 | K68: 44.004458 | L68: 56.490265 | M68: 55.407946 | N68: 47.573271 | O68: 60.196802 | P68: =668098425/10^7 -> 66.809843
B69: Matured | C69: INR Cr | D69: 15.123891 | E69: 12.116637 | F69: 31.217728 | G69: 42.811919 | H69: 30.082365 | I69: 26.932877 | J69: 55.073216 | K69: 50.707652 | L69: 74.533082 | M69: 92.380038 | N69: 88.127254 | O69: 95.718603 | P69: =965506538/10^7 -> 96.550654
B70: Closing FD AUM (without interest) | C70: INR Cr | D70: =D66+D67-D68-D69 -> 1389.3356 | E70: =E66+E67-E68-E69 -> 1581.6737 | F70: =F66+F67-F68-F69 -> 1715.0616 | G70: =G66+G67-G68-G69 -> 1868.6271 | H70: =H66+H67-H68-H69 -> 2009.0095 | I70: =I66+I67-I68-I69 -> 2180.5157 | J70: =J66+J67-J68-J69 -> 2299.4196 | K70: =K66+K67-K68-K69 -> 2390.9004 | ... P70: =P66+P67-P68-P69 -> 2709.4933
B72: Closing FD AUM (incl. interest) | C72: INR Cr | D72: =D5 -> 1439.89 | E72: =E5 -> 1639.58 | F72: =F5 -> 1755.19 | G72: =G5 -> 1940.5 | H72: =H5 -> 2086.05 | I72: =I5 -> 2298.3017 | J72: =J5 -> 2360.197 | K72: =K5 -> 2422.6797 | ... P72: =P5 -> 2835.867
B74: FD Revenue | C74: INR Cr | D74: ='Revised MIS Template - P&L'!C10 -> 0.5063818 | E74: ='Revised MIS Template - P&L'!D10 -> 0.59355137 | F74: ='Revised MIS Template - P&L'!E10 -> 0.73453594 | G74: ='Revised MIS Template - P&L'!F10 -> 0.92029825 | H74: ='Revised MIS Template - P&L'!G10 -> 0.79198632 | I74: ='Revised MIS Template - P&L'!H10 -> 0.83870419 | J74: ='Revised MIS Template - P&L'!I10 -> 1.087871 | K74: ='Revised MIS Template - P&L'!J10 -> 0.8831191 | ... P74: ='Revised MIS Template - P&L'!O10 -> 1.2196091
B75: Take Rate | C75: % | D75: =D74/AVERAGE(D70)*12 -> 0.0043737321 | E75: =E74/AVERAGE(D70:E70)*12 -> 0.0047947454 | F75: =F74/AVERAGE(E70:F70)*12 -> 0.0053473697 | G75: =G74/AVERAGE(F70:G70)*12 -> 0.0061632468 | H75: =H74/AVERAGE(G70:H70)*12 -> 0.0049018702 | I75: =I74/AVERAGE(H70:I70)*12 -> 0.0048045779 | J75: =J74/AVERAGE(I70:J70)*12 -> 0.0058279645 | K75: =K74/AVERAGE(J70:K70)*12 -> 0.0045188513 | L75: =L74/AVERAGE(K70:L70)*12 -> 0.0051839293 | ... O75: =O74/AVERAGE(N70:O70)*12 -> 0.0052957298 | P75: =O75 -> 0.0052957298
B76: FD ARPU | C76: INR | D76: =D74*10^7/D54 -> 275.85215 | E76: =E74*10^7/E54 -> 296.58291 | F76: =F74*10^7/F54 -> 354.33475 | G76: =G74*10^7/G54 -> 406.97751 | H76: =H74*10^7/H54 -> 334.96292 | I76: =I74*10^7/I54 -> 310.97671 | J76: =J74*10^7/J54 -> 432.74235 | K76: =K74*10^7/K54 -> 341.5925 | ... P76: =P74*10^7/P54 -> 314.08129
B78: Amt. invested in FD / user (TD) | C78: INR L | D78: =D62/D54*10^2 -> 1.1750479 | E78: =E62/E54*10^2 -> 1.2027074 | F78: =F62/F54*10^2 -> 0.97363593 | G78: =G62/G54*10^2 -> 1.0480736 | H78: =H62/H54*10^2 -> 0.89304869 | I78: =I62/I54*10^2 -> 0.88019813 | J78: =J62/J54*10^2 -> 0.86122886 | K78: =K62/K54*10^2 -> 0.72019852 | ... P78: =P62/P54*10^2 -> 0.58408991
B79: ATS / transaction (TD) | C79: INR L | D79: =D62/D57*10^2 -> 0.61105818 | E79: =E62/E57*10^2 -> 0.64609931 | F79: =F62/F57*10^2 -> 0.5418382 | G79: =G62/G57*10^2 -> 0.57712191 | H79: =H62/H57*10^2 -> 0.49828307 | I79: =I62/I57*10^2 -> 0.48594591 | J79: =J62/J57*10^2 -> 0.5285234 | K79: =K62/K57*10^2 -> 0.44097512 | ... P79: =P62/P57*10^2 -> 0.38488996
B80: # FDs / transacting user / month (TD) | C80: # | D80: =D57/D54 -> 1.9229722 | E80: =E57/E54 -> 1.86149 | F80: =F57/F54 -> 1.7969127 | G80: =G57/G54 -> 1.816035 | H80: =H57/H54 -> 1.7922517 | I80: =I57/I54 -> 1.8113089 | J80: =J57/J54 -> 1.6295 | K80: =K57/K54 -> 1.6331954 | ... P80: =P57/P54 -> 1.5175504
B82: # banks onboarded | C82: #
B83: # banks with direct integration | C83: #
B84: Direct Bank FDs as % of Total FD inflows | C84: %
B86: FD-backed credit cards | D86: 45658 | E86: =EDATE(D86,1) -> 45689 | F86: =EDATE(E86,1) -> 45717 | G86: =EDATE(F86,1) -> 45748 | H86: =EDATE(G86,1) -> 45778 | I86: =EDATE(H86,1) -> 45809 | J86: =EDATE(I86,1) -> 45839 | K86: =EDATE(J86,1) -> 45870 | L86: =EDATE(K86,1) -> 45901 | ... P86: =EDATE(O86,1) -> 46023
B87: # banks live on FD credit cards | C87: # | G87: 1 | H87: 1 | I87: 1 | J87: 1 | K87: 1 | L87: 1 | M87: 1 | N87: 1 | O87: 1 | P87: 1
B88: # cards issued monthly | C88: # | F88: 23 | G88: 1574 | H88: 1507 | I88: 2404 | J88: 2159 | K88: 1893 | L88: 2743 | M88: 4163 | N88: 4526 | O88: 4202 | P88: 6393
B89: # cards issued LTD | C89: # | F89: 23 | G89: =G88+F89 -> 1597 | H89: =H88+G89 -> 3104 | I89: =I88+H89 -> 5508 | J89: =J88+I89 -> 7667 | K89: =K88+J89 -> 9560 | L89: =L88+K89 -> 12303 | M89: =M88+L89 -> 16466 | N89: =N88+M89 -> 20992 | ... P89: =P88+O89 -> 31587
B91: # Platinum cards issued monthly | C91: # | F91: 9 | G91: 1038 | H91: 1099 | I91: 1930 | J91: 1582 | K91: 1413 | L91: 2208 | M91: 3581 | N91: 3881 | O91: 3636 | P91: 5590
B92: # Select cards issued monthly | C92: # | F92: 14 | G92: 537 | H92: 408 | I92: 474 | J92: 577 | K92: 480 | L92: 535 | M92: 582 | N92: 645 | O92: 566 | P92: 861
B94: Active cards as % of issued | C94: % | F94: 0 | G94: 0.29 | H94: 0.64 | I94: 0.65 | J94: 0.65 | K94: 0.64 | L94: 0.63 | M94: 0.64 | N94: 0.64 | O94: 0.63 | P94: 0.63
B95: Avg. spend / CC | C95: INR | F95: 0 | G95: 3246 | H95: 8534 | I95: 11241 | J95: 18676 | K95: 13441 | L95: 13333 | M95: 13201 | N95: 10795 | O95: 11537 | P95: 11091
B96: Avg. spend limit / CC | C96: INR | F96: 164639 | G96: 75956 | H96: 56606 | I96: 45542 | J96: 63260 | K96: 63531 | L96: 49318 | M96: 36545 | N96: 38230 | O96: 39466 | P96: 34967
B99: Bonds | D99: 45658 | E99: =EDATE(D99,1) -> 45689 | F99: =EDATE(E99,1) -> 45717 | G99: =EDATE(F99,1) -> 45748 | H99: =EDATE(G99,1) -> 45778 | I99: =EDATE(H99,1) -> 45809 | J99: =EDATE(I99,1) -> 45839 | K99: =EDATE(J99,1) -> 45870 | L99: =EDATE(K99,1) -> 45901 | ... P99: =EDATE(O99,1) -> 46023
B100: # Bookings | C100: # | D100: 4583 | E100: 4711 | F100: 5931 | G100: 7013 | H100: 9278 | I100: 11348 | J100: 13439 | K100: 13428 | L100: 14162 | M100: 18659 | N100: 22057 | O100: 24767 | P100: 29112
B101: # Users | C101: # | D101: 2482 | E101: 2698 | F101: 3468 | G101: 3981 | H101: 5127 | I101: 6262 | J101: 7838 | K101: 7529 | L101: 8174 | M101: 10901 | N101: 12425 | O101: 14103 | P101: 16899
B102: # users new to bonds | C102: # | D102: 1880 | E102: 1782 | F102: 2027 | G102: 2228 | H102: 2898 | I102: 3683 | J102: 4568 | K102: 3912 | L102: 4158 | M102: 6124 | N102: 6339 | O102: 6801 | P102: 7914
B103: # users repeat to Bonds | C103: # | D103: 602 | E103: 916 | F103: 1441 | G103: 1753 | H103: 2229 | I103: 2579 | J103: 3270 | K103: 3617 | L103: 4016 | M103: 4777 | N103: 6086 | O103: 7302 | P103: 8985
B105: Bonds payments (D2C) | C105: INR Cr | D105: 25.738444 | E105: 31.756236 | F105: 46.063175 | G105: 64.701603 | H105: 90.650764 | I105: 110.5991 | J105: 149.42952 | K105: 147.57216 | L105: 164.52655 | M105: 208.58126 | N105: 231.60483 | O105: 279.38761 | P105: =3058632560.03/10000000 -> 305.86326
B106: Withdrawal | C106: INR Cr | K106: 0.34086108 | L106: 2.6365126 | M106: 7.9290396 | N106: 14.158814 | O106: 24.793844 | P106: 32.145233
B107: Matured bonds | C107: INR Cr | D107: 0.4357093 | E107: 0.3835715 | F107: 7.1966214 | G107: 0.1146695 | H107: 11.228786 | I107: 11.5 | J107: 22.261973 | K107: 38.205694 | L107: 38.997953 | M107: 9.418665 | N107: 17.664455 | O107: 21.259786 | P107: 36.746125
B108: Net Bonds AUM (D2C) | C108: INR Cr | D108: 48.457 | E108: =D108+E105-E106-E107 -> 79.829664 | F108: =E108+F105-F106-F107 -> 118.69622 | G108: =F108+G105-G106-G107 -> 183.28315 | H108: =G108+H105-H106-H107 -> 262.70513 | I108: =H108+I105-I106-I107 -> 361.80423 | J108: =I108+J105-J106-J107 -> 488.97178 | K108: =J108+K105-K106-K107 -> 597.99738 | L108: =K108+L105-L106-L107 -> 720.88946 | ... P108: =O108+P105-P106-P107 -> 1582.2105
B110: ATS / user | C110: INR L | D110: =D105*10^7/(D101)/10^5 -> 1.0370042 | E110: =E105*10^7/(E101)/10^5 -> 1.1770287 | F110: =F105*10^7/(F101)/10^5 -> 1.3282346 | G110: =G105*10^7/(G101)/10^5 -> 1.6252601 | H110: =H105*10^7/(H101)/10^5 -> 1.7681054 | I110: =I105*10^7/(I101)/10^5 -> 1.7661944 | J110: =J105*10^7/(J101)/10^5 -> 1.9064752 | K110: =K105*10^7/(K101)/10^5 -> 1.9600499 | ... P110: =P105*10^7/(P101)/10^5 -> 1.8099488
B112: Bonds Revenue (D2C) | C112: INR Cr | D112: 0.0918894 | E112: 0.0996418 | F112: 0.11976426 | G112: 0.20704513 | H112: 0.10878092 | I112: 0.29861756 | J112: 0.6171346 | K112: 0.5032173 | L112: 0.65 | M112: 1.04 | N112: 1.6595499 | O112: =20477080/10^7 -> 2.047708 | P112: =21352274/10^7 -> 2.1352274
B113: Take Rate | C113: % | D113: =D112/D105 -> 0.0035701226 | E113: =E112/E105 -> 0.0031377082 | F113: =F112/F105 -> 0.0026 | G113: =G112/G105 -> 0.0032 | H113: =H112/H105 -> 0.0012 | I113: =I112/I105 -> 0.0027 | J113: =J112/J105 -> 0.0041299376 | K113: =K112/K105 -> 0.0034099746 | ... P113: =P112/P105 -> 0.006980987
B114: Bonds ARPU | C114: INR | D114: =D112*10^7/D101 -> 370.22321 | E114: =E112*10^7/E101 -> 369.31727 | F114: =F112*10^7/F101 -> 345.34099 | G114: =G112*10^7/G101 -> 520.08322 | H114: =H112*10^7/H101 -> 212.17265 | I114: =I112*10^7/I101 -> 476.8725 | J114: =J112*10^7/J101 -> 787.36234 | K114: =K112*10^7/K101 -> 668.37203 | ... P114: =P112*10^7/P101 -> 1263.5229
B116: # ISINs listed on the platform | C116: #
B119: % primary | C119: %
B120: % direct sourcing | C120: %
B123: Gold / Silver MF | D123: 45658 | E123: =EDATE(D123,1) -> 45689 | F123: =EDATE(E123,1) -> 45717 | G123: =EDATE(F123,1) -> 45748 | H123: =EDATE(G123,1) -> 45778 | I123: =EDATE(H123,1) -> 45809 | J123: =EDATE(I123,1) -> 45839 | K123: =EDATE(J123,1) -> 45870 | L123: =EDATE(K123,1) -> 45901 | ... P123: =EDATE(O123,1) -> 46023
B124: #Users | C124: # | D124: 0 | E124: 0 | F124: 0 | G124: 0 | H124: 0 | I124: 0 | J124: 0 | K124: 0 | L124: 88 | M124: 3818 | N124: 5522 | O124: 10221 | P124: 20199
B125: #Bookings | C125: # | D125: 0 | E125: 0 | F125: 0 | G125: 0 | H125: 0 | I125: 0 | J125: 0 | K125: 0 | L125: 238 | M125: 9821 | N125: 20812 | O125: 50647 | P125: 117789
B127: Monthly Bookings | C127: INR Cr | D127: =SUM(D128:D130) -> 0 | E127: =SUM(E128:E130) -> 0 | F127: =SUM(F128:F130) -> 0 | G127: =SUM(G128:G130) -> 0 | H127: =SUM(H128:H130) -> 0 | I127: =SUM(I128:I130) -> 0 | J127: =SUM(J128:J130) -> 0 | K127: =SUM(K128:K130) -> 0 | ... P127: =SUM(P128:P130) -> 50.671131
B128: SIP-Daily | C128: INR Cr | D128: 0 | E128: 0 | F128: 0 | G128: 0 | H128: 0 | I128: 0 | J128: 0 | K128: 0 | L128: 0 | M128: 0.131215 | N128: 0.1830003 | O128: 0.6677028 | P128: =18437670/10000000 -> 1.843767
B129: SIP-Monthly | C129: INR Cr | D129: 0 | E129: 0 | F129: 0 | G129: 0 | H129: 0 | I129: 0 | J129: 0 | K129: 0 | L129: 0 | M129: 0.3164845 | N129: 0.7895505 | O129: 1.2533018 | P129: =19970118/10000000 -> 1.9970118
B130: Lumpsum | C130: INR Cr | D130: 0 | E130: 0 | F130: 0 | G130: 0 | H130: 0 | I130: 0 | J130: 0 | K130: 0 | L130: 0.2004357 | M130: 7.2269421 | N130: 6.4012402 | O130: 18.861341 | P130: =468303524/10^7 -> 46.830352
...

Sheet Revised MIS Template - P&L
B2: P&L (INR Cr) | C2: 45658 | D2: 45689 | E2: 45717 | F2: 45748 | G2: 45778 | H2: 45809 | I2: 45839 | J2: 45870 | K2: 45901 | L2: 45931 | M2: 45962 | N2: 45992 | O2: Jan-26 | P2: Jan-26 | Q2: Actual vs Plan | R2: Actual vs Plan | S2: MOM | T2: MOM
C3: Actual | D3: Actual | E3: Actual | F3: Actual | G3: Actual | H3: Actual | I3: Actual | J3: Actual | K3: Actual | L3: Actual | M3: Actual | N3: Actual | O3: Actual | P3: Plan | Q3: Variance | R3: Variance % | S3: Variance | T3: Variance %
B4: Gross Bookings | C4: =SUM(C5:C7) -> 241.44198 | D4: =SUM(D5:D7) -> 272.45407 | E4: =SUM(E5:E7) -> 247.8979 | F4: =SUM(F5:F7) -> 301.70248 | G4: =SUM(G5:G7) -> 301.8032 | H4: =SUM(H5:H7) -> 347.98853 | I4: =SUM(I5:I7) -> 365.93385 | J4: =SUM(J5:J7) -> 333.76508 | ... Q4: =SUM(Q5:Q7) -> 61.82688 | R4: =IFERROR(O4/P4-1,"") -> 0.11879497 | S4: =SUM(S5:S7) -> 61.415444 | T4: =IFERROR(O4/N4-1,"") -> 0.11791122
B5: Fixed Deposits | C5: ='Revised MIS Template - KPIs'!D10 -> 215.70354 | D5: ='Revised MIS Template - KPIs'!E10 -> 240.69784 | E5: ='Revised MIS Template - KPIs'!F10 -> 201.83473 | F5: ='Revised MIS Template - KPIs'!G10 -> 237.00088 | G5: ='Revised MIS Template - KPIs'!H10 -> 211.15243 | H5: ='Revised MIS Template - KPIs'!I10 -> 237.38944 | I5: ='Revised MIS Template - KPIs'!J10 -> 216.50432 | J5: ='Revised MIS Template - KPIs'!K10 -> 186.19292 | ... O5: ='Revised MIS Template - KPIs'!P10 -> 226.80795 | P5: 222.6212 | Q5: =O5-P5 -> 4.1867551 | R5: =IFERROR(O5/P5-1,"") -> 0.018806633 | S5: =O5-N5 -> 6.1161417 | T5: =IFERROR(O5/N5-1,"") -> 0.027713496
B6: Bonds | C6: ='Revised MIS Template - KPIs'!D11 -> 25.738444 | D6: ='Revised MIS Template - KPIs'!E11 -> 31.756236 | E6: ='Revised MIS Template - KPIs'!F11 -> 46.063175 | F6: ='Revised MIS Template - KPIs'!G11 -> 64.701603 | G6: ='Revised MIS Template - KPIs'!H11 -> 90.650764 | H6: ='Revised MIS Template - KPIs'!I11 -> 110.5991 | I6: ='Revised MIS Template - KPIs'!J11 -> 149.42952 | J6: ='Revised MIS Template - KPIs'!K11 -> 147.57216 | ... O6: ='Revised MIS Template - KPIs'!P11 -> 305.86326 | P6: 278.39272 | Q6: =O6-P6 -> 27.470535 | R6: =IFERROR(O6/P6-1,"") -> 0.098675478 | S6: =O6-N6 -> 26.475648 | T6: =IFERROR(O6/N6-1,"") -> 0.094763143
B7: Gold & Silver | C7: ='Revised MIS Template - KPIs'!D12 -> 0 | D7: ='Revised MIS Template - KPIs'!E12 -> 0 | E7: ='Revised MIS Template - KPIs'!F12 -> 0 | F7: ='Revised MIS Template - KPIs'!G12 -> 0 | G7: ='Revised MIS Template - KPIs'!H12 -> 0 | H7: ='Revised MIS Template - KPIs'!I12 -> 0 | I7: ='Revised MIS Template - KPIs'!J12 -> 0 | J7: ='Revised MIS Template - KPIs'!K12 -> 0 | ... O7: ='Revised MIS Template - KPIs'!P12 -> 49.606 | P7: 19.43641 | Q7: =O7-P7 -> 30.16959 | R7: =IFERROR(O7/P7-1,"") -> 1.5522203 | S7: =O7-N7 -> 28.823654 | T7: =IFERROR(O7/N7-1,"") -> 1.3869298
B9: Revenue | C9: =SUM(C10:C11,C14) -> 0.5981954 | D9: =SUM(D10:D11,D14) -> 0.69319297 | E9: =SUM(E10:E11,E14) -> 0.84375604 | F9: =SUM(F10:F11,F14) -> 1.1109012 | G9: =SUM(G10:G11,G14) -> 0.97191732 | H9: =SUM(H10:H11,H14) -> 1.2194894 | I9: =SUM(I10:I11,I14) -> 1.7050056 | J9: =SUM(J10:J11,J14) -> 1.3863364 | ... Q9: =SUM(Q10:Q11,Q14) -> 0.24949415 | R9: =IFERROR(O9/P9-1,"") -> 0.080480314 | S9: =SUM(S10:S11,S14) -> -0.027364196 | T9: =IFERROR(O9/N9-1,"") -> -0.0081032936
B10: FD income | C10: 0.5063818 | D10: 0.59355137 | E10: 0.73453594 | F10: 0.92029825 | G10: 0.79198632 | H10: 0.83870419 | I10: 1.087871 | J10: 0.8831191 | K10: 1.048695 | L10: 1.0489075 | M10: 1.1347712 | N10: 1.1534354 | O10: 1.2196091 | P10: 1.1309532 | Q10: =O10-P10 -> 0.088655893 | R10: =IFERROR(O10/P10-1,"") -> 0.07839042 | S10: =O10-N10 -> 0.066173683 | T10: =IFERROR(O10/N10-1,"") -> 0.05737095
B11: Bonds net income | C11: 0.0918136 | D11: 0.0996416 | E11: 0.1092201 | F11: 0.19060296 | G11: 0.17993099 | H11: 0.3807852 | I11: 0.6171346 | J11: 0.5032173 | K11: 0.7684542 | L11: 1.1613231 | M11: 1.4708946 | N11: 2.2181708 | O11: 2.1207348 | P11: 1.948749 | Q11: =O11-P11 -> 0.17198575 | R11: =IFERROR(O11/P11-1,"") -> 0.088254438 | S11: =O11-N11 -> -0.097435967 | T11: =IFERROR(O11/N11-1,"") -> -0.04392627
B12: D2C | C12: =C11-C13 -> 0.0918136 | D12: =D11-D13 -> 0.0996416 | E12: =E11-E13 -> 0.1092201 | F12: =F11-F13 -> 0.19060296 | G12: =G11-G13 -> 0.17993099 | H12: =H11-H13 -> 0.3807852 | I12: =I11-I13 -> 0.6171346 | J12: =J11-J13 -> 0.4952973 | ... P12: =P11-P13 -> 1.948749 | Q12: =O12-P12 -> 0.15354575 | R12: =IFERROR(O12/P12-1,"") -> 0.078791958 | S12: =O12-N12 -> 0.003024033 | T12: =IFERROR(O12/N12-1,"") -> 0.0014405159
B13: Non D2C | C13: 0 | D13: 0 | E13: 0 | F13: 0 | G13: 0 | H13: 0 | I13: 0 | J13: 0.00792 | K13: 0.0034 | L13: 0.01772 | M13: 0.00688 | N13: 0.1189 | O13: 0.01844 | P13: 0 | Q13: =O13-P13 -> 0.01844 | R13: =IFERROR(O13/P13-1,"") | S13: =O13-N13 -> -0.10046 | T13: =IFERROR(O13/N13-1,"") -> -0.84491169
B14: G/S net income | M14: 0.0040478 | N14: 0.005316512 | O14: 0.0092146 | P14: 0.020362097 | Q14: =O14-P14 -> -0.011147497 | R14: =IFERROR(O14/P14-1,"") -> -0.54746311 | S14: =O14-N14 -> 0.003898088 | T14: =IFERROR(O14/N14-1,"") -> 0.73320403
B16: Direct costs
B17: Upswing integration fee | C17: 0.035 | D17: 0.035 | E17: 0.035 | F17: 0.035 | G17: 0.035 | H17: 0.035 | I17: 0.035 | J17: 0.035 | K17: 0.035 | L17: 0.035 | M17: 0.035 | N17: 0.035 | O17: 0.035 | P17: =350000/10^7 -> 0.035 | Q17: =O17-P17 -> 0 | R17: =IFERROR(O17/P17-1,"") -> 0 | S17: =O17-N17 -> 0 | T17: =IFERROR(O17/N17-1,"") -> 0
B18: PG fee | C18: 0.035633315 | D18: 0.042074739 | E18: 0.019962606 | F18: 0.012811125 | G18: 0.0150839 | H18: 0.017213575 | I18: 0.000108323 | J18: 5.13e-05 | K18: 1.05e-05 | L18: 1.3e-05 | M18: 1.71e-05 | N18: 1.445e-05 | O18: 1.185e-05 | P18: 0 | Q18: =O18-P18 -> 1.185e-05 | R18: =IFERROR(O18/P18-1,"") | S18: =O18-N18 -> -2.6e-06 | T18: =IFERROR(O18/N18-1,"") -> -0.1799308
B19: Onboarding charges/Settlement charges | C19: 0.063136569 | D19: 0.078885473 | E19: 0.0851216 | F19: 0.062895391 | G19: 0.011621403 | H19: 0.041938808 | I19: 0.079896772 | J19: 0.0880468 | K19: 0.0981505 | L19: 0.1533222 | M19: 0.189543 | N19: 0.20520887 | O19: 0.17572624 | P19: 0.2215 | Q19: =O19-P19 -> -0.045773757 | R19: =IFERROR(O19/P19-1,"") -> -0.20665353 | S19: =O19-N19 -> -0.02948263 | T19: =IFERROR(O19/N19-1,"") -> -0.14367132
B20: Gross Profit | C20: =C9-C17-C18-C19 -> 0.46442552 | D20: =D9-D17-D18-D19 -> 0.53723276 | E20: =E9-E17-E18-E19 -> 0.70367184 | F20: =F9-F17-F18-F19 -> 1.0001947 | G20: =G9-G17-G18-G19 -> 0.91021201 | H20: =H9-H17-H18-H19 -> 1.125337 | I20: =I9-I17-I18-I19 -> 1.5900005 | J20: =J9-J17-J18-J19 -> 1.2632383 | ... Q20: =Q9-Q17-Q18-Q19 -> 0.29525606 | R20: =IFERROR(O20/P20-1,"") -> 0.10383309 | S20: =O20-N20 -> 0.0021210342 | T20: =IFERROR(O20/N20-1,"") -> 0.00067619941
B21: % | C21: =IFERROR(C20/C$9,"") -> 0.77637761 | D21: =IFERROR(D20/D$9,"") -> 0.77501184 | E21: =IFERROR(E20/E$9,"") -> 0.83397546 | F21: =IFERROR(F20/F$9,"") -> 0.90034531 | G21: =IFERROR(G20/G$9,"") -> 0.93651178 | H21: =IFERROR(H20/H$9,"") -> 0.9227936 | I21: =IFERROR(I20/I$9,"") -> 0.93254855 | J21: =IFERROR(J20/J$9,"") -> 0.91120618 | ... P21: =IFERROR(P20/P$9,"") -> 0.91725978
B23: Acquisition Cost | C23: =SUM(C24:C27) -> 2.6359043 | D23: =SUM(D24:D27) -> 2.2192264 | E23: =SUM(E24:E27) -> 2.0421741 | F23: =SUM(F24:F27) -> 2.1830482 | G23: =SUM(G24:G27) -> 1.9877187 | H23: =SUM(H24:H27) -> 2.6503609 | I23: =SUM(I24:I27) -> 3.1870463 | J23: =SUM(J24:J27) -> 4.1640657 | ... Q23: =SUM(Q24:Q27) -> -0.63919913 | R23: =IFERROR(O23/P23-1,"") -> -0.085325697 | S23: =SUM(S24:S27) -> 1.2372248 | T23: =IFERROR(O23/N23-1,"") -> 0.22034823
B24: New user reward | C24: 0.03971 | D24: 0.04141 | E24: 0.02681 | F24: 0.03042 | G24: 0.0538605 | H24: 0.091075103 | I24: 0.085828783 | J24: 0.1229059 | K24: 0.0799848 | L24: 0.1281511 | M24: 0.1235411 | N24: 0.14043821 | O24: 0.21030787 | P24: 0.14920021 | Q24: =O24-P24 -> 0.061107655 | R24: =IFERROR(O24/P24-1,"") -> 0.40956816 | S24: =O24-N24 -> 0.069869653 | T24: =IFERROR(O24/N24-1,"") -> 0.49751169
B25: Digital acquisition spend | C25: 2.1107443 | D25: 1.8623384 | E25: 1.8773497 | F25: 1.9976282 | G25: 1.8635482 | H25: 2.3436195 | I25: 2.9132175 | J25: 3.8882598 | K25: 4.3185136 | L25: 5.326794 | M25: 5.1871821 | N25: 5.0020431 | O25: 6.040677 | P25: 6.4947659 | Q25: =O25-P25 -> -0.45408898 | R25: =IFERROR(O25/P25-1,"") -> -0.069916143 | S25: =O25-N25 -> 1.0386339 | T25: =IFERROR(O25/N25-1,"") -> 0.20764194
B26: Influencer spends | C26: 0.48545 | D26: 0.315478 | E26: 0.1380144 | F26: 0.155 | G26: 0.07031 | H26: 0.2156663 | I26: 0.188 | J26: 0.1529 | K26: 0.377515 | L26: 0.3345 | M26: 0.33623 | N26: 0.26988 | O26: 0.37195 | P26: 0.5 | Q26: =O26-P26 -> -0.12805 | R26: =IFERROR(O26/P26-1,"") -> -0.2561 | S26: =O26-N26 -> 0.10207 | T26: =IFERROR(O26/N26-1,"") -> 0.37820513
B27: Offline and Inside sales (Reclass from Manpower) | N27: =N40 -> 0.2025 | O27: =O40 -> 0.2291512 | P27: =P40 -> 0.347319 | Q27: =O27-P27 -> -0.1181678 | R27: =IFERROR(O27/P27-1,"") -> -0.34022844 | S27: =O27-N27 -> 0.0266512 | T27: =IFERROR(O27/N27-1,"") -> 0.13161086
B28: CM 1 | C28: =C20-C24-C25-C27-C26 -> -2.1714788 | D28: =D20-D24-D25-D27-D26 -> -1.6819937 | E28: =E20-E24-E25-E27-E26 -> -1.3385023 | F28: =F20-F24-F25-F27-F26 -> -1.1828535 | G28: =G20-G24-G25-G27-G26 -> -1.0775067 | H28: =H20-H24-H25-H27-H26 -> -1.5250239 | I28: =I20-I24-I25-I27-I26 -> -1.5970458 | J28: =J20-J24-J25-J27-J26 -> -2.9008274 | ... P28: =P20-P24-P25-P27-P26 -> -4.6477208 | Q28: =Q20-Q24-Q25-Q27 -> 0.80640518 | R28: =IFERROR(O28/P28-1,"") -> -0.20105665 | S28: =O28-N28 -> -1.2351037 | T28: =IFERROR(O28/N28-1,"") -> 0.49839508
B29: % | C29: =C28/C9 -> -3.6300492 | D29: =D28/D9 -> -2.4264436 | E29: =E28/E9 -> -1.5863617 | F29: =F28/F9 -> -1.0647692 | G29: =G28/G9 -> -1.1086403 | H29: =H28/H9 -> -1.250543 | I29: =I28/I9 -> -0.93668068 | J29: =J28/J9 -> -2.0924412 | ... P29: =P28/P9 -> -1.4992337
B31: Variable cost | C31: =SUM(C32:C34) -> 0.73640499 | D31: =SUM(D32:D34) -> 3.0136103 | E31: =SUM(E32:E34) -> 1.3589364 | F31: =SUM(F32:F34) -> 0.52499297 | G31: =SUM(G32:G34) -> 0.4708057 | H31: =SUM(H32:H34) -> 0.54228813 | I31: =SUM(I32:I34) -> 3.6337026 | J31: =SUM(J32:J34) -> 4.8723422 | ... Q31: =SUM(Q32:Q34) -> 0.32571063 | R31: =IFERROR(O31/P31-1,"") -> 0.4884829 | S31: =SUM(S32:S35) -> -1.2351037 | T31: =IFERROR(O31/N31-1,"") -> -0.83701021
B32: Communication | C32: 0.057718261 | D32: 0.10788411 | E32: 0.10048934 | F32: 0.13957092 | G32: 0.15227717 | H32: 0.14469617 | I32: 0.16440163 | J32: 0.1484754 | K32: 0.1444091 | L32: 0.1786202 | M32: 0.2244811 | N32: 0.23831876 | O32: 0.24083771 | P32: 0.24382795 | Q32: =O32-P32 -> -0.002990243 | R32: =IFERROR(O32/P32-1,"") -> -0.012263742 | S32: =O32-N32 -> 0.002518946 | T32: =IFERROR(O32/N32-1,"") -> 0.01056965
B33: Branding & Agency | C33: 0.66076243 | D33: 2.8642605 | E33: 1.2111444 | F33: 0.33176996 | G33: 0.28736043 | H33: 0.36673476 | I33: 3.4496516 | J33: 4.6907059 | K33: 6.823355 | L33: 7.9757324 | M33: 5.9876254 | N33: 5.7760869 | O33: 0.65870087 | P33: 0.33 | Q33: =O33-P33 -> 0.32870087 | R33: =IFERROR(O33/P33-1,"") -> 0.99606325 | S33: =O33-N33 -> -5.117386 | T33: =IFERROR(O33/N33-1,"") -> -0.88596071
B34: Rewards & Incentives | C34: 0.0179243 | D34: 0.0414657 | E34: 0.0473027 | F34: 0.053652089 | G34: 0.0311681 | H34: 0.0308572 | I34: 0.0196494 | J34: 0.0331609 | K34: 0.0450543 | L34: 0.046686 | M34: 0.0310845 | N34: 0.0748753 | O34: 0.092952047 | P34: =O34 -> 0.092952047 | Q34: =O34-P34 -> 0 | R34: =IFERROR(O34/P34-1,"") -> 0 | S34: =O34-N34 -> 0.018076747 | T34: =IFERROR(O34/N34-1,"") -> 0.2414247
B35: CM 2 | C35: =C28-C32-C33-C34 -> -2.9078837 | D35: =D28-D32-D33-D34 -> -4.695604 | E35: =E28-E32-E33-E34 -> -2.6974387 | F35: =F28-F32-F33-F34 -> -1.7078464 | G35: =G28-G32-G33-G34 -> -1.5483124 | H35: =H28-H32-H33-H34 -> -2.067312 | I35: =I28-I32-I33-I34 -> -5.2307484 | J35: =J28-J32-J33-J34 -> -7.7731696 | ... Q35: =Q28-Q32-Q33-Q34 -> 0.48069455 | R35: =IFERROR(O35/P35-1,"") -> -0.11454407 | S35: =O35-N35 -> 3.8616866 | T35: =IFERROR(O35/N35-1,"") -> -0.4507397
B36: % | C36: =C35/C9 -> -4.8610935 | D36: =D35/D9 -> -6.7738771 | E36: =E35/E9 -> -3.1969414 | F36: =F35/F9 -> -1.5373522 | G36: =G35/G9 -> -1.5930495 | H36: =H35/H9 -> -1.6952275 | I36: =I35/I9 -> -3.0678776 | J36: =J35/J9 -> -5.6069866 | ... P36: =P35/P9 -> -1.7143196
B38: Corporate cost | C38: =SUM(C41:C44) -> 2.6359806 | D38: =SUM(D41:D44) -> 2.5888964 | E38: =SUM(E41:E44) -> 2.5715903 | F38: =SUM(F41:F44) -> 2.515271 | G38: =SUM(G41:G44) -> 2.8282529 | H38: =SUM(H41:H44) -> 2.6736752 | I38: =SUM(I41:I44) -> 3.456427 | J38: =SUM(J41:J44) -> 3.551204 | ... Q38: =SUM(Q41:Q44) -> 0.29086092 | R38: =IFERROR(O38/P38-1,"") -> 0.064767598 | S38: =SUM(S39:S42) -> 0.54267857 | T38: =IFERROR(O38/N38-1,"") -> 0.081579969
B39: Gross Man Power | C39: 2.2928516 | D39: 1.9038482 | E39: 1.8028139 | F39: 1.954379 | G39: 2.1854121 | H39: 2.1037436 | I39: 2.4108402 | J39: 2.6032751 | K39: 2.7230566 | L39: 2.8616584 | M39: 2.8577018 | N39: 3.5961045 | O39: 3.852241 | P39: 3.816799 | Q39: =O39-P39 -> 0.035441967 | R39: =IFERROR(O39/P39-1,"") -> 0.0092857829 | S39: =O39-N39 -> 0.25613648 | T39: =IFERROR(O39/N39-1,"") -> 0.071226096
B40: Less: Offline and Inside sales (Reclassed to CAC) | N40: 0.2025 | O40: =2291512/10^7 -> 0.2291512 | P40: 0.347319 | Q40: =O40-P40 -> -0.1181678 | R40: =IFERROR(O40/P40-1,"") -> -0.34022844 | S40: =O40-N40 -> 0.0266512 | T40: =IFERROR(O40/N40-1,"") -> 0.13161086
B41: Net Man Power | C41: =C39-C40 -> 2.2928516 | D41: =D39-D40 -> 1.9038482 | E41: =E39-E40 -> 1.8028139 | F41: =F39-F40 -> 1.954379 | G41: =G39-G40 -> 2.1854121 | H41: =H39-H40 -> 2.1037436 | I41: =I39-I40 -> 2.4108402 | J41: =J39-J40 -> 2.6032751 | ... P41: =P39-P40 -> 3.46948 | Q41: =O41-P41 -> 0.15360977 | R41: =IFERROR(O41/P41-1,"") -> 0.044274579 | S41: =O41-N41 -> 0.22948528 | T41: =IFERROR(O41/N41-1,"") -> 0.067622872
B42: Tech cost | C42: 0.19125444 | D42: 0.30083295 | E42: 0.33504187 | F42: 0.22369761 | G42: 0.29183226 | H42: 0.28668766 | I42: 0.29698963 | J42: 0.3904008 | K42: 0.2886033 | L42: 0.3377396 | M42: 0.4300918 | N42: 0.39887689 | O42: 0.42928249 | P42: 0.41279492 | Q42: =O42-P42 -> 0.016487572 | R42: =IFERROR(O42/P42-1,"") -> 0.039941315 | S42: =O42-N42 -> 0.030405601 | T42: =IFERROR(O42/N42-1,"") -> 0.076228033
B43: Platform services | C43: 0.070656779 | D43: 0.07843967 | E43: 0.067735701 | F43: 0.080448338 | G43: 0.090684423 | H43: 0.079199055 | I43: 0.08152917 | J43: 0.1953063 | K43: 0.1614566 | L43: 0.0693922 | M43: 0.0809986 | N43: 0.087591329 | O43: 0.09720508 | P43: =O43 -> 0.09720508 | Q43: =O43-P43 -> 0 | R43: =IFERROR(O43/P43-1,"") -> 0 | S43: =O43-N43 -> 0.009613751 | T43: =IFERROR(O43/N43-1,"") -> 0.10975688
B44: General & Admin | C44: 0.081217777 | D44: 0.30577555 | E44: 0.36599886 | F44: 0.25674605 | G44: 0.26032409 | H44: 0.20404498 | I44: 0.66706796 | J44: 0.3622218 | K44: 0.4042591 | L44: 0.4537161 | M44: 0.4543679 | N44: 0.54096047 | O44: 0.63212358 | P44: 0.51136 | Q44: =O44-P44 -> 0.12076358 | R44: =IFERROR(O44/P44-1,"") -> 0.23616158 | S44: =O44-N44 -> 0.091163117 | T44: =IFERROR(O44/N44-1,"") -> 0.16852085
B45: Corporate | Q45: =O45-P45 -> 0 | R45: =IFERROR(O45/P45-1,"") | S45: =O45-N45 -> 0 | T45: =IFERROR(O45/N45-1,"")
B46: Offline | Q46: =O46-P46 -> 0 | R46: =IFERROR(O46/P46-1,"") | S46: =O46-N46 -> 0 | T46: =IFERROR(O46/N46-1,"")
B48: Operating EBITDA | C48: =C35-SUM(C41:C44) -> -5.5438643 | D48: =D35-SUM(D41:D44) -> -7.2845004 | E48: =E35-SUM(E41:E44) -> -5.269029 | F48: =F35-SUM(F41:F44) -> -4.2231174 | G48: =G35-SUM(G41:G44) -> -4.3765653 | H48: =H35-SUM(H41:H44) -> -4.7409872 | I48: =I35-SUM(I41:I44) -> -8.6871754 | J48: =J35-SUM(J41:J44) -> -11.324374 | ... Q48: =Q35-SUM(Q41:Q44) -> 0.18983363 | R48: =IFERROR(O48/P48-1,"") -> -0.032419437 | S48: =O48-N48 -> 3.5010189 | T48: =IFERROR(O48/N48-1,"") -> -0.26954809
B49: % | C49: =C48/C9 -> -9.2676479 | D49: =D48/D9 -> -10.508618 | E49: =E48/E9 -> -6.2447303 | F49: =F48/F9 -> -3.8015238 | G49: =G48/G9 -> -4.5030223 | H49: =H48/H9 -> -3.8876822 | I49: =I48/I9 -> -5.0951008 | J49: =J48/J9 -> -8.1685611 | ... P49: =P48/P9 -> -3.1629476
B51: Other income | C51: 0.4552157 | D51: 0.67569422 | E51: 0.56606598 | F51: 0.83244365 | G51: 0.71868597 | H51: 1.901913 | I51: 1.5871407 | J51: 1.3262718 | K51: 1.6005964 | L51: 1.5432708 | M51: 1.7120367 | N51: 1.4974601 | O51: 1.3134965 | P51: 1.4947327 | Q51: =O51-P51 -> -0.18123618 | R51: =IFERROR(O51/P51-1,"") -> -0.1212499 | S51: =O51-N51 -> -0.18396356 | T51: =IFERROR(O51/N51-1,"") -> -0.1228504
B52: Finance cost | C52: 0.0097795 | D52: 0.0101696 | E52: 0.0009792 | F52: 0.0037333 | G52: 0.0122276 | H52: 0.0274431 | I52: 0.0678577 | J52: 0.1174117 | K52: 0.1455627 | L52: 0.1583196 | M52: 0.1396098 | N52: 0.2051436 | O52: 0.2627327 | P52: =O52 -> 0.2627327 | Q52: =O52-P52 -> 0 | R52: =IFERROR(O52/P52-1,"") -> 0 | S52: =O52-N52 -> 0.0575891 | T52: =IFERROR(O52/N52-1,"") -> 0.28072579
B53: One-off expenses | C53: 0 | D53: 0.125 | E53: 0.03756 | F53: 0 | G53: 0.014 | H53: 0.72717 | I53: 0.18756 | J53: 0.0505 | K53: 0.18 | L53: 0 | M53: 0 | N53: 0.4324145 | O53: 0 | P53: 0.1 | Q53: =O53-P53 -> -0.1 | R53: =IFERROR(O53/P53-1,"") -> -1 | S53: =O53-N53 -> -0.4324145 | T53: =IFERROR(O53/N53-1,"") -> -1
B54: Overall EBITDA | C54: =C48+C51-C52-C53 -> -5.0984281 | D54: =D48+D51-D52-D53 -> -6.7439757 | E54: =E48+E51-E52-E53 -> -4.7415022 | F54: =F48+F51-F52-F53 -> -3.3944071 | G54: =G48+G51-G52-G53 -> -3.6841069 | H54: =H48+H51-H52-H53 -> -3.5936874 | I54: =I48+I51-I52-I53 -> -7.3554524 | J54: =J48+J51-J52-J53 -> -10.166014 | ... Q54: =Q48+Q51-Q52-Q53 -> 0.10859745 | R54: =IFERROR(O54/P54-1,"") -> -0.027284463 | S54: =O54-N54 -> 3.6918807 | T54: =IFERROR(O54/N54-1,"") -> -0.30439528
B55: % | C55: =C54/C9 -> -8.5230146 | D55: =D54/D9 -> -9.7288576 | E55: =E54/E9 -> -5.6195179 | F55: =F54/F9 -> -3.0555436 | G55: =G54/G9 -> -3.7905559 | H55: =H54/H9 -> -2.9468788 | I55: =I54/I9 -> -4.3140342 | J55: =J54/J9 -> -7.3330063 | ... P55: =P54/P9 -> -2.7977939
B57: Platfform CAC (excl infleuncer, offline, inside sales) | C57: =(C24+C25)*10^7/'Revised MIS Template - KPIs'!D22 -> 2261.9694 | D57: =(D24+D25)*10^7/'Revised MIS Template - KPIs'!E22 -> 2031.315 | E57: =(E24+E25)*10^7/'Revised MIS Template - KPIs'!F22 -> 2209.5146 | F57: =(F24+F25)*10^7/'Revised MIS Template - KPIs'!G22 -> 2288.9934 | G57: =(G24+G25)*10^7/'Revised MIS Template - KPIs'!H22 -> 2013.6617 | H57: =(H24+H25)*10^7/'Revised MIS Template - KPIs'!I22 -> 2102.6812 | I57: =(I24+I25)*10^7/'Revised MIS Template - KPIs'!J22 -> 2813.1004 | J57: =(J24+J25)*10^7/'Revised MIS Template - KPIs'!K22 -> 3809.2742 | ... O57: =(O24+O25)*10^7/'Revised MIS Template - KPIs'!P22 -> 2278.3048
B58: Platfform CAC (incl infleuncer, offline, inside sales) | C58: =(C24+C25+C26+C27)*10^7/'Revised MIS Template - KPIs'!D22 -> 2772.5931 | D58: =(D24+D25+D26+D27)*10^7/'Revised MIS Template - KPIs'!E22 -> 2367.9326 | E58: =(E24+E25+E26+E27)*10^7/'Revised MIS Template - KPIs'!F22 -> 2369.6613 | F58: =(F24+F25+F26+F27)*10^7/'Revised MIS Template - KPIs'!G22 -> 2463.937 | G58: =(G24+G25+G26+G27)*10^7/'Revised MIS Template - KPIs'!H22 -> 2087.5013 | H58: =(H24+H25+H26+H27)*10^7/'Revised MIS Template - KPIs'!I22 -> 2288.9376 | I58: =(I24+I25+I26+I27)*10^7/'Revised MIS Template - KPIs'!J22 -> 2989.444 | J58: =(J24+J25+J26+J27)*10^7/'Revised MIS Template - KPIs'!K22 -> 3954.4783 | ... O58: =(O24+O25+O26+O27)*10^7/'Revised MIS Template - KPIs'!P22 -> 2497.3889
B62: Key Balance Sheet Metrics (INR Cr) | F62: =F2 -> 45748 | G62: =G2 -> 45778 | H62: =H2 -> 45809 | I62: =I2 -> 45839 | J62: =J2 -> 45870 | K62: =K2 -> 45901 | L62: =L2 -> 45931 | M62: =M2 -> 45962 | ... O62: =O2 -> Jan-26
B63: Bonds Inventory (held for sale) | F63: 23.13 | G63: 22.87 | H63: 41.22 | I63: 54.24 | J63: 58.01 | K63: 58.66 | L63: 77.89 | M63: 73.51 | N63: 82.72 | O63: 78.62
B64: Bond inventory > 30 days
B65: Cash / Investments | F65: 78.93 | G65: 248.76 | H65: 227.05 | I65: 202.03 | J65: 176.67 | K65: 164.14 | L65: 136.32 | M65: 134.73 | N65: 109.83 | O65: 98.78
B66: Cash+Investments+Bonds | F66: =F63+F65 -> 102.06 | G66: =G63+G65 -> 271.63 | H66: =H63+H65 -> 268.27 | I66: =I63+I65 -> 256.27 | J66: =J63+J65 -> 234.68 | K66: =K63+K65 -> 222.8 | L66: =L63+L65 -> 214.21 | M66: =M63+M65 -> 208.24 | ... O66: =O63+O65 -> 177.4
B67: Investment receipt | G67: 173.14 | H67: 0 | I67: 0 | J67: 0 | K67: 0 | L67: 0 | M67: 0 | N67: 0 | O67: 0
B68: Net Operating Cash Outflow | G68: =G66-F66-G67 -> -3.57 | H68: =H66-G66-H67 -> -3.36 | I68: =I66-H66-I67 -> -12 | J68: =J66-I66-J67 -> -21.59 | K68: =K66-J66-K67 -> -11.88 | L68: =L66-K66-L67 -> -8.59 | M68: =M66-L66-M67 -> -5.97 | N68: =N66-M66-N67 -> -15.69 | O68: =O66-N66-O67 -> -15.15
C71: Cells highlighted in grey would be filled in due course of time

Sheet Revised MIS Template - Cohorts
A3: Net AUM Retention: Platform | F3: Growth of Net AUM each month compared to the base month’s Net AUM
B5: Base Month | C5: M0 | D5: M1 | E5: M2 | F5: M3 | G5: M4 | H5: M5 | I5: M6 | J5: M7 | K5: M8 | L5: M9 | M5: M10 | N5: M11 | O5: M12 | P5: M13 | Q5: M14 | R5: M15 | S5: M16 | T5: M17 | U5: M18 | V5: M19 | W5: M20 | X5: M21 | Y5: M22 | Z5: M23 | AA5: M24 | AB5: M25 | AC5: M26 | AD5: M27
B6: 45139 | C6: ₹11 Cr | D6: 1.49 | E6: 1.7 | F6: 1.94 | G6: 2.16 | H6: 2.28 | I6: 2.37 | J6: 2.49 | K6: 2.61 | L6: 2.72 | M6: 2.81 | N6: 2.9 | O6: 2.9 | P6: 3 | Q6: 3.15 | R6: 3.22 | S6: 3.34 | T6: 3.55 | U6: 3.84 | V6: 4.02 | W6: 4.23 | X6: 4.64 | Y6: 4.94 | Z6: 5.19 | AA6: 5.2 | AB6: 5.28 | AC6: 5.45 | AD6: 5.59
B7: 45170 | C7: ₹40 Cr | D7: 1.19 | E7: 1.33 | F7: 1.47 | G7: 1.54 | H7: 1.57 | I7: 1.66 | J7: 1.76 | K7: 1.81 | L7: 1.86 | M7: 1.91 | N7: 1.95 | O7: 1.92 | P7: 2.01 | Q7: 2.1 | R7: 2.17 | S7: 2.25 | T7: 2.35 | U7: 2.41 | V7: 2.5 | W7: 2.6 | X7: 2.71 | Y7: 2.75 | Z7: 2.8 | AA7: 2.66 | AB7: 2.67 | AC7: 2.73
B8: 45200 | C8: ₹33 Cr | D8: 1.24 | E8: 1.39 | F8: 1.44 | G8: 1.46 | H8: 1.55 | I8: 1.64 | J8: 1.69 | K8: 1.74 | L8: 1.8 | M8: 1.85 | N8: 1.91 | O8: 1.88 | P8: 1.95 | Q8: 2.01 | R8: 2.09 | S8: 2.21 | T8: 2.27 | U8: 2.34 | V8: 2.44 | W8: 2.57 | X8: 2.59 | Y8: 2.67 | Z8: 2.72 | AA8: 2.58 | AB8: 2.63
B9: 45231 | C9: ₹34 Cr | D9: 1.2 | E9: 1.26 | F9: 1.28 | G9: 1.37 | H9: 1.45 | I9: 1.48 | J9: 1.53 | K9: 1.57 | L9: 1.61 | M9: 1.67 | N9: 1.72 | O9: 1.71 | P9: 1.76 | Q9: 1.85 | R9: 1.94 | S9: 1.98 | T9: 2.07 | U9: 2.17 | V9: 2.29 | W9: 2.21 | X9: 2.29 | Y9: 2.31 | Z9: 2.37 | AA9: 2.33
B10: 45261 | C10: ₹33 Cr | D10: 1.15 | E10: 1.18 | F10: 1.25 | G10: 1.34 | H10: 1.38 | I10: 1.44 | J10: 1.49 | K10: 1.55 | L10: 1.59 | M10: 1.67 | N10: 1.75 | O10: 1.69 | P10: 1.77 | Q10: 1.86 | R10: 1.9 | S10: 2 | T10: 2.08 | U10: 2.17 | V10: 2.26 | W10: 2.32 | X10: 2.35 | Y10: 2.39 | Z10: 2.42
B11: 45292 | C11: ₹27 Cr | D11: 1.13 | E11: 1.25 | F11: 1.34 | G11: 1.38 | H11: 1.4 | I11: 1.45 | J11: 1.51 | K11: 1.57 | L11: 1.64 | M11: 1.71 | N11: 1.78 | O11: 1.74 | P11: 1.85 | Q11: 1.91 | R11: 2 | S11: 2.1 | T11: 2.2 | U11: 2.26 | V11: 2.32 | W11: 2.35 | X11: 2.4 | Y11: 2.46
B12: 45323 | C12: ₹26 Cr | D12: 1.23 | E12: 1.32 | F12: 1.38 | G12: 1.4 | H12: 1.45 | I12: 1.51 | J12: 1.55 | K12: 1.63 | L12: 1.7 | M12: 1.75 | N12: 1.8 | O12: 1.81 | P12: 1.86 | Q12: 1.94 | R12: 2.01 | S12: 2.11 | T12: 2.16 | U12: 2.2 | V12: 2.2 | W12: 2.23 | X12: 2.26
B13: 45352 | C13: ₹28 Cr | D13: 1.22 | E13: 1.3 | F13: 1.34 | G13: 1.39 | H13: 1.44 | I13: 1.5 | J13: 1.59 | K13: 1.64 | L13: 1.72 | M13: 1.78 | N13: 1.87 | O13: 1.79 | P13: 1.84 | Q13: 1.95 | R13: 2.02 | S13: 2.09 | T13: 2.13 | U13: 2.07 | V13: 2.05 | W13: 2.07
B14: 45383 | C14: ₹55 Cr | D14: 1.13 | E14: 1.19 | F14: 1.24 | G14: 1.27 | H14: 1.33 | I14: 1.4 | J14: 1.43 | K14: 1.47 | L14: 1.52 | M14: 1.6 | N14: 1.65 | O14: 1.57 | P14: 1.63 | Q14: 1.73 | R14: 1.79 | S14: 1.81 | T14: 1.86 | U14: 1.82 | V14: 1.83
B15: 45413 | C15: ₹38 Cr | D15: 1.13 | E15: 1.2 | F15: 1.24 | G15: 1.29 | H15: 1.36 | I15: 1.41 | J15: 1.47 | K15: 1.53 | L15: 1.61 | M15: 1.69 | N15: 1.76 | O15: 1.72 | P15: 1.8 | Q15: 1.88 | R15: 1.95 | S15: 1.94 | T15: 1.97 | U15: 1.93
B16: 45444 | C16: ₹36 Cr | D16: 1.18 | E16: 1.26 | F16: 1.32 | G16: 1.4 | H16: 1.42 | I16: 1.46 | J16: 1.52 | K16: 1.58 | L16: 1.63 | M16: 1.69 | N16: 1.77 | O16: 1.83 | P16: 1.9 | Q16: 1.95 | R16: 2 | S16: 1.98 | T16: 2.01
B17: 45474 | C17: ₹55 Cr | D17: 1.18 | E17: 1.27 | F17: 1.36 | G17: 1.43 | H17: 1.48 | I17: 1.52 | J17: 1.57 | K17: 1.64 | L17: 1.71 | M17: 1.77 | N17: 1.84 | O17: 1.87 | P17: 1.91 | Q17: 1.97 | R17: 2 | S17: 2.01
B18: 45505 | C18: ₹74 Cr | D18: 1.21 | E18: 1.32 | F18: 1.38 | G18: 1.44 | H18: 1.5 | I18: 1.57 | J18: 1.61 | K18: 1.68 | L18: 1.76 | M18: 1.85 | N18: 1.92 | O18: 1.92 | P18: 1.95 | Q18: 1.98 | R18: 2.03
B19: 45536 | C19: ₹86 Cr | D19: 1.2 | E19: 1.29 | F19: 1.36 | G19: 1.44 | H19: 1.52 | I19: 1.58 | J19: 1.65 | K19: 1.74 | L19: 1.82 | M19: 1.9 | N19: 1.97 | O19: 1.98 | P19: 2 | Q19: 2.04
B20: 45566 | C20: ₹84 Cr | D20: 1.21 | E20: 1.28 | F20: 1.4 | G20: 1.5 | H20: 1.57 | I20: 1.64 | J20: 1.72 | K20: 1.82 | L20: 1.9 | M20: 1.98 | N20: 2.03 | O20: 1.97 | P20: 2
B21: 45597 | C21: ₹90 Cr | D21: 1.18 | E21: 1.29 | F21: 1.39 | G21: 1.48 | H21: 1.58 | I21: 1.65 | J21: 1.75 | K21: 1.83 | L21: 1.9 | M21: 1.95 | N21: 2.01 | O21: 1.94
B22: 45627 | C22: ₹88 Cr | D22: 1.21 | E22: 1.34 | F22: 1.43 | G22: 1.54 | H22: 1.64 | I22: 1.73 | J22: 1.8 | K22: 1.88 | L22: 1.95 | M22: 2 | N22: 2.05
B23: 45658 | C23: ₹116 Cr | D23: 1.21 | E23: 1.32 | F23: 1.43 | G23: 1.51 | H23: 1.6 | I23: 1.66 | J23: 1.71 | K23: 1.77 | L23: 1.82 | M23: 1.87
B24: 45689 | C24: ₹126 Cr | D24: 1.15 | E24: 1.27 | F24: 1.36 | G24: 1.44 | H24: 1.52 | I24: 1.57 | J24: 1.61 | K24: 1.66 | L24: 1.71
B25: 45717 | C25: ₹94 Cr | D25: 1.23 | E25: 1.36 | F25: 1.45 | G25: 1.53 | H25: 1.61 | I25: 1.64 | J25: 1.68 | K25: 1.73
B26: 45748 | C26: ₹108 Cr | D26: 1.19 | E26: 1.31 | F26: 1.41 | G26: 1.48 | H26: 1.54 | I26: 1.59 | J26: 1.63
B27: 45778 | C27: ₹106 Cr | D27: 1.24 | E27: 1.36 | F27: 1.43 | G27: 1.51 | H27: 1.58 | I27: 1.62
B28: 45809 | C28: ₹129 Cr | D28: 1.21 | E28: 1.32 | F28: 1.4 | G28: 1.49 | H28: 1.57
B29: 45839 | C29: ₹140 Cr | D29: 1.18 | E29: 1.29 | F29: 1.39 | G29: 1.47
B30: 45870 | C30: ₹116 Cr | D30: 1.21 | E30: 1.34 | F30: 1.45
B31: 45901 | C31: ₹124 Cr | D31: 1.22 | E31: 1.35
B32: 45931 | C32: ₹139 Cr | D32: 1.24
B33: 45962 | C33: ₹143 Cr
B35: Monthly active user retention (AUM > 0)
B36: Month | C36: M0 # users | D36: M0 | E36: M1 | F36: M2 | G36: M3 | H36: M4 | I36: M5 | J36: M6 | K36: M7 | L36: M8 | M36: M9 | N36: M10 | O36: M11 | P36: M12 | Q36: M13 | R36: M14 | S36: M15 | T36: M16 | U36: M17 | V36: M18 | W36: M19
B37: 45292 | C37: 3134 | D37: 0.9 | E37: 0.97 | F37: 0.96 | G37: 0.93 | H37: 0.9 | I37: 0.88 | J37: 0.87 | K37: 0.86 | L37: 0.85 | M37: 0.84 | N37: 0.84 | O37: 0.83 | P37: 0.73 | Q37: 0.73 | R37: 0.73 | S37: 0.73 | T37: 0.72 | U37: 0.73 | V37: 0.73 | W37: 0.73
B38: =EOMONTH(B37,1) -> 45351 | C38: 2530 | D38: 0.95 | E38: 0.96 | F38: 0.93 | G38: 0.9 | H38: 0.87 | I38: 0.85 | J38: 0.83 | K38: 0.82 | L38: 0.82 | M38: 0.81 | N38: 0.81 | O38: 0.8 | P38: 0.74 | Q38: 0.73 | R38: 0.73 | S38: 0.73 | T38: 0.73 | U38: 0.73 | V38: 0.72
B39: =EOMONTH(B38,1) -> 45382 | C39: 2415 | D39: 0.95 | E39: 0.93 | F39: 0.9 | G39: 0.88 | H39: 0.86 | I39: 0.85 | J39: 0.84 | K39: 0.83 | L39: 0.82 | M39: 0.82 | N39: 0.82 | O39: 0.82 | P39: 0.7 | Q39: 0.7 | R39: 0.7 | S39: 0.71 | T39: 0.71 | U39: 0.71
B40: =EOMONTH(B39,1) -> 45412 | C40: 3927 | D40: 0.93 | E40: 0.91 | F40: 0.87 | G40: 0.85 | H40: 0.83 | I40: 0.82 | J40: 0.81 | K40: 0.8 | L40: 0.79 | M40: 0.79 | N40: 0.79 | O40: 0.79 | P40: 0.66 | Q40: 0.66 | R40: 0.67 | S40: 0.67 | T40: 0.66
B41: =EOMONTH(B40,1) -> 45443 | C41: 2850 | D41: 0.9 | E41: 0.88 | F41: 0.85 | G41: 0.82 | H41: 0.81 | I41: 0.79 | J41: 0.78 | K41: 0.78 | L41: 0.77 | M41: 0.77 | N41: 0.77 | O41: 0.77 | P41: 0.69 | Q41: 0.69 | R41: 0.69 | S41: 0.69
B42: =EOMONTH(B41,1) -> 45473 | C42: 2901 | D42: 0.89 | E42: 0.87 | F42: 0.84 | G42: 0.83 | H42: 0.81 | I42: 0.8 | J42: 0.78 | K42: 0.78 | L42: 0.77 | M42: 0.77 | N42: 0.76 | O42: 0.76 | P42: 0.72 | Q42: 0.72 | R42: 0.72
B43: =EOMONTH(B42,1) -> 45504 | C43: 3699 | D43: 0.91 | E43: 0.88 | F43: 0.86 | G43: 0.84 | H43: 0.83 | I43: 0.82 | J43: 0.8 | K43: 0.8 | L43: 0.8 | M43: 0.79 | N43: 0.79 | O43: 0.79 | P43: 0.74 | Q43: 0.74
B44: =EOMONTH(B43,1) -> 45535 | C44: 5511 | D44: 0.89 | E44: 0.89 | F44: 0.85 | G44: 0.83 | H44: 0.82 | I44: 0.81 | J44: 0.8 | K44: 0.79 | L44: 0.78 | M44: 0.78 | N44: 0.78 | O44: 0.78 | P44: 0.73
B45: =EOMONTH(B44,1) -> 45565 | C45: 5894 | D45: 0.92 | E45: 0.88 | F45: 0.85 | G45: 0.83 | H45: 0.83 | I45: 0.82 | J45: 0.8 | K45: 0.79 | L45: 0.79 | M45: 0.78 | N45: 0.79 | O45: 0.78
B46: =EOMONTH(B45,1) -> 45596 | C46: 6847 | D46: 0.89 | E46: 0.84 | F46: 0.81 | G46: 0.79 | H46: 0.78 | I46: 0.77 | J46: 0.75 | K46: 0.74 | L46: 0.74 | M46: 0.74 | N46: 0.74
B47: =EOMONTH(B46,1) -> 45626 | C47: 8883 | D47: 0.84 | E47: 0.75 | F47: 0.72 | G47: 0.71 | H47: 0.7 | I47: 0.69 | J47: 0.67 | K47: 0.66 | L47: 0.66 | M47: 0.66
B48: =EOMONTH(B47,1) -> 45657 | C48: 8249 | D48: 0.83 | E48: 0.78 | F48: 0.76 | G48: 0.75 | H48: 0.73 | I48: 0.72 | J48: 0.7 | K48: 0.69 | L48: 0.68
B49: =EOMONTH(B48,1) -> 45688 | C49: 9507 | D49: 0.86 | E49: 0.83 | F49: 0.8 | G49: 0.79 | H49: 0.77 | I49: 0.76 | J49: 0.73 | K49: 0.72
B50: =EOMONTH(B49,1) -> 45716 | C50: 9372 | D50: 0.88 | E50: 0.85 | F50: 0.82 | G50: 0.8 | H50: 0.78 | I50: 0.77 | J50: 0.74
B51: =EOMONTH(B50,1) -> 45747 | C51: 8618 | D51: 0.87 | E51: 0.83 | F51: 0.8 | G51: 0.78 | H51: 0.77 | I51: 0.75
B52: =EOMONTH(B51,1) -> 45777 | C52: 8860 | D52: 0.87 | E52: 0.85 | F52: 0.83 | G52: 0.81 | H52: 0.79
B53: =EOMONTH(B52,1) -> 45808 | C53: 9522 | D53: 0.85 | E53: 0.83 | F53: 0.8 | G53: 0.78
B54: =EOMONTH(B53,1) -> 45838 | C54: 11579 | D54: 0.86 | E54: 0.82 | F54: 0.79
B55: =EOMONTH(B54,1) -> 45869 | C55: 10661 | D55: 0.87 | E55: 0.86
B56: =EOMONTH(B55,1) -> 45900 | C56: 10530 | D56: 0.87
A59: Transacting user retention : Platform | F59: % of users reinvesting in months following their first investment month
B61: Base Month | C61: M0 | D61: M1 | E61: M2 | F61: M3 | G61: M4 | H61: M5 | I61: M6 | J61: M7 | K61: M8 | L61: M9 | M61: M10 | N61: M11 | O61: M12 | P61: M13 | Q61: M14 | R61: M15 | S61: M16 | T61: M17 | U61: M18 | V61: M19 | W61: M20 | X61: M21 | Y61: M22 | Z61: M23 | AA61: M24 | AB61: M25 | AC61: M26 | AD61: M27
B62: 45139 | C62: 3.5K | D62: 0.15 | E62: 0.1 | F62: 0.09 | G62: 0.09 | H62: 0.06 | I62: 0.05 | J62: 0.06 | K62: 0.06 | L62: 0.05 | M62: 0.05 | N62: 0.05 | O62: 0.06 | P62: 0.06 | Q62: 0.07 | R62: 0.06 | S62: 0.06 | T62: 0.07 | U62: 0.07 | V62: 0.07 | W62: 0.08 | X62: 0.07 | Y62: 0.08 | Z62: 0.07 | AA62: 0.07 | AB62: 0.06 | AC62: 0.07 | AD62: 0.07
B63: 45170 | C63: 4.2K | D63: 0.21 | E63: 0.16 | F63: 0.15 | G63: 0.09 | H63: 0.07 | I63: 0.1 | J63: 0.1 | K63: 0.07 | L63: 0.07 | M63: 0.07 | N63: 0.07 | O63: 0.11 | P63: 0.11 | Q63: 0.1 | R63: 0.09 | S63: 0.09 | T63: 0.1 | U63: 0.1 | V63: 0.11 | W63: 0.1 | X63: 0.1 | Y63: 0.09 | Z63: 0.07 | AA63: 0.11 | AB63: 0.09 | AC63: 0.08
B64: 45200 | C64: 3.2K | D64: 0.21 | E64: 0.17 | F64: 0.09 | G64: 0.06 | H64: 0.11 | I64: 0.09 | J64: 0.07 | K64: 0.07 | L64: 0.08 | M64: 0.07 | N64: 0.08 | O64: 0.12 | P64: 0.1 | Q64: 0.09 | R64: 0.1 | S64: 0.11 | T64: 0.1 | U64: 0.11 | V64: 0.1 | W64: 0.11 | X64: 0.11 | Y64: 0.08 | Z64: 0.08 | AA64: 0.11 | AB64: 0.1
B65: 45231 | C65: 3.1K | D65: 0.2 | E65: 0.1 | F65: 0.07 | G65: 0.1 | H65: 0.09 | I65: 0.07 | J65: 0.06 | K65: 0.06 | L65: 0.07 | M65: 0.06 | N65: 0.07 | O65: 0.1 | P65: 0.1 | Q65: 0.1 | R65: 0.11 | S65: 0.09 | T65: 0.09 | U65: 0.09 | V65: 0.1 | W65: 0.11 | X65: 0.08 | Y65: 0.07 | Z65: 0.08 | AA65: 0.08
B66: 45261 | C66: 3.3K | D66: 0.16 | E66: 0.08 | F66: 0.1 | G66: 0.1 | H66: 0.06 | I66: 0.06 | J66: 0.06 | K66: 0.06 | L66: 0.07 | M66: 0.08 | N66: 0.08 | O66: 0.11 | P66: 0.11 | Q66: 0.1 | R66: 0.09 | S66: 0.1 | T66: 0.09 | U66: 0.09 | V66: 0.08 | W66: 0.06 | X66: 0.06 | Y66: 0.07 | Z66: 0.07
B67: 45292 | C67: 3.2K | D67: 0.13 | E67: 0.12 | F67: 0.09 | G67: 0.06 | H67: 0.06 | I67: 0.06 | J67: 0.06 | K67: 0.06 | L67: 0.07 | M67: 0.07 | N67: 0.07 | O67: 0.11 | P67: 0.1 | Q67: 0.09 | R67: 0.09 | S67: 0.09 | T67: 0.08 | U67: 0.07 | V67: 0.06 | W67: 0.07 | X67: 0.07 | Y67: 0.07
B68: 45323 | C68: 2.5K | D68: 0.23 | E68: 0.14 | F68: 0.1 | G68: 0.09 | H68: 0.09 | I68: 0.09 | J68: 0.09 | K68: 0.09 | L68: 0.09 | M68: 0.09 | N68: 0.09 | O68: 0.15 | P68: 0.13 | Q68: 0.12 | R68: 0.11 | S68: 0.11 | T68: 0.09 | U68: 0.07 | V68: 0.08 | W68: 0.08 | X68: 0.08
B69: 45352 | C69: 2.4K | D69: 0.22 | E69: 0.13 | F69: 0.11 | G69: 0.1 | H69: 0.1 | I69: 0.1 | J69: 0.12 | K69: 0.1 | L69: 0.11 | M69: 0.11 | N69: 0.12 | O69: 0.2 | P69: 0.16 | Q69: 0.13 | R69: 0.12 | S69: 0.11 | T69: 0.09 | U69: 0.1 | V69: 0.1 | W69: 0.09
B70: 45383 | C70: 3.9K | D70: 0.19 | E70: 0.13 | F70: 0.12 | G70: 0.11 | H70: 0.11 | I70: 0.12 | J70: 0.1 | K70: 0.1 | L70: 0.1 | M70: 0.12 | N70: 0.11 | O70: 0.21 | P70: 0.15 | Q70: 0.13 | R70: 0.1 | S70: 0.09 | T70: 0.1 | U70: 0.11 | V70: 0.09
B71: 45413 | C71: 2.9K | D71: 0.19 | E71: 0.13 | F71: 0.12 | G71: 0.1 | H71: 0.11 | I71: 0.1 | J71: 0.11 | K71: 0.12 | L71: 0.11 | M71: 0.11 | N71: 0.11 | O71: 0.15 | P71: 0.13 | Q71: 0.11 | R71: 0.09 | S71: 0.1 | T71: 0.09 | U71: 0.1
B72: 45444 | C72: 2.9K | D72: 0.22 | E72: 0.15 | F72: 0.13 | G72: 0.13 | H72: 0.11 | I72: 0.12 | J72: 0.11 | K72: 0.12 | L72: 0.11 | M72: 0.11 | N72: 0.12 | O72: 0.15 | P72: 0.11 | Q72: 0.1 | R72: 0.08 | S72: 0.11 | T72: 0.09
B73: 45474 | C73: 3.9K | D73: 0.23 | E73: 0.14 | F73: 0.15 | G73: 0.13 | H73: 0.13 | I73: 0.13 | J73: 0.13 | K73: 0.13 | L73: 0.13 | M73: 0.12 | N73: 0.13 | O73: 0.14 | P73: 0.11 | Q73: 0.1 | R73: 0.1 | S73: 0.11
B74: 45505 | C74: 5.6K | D74: 0.24 | E74: 0.19 | F74: 0.15 | G74: 0.14 | H74: 0.14 | I74: 0.14 | J74: 0.13 | K74: 0.13 | L74: 0.13 | M74: 0.13 | N74: 0.12 | O74: 0.12 | P74: 0.1 | Q74: 0.1 | R74: 0.11
B75: 45536 | C75: 5.8K | D75: 0.26 | E75: 0.18 | F75: 0.16 | G75: 0.16 | H75: 0.15 | I75: 0.15 | J75: 0.14 | K75: 0.14 | L75: 0.14 | M75: 0.13 | N75: 0.11 | O75: 0.12 | P75: 0.12 | Q75: 0.11
B76: 45566 | C76: 6.8K | D76: 0.25 | E76: 0.18 | F76: 0.18 | G76: 0.17 | H76: 0.15 | I76: 0.15 | J76: 0.14 | K76: 0.14 | L76: 0.12 | M76: 0.11 | N76: 0.1 | O76: 0.13 | P76: 0.12
B77: 45597 | C77: 8.9K | D77: 0.22 | E77: 0.17 | F77: 0.15 | G77: 0.14 | H77: 0.13 | I77: 0.13 | J77: 0.12 | K77: 0.1 | L77: 0.1 | M77: 0.09 | N77: 0.09 | O77: 0.11
B78: 45627 | C78: 8.3K | D78: 0.25 | E78: 0.19 | F78: 0.16 | G78: 0.14 | H78: 0.14 | I78: 0.13 | J78: 0.12 | K78: 0.11 | L78: 0.1 | M78: 0.09 | N78: 0.1
B79: 45658 | C79: 9.5K | D79: 0.26 | E79: 0.2 | F79: 0.18 | G79: 0.15 | H79: 0.14 | I79: 0.12 | J79: 0.11 | K79: 0.11 | L79: 0.11 | M79: 0.1
B80: 45689 | C80: 9.4K | D80: 0.21 | E80: 0.16 | F80: 0.14 | G80: 0.13 | H80: 0.1 | I80: 0.1 | J80: 0.1 | K80: 0.09 | L80: 0.08
B81: 45717 | C81: 8.5K | D81: 0.23 | E81: 0.15 | F81: 0.13 | G81: 0.11 | H81: 0.1 | I81: 0.1 | J81: 0.1 | K81: 0.09
B82: 45748 | C82: 8.8K | D82: 0.21 | E82: 0.15 | F82: 0.12 | G82: 0.1 | H82: 0.09 | I82: 0.1 | J82: 0.09
B83: 45778 | C83: 9.1K | D83: 0.22 | E83: 0.14 | F83: 0.11 | G83: 0.1 | H83: 0.1 | I83: 0.1
B84: 45809 | C84: 11.5K | D84: 0.19 | E84: 0.12 | F84: 0.1 | G84: 0.1 | H84: 0.09
B85: 45839 | C85: 10.6K | D85: 0.19 | E85: 0.12 | F85: 0.12 | G85: 0.11
B86: 45870 | C86: 10.3K | D86: 0.19 | E86: 0.15 | F86: 0.13
B87: 45901 | C87: 13.4K | D87: 0.19 | E87: 0.12
B88: 45931 | C88: 17.3K | D88: 0.2
B89: 45962 | C89: 17.3K
